Workbook

Sheet README
A1: Stride: Financial Model
A3: 10-year operating model, three statements, and a valuation. EUR. Y1 = 2027.
A5: COLOUR CODE
A6: LIGHT BLUE | B6: Estimated input
A7: LIGHT YELLOW | B7: Sourced input (Stripe pricing, Spanish tax law, AWS list)
A8: WHITE | B8: Computed formula
A9: LIGHT GREEN | B9: Dependent value, pulled from another sheet or from the one input at the head of its row
A10: LIGHT GREY | B10: Total or subtotal
A11: LIGHT RED | B11: The balance-sheet check, which must read zero
A13: SHEETS
A14: INPUTS
A15: Assumptions | B15: Every input and assumption taken into consideration
A17: BUILD-UP
A18: Drivers | B18: Athletes and fans, including monthly cohort churn
A19: Revenue | B19: GMV and net revenue, stream by stream
A20: Costs | B20: COGS and operating costs, line by line
A21: WorkingCap | B21: Receivables, payables, athlete float, capex, D&A
A23: THE THREE FINANCIAL STATEMENTS
A24: P&L | B24: Income statement
A25: CashFlow | B25: Cash flow statement, indirect method, tying to closing cash
A26: BalanceSheet | B26: Balance sheet, with an explicit check row so it must balance
A28: VALUATION AND FUNDING
A29: Valuation | B29: DCF, NPV, IRR, exit multiples, sensitivity
A30: Funding | B30: Funding rounds, dilution, ownership shares
A32: OPERATING PLANS
A33: HiringPlan | B33: Headcount by role, at Spanish loaded salaries
A34: CAC_CLV | B34: Acquisition cost against lifetime value
A35: KPIs | B35: Scale, quality of revenue, efficiency
A37: APPENDIX: RESEARCH AND MODELLING
A38: Comparables | B38: Published facts about Patreon, Passes and agents. The benchmarking source
A39: MarketModel | B39: Modelled assumptions, per market dynamics
A40: Research | B40: Where each baseline assumption came from, and how confident it is

Sheet Assumptions
A1: Assumptions
A2: Line | B2: Unit | C2: Y1 | D2: Y2 | E2: Y3 | F2: Y4 | G2: Y5 | H2: Y6 | I2: Y7 | J2: Y8 | K2: Y9 | L2: Y10
A4: MARKET: the plan's shape
A5: Active athletes (year end) | B5: count | C5: 250 | D5: 750 | E5: 1700 | F5: 2800 | G5: 4000 | H5: 5200 | I5: 6300 | J5: 7200 | K5: 7900 | L5: 8500
A6: Niche share of athletes | B6: % | C6: 0.95 | D6: 0.92 | E6: 0.8 | F6: 0.68 | G6: 0.58 | H6: 0.5 | I6: 0.45 | J6: 0.43 | K6: 0.42 | L6: 0.41
A7: Athletes needed for full SaaS value | B7: count | C7: 2000 | D7: =C7 -> 2000 | E7: =C7 -> 2000 | F7: =C7 -> 2000 | G7: =C7 -> 2000 | H7: =C7 -> 2000 | I7: =C7 -> 2000 | J7: =C7 -> 2000 | K7: =C7 -> 2000 | L7: =C7 -> 2000 | N7: Below this, sponsor conversion scales with supply, a matching product is worth nothing against an empty directory
A9: SEGMENT: NICHE
A10: Monetising athletes (niche) | B10: % of segment | C10: 0 | D10: 0.32 | E10: 0.37 | F10: 0.41 | G10: 0.44 | H10: 0.46 | I10: 0.48 | J10: 0.49 | K10: 0.5 | L10: 0.5
A11: Paying fans per monetising athlete (niche) | B11: count | C11: 20 | D11: 22 | E11: 25 | F11: 28 | G11: 30 | H11: 32 | I11: 34 | J11: 35 | K11: 36 | L11: 37 | N11: derived on MarketModel from Patreon members-per-creator
A12: Fan ARPU per month (niche) | B12: EUR | C12: 8 | D12: 8.3 | E12: 8.6 | F12: 8.8 | G12: 9 | H12: 9.1 | I12: 9.2 | J12: 9.3 | K12: 9.4 | L12: 9.5 | N12: derived on MarketModel from our tier mix, cross-checked against Patreon
A13: Fan churn per month (niche) | B13: % | C13: 0.09 | D13: 0.085 | E13: 0.08 | F13: 0.075 | G13: 0.07 | H13: 0.065 | I13: 0.06 | J13: 0.058 | K13: 0.056 | L13: 0.055 | N13: derived on MarketModel from Patreon churn and our annual-plan mix
A14: Athlete churn per year (niche) | B14: % | C14: 0.3 | D14: 0.27 | E14: 0.24 | F14: 0.22 | G14: 0.2 | H14: 0.19 | I14: 0.18 | J14: 0.17 | K14: 0.16 | L14: 0.16
A15: Max new fans per athlete per year (niche) | B15: capacity ceiling | C15: 30 | D15: 33 | E15: 36 | F15: 40 | G15: 43 | H15: 45 | I15: 47 | J15: 49 | K15: 50 | L15: 52 | N15: An audience is finite; without this ceiling higher churn RAISES revenue
A16: Athletes landing a deal (niche) | B16: % of segment | C16: 0.05 | D16: 0.07 | E16: 0.09 | F16: 0.11 | G16: 0.13 | H16: 0.15 | I16: 0.16 | J16: 0.17 | K16: 0.17 | L16: 0.18
A17: Deals per dealing athlete (niche) | B17: count | C17: 1.1 | D17: 1.2 | E17: 1.3 | F17: 1.5 | G17: 1.6 | H17: 1.7 | I17: 1.8 | J17: 1.9 | K17: 1.9 | L17: 2
A18: Average deal value (niche) | B18: EUR | C18: 900 | D18: 1050 | E18: 1200 | F18: 1350 | G18: 1500 | H18: 1600 | I18: 1700 | J18: 1800 | K18: 1900 | L18: 2000
A19: Athlete CAC (niche) | B19: EUR | C19: 16 | D19: 18 | E19: 21 | F19: 24 | G19: 27 | H19: 30 | I19: 32 | J19: 34 | K19: 35 | L19: 36
A21: SEGMENT: POPULAR
A22: Monetising athletes (popular) | B22: % of segment | C22: 0 | D22: 0.17 | E22: 0.2 | F22: 0.23 | G22: 0.26 | H22: 0.28 | I22: 0.3 | J22: 0.31 | K22: 0.32 | L22: 0.32
A23: Paying fans per monetising athlete (popular) | B23: count | C23: 26 | D23: 29 | E23: 32 | F23: 35 | G23: 38 | H23: 41 | I23: 44 | J23: 46 | K23: 47 | L23: 48 | N23: derived on MarketModel from Patreon members-per-creator
A24: Fan ARPU per month (popular) | B24: EUR | C24: 7 | D24: 7.2 | E24: 7.4 | F24: 7.6 | G24: 7.8 | H24: 7.9 | I24: 8 | J24: 8.1 | K24: 8.2 | L24: 8.3 | N24: derived on MarketModel from our tier mix, cross-checked against Patreon
A25: Fan churn per month (popular) | B25: % | C25: 0.13 | D25: 0.125 | E25: 0.12 | F25: 0.11 | G25: 0.105 | H25: 0.1 | I25: 0.09 | J25: 0.088 | K25: 0.086 | L25: 0.085 | N25: derived on MarketModel from Patreon churn and our annual-plan mix
A26: Athlete churn per year (popular) | B26: % | C26: 0.35 | D26: 0.32 | E26: 0.3 | F26: 0.27 | G26: 0.25 | H26: 0.23 | I26: 0.22 | J26: 0.21 | K26: 0.21 | L26: 0.2
A27: Max new fans per athlete per year (popular) | B27: capacity ceiling | C27: 38 | D27: 42 | E27: 46 | F27: 50 | G27: 54 | H27: 58 | I27: 62 | J27: 65 | K27: 67 | L27: 69 | N27: An audience is finite; without this ceiling higher churn RAISES revenue
A28: Athletes landing a deal (popular) | B28: % of segment | C28: 0.14 | D28: 0.17 | E28: 0.2 | F28: 0.24 | G28: 0.27 | H28: 0.29 | I28: 0.3 | J28: 0.31 | K28: 0.31 | L28: 0.32
A29: Deals per dealing athlete (popular) | B29: count | C29: 1.3 | D29: 1.5 | E29: 1.7 | F29: 1.9 | G29: 2.1 | H29: 2.3 | I29: 2.4 | J29: 2.5 | K29: 2.5 | L29: 2.6
A30: Average deal value (popular) | B30: EUR | C30: 2200 | D30: 2500 | E30: 2800 | F30: 3100 | G30: 3400 | H30: 3700 | I30: 4000 | J30: 4200 | K30: 4400 | L30: 4600
A31: Athlete CAC (popular) | B31: EUR | C31: 40 | D31: 46 | E31: 53 | F31: 60 | G31: 67 | H31: 73 | I31: 78 | J31: 82 | K31: 85 | L31: 88
A33: SPONSORS
A34: Registered sponsors | B34: count | C34: 18 | D34: 55 | E34: 125 | F34: 240 | G34: 380 | H34: 510 | I34: 620 | J34: 710 | K34: 790 | L34: 850
A35: Share on a paid plan | B35: % | C35: 0.1 | D35: 0.14 | E35: 0.17 | F35: 0.19 | G35: 0.2 | H35: 0.2 | I35: 0.2 | J35: 0.2 | K35: 0.2 | L35: 0.2
A36: Sponsor plan ARPU per month | B36: EUR | C36: 199 | D36: 229 | E36: 260 | F36: 290 | G36: 320 | H36: 360 | I36: 400 | J36: 430 | K36: 455 | L36: 475
A37: Sponsor CAC | B37: EUR | C37: 900 | D37: 1050 | E37: 1200 | F37: 1400 | G37: 1600 | H37: 1750 | I37: 1900 | J37: 2000 | K37: 2100 | L37: 2200
A39: TAKE RATES & PAYMENT RAILS
A40: Take rate: fan revenue | B40: % | C40: 0.15 | D40: =C40 -> 0.15 | E40: =C40 -> 0.15 | F40: =C40 -> 0.15 | G40: =C40 -> 0.15 | H40: =C40 -> 0.15 | I40: =C40 -> 0.15 | J40: =C40 -> 0.15 | K40: =C40 -> 0.15 | L40: =C40 -> 0.15 | N40: Our pricing decision. OnlyFans/Fansly/Fanfix 20%, Passes 10% + $29/mo
A41: Take rate: sponsorship, base | B41: % | C41: 0.1 | D41: =C41 -> 0.1 | E41: =C41 -> 0.1 | F41: =C41 -> 0.1 | G41: =C41 -> 0.1 | H41: =C41 -> 0.1 | I41: =C41 -> 0.1 | J41: =C41 -> 0.1 | K41: =C41 -> 0.1 | L41: =C41 -> 0.1 | N41: Free and Starter plans. Agents take 10-20% of an endorsement
A42: Take rate: sponsorship, Scout Pro | B42: % | C42: 0.07 | D42: =C42 -> 0.07 | E42: =C42 -> 0.07 | F42: =C42 -> 0.07 | G42: =C42 -> 0.07 | H42: =C42 -> 0.07 | I42: =C42 -> 0.07 | J42: =C42 -> 0.07 | K42: =C42 -> 0.07 | L42: =C42 -> 0.07 | N42: A sponsor paying for the tooling pays less on the deal
A43: Take rate: sponsorship, Scout Agency | B43: % | C43: 0.05 | D43: =C43 -> 0.05 | E43: =C43 -> 0.05 | F43: =C43 -> 0.05 | G43: =C43 -> 0.05 | H43: =C43 -> 0.05 | I43: =C43 -> 0.05 | J43: =C43 -> 0.05 | K43: =C43 -> 0.05 | L43: =C43 -> 0.05 | N43: The most committed tier. Half what an agent charges at the low end
A44: Subscriber deal volume, multiple of average | B44: x | C44: 2 | D44: =C44 -> 2 | E44: =C44 -> 2 | F44: =C44 -> 2 | G44: =C44 -> 2 | H44: =C44 -> 2 | I44: =C44 -> 2 | J44: =C44 -> 2 | K44: =C44 -> 2 | L44: =C44 -> 2 | N44: Subscribers buy campaign capacity, so they run more volume than the average sponsor. The only estimate in the tiering
A45: Scout Starter price | B45: EUR/mo | C45: 99 | D45: =C45 -> 99 | E45: =C45 -> 99 | F45: =C45 -> 99 | G45: =C45 -> 99 | H45: =C45 -> 99 | I45: =C45 -> 99 | J45: =C45 -> 99 | K45: =C45 -> 99 | L45: =C45 -> 99
A46: Scout Pro price | B46: EUR/mo | C46: 249 | D46: =C46 -> 249 | E46: =C46 -> 249 | F46: =C46 -> 249 | G46: =C46 -> 249 | H46: =C46 -> 249 | I46: =C46 -> 249 | J46: =C46 -> 249 | K46: =C46 -> 249 | L46: =C46 -> 249
A47: Scout Agency price | B47: EUR/mo | C47: 999 | D47: =C47 -> 999 | E47: =C47 -> 999 | F47: =C47 -> 999 | G47: =C47 -> 999 | H47: =C47 -> 999 | I47: =C47 -> 999 | J47: =C47 -> 999 | K47: =C47 -> 999 | L47: =C47 -> 999
A48: VAT on fan subscriptions | B48: % | C48: 0.21 | D48: =C48 -> 0.21 | E48: =C48 -> 0.21 | F48: =C48 -> 0.21 | G48: =C48 -> 0.21 | H48: =C48 -> 0.21 | I48: =C48 -> 0.21 | J48: =C48 -> 0.21 | K48: =C48 -> 0.21 | L48: =C48 -> 0.21 | N48: Spain's rate. Fan prices are displayed VAT-inclusive, so the take applies to price/(1+VAT) while the processor charges on the price
A49: PPV & tips as multiple of subs | B49: x | C49: 0.35 | D49: =C49 -> 0.35 | E49: =C49 -> 0.35 | F49: =C49 -> 0.35 | G49: =C49 -> 0.35 | H49: =C49 -> 0.35 | I49: =C49 -> 0.35 | J49: =C49 -> 0.35 | K49: =C49 -> 0.35 | L49: =C49 -> 0.35
A50: PSP percentage fee | B50: % | C50: 0.019 | D50: =C50 -> 0.019 | E50: =C50 -> 0.019 | F50: =C50 -> 0.019 | G50: =C50 -> 0.019 | H50: =C50 -> 0.019 | I50: =C50 -> 0.019 | J50: =C50 -> 0.019 | K50: =C50 -> 0.019 | L50: =C50 -> 0.019 | N50: Stripe published pricing
A51: PSP fixed fee per transaction | B51: EUR | C51: 0.25 | D51: =C51 -> 0.25 | E51: =C51 -> 0.25 | F51: =C51 -> 0.25 | G51: =C51 -> 0.25 | H51: =C51 -> 0.25 | I51: =C51 -> 0.25 | J51: =C51 -> 0.25 | K51: =C51 -> 0.25 | L51: =C51 -> 0.25 | N51: Stripe. The single most damaging cost at small ticket sizes
A52: Payout percentage fee | B52: % | C52: 0.0025 | D52: =C52 -> 0.0025 | E52: =C52 -> 0.0025 | F52: =C52 -> 0.0025 | G52: =C52 -> 0.0025 | H52: =C52 -> 0.0025 | I52: =C52 -> 0.0025 | J52: =C52 -> 0.0025 | K52: =C52 -> 0.0025 | L52: =C52 -> 0.0025 | N52: Stripe Connect
A53: Payout fixed fee | B53: EUR | C53: 0.25 | D53: =C53 -> 0.25 | E53: =C53 -> 0.25 | F53: =C53 -> 0.25 | G53: =C53 -> 0.25 | H53: =C53 -> 0.25 | I53: =C53 -> 0.25 | J53: =C53 -> 0.25 | K53: =C53 -> 0.25 | L53: =C53 -> 0.25 | N53: Stripe Connect
A54: Average fan transaction | B54: EUR | C54: 9.2 | D54: =C54 -> 9.2 | E54: =C54 -> 9.2 | F54: =C54 -> 9.2 | G54: =C54 -> 9.2 | H54: =C54 -> 9.2 | I54: =C54 -> 9.2 | J54: =C54 -> 9.2 | K54: =C54 -> 9.2 | L54: =C54 -> 9.2
A55: Average deal transaction | B55: EUR | C55: 1800 | D55: =C55 -> 1800 | E55: =C55 -> 1800 | F55: =C55 -> 1800 | G55: =C55 -> 1800 | H55: =C55 -> 1800 | I55: =C55 -> 1800 | J55: =C55 -> 1800 | K55: =C55 -> 1800 | L55: =C55 -> 1800
A57: INFRASTRUCTURE & CONTENT COSTS
A58: AWS base cost per month | B58: EUR | C58: 150 | D58: 420 | E58: 1000 | F58: 2000 | G58: 3200 | H58: 4300 | I58: 5300 | J58: 6200 | K58: 7000 | L58: 7800
A59: Media GB per paying fan per month | B59: GB | C59: 1.8 | D59: =C59 -> 1.8 | E59: =C59 -> 1.8 | F59: =C59 -> 1.8 | G59: =C59 -> 1.8 | H59: =C59 -> 1.8 | I59: =C59 -> 1.8 | J59: =C59 -> 1.8 | K59: =C59 -> 1.8 | L59: =C59 -> 1.8
A60: Egress cost per GB (zero-egress CDN) | B60: EUR | C60: 0.008 | D60: =C60 -> 0.008 | E60: =C60 -> 0.008 | F60: =C60 -> 0.008 | G60: =C60 -> 0.008 | H60: =C60 -> 0.008 | I60: =C60 -> 0.008 | J60: =C60 -> 0.008 | K60: =C60 -> 0.008 | L60: =C60 -> 0.008 | N60: Cloudflare R2 / Backblaze B2 list
A61: Egress cost per GB (CloudFront list) | B61: EUR | C61: 0.075 | D61: =C61 -> 0.075 | E61: =C61 -> 0.075 | F61: =C61 -> 0.075 | G61: =C61 -> 0.075 | H61: =C61 -> 0.075 | I61: =C61 -> 0.075 | J61: =C61 -> 0.075 | K61: =C61 -> 0.075 | L61: =C61 -> 0.075 | N61: AWS CloudFront list price: the EUR 1.1M/yr trap
A62: Moderation cost per 1,000 items | B62: EUR | C62: 22 | D62: =C62 -> 22 | E62: =C62 -> 22 | F62: =C62 -> 22 | G62: =C62 -> 22 | H62: =C62 -> 22 | I62: =C62 -> 22 | J62: =C62 -> 22 | K62: =C62 -> 22 | L62: =C62 -> 22
A63: Items per athlete per month | B63: count | C63: 12 | D63: =C63 -> 12 | E63: =C63 -> 12 | F63: =C63 -> 12 | G63: =C63 -> 12 | H63: =C63 -> 12 | I63: =C63 -> 12 | J63: =C63 -> 12 | K63: =C63 -> 12 | L63: =C63 -> 12
A65: PEOPLE & OVERHEAD
A66: Headcount | B66: FTE | C66: =HiringPlan!C12 -> 1 | D66: =HiringPlan!D12 -> 1.5 | E66: =HiringPlan!E12 -> 1.5 | F66: =HiringPlan!F12 -> 2 | G66: =HiringPlan!G12 -> 4 | H66: =HiringPlan!H12 -> 7 | I66: =HiringPlan!I12 -> 10 | J66: =HiringPlan!J12 -> 12.5 | ... L66: =HiringPlan!L12 -> 16
A67: Loaded salary (incl. ~32% employer SS) | B67: EUR | C67: 38000 | D67: 52000 | E67: 60000 | F67: 64000 | G67: 66000 | H67: 68000 | I67: 70000 | J67: 72000 | K67: 74000 | L67: 76000
A68: Markets live | B68: count | C68: 1 | D68: 2 | E68: 2 | F68: 2 | G68: 3 | H68: 4 | I68: 5 | J68: 6 | K68: 6 | L68: 6
A69: Legal: base compliance | B69: EUR/yr | C69: 3600 | D69: 3600 | E69: 3600 | F69: 3600 | G69: 3600 | H69: 3600 | I69: 3600 | J69: 3600 | K69: 3600 | L69: 3600
A70: Legal: base, per extra head | B70: EUR | C70: 900 | D70: 900 | E70: 900 | F70: 900 | G70: 900 | H70: 900 | I70: 900 | J70: 900 | K70: 900 | L70: 900
A71: Legal: incorporation | B71: EUR, Y1 | C71: 2500 | D71: 2500 | E71: 2500 | F71: 2500 | G71: 2500 | H71: 2500 | I71: 2500 | J71: 2500 | K71: 2500 | L71: 2500
A72: Legal: launch pack | B72: EUR, Y1 | C72: 8000 | D72: 8000 | E72: 8000 | F72: 8000 | G72: 8000 | H72: 8000 | I72: 8000 | J72: 8000 | K72: 8000 | L72: 8000
A73: Legal: DAC7 annual | B73: EUR | C73: 2500 | D73: 2500 | E73: 2500 | F73: 2500 | G73: 2500 | H73: 2500 | I73: 2500 | J73: 2500 | K73: 2500 | L73: 2500
A74: Legal: content and DSA | B74: EUR/yr from Y2 | C74: 0 | D74: 6000 | E74: 5400 | F74: 5800 | G74: 6200 | H74: 6600 | I74: 7000 | J74: 7400 | K74: 7800 | L74: 8200
A75: Legal: market entry | B75: EUR per new market | C75: 7000 | D75: 7000 | E75: 7000 | F75: 7000 | G75: 7000 | H75: 7000 | I75: 7000 | J75: 7000 | K75: 7000 | L75: 7000
A76: Legal: VAT and tax per market | B76: EUR/yr | C76: 2500 | D76: 2500 | E76: 2500 | F76: 2500 | G76: 2500 | H76: 2500 | I76: 2500 | J76: 2500 | K76: 2500 | L76: 2500
A77: Legal: round documentation | B77: EUR | C77: 8000 | D77: 10000 | E77: 0 | F77: 0 | G77: 0 | H77: 25000 | I77: 0 | J77: 0 | K77: 0 | L77: 0
A78: Legal: IP | B78: EUR | C78: 6000 | D78: 1500 | E78: 1500 | F78: 1500 | G78: 1500 | H78: 1500 | I78: 1500 | J78: 1500 | K78: 1500 | L78: 1500
... A84: Legal: contingency | B84: on the whole | C84: 0.15 | D84: 0.15 | E84: 0.15 | F84: 0.15 | G84: 0.15 | H84: 0.15 | I84: 0.15 | J84: 0.15 | K84: 0.15 | L84: 0.15
A85: Other opex as % of revenue | B85: % | C85: 0.08 | D85: =C85 -> 0.08 | E85: =C85 -> 0.08 | F85: =C85 -> 0.08 | G85: =C85 -> 0.08 | H85: =C85 -> 0.08 | I85: =C85 -> 0.08 | J85: =C85 -> 0.08 | K85: =C85 -> 0.08 | L85: =C85 -> 0.08
A87: WORKING CAPITAL, CAPEX & TAX
A88: Athlete payout float | B88: days | C88: 15 | D88: =C88 -> 15 | E88: =C88 -> 15 | F88: =C88 -> 15 | G88: =C88 -> 15 | H88: =C88 -> 15 | I88: =C88 -> 15 | J88: =C88 -> 15 | K88: =C88 -> 15 | L88: =C88 -> 15 | N88: We hold fan money before paying athletes, a cash benefit
A89: Sponsor receivable days | B89: days | C89: 45 | D89: =C89 -> 45 | E89: =C89 -> 45 | F89: =C89 -> 45 | G89: =C89 -> 45 | H89: =C89 -> 45 | I89: =C89 -> 45 | J89: =C89 -> 45 | K89: =C89 -> 45 | L89: =C89 -> 45
A90: Trade payable days | B90: days | C90: 30 | D90: =C90 -> 30 | E90: =C90 -> 30 | F90: =C90 -> 30 | G90: =C90 -> 30 | H90: =C90 -> 30 | I90: =C90 -> 30 | J90: =C90 -> 30 | K90: =C90 -> 30 | L90: =C90 -> 30
A91: Capitalised development | B91: % of people cost | C91: 0.3 | D91: =C91 -> 0.3 | E91: =C91 -> 0.3 | F91: =C91 -> 0.3 | G91: =C91 -> 0.3 | H91: =C91 -> 0.3 | I91: =C91 -> 0.3 | J91: =C91 -> 0.3 | K91: =C91 -> 0.3 | L91: =C91 -> 0.3
A92: Amortisation period | B92: years | C92: 3 | D92: =C92 -> 3 | E92: =C92 -> 3 | F92: =C92 -> 3 | G92: =C92 -> 3 | H92: =C92 -> 3 | I92: =C92 -> 3 | J92: =C92 -> 3 | K92: =C92 -> 3 | L92: =C92 -> 3
A93: Corporate tax: startup rate | B93: % | C93: 0.15 | D93: =C93 -> 0.15 | E93: =C93 -> 0.15 | F93: =C93 -> 0.15 | G93: =C93 -> 0.15 | H93: =C93 -> 0.15 | I93: =C93 -> 0.15 | J93: =C93 -> 0.15 | K93: =C93 -> 0.15 | L93: =C93 -> 0.15 | N93: Spanish Startup Law, first 4 profitable years
A94: Corporate tax: standard rate | B94: % | C94: 0.25 | D94: =C94 -> 0.25 | E94: =C94 -> 0.25 | F94: =C94 -> 0.25 | G94: =C94 -> 0.25 | H94: =C94 -> 0.25 | I94: =C94 -> 0.25 | J94: =C94 -> 0.25 | K94: =C94 -> 0.25 | L94: =C94 -> 0.25 | N94: Spanish corporate income tax
A95: Years at startup rate (from first profit) | B95: years | C95: 4 | D95: =C95 -> 4 | E95: =C95 -> 4 | F95: =C95 -> 4 | G95: =C95 -> 4 | H95: =C95 -> 4 | I95: =C95 -> 4 | J95: =C95 -> 4 | K95: =C95 -> 4 | L95: =C95 -> 4
A97: ADMISSION: the gate between an applicant and an athlete
A98: Admission rate: direct applicants | B98: % admitted | C98: 0.2 | D98: =C98 -> 0.2 | E98: =C98 -> 0.2 | F98: =C98 -> 0.2 | G98: =C98 -> 0.2 | H98: =C98 -> 0.2 | I98: =C98 -> 0.2 | J98: =C98 -> 0.2 | K98: =C98 -> 0.2 | L98: =C98 -> 0.2 | N98: ops-load output of scripts/admission_stress.py
A99: Review rate: direct applicants | B99: % needing a human | C99: 0.25 | D99: =C99 -> 0.25 | E99: =C99 -> 0.25 | F99: =C99 -> 0.25 | G99: =C99 -> 0.25 | H99: =C99 -> 0.25 | I99: =C99 -> 0.25 | J99: =C99 -> 0.25 | K99: =C99 -> 0.25 | L99: =C99 -> 0.25 | N99: ops-load output of scripts/admission_stress.py
A100: Admission rate: club-nominated | B100: % admitted | C100: 0.45 | D100: =C100 -> 0.45 | E100: =C100 -> 0.45 | F100: =C100 -> 0.45 | G100: =C100 -> 0.45 | H100: =C100 -> 0.45 | I100: =C100 -> 0.45 | J100: =C100 -> 0.45 | K100: =C100 -> 0.45 | L100: =C100 -> 0.45 | N100: ESTIMATE: a verified club's floor carries more of them past the bar
A101: Review rate: club-nominated | B101: % needing a human | C101: 0.18 | D101: =C101 -> 0.18 | E101: =C101 -> 0.18 | F101: =C101 -> 0.18 | G101: =C101 -> 0.18 | H101: =C101 -> 0.18 | I101: =C101 -> 0.18 | J101: =C101 -> 0.18 | K101: =C101 -> 0.18 | L101: =C101 -> 0.18 | N101: ESTIMATE
A102: Applicants arriving via a club | B102: % of applicants | C102: 0 | D102: 0.1 | E102: 0.2 | F102: 0.28 | G102: 0.34 | H102: 0.38 | I102: 0.42 | J102: 0.44 | K102: 0.46 | L102: 0.47 | N102: Grows as federation and club partnerships land
A103: Minutes per manual review | B103: min | C103: 4 | D103: =C103 -> 4 | E103: =C103 -> 4 | F103: =C103 -> 4 | G103: =C103 -> 4 | H103: =C103 -> 4 | I103: =C103 -> 4 | J103: =C103 -> 4 | K103: =C103 -> 4 | L103: =C103 -> 4 | N103: Open the link, decide whether it names the applicant
A104: Productive hours per reviewer-year | B104: h | C104: 1700 | D104: =C104 -> 1700 | E104: =C104 -> 1700 | F104: =C104 -> 1700 | G104: =C104 -> 1700 | H104: =C104 -> 1700 | I104: =C104 -> 1700 | J104: =C104 -> 1700 | K104: =C104 -> 1700 | L104: =C104 -> 1700 | N104: Prices review time off the same loaded salary line
A106: VALUATION
A107: Mature listed software, Europe, in EUR | B107: % | C107: 0.0601 | D107: =C107 -> 0.0601 | E107: =C107 -> 0.0601 | F107: =C107 -> 0.0601 | G107: =C107 -> 0.0601 | H107: =C107 -> 0.0601 | I107: =C107 -> 0.0601 | J107: =C107 -> 0.0601 | K107: =C107 -> 0.0601 | L107: =C107 -> 0.0601 | N107: Damodaran, NYU Stern, Cost of Capital by Industry (Europe), 5 Jan 2026. 23 listed firms
A108: Spain country risk premium | B108: % | C108: 0.0155 | D108: =C108 -> 0.0155 | E108: =C108 -> 0.0155 | F108: =C108 -> 0.0155 | G108: =C108 -> 0.0155 | H108: =C108 -> 0.0155 | I108: =C108 -> 0.0155 | J108: =C108 -> 0.0155 | K108: =C108 -> 0.0155 | L108: =C108 -> 0.0155 | N108: Damodaran, country risk premiums, 5 Jan 2026. The sector figure above is pan-European; the company is Spanish
A109: Size and stage premium | B109: % | C109: 0.1744 | D109: =C109 -> 0.1744 | E109: =C109 -> 0.1744 | F109: =C109 -> 0.1744 | G109: =C109 -> 0.1744 | H109: =C109 -> 0.1744 | I109: =C109 -> 0.1744 | J109: =C109 -> 0.1744 | K109: =C109 -> 0.1744 | L109: =C109 -> 0.1744 | N109: NOT SOURCED. A pre-revenue company with one product and no operating history does not finance itself at a listed company's cost of capital. Convention puts early-stage venture at 20-35% all-in. The largest single judgement in the valuation
A110: WACC / discount rate | B110: % | C110: =C107+C108+C109 -> 0.25 | D110: =D107+D108+D109 -> 0.25 | E110: =E107+E108+E109 -> 0.25 | F110: =F107+F108+F109 -> 0.25 | G110: =G107+G108+G109 -> 0.25 | H110: =H107+H108+H109 -> 0.25 | I110: =I107+I108+I109 -> 0.25 | J110: =J107+J108+J109 -> 0.25 | ... L110: =L107+L108+L109 -> 0.25 | N110: The sum of the three rows above. Trace precedents from here to see which parts are published and which is judgement
A111: Terminal growth | B111: % | C111: 0.03 | D111: =C111 -> 0.03 | E111: =C111 -> 0.03 | F111: =C111 -> 0.03 | G111: =C111 -> 0.03 | H111: =C111 -> 0.03 | I111: =C111 -> 0.03 | J111: =C111 -> 0.03 | K111: =C111 -> 0.03 | L111: =C111 -> 0.03
A112: Exit revenue multiple | B112: x | C112: 6.5 | D112: =C112 -> 6.5 | E112: =C112 -> 6.5 | F112: =C112 -> 6.5 | G112: =C112 -> 6.5 | H112: =C112 -> 6.5 | I112: =C112 -> 6.5 | J112: =C112 -> 6.5 | K112: =C112 -> 6.5 | L112: =C112 -> 6.5 | N112: Blended marketplace + SaaS comparables
A113: Risk-free rate (Spanish 10Y) | B113: % | C113: 0.032 | D113: =C113 -> 0.032 | E113: =C113 -> 0.032 | F113: =C113 -> 0.032 | G113: =C113 -> 0.032 | H113: =C113 -> 0.032 | I113: =C113 -> 0.032 | J113: =C113 -> 0.032 | K113: =C113 -> 0.032 | L113: =C113 -> 0.032 | N113: Spanish 10Y government bond, mid-2026
A114: Founder alternative return | B114: % | C114: 0.07 | D114: =C114 -> 0.07 | E114: =C114 -> 0.07 | F114: =C114 -> 0.07 | G114: =C114 -> 0.07 | H114: =C114 -> 0.07 | I114: =C114 -> 0.07 | J114: =C114 -> 0.07 | K114: =C114 -> 0.07 | L114: =C114 -> 0.07

Sheet Drivers
A1: Drivers: Growth Assumptions
A2: Line | B2: Unit | C2: Y1 | D2: Y2 | E2: Y3 | F2: Y4 | G2: Y5 | H2: Y6 | I2: Y7 | J2: Y8 | K2: Y9 | L2: Y10
A4: ATHLETES
A5: Total athletes (year end) | C5: =Assumptions!C5 -> 250 | D5: =Assumptions!D5 -> 750 | E5: =Assumptions!E5 -> 1700 | F5: =Assumptions!F5 -> 2800 | G5: =Assumptions!G5 -> 4000 | H5: =Assumptions!H5 -> 5200 | I5: =Assumptions!I5 -> 6300 | J5: =Assumptions!J5 -> 7200 | ... L5: =Assumptions!L5 -> 8500
A6: Niche athletes | C6: =Drivers!C5*Assumptions!C6 -> 237.5 | D6: =Drivers!D5*Assumptions!D6 -> 690 | E6: =Drivers!E5*Assumptions!E6 -> 1360 | F6: =Drivers!F5*Assumptions!F6 -> 1904 | G6: =Drivers!G5*Assumptions!G6 -> 2320 | H6: =Drivers!H5*Assumptions!H6 -> 2600 | I6: =Drivers!I5*Assumptions!I6 -> 2835 | J6: =Drivers!J5*Assumptions!J6 -> 3096 | ... L6: =Drivers!L5*Assumptions!L6 -> 3485
A7: Popular athletes | C7: =Drivers!C5-Drivers!C6 -> 12.5 | D7: =Drivers!D5-Drivers!D6 -> 60 | E7: =Drivers!E5-Drivers!E6 -> 340 | F7: =Drivers!F5-Drivers!F6 -> 896 | G7: =Drivers!G5-Drivers!G6 -> 1680 | H7: =Drivers!H5-Drivers!H6 -> 2600 | I7: =Drivers!I5-Drivers!I6 -> 3465 | J7: =Drivers!J5-Drivers!J6 -> 4104 | ... L7: =Drivers!L5-Drivers!L6 -> 5015
A9: NICHE: fans and churn
A10: Niche athletes lost to churn | C10: =IF(1=1,0,C6*Assumptions!C14) -> 0 | D10: =IF(2=1,0,C6*Assumptions!D14) -> 64.125 | E10: =IF(3=1,0,D6*Assumptions!E14) -> 165.6 | F10: =IF(4=1,0,E6*Assumptions!F14) -> 299.2 | G10: =IF(5=1,0,F6*Assumptions!G14) -> 380.8 | H10: =IF(6=1,0,G6*Assumptions!H14) -> 440.8 | I10: =IF(7=1,0,H6*Assumptions!I14) -> 468 | J10: =IF(8=1,0,I6*Assumptions!J14) -> 481.95 | K10: =IF(9=1,0,J6*Assumptions!K14) -> 495.36 | L10: =IF(10=1,0,K6*Assumptions!L14) -> 530.88
A11: Niche athletes acquired (gross) | C11: =MAX(0,C6-IF(1=1,0,C6)+C10) -> 237.5 | D11: =MAX(0,D6-IF(2=1,0,C6)+D10) -> 516.625 | E11: =MAX(0,E6-IF(3=1,0,D6)+E10) -> 835.6 | F11: =MAX(0,F6-IF(4=1,0,E6)+F10) -> 843.2 | G11: =MAX(0,G6-IF(5=1,0,F6)+G10) -> 796.8 | H11: =MAX(0,H6-IF(6=1,0,G6)+H10) -> 720.8 | I11: =MAX(0,I6-IF(7=1,0,H6)+I10) -> 703 | J11: =MAX(0,J6-IF(8=1,0,I6)+J10) -> 742.95 | K11: =MAX(0,K6-IF(9=1,0,J6)+K10) -> 717.36 | L11: =MAX(0,L6-IF(10=1,0,K6)+L10) -> 697.88
A12: Niche monetising athletes | C12: =C6*Assumptions!C10 -> 0 | D12: =D6*Assumptions!D10 -> 220.8 | E12: =E6*Assumptions!E10 -> 503.2 | F12: =F6*Assumptions!F10 -> 780.64 | G12: =G6*Assumptions!G10 -> 1020.8 | H12: =H6*Assumptions!H10 -> 1196 | I12: =I6*Assumptions!I10 -> 1360.8 | J12: =J6*Assumptions!J10 -> 1517.04 | ... L12: =L6*Assumptions!L10 -> 1742.5
A13: Niche paying fans (target, year end) | C13: =C12*Assumptions!C11 -> 0 | D13: =D12*Assumptions!D11 -> 4857.6 | E13: =E12*Assumptions!E11 -> 12580 | F13: =F12*Assumptions!F11 -> 21857.92 | G13: =G12*Assumptions!G11 -> 30624 | H13: =H12*Assumptions!H11 -> 38272 | I13: =I12*Assumptions!I11 -> 46267.2 | J13: =J12*Assumptions!J11 -> 53096.4 | ... L13: =L12*Assumptions!L11 -> 64472.5
A14: Niche monthly retention r = 1-churn | B14: factor | C14: =1-Assumptions!C13 -> 0.91 | D14: =1-Assumptions!D13 -> 0.915 | E14: =1-Assumptions!E13 -> 0.92 | F14: =1-Assumptions!F13 -> 0.925 | G14: =1-Assumptions!G13 -> 0.93 | H14: =1-Assumptions!H13 -> 0.935 | I14: =1-Assumptions!I13 -> 0.94 | J14: =1-Assumptions!J13 -> 0.942 | ... L14: =1-Assumptions!L13 -> 0.945
A15: Niche opening fans survived 12 months | B15: open x r^12 | C15: =0 -> 0 | D15: =C17*D14^12 -> 0 | E15: =D17*E14^12 -> 1721.9121 | F15: =E17*F14^12 -> 4936.0714 | G15: =F17*G14^12 -> 9149.6444 | H15: =G17*H14^12 -> 13671.03 | I15: =H17*I14^12 -> 18214.422 | J15: =I17*J14^12 -> 22588.326 | K15: =J17*K14^12 -> 26590.653 | L15: =K17*L14^12 -> 30292.184
A16: Niche monthly gross adds | B16: solved, then capped by capacity | C16: =MIN(MAX(0,(C13-C15)/((1-C14^12)/(1-C14))),C12*Assumptions!C15/12) -> 0 | D16: =MIN(MAX(0,(D13-D15)/((1-D14^12)/(1-D14))),D12*Assumptions!D15/12) -> 607.2 | E16: =MIN(MAX(0,(E13-E15)/((1-E14^12)/(1-E14))),E12*Assumptions!E15/12) -> 1373.7164 | F16: =MIN(MAX(0,(F13-F15)/((1-F14^12)/(1-F14))),F12*Assumptions!F15/12) -> 2088.6857 | G16: =MIN(MAX(0,(G13-G15)/((1-G14^12)/(1-G14))),G12*Assumptions!G15/12) -> 2585.4753 | H16: =MIN(MAX(0,(H13-H15)/((1-H14^12)/(1-H14))),H12*Assumptions!H15/12) -> 2888.5621 | I16: =MIN(MAX(0,(I13-I15)/((1-I14^12)/(1-I14))),I12*Assumptions!I15/12) -> 3211.6617 | J16: =MIN(MAX(0,(J13-J15)/((1-J14^12)/(1-J14))),J12*Assumptions!J15/12) -> 3457.4424 | ... L16: =MIN(MAX(0,(L13-L15)/((1-L14^12)/(1-L14))),L12*Assumptions!L15/12) -> 3814.7896
A17: Niche paying fans (year end) | B17: survivors + capped adds | C17: =C15+C16*(1-C14^12)/(1-C14) -> 0 | D17: =D15+D16*(1-D14^12)/(1-D14) -> 4683.3546 | E17: =E15+E16*(1-E14^12)/(1-E14) -> 12580 | F17: =F15+F16*(1-F14^12)/(1-F14) -> 21857.92 | G17: =G15+G16*(1-G14^12)/(1-G14) -> 30624 | H17: =H15+H16*(1-H14^12)/(1-H14) -> 38272 | I17: =I15+I16*(1-I14^12)/(1-I14) -> 46267.2 | J17: =J15+J16*(1-J14^12)/(1-J14) -> 53096.4 | ... L17: =L15+L16*(1-L14^12)/(1-L14) -> 64472.5
A18: Niche fans acquired (gross) | B18: x12 months | C18: =C16*12 -> 0 | D18: =D16*12 -> 7286.4 | E18: =E16*12 -> 16484.596 | F18: =F16*12 -> 25064.228 | G18: =G16*12 -> 31025.703 | H18: =H16*12 -> 34662.746 | I18: =I16*12 -> 38539.941 | J18: =J16*12 -> 41489.309 | ... L18: =L16*12 -> 45777.475
A19: Niche S = r(1-r^12)/(1-r) | B19: geometric sum | C19: =C14*(1-C14^12)/(1-C14) -> 6.8505256 | D19: =D14*(1-D14^12)/(1-D14) -> 7.0574267 | E19: =E14*(1-E14^12)/(1-E14) -> 7.2718365 | F19: =F14*(1-F14^12)/(1-F14) -> 7.4940476 | G19: =G14*(1-G14^12)/(1-G14) -> 7.7243635 | H19: =H14*(1-H14^12)/(1-H14) -> 7.9630992 | I19: =I14*(1-I14^12)/(1-I14) -> 8.2105817 | J19: =J14*(1-J14^12)/(1-J14) -> 8.3120995 | ... L19: =L14*(1-L14^12)/(1-L14) -> 8.4671507
A20: Niche average fans during year | B20: exact mean, revenue basis | C20: =(C16/(1-C14)*(12-C19))/12 -> 0 | D20: =(C17*D19+D16/(1-D14)*(12-D19))/12 -> 2942.2848 | E20: =(D17*E19+E16/(1-E14)*(12-E19))/12 -> 9603.8361 | F20: =(E17*F19+F16/(1-F14)*(12-F19))/12 -> 18313.502 | G20: =(F17*G19+G16/(1-G14)*(12-G19))/12 -> 27230.058 | H20: =(G17*H19+H16/(1-H14)*(12-H19))/12 -> 35271.623 | I20: =(H17*I19+I16/(1-I14)*(12-I19))/12 -> 43089.518 | J20: =(I17*J19+J16/(1-J14)*(12-J19))/12 -> 50368.107 | K20: =(J17*K19+K16/(1-K14)*(12-K19))/12 -> 57062.63 | L20: =(K17*L19+L16/(1-L14)*(12-L19))/12 -> 62560.822
A21: Niche fans lost to churn | B21: opening + gross adds - closing | C21: =C18-C17 -> 0 | D21: =C17+D18-D17 -> 2603.0454 | E21: =D17+E18-E17 -> 8587.951 | F21: =E17+F18-F17 -> 15786.308 | G21: =F17+G18-G17 -> 22259.623 | H21: =G17+H18-H17 -> 27014.746 | I21: =H17+I18-I17 -> 30544.741 | J21: =I17+J18-J17 -> 34660.109 | K21: =J17+K18-K17 -> 37974.942 | L21: =K17+L18-L17 -> 41028.975
A23: POPULAR: fans and churn
A24: Popular athletes lost to churn | C24: =IF(1=1,0,C7*Assumptions!C26) -> 0 | D24: =IF(2=1,0,C7*Assumptions!D26) -> 4 | E24: =IF(3=1,0,D7*Assumptions!E26) -> 18 | F24: =IF(4=1,0,E7*Assumptions!F26) -> 91.8 | G24: =IF(5=1,0,F7*Assumptions!G26) -> 224 | H24: =IF(6=1,0,G7*Assumptions!H26) -> 386.4 | I24: =IF(7=1,0,H7*Assumptions!I26) -> 572 | J24: =IF(8=1,0,I7*Assumptions!J26) -> 727.65 | K24: =IF(9=1,0,J7*Assumptions!K26) -> 861.84 | L24: =IF(10=1,0,K7*Assumptions!L26) -> 916.4
A25: Popular athletes acquired (gross) | C25: =MAX(0,C7-IF(1=1,0,C7)+C24) -> 12.5 | D25: =MAX(0,D7-IF(2=1,0,C7)+D24) -> 51.5 | E25: =MAX(0,E7-IF(3=1,0,D7)+E24) -> 298 | F25: =MAX(0,F7-IF(4=1,0,E7)+F24) -> 647.8 | G25: =MAX(0,G7-IF(5=1,0,F7)+G24) -> 1008 | H25: =MAX(0,H7-IF(6=1,0,G7)+H24) -> 1306.4 | I25: =MAX(0,I7-IF(7=1,0,H7)+I24) -> 1437 | J25: =MAX(0,J7-IF(8=1,0,I7)+J24) -> 1366.65 | K25: =MAX(0,K7-IF(9=1,0,J7)+K24) -> 1339.84 | L25: =MAX(0,L7-IF(10=1,0,K7)+L24) -> 1349.4
A26: Popular monetising athletes | C26: =C7*Assumptions!C22 -> 0 | D26: =D7*Assumptions!D22 -> 10.2 | E26: =E7*Assumptions!E22 -> 68 | F26: =F7*Assumptions!F22 -> 206.08 | G26: =G7*Assumptions!G22 -> 436.8 | H26: =H7*Assumptions!H22 -> 728 | I26: =I7*Assumptions!I22 -> 1039.5 | J26: =J7*Assumptions!J22 -> 1272.24 | ... L26: =L7*Assumptions!L22 -> 1604.8
A27: Popular paying fans (target, year end) | C27: =C26*Assumptions!C23 -> 0 | D27: =D26*Assumptions!D23 -> 295.8 | E27: =E26*Assumptions!E23 -> 2176 | F27: =F26*Assumptions!F23 -> 7212.8 | G27: =G26*Assumptions!G23 -> 16598.4 | H27: =H26*Assumptions!H23 -> 29848 | I27: =I26*Assumptions!I23 -> 45738 | J27: =J26*Assumptions!J23 -> 58523.04 | ... L27: =L26*Assumptions!L23 -> 77030.4
A28: Popular monthly retention r = 1-churn | B28: factor | C28: =1-Assumptions!C25 -> 0.87 | D28: =1-Assumptions!D25 -> 0.875 | E28: =1-Assumptions!E25 -> 0.88 | F28: =1-Assumptions!F25 -> 0.89 | G28: =1-Assumptions!G25 -> 0.895 | H28: =1-Assumptions!H25 -> 0.9 | I28: =1-Assumptions!I25 -> 0.91 | J28: =1-Assumptions!J25 -> 0.912 | ... L28: =1-Assumptions!L25 -> 0.915
A29: Popular opening fans survived 12 months | B29: open x r^12 | C29: =0 -> 0 | D29: =C31*D28^12 -> 0 | E29: =D31*E28^12 -> 49.18925 | F29: =E31*F28^12 -> 432.95585 | G29: =F31*G28^12 -> 1667.1482 | H29: =G31*H28^12 -> 4361.2674 | I29: =H31*I28^12 -> 9548.5573 | J29: =I31*J28^12 -> 15143.115 | K29: =J31*K28^12 -> 19892.127 | L29: =K31*L28^12 -> 23733.186
A30: Popular monthly gross adds | B30: solved, then capped by capacity | C30: =MIN(MAX(0,(C27-C29)/((1-C28^12)/(1-C28))),C26*Assumptions!C27/12) -> 0 | D30: =MIN(MAX(0,(D27-D29)/((1-D28^12)/(1-D28))),D26*Assumptions!D27/12) -> 35.7 | E30: =MIN(MAX(0,(E27-E29)/((1-E28^12)/(1-E28))),E26*Assumptions!E27/12) -> 260.66667 | F30: =MIN(MAX(0,(F27-F29)/((1-F28^12)/(1-F28))),F26*Assumptions!F27/12) -> 858.66667 | G30: =MIN(MAX(0,(G27-G29)/((1-G28^12)/(1-G28))),G26*Assumptions!G27/12) -> 1965.6 | H30: =MIN(MAX(0,(H27-H29)/((1-H28^12)/(1-H28))),H26*Assumptions!H27/12) -> 3518.6667 | I30: =MIN(MAX(0,(I27-I29)/((1-I28^12)/(1-I28))),I26*Assumptions!I27/12) -> 4807.2797 | J30: =MIN(MAX(0,(J27-J29)/((1-J28^12)/(1-J28))),J26*Assumptions!J27/12) -> 5706.8941 | ... L30: =MIN(MAX(0,(L27-L29)/((1-L28^12)/(1-L28))),L26*Assumptions!L27/12) -> 6910.0187
A31: Popular paying fans (year end) | B31: survivors + capped adds | C31: =C29+C30*(1-C28^12)/(1-C28) -> 0 | D31: =D29+D30*(1-D28^12)/(1-D28) -> 228.07524 | E31: =E29+E30*(1-E28^12)/(1-E28) -> 1752.9258 | F31: =F29+F30*(1-F28^12)/(1-F28) -> 6310.9944 | G31: =G29+G30*(1-G28^12)/(1-G28) -> 15441.966 | H31: =H29+H30*(1-H28^12)/(1-H28) -> 29610.18 | I31: =I29+I30*(1-I28^12)/(1-I28) -> 45738 | J31: =J29+J30*(1-J28^12)/(1-J28) -> 58523.04 | ... L31: =L29+L30*(1-L28^12)/(1-L28) -> 77030.4
A32: Popular fans acquired (gross) | B32: x12 months | C32: =C30*12 -> 0 | D32: =D30*12 -> 428.4 | E32: =E30*12 -> 3128 | F32: =F30*12 -> 10304 | G32: =G30*12 -> 23587.2 | H32: =H30*12 -> 42224 | I32: =I30*12 -> 57687.357 | J32: =J30*12 -> 68482.729 | ... L32: =L30*12 -> 82920.225
A33: Popular S = r(1-r^12)/(1-r) | B33: geometric sum | C33: =C28*(1-C28^12)/(1-C28) -> 5.4339418 | D33: =D28*(1-D28^12)/(1-D28) -> 5.5900793 | E33: =E28*(1-E28^12)/(1-E28) -> 5.7517449 | F33: =F28*(1-F28^12)/(1-F28) -> 6.0925322 | G33: =G28*(1-G28^12)/(1-G28) -> 6.2721114 | H33: =H28*(1-H28^12)/(1-H28) -> 6.4581342 | I33: =I28*(1-I28^12)/(1-I28) -> 6.8505256 | J33: =J28*(1-J28^12)/(1-J28) -> 6.9324032 | ... L33: =L28*(1-L28^12)/(1-L28) -> 7.0574267
A34: Popular average fans during year | B34: exact mean, revenue basis | C34: =(C30/(1-C28)*(12-C33))/12 -> 0 | D34: =(C31*D33+D30/(1-D28)*(12-D33))/12 -> 152.55611 | E34: =(D31*E33+E30/(1-E28)*(12-E33))/12 -> 1240.3691 | F34: =(E31*F33+F30/(1-F28)*(12-F33))/12 -> 4732.8174 | G34: =(F31*G33+G30/(1-G28)*(12-G33))/12 -> 12234.111 | H34: =(G31*H33+H30/(1-H28)*(12-H33))/12 -> 24560.506 | I34: =(H31*I33+I30/(1-I28)*(12-I33))/12 -> 39825.037 | J34: =(I31*J33+J30/(1-J28)*(12-J33))/12 -> 53809.444 | K34: =(J31*K33+K30/(1-K28)*(12-K33))/12 -> 65061.294 | L34: =(K31*L33+L30/(1-L28)*(12-L33))/12 -> 74012.804
A35: Popular fans lost to churn | B35: opening + gross adds - closing | C35: =C32-C31 -> 0 | D35: =C31+D32-D31 -> 200.32476 | E35: =D31+E32-E31 -> 1603.1494 | F35: =E31+F32-F31 -> 5745.9314 | G35: =F31+G32-G31 -> 14456.228 | H35: =G31+H32-H31 -> 28055.786 | I35: =H31+I32-I31 -> 41559.537 | J35: =I31+J32-J31 -> 55697.689 | K35: =J31+K32-K31 -> 66249.694 | L35: =K31+L32-L31 -> 74803.105
A37: TOTALS
A38: Paying fans (year end) | C38: =C17+C31 -> 0 | D38: =D17+D31 -> 4911.4298 | E38: =E17+E31 -> 14332.926 | F38: =F17+F31 -> 28168.914 | G38: =G17+G31 -> 46065.966 | H38: =H17+H31 -> 67882.18 | I38: =I17+I31 -> 92005.2 | J38: =J17+J31 -> 111619.44 | ... L38: =L17+L31 -> 141502.9
A39: Average paying fans | C39: =C20+C34 -> 0 | D39: =D20+D34 -> 3094.8409 | E39: =E20+E34 -> 10844.205 | F39: =F20+F34 -> 23046.32 | G39: =G20+G34 -> 39464.169 | H39: =H20+H34 -> 59832.129 | I39: =I20+I34 -> 82914.555 | J39: =J20+J34 -> 104177.55 | ... L39: =L20+L34 -> 136573.63
A40: Athletes acquired (gross) | C40: =C11+C25 -> 250 | D40: =D11+D25 -> 568.125 | E40: =E11+E25 -> 1133.6 | F40: =F11+F25 -> 1491 | G40: =G11+G25 -> 1804.8 | H40: =H11+H25 -> 2027.2 | I40: =I11+I25 -> 2140 | J40: =J11+J25 -> 2109.6 | ... L40: =L11+L25 -> 2047.28
A41: Fans lost to churn | C41: =C21+C35 -> 0 | D41: =D21+D35 -> 2803.3702 | E41: =E21+E35 -> 10191.1 | F41: =F21+F35 -> 21532.239 | G41: =G21+G35 -> 36715.851 | H41: =H21+H35 -> 55070.532 | I41: =I21+I35 -> 72104.277 | J41: =J21+J35 -> 90357.799 | ... L41: =L21+L35 -> 115832.08
A43: DEALS
A44: Niche deals | C44: =C6*Assumptions!C16*Assumptions!C17 -> 13.0625 | D44: =D6*Assumptions!D16*Assumptions!D17 -> 57.96 | E44: =E6*Assumptions!E16*Assumptions!E17 -> 159.12 | F44: =F6*Assumptions!F16*Assumptions!F17 -> 314.16 | G44: =G6*Assumptions!G16*Assumptions!G17 -> 482.56 | H44: =H6*Assumptions!H16*Assumptions!H17 -> 663 | I44: =I6*Assumptions!I16*Assumptions!I17 -> 816.48 | J44: =J6*Assumptions!J16*Assumptions!J17 -> 1000.008 | ... L44: =L6*Assumptions!L16*Assumptions!L17 -> 1254.6
A45: Popular deals | C45: =C7*Assumptions!C28*Assumptions!C29 -> 2.275 | D45: =D7*Assumptions!D28*Assumptions!D29 -> 15.3 | E45: =E7*Assumptions!E28*Assumptions!E29 -> 115.6 | F45: =F7*Assumptions!F28*Assumptions!F29 -> 408.576 | G45: =G7*Assumptions!G28*Assumptions!G29 -> 952.56 | H45: =H7*Assumptions!H28*Assumptions!H29 -> 1734.2 | I45: =I7*Assumptions!I28*Assumptions!I29 -> 2494.8 | J45: =J7*Assumptions!J28*Assumptions!J29 -> 3180.6 | ... L45: =L7*Assumptions!L28*Assumptions!L29 -> 4172.48
A46: Total deals | C46: =C44+C45 -> 15.3375 | D46: =D44+D45 -> 73.26 | E46: =E44+E45 -> 274.72 | F46: =F44+F45 -> 722.736 | G46: =G44+G45 -> 1435.12 | H46: =H44+H45 -> 2397.2 | I46: =I44+I45 -> 3311.28 | J46: =J44+J45 -> 4180.608 | ... L46: =L44+L45 -> 5427.08
A47: Supply factor | B47: athletes / floor, capped at 1 | C47: =MIN(1,C5/Assumptions!C7) -> 0.125 | D47: =MIN(1,D5/Assumptions!D7) -> 0.375 | E47: =MIN(1,E5/Assumptions!E7) -> 0.85 | F47: =MIN(1,F5/Assumptions!F7) -> 1 | G47: =MIN(1,G5/Assumptions!G7) -> 1 | H47: =MIN(1,H5/Assumptions!H7) -> 1 | I47: =MIN(1,I5/Assumptions!I7) -> 1 | J47: =MIN(1,J5/Assumptions!J7) -> 1 | ... L47: =MIN(1,L5/Assumptions!L7) -> 1
A48: Paying sponsors | C48: =Assumptions!C34*Assumptions!C35*C47 -> 0.225 | D48: =Assumptions!D34*Assumptions!D35*D47 -> 2.8875 | E48: =Assumptions!E34*Assumptions!E35*E47 -> 18.0625 | F48: =Assumptions!F34*Assumptions!F35*F47 -> 45.6 | G48: =Assumptions!G34*Assumptions!G35*G47 -> 76 | H48: =Assumptions!H34*Assumptions!H35*H47 -> 102 | I48: =Assumptions!I34*Assumptions!I35*I47 -> 124 | J48: =Assumptions!J34*Assumptions!J35*J47 -> 142 | ... L48: =Assumptions!L34*Assumptions!L35*L47 -> 170
A49: Sponsors acquired (gross) | C49: =MAX(0,Assumptions!C34-IF(1=1,0,Assumptions!C34)) -> 18 | D49: =MAX(0,Assumptions!D34-IF(2=1,0,Assumptions!C34)) -> 37 | E49: =MAX(0,Assumptions!E34-IF(3=1,0,Assumptions!D34)) -> 70 | F49: =MAX(0,Assumptions!F34-IF(4=1,0,Assumptions!E34)) -> 115 | G49: =MAX(0,Assumptions!G34-IF(5=1,0,Assumptions!F34)) -> 140 | H49: =MAX(0,Assumptions!H34-IF(6=1,0,Assumptions!G34)) -> 130 | I49: =MAX(0,Assumptions!I34-IF(7=1,0,Assumptions!H34)) -> 110 | J49: =MAX(0,Assumptions!J34-IF(8=1,0,Assumptions!I34)) -> 90 | K49: =MAX(0,Assumptions!K34-IF(9=1,0,Assumptions!J34)) -> 80 | L49: =MAX(0,Assumptions!L34-IF(10=1,0,Assumptions!K34)) -> 60
A51: ADMISSION FUNNEL
A52: Blended admission rate | B52: weighted by channel | C52: =Assumptions!C102*Assumptions!C100+(1-Assumptions!C102)*Assumptions!C98 -> 0.2 | D52: =Assumptions!D102*Assumptions!D100+(1-Assumptions!D102)*Assumptions!D98 -> 0.225 | E52: =Assumptions!E102*Assumptions!E100+(1-Assumptions!E102)*Assumptions!E98 -> 0.25 | F52: =Assumptions!F102*Assumptions!F100+(1-Assumptions!F102)*Assumptions!F98 -> 0.27 | G52: =Assumptions!G102*Assumptions!G100+(1-Assumptions!G102)*Assumptions!G98 -> 0.285 | H52: =Assumptions!H102*Assumptions!H100+(1-Assumptions!H102)*Assumptions!H98 -> 0.295 | I52: =Assumptions!I102*Assumptions!I100+(1-Assumptions!I102)*Assumptions!I98 -> 0.305 | J52: =Assumptions!J102*Assumptions!J100+(1-Assumptions!J102)*Assumptions!J98 -> 0.31 | ... L52: =Assumptions!L102*Assumptions!L100+(1-Assumptions!L102)*Assumptions!L98 -> 0.3175
A53: Blended review rate | B53: weighted by channel | C53: =Assumptions!C102*Assumptions!C101+(1-Assumptions!C102)*Assumptions!C99 -> 0.25 | D53: =Assumptions!D102*Assumptions!D101+(1-Assumptions!D102)*Assumptions!D99 -> 0.243 | E53: =Assumptions!E102*Assumptions!E101+(1-Assumptions!E102)*Assumptions!E99 -> 0.236 | F53: =Assumptions!F102*Assumptions!F101+(1-Assumptions!F102)*Assumptions!F99 -> 0.2304 | G53: =Assumptions!G102*Assumptions!G101+(1-Assumptions!G102)*Assumptions!G99 -> 0.2262 | H53: =Assumptions!H102*Assumptions!H101+(1-Assumptions!H102)*Assumptions!H99 -> 0.2234 | I53: =Assumptions!I102*Assumptions!I101+(1-Assumptions!I102)*Assumptions!I99 -> 0.2206 | J53: =Assumptions!J102*Assumptions!J101+(1-Assumptions!J102)*Assumptions!J99 -> 0.2192 | ... L53: =Assumptions!L102*Assumptions!L101+(1-Assumptions!L102)*Assumptions!L99 -> 0.2171
A54: Applications required | B54: gross adds / admission rate | C54: =C40/C52 -> 1250 | D54: =D40/D52 -> 2525 | E54: =E40/E52 -> 4534.4 | F54: =F40/F52 -> 5522.2222 | G54: =G40/G52 -> 6332.6316 | H54: =H40/H52 -> 6871.8644 | I54: =I40/I52 -> 7016.3934 | J54: =J40/J52 -> 6805.1613 | ... L54: =L40/L52 -> 6448.126
A55: Manual reviews | B55: applications x review rate | C55: =C54*C53 -> 312.5 | D55: =D54*D53 -> 613.575 | E55: =E54*E53 -> 1070.1184 | F55: =F54*F53 -> 1272.32 | G55: =G54*G53 -> 1432.4413 | H55: =H54*H53 -> 1535.1745 | I55: =I54*I53 -> 1547.8164 | J55: =J54*J53 -> 1491.6914 | ... L55: =L54*L53 -> 1399.8882
A56: Reviewer FTE implied | B56: the real constraint, not the euros | C56: =C55*Assumptions!C103/60/Assumptions!C104 -> 0.012254902 | D56: =D55*Assumptions!D103/60/Assumptions!D104 -> 0.024061765 | E56: =E55*Assumptions!E103/60/Assumptions!E104 -> 0.041965427 | F56: =F55*Assumptions!F103/60/Assumptions!F104 -> 0.049894902 | G56: =G55*Assumptions!G103/60/Assumptions!G104 -> 0.056174167 | H56: =H55*Assumptions!H103/60/Assumptions!H104 -> 0.060202922 | I56: =I55*Assumptions!I103/60/Assumptions!I104 -> 0.060698682 | J56: =J55*Assumptions!J103/60/Assumptions!J104 -> 0.0584977 | ... L56: =L55*Assumptions!L103/60/Assumptions!L104 -> 0.054897575

Sheet Revenue
A1: Revenue: Stream by stream breakdown
A2: Line | B2: Unit | C2: Y1 | D2: Y2 | E2: Y3 | F2: Y4 | G2: Y5 | H2: Y6 | I2: Y7 | J2: Y8 | K2: Y9 | L2: Y10
A4: FAN GMV: what fans pay athletes, net of VAT
A5: Niche subscription GMV | B5: avg fans x ARPU x 12, ex-VAT | C5: =Drivers!C20*Assumptions!C12*12/(1+Assumptions!C48) -> 0 | D5: =Drivers!D20*Assumptions!D12*12/(1+Assumptions!D48) -> 242191.38 | E5: =Drivers!E20*Assumptions!E12*12/(1+Assumptions!E48) -> 819104.04 | F5: =Drivers!F20*Assumptions!F12*12/(1+Assumptions!F48) -> 1598269.3 | G5: =Drivers!G20*Assumptions!G12*12/(1+Assumptions!G48) -> 2430451.5 | H5: =Drivers!H20*Assumptions!H12*12/(1+Assumptions!H48) -> 3183191.1 | I5: =Drivers!I20*Assumptions!I12*12/(1+Assumptions!I48) -> 3931473.3 | J5: =Drivers!J20*Assumptions!J12*12/(1+Assumptions!J48) -> 4645521.3 | ... L5: =Drivers!L20*Assumptions!L12*12/(1+Assumptions!L48) -> 5894160.1
A6: Popular subscription GMV | B6: ex-VAT | C6: =Drivers!C34*Assumptions!C24*12/(1+Assumptions!C48) -> 0 | D6: =Drivers!D34*Assumptions!D24*12/(1+Assumptions!D48) -> 10893.263 | E6: =Drivers!E34*Assumptions!E24*12/(1+Assumptions!E48) -> 91028.741 | F6: =Drivers!F34*Assumptions!F24*12/(1+Assumptions!F48) -> 356721.44 | G6: =Drivers!G34*Assumptions!G24*12/(1+Assumptions!G48) -> 946374.22 | H6: =Drivers!H34*Assumptions!H24*12/(1+Assumptions!H48) -> 1924244.6 | I6: =Drivers!I34*Assumptions!I24*12/(1+Assumptions!I48) -> 3159672.4 | J6: =Drivers!J34*Assumptions!J24*12/(1+Assumptions!J48) -> 4322543.8 | ... L6: =Drivers!L34*Assumptions!L24*12/(1+Assumptions!L48) -> 6092293.6
A7: Subscription GMV | C7: =C5+C6 -> 0 | D7: =D5+D6 -> 253084.64 | E7: =E5+E6 -> 910132.78 | F7: =F5+F6 -> 1954990.7 | G7: =G5+G6 -> 3376825.7 | H7: =H5+H6 -> 5107435.7 | I7: =I5+I6 -> 7091145.7 | J7: =J5+J6 -> 8968065.1 | ... L7: =L5+L6 -> 11986454
A8: PPV and tips GMV | B8: x multiple | C8: =C7*Assumptions!C49 -> 0 | D8: =D7*Assumptions!D49 -> 88579.625 | E8: =E7*Assumptions!E49 -> 318546.47 | F8: =F7*Assumptions!F49 -> 684246.76 | G8: =G7*Assumptions!G49 -> 1181889 | H8: =H7*Assumptions!H49 -> 1787602.5 | I8: =I7*Assumptions!I49 -> 2481901 | J8: =J7*Assumptions!J49 -> 3138822.8 | ... L8: =L7*Assumptions!L49 -> 4195258.8
A9: Total fan GMV | B9: ex-VAT, the take base | C9: =C7+C8 -> 0 | D9: =D7+D8 -> 341664.27 | E9: =E7+E8 -> 1228679.3 | F9: =F7+F8 -> 2639237.5 | G9: =G7+G8 -> 4558714.7 | H9: =H7+H8 -> 6895038.2 | I9: =I7+I8 -> 9573046.7 | J9: =J7+J8 -> 12106888 | ... L9: =L7+L8 -> 16181713
A10: Fan GMV including VAT | B10: what cards are charged | C10: =C9*(1+Assumptions!C48) -> 0 | D10: =D9*(1+Assumptions!D48) -> 413413.76 | E10: =E9*(1+Assumptions!E48) -> 1486701.9 | F10: =F9*(1+Assumptions!F48) -> 3193477.4 | G10: =G9*(1+Assumptions!G48) -> 5516044.8 | H10: =H9*(1+Assumptions!H48) -> 8342996.2 | I10: =I9*(1+Assumptions!I48) -> 11583387 | J10: =J9*(1+Assumptions!J48) -> 14649334 | ... L10: =L9*(1+Assumptions!L48) -> 19579872
A12: SPONSORSHIP GMV: what sponsors pay athletes and clubs
A13: Niche sponsorship GMV | C13: =Drivers!C44*Assumptions!C18 -> 11756.25 | D13: =Drivers!D44*Assumptions!D18 -> 60858 | E13: =Drivers!E44*Assumptions!E18 -> 190944 | F13: =Drivers!F44*Assumptions!F18 -> 424116 | G13: =Drivers!G44*Assumptions!G18 -> 723840 | H13: =Drivers!H44*Assumptions!H18 -> 1060800 | I13: =Drivers!I44*Assumptions!I18 -> 1388016 | J13: =Drivers!J44*Assumptions!J18 -> 1800014.4 | ... L13: =Drivers!L44*Assumptions!L18 -> 2509200
A14: Popular sponsorship GMV | C14: =Drivers!C45*Assumptions!C30 -> 5005 | D14: =Drivers!D45*Assumptions!D30 -> 38250 | E14: =Drivers!E45*Assumptions!E30 -> 323680 | F14: =Drivers!F45*Assumptions!F30 -> 1266585.6 | G14: =Drivers!G45*Assumptions!G30 -> 3238704 | H14: =Drivers!H45*Assumptions!H30 -> 6416540 | I14: =Drivers!I45*Assumptions!I30 -> 9979200 | J14: =Drivers!J45*Assumptions!J30 -> 13358520 | ... L14: =Drivers!L45*Assumptions!L30 -> 19193408
A15: Total sponsorship GMV | C15: =C13+C14 -> 16761.25 | D15: =D13+D14 -> 99108 | E15: =E13+E14 -> 514624 | F15: =F13+F14 -> 1690701.6 | G15: =G13+G14 -> 3962544 | H15: =H13+H14 -> 7477340 | I15: =I13+I14 -> 11367216 | J15: =J13+J14 -> 15158534 | ... L15: =L13+L14 -> 21702608
A16: Agency share of subscribers | C16: =MAX(0,(Assumptions!C36-Assumptions!C46)/(Assumptions!C47-Assumptions!C46)) -> 0 | D16: =MAX(0,(Assumptions!D36-Assumptions!D46)/(Assumptions!D47-Assumptions!D46)) -> 0 | E16: =MAX(0,(Assumptions!E36-Assumptions!E46)/(Assumptions!E47-Assumptions!E46)) -> 0.014666667 | F16: =MAX(0,(Assumptions!F36-Assumptions!F46)/(Assumptions!F47-Assumptions!F46)) -> 0.054666667 | G16: =MAX(0,(Assumptions!G36-Assumptions!G46)/(Assumptions!G47-Assumptions!G46)) -> 0.094666667 | H16: =MAX(0,(Assumptions!H36-Assumptions!H46)/(Assumptions!H47-Assumptions!H46)) -> 0.148 | I16: =MAX(0,(Assumptions!I36-Assumptions!I46)/(Assumptions!I47-Assumptions!I46)) -> 0.20133333 | J16: =MAX(0,(Assumptions!J36-Assumptions!J46)/(Assumptions!J47-Assumptions!J46)) -> 0.24133333 | ... L16: =MAX(0,(Assumptions!L36-Assumptions!L46)/(Assumptions!L47-Assumptions!L46)) -> 0.30133333
A17: Starter share of subscribers | C17: =MAX(0,(Assumptions!C46-Assumptions!C36)/(Assumptions!C46-Assumptions!C45)) -> 0.33333333 | D17: =MAX(0,(Assumptions!D46-Assumptions!D36)/(Assumptions!D46-Assumptions!D45)) -> 0.13333333 | E17: =MAX(0,(Assumptions!E46-Assumptions!E36)/(Assumptions!E46-Assumptions!E45)) -> 0 | F17: =MAX(0,(Assumptions!F46-Assumptions!F36)/(Assumptions!F46-Assumptions!F45)) -> 0 | G17: =MAX(0,(Assumptions!G46-Assumptions!G36)/(Assumptions!G46-Assumptions!G45)) -> 0 | H17: =MAX(0,(Assumptions!H46-Assumptions!H36)/(Assumptions!H46-Assumptions!H45)) -> 0 | I17: =MAX(0,(Assumptions!I46-Assumptions!I36)/(Assumptions!I46-Assumptions!I45)) -> 0 | J17: =MAX(0,(Assumptions!J46-Assumptions!J36)/(Assumptions!J46-Assumptions!J45)) -> 0 | ... L17: =MAX(0,(Assumptions!L46-Assumptions!L36)/(Assumptions!L46-Assumptions!L45)) -> 0
A18: Subscriber share of deal volume | C18: =MIN(1,Assumptions!C35*Assumptions!C44) -> 0.2 | D18: =MIN(1,Assumptions!D35*Assumptions!D44) -> 0.28 | E18: =MIN(1,Assumptions!E35*Assumptions!E44) -> 0.34 | F18: =MIN(1,Assumptions!F35*Assumptions!F44) -> 0.38 | G18: =MIN(1,Assumptions!G35*Assumptions!G44) -> 0.4 | H18: =MIN(1,Assumptions!H35*Assumptions!H44) -> 0.4 | I18: =MIN(1,Assumptions!I35*Assumptions!I44) -> 0.4 | J18: =MIN(1,Assumptions!J35*Assumptions!J44) -> 0.4 | ... L18: =MIN(1,Assumptions!L35*Assumptions!L44) -> 0.4
A19: Effective sponsorship take | C19: =(1-C18)*Assumptions!C41+C18*(C17*Assumptions!C41+(1-C17-C16)*Assumptions!C42+C16*Assumptions!C43) -> 0.096 | D19: =(1-D18)*Assumptions!D41+D18*(D17*Assumptions!D41+(1-D17-D16)*Assumptions!D42+D16*Assumptions!D43) -> 0.09272 | E19: =(1-E18)*Assumptions!E41+E18*(E17*Assumptions!E41+(1-E17-E16)*Assumptions!E42+E16*Assumptions!E43) -> 0.089700267 | F19: =(1-F18)*Assumptions!F41+F18*(F17*Assumptions!F41+(1-F17-F16)*Assumptions!F42+F16*Assumptions!F43) -> 0.088184533 | G19: =(1-G18)*Assumptions!G41+G18*(G17*Assumptions!G41+(1-G17-G16)*Assumptions!G42+G16*Assumptions!G43) -> 0.087242667 | H19: =(1-H18)*Assumptions!H41+H18*(H17*Assumptions!H41+(1-H17-H16)*Assumptions!H42+H16*Assumptions!H43) -> 0.086816 | I19: =(1-I18)*Assumptions!I41+I18*(I17*Assumptions!I41+(1-I17-I16)*Assumptions!I42+I16*Assumptions!I43) -> 0.086389333 | J19: =(1-J18)*Assumptions!J41+J18*(J17*Assumptions!J41+(1-J17-J16)*Assumptions!J42+J16*Assumptions!J43) -> 0.086069333 | ... L19: =(1-L18)*Assumptions!L41+L18*(L17*Assumptions!L41+(1-L17-L16)*Assumptions!L42+L16*Assumptions!L43) -> 0.085589333
A20: TOTAL GMV | C20: =C9+C15 -> 16761.25 | D20: =D9+D15 -> 440772.27 | E20: =E9+E15 -> 1743303.3 | F20: =F9+F15 -> 4329939.1 | G20: =G9+G15 -> 8521258.7 | H20: =H9+H15 -> 14372378 | I20: =I9+I15 -> 20940263 | J20: =J9+J15 -> 27265422 | ... L20: =L9+L15 -> 37884321
A22: NET REVENUE: our share
A23: Fan take | B23: fan GMV x take rate | C23: =C9*Assumptions!C40 -> 0 | D23: =D9*Assumptions!D40 -> 51249.64 | E23: =E9*Assumptions!E40 -> 184301.89 | F23: =F9*Assumptions!F40 -> 395885.62 | G23: =G9*Assumptions!G40 -> 683807.2 | H23: =H9*Assumptions!H40 -> 1034255.7 | I23: =I9*Assumptions!I40 -> 1435957 | J23: =J9*Assumptions!J40 -> 1816033.2 | ... L23: =L9*Assumptions!L40 -> 2427256.9
A24: Sponsorship take | C24: =C15*C19 -> 1609.08 | D24: =D15*D19 -> 9189.2938 | E24: =E15*E19 -> 46161.91 | F24: =F15*F19 -> 149093.73 | G24: =G15*G19 -> 345702.91 | H24: =H15*H19 -> 649152.75 | I24: =I15*I19 -> 982006.21 | J24: =J15*J19 -> 1304685 | ... L24: =L15*L19 -> 1857511.8
A25: Sponsor SaaS | B25: paying sponsors x ARPU x 12 | C25: =Drivers!C48*Assumptions!C36*12 -> 537.3 | D25: =Drivers!D48*Assumptions!D36*12 -> 7934.85 | E25: =Drivers!E48*Assumptions!E36*12 -> 56355 | F25: =Drivers!F48*Assumptions!F36*12 -> 158688 | G25: =Drivers!G48*Assumptions!G36*12 -> 291840 | H25: =Drivers!H48*Assumptions!H36*12 -> 440640 | I25: =Drivers!I48*Assumptions!I36*12 -> 595200 | J25: =Drivers!J48*Assumptions!J36*12 -> 732720 | ... L25: =Drivers!L48*Assumptions!L36*12 -> 969000
A26: NET REVENUE | C26: =SUM(C23:C25) -> 2146.38 | D26: =SUM(D23:D25) -> 68373.784 | E26: =SUM(E23:E25) -> 286818.8 | F26: =SUM(F23:F25) -> 703667.36 | G26: =SUM(G23:G25) -> 1321350.1 | H26: =SUM(H23:H25) -> 2124048.5 | I26: =SUM(I23:I25) -> 3013163.2 | J26: =SUM(J23:J25) -> 3853438.1 | ... L26: =SUM(L23:L25) -> 5253768.6
A27: Growth | B27: % YoY | C27: =IF(1=1,"",C26/C26-1) | D27: =IF(2=1,"",D26/C26-1) -> 30.855396 | E27: =IF(3=1,"",E26/D26-1) -> 3.1948651 | F27: =IF(4=1,"",F26/E26-1) -> 1.4533516 | G27: =IF(5=1,"",G26/F26-1) -> 0.87780504 | H27: =IF(6=1,"",H26/G26-1) -> 0.60748349 | I27: =IF(7=1,"",I26/H26-1) -> 0.41859438 | J27: =IF(8=1,"",J26/I26-1) -> 0.27886803 | K27: =IF(9=1,"",K26/J26-1) -> 0.17470552 | L27: =IF(10=1,"",L26/K26-1) -> 0.16062933
A28: Take rate on GMV | B28: blended | C28: =C26/C20 -> 0.12805608 | D28: =D26/D20 -> 0.1551227 | E28: =E26/E20 -> 0.16452605 | F28: =F26/F20 -> 0.16251207 | G28: =G26/G20 -> 0.15506513 | H28: =H26/H20 -> 0.14778685 | I28: =I26/I20 -> 0.14389329 | J28: =J26/J20 -> 0.14133059 | ... L28: =L26/L20 -> 0.13867924

Sheet Costs
A1: Costs
A2: Line | B2: Unit | C2: Y1 | D2: Y2 | E2: Y3 | F2: Y4 | G2: Y5 | H2: Y6 | I2: Y7 | J2: Y8 | K2: Y9 | L2: Y10
A4: COST OF SALES
A5: Fan transactions | B5: fan GMV incl VAT / avg ticket | C5: =Revenue!C10/Assumptions!C54 -> 0 | D5: =Revenue!D10/Assumptions!D54 -> 44936.279 | E5: =Revenue!E10/Assumptions!E54 -> 161598.03 | F5: =Revenue!F10/Assumptions!F54 -> 347117.11 | G5: =Revenue!G10/Assumptions!G54 -> 599570.08 | H5: =Revenue!H10/Assumptions!H54 -> 906847.41 | I5: =Revenue!I10/Assumptions!I54 -> 1259063.8 | J5: =Revenue!J10/Assumptions!J54 -> 1592318.9 | ... L5: =Revenue!L10/Assumptions!L54 -> 2128247
A6: Deal transactions | B6: count | C6: =Revenue!C15/Assumptions!C55 -> 9.3118056 | D6: =Revenue!D15/Assumptions!D55 -> 55.06 | E6: =Revenue!E15/Assumptions!E55 -> 285.90222 | F6: =Revenue!F15/Assumptions!F55 -> 939.27867 | G6: =Revenue!G15/Assumptions!G55 -> 2201.4133 | H6: =Revenue!H15/Assumptions!H55 -> 4154.0778 | I6: =Revenue!I15/Assumptions!I55 -> 6315.12 | J6: =Revenue!J15/Assumptions!J55 -> 8421.408 | ... L6: =Revenue!L15/Assumptions!L55 -> 12057.004
A7: Payment processing | B7: % of processed + fixed | C7: =(Revenue!C10+Revenue!C15)*Assumptions!C50+(C5+C6)*Assumptions!C51 -> 320.7917 | D7: =(Revenue!D10+Revenue!D15)*Assumptions!D50+(D5+D6)*Assumptions!D51 -> 20985.748 | E7: =(Revenue!E10+Revenue!E15)*Assumptions!E50+(E5+E6)*Assumptions!E51 -> 78496.176 | F7: =(Revenue!F10+Revenue!F15)*Assumptions!F50+(F5+F6)*Assumptions!F51 -> 179813.5 | G7: =(Revenue!G10+Revenue!G15)*Assumptions!G50+(G5+G6)*Assumptions!G51 -> 330536.06 | H7: =(Revenue!H10+Revenue!H15)*Assumptions!H50+(H5+H6)*Assumptions!H51 -> 528336.76 | I7: =(Revenue!I10+Revenue!I15)*Assumptions!I50+(I5+I6)*Assumptions!I51 -> 752406.17 | J7: =(Revenue!J10+Revenue!J15)*Assumptions!J50+(J5+J6)*Assumptions!J51 -> 966534.59 | ... L7: =(Revenue!L10+Revenue!L15)*Assumptions!L50+(L5+L6)*Assumptions!L51 -> 1319443.1
A8: Payouts to athletes | B8: % + fixed | C8: =(Revenue!C10+Revenue!C15)*Assumptions!C52+(C5/30+C6)*Assumptions!C53 -> 44.231076 | D8: =(Revenue!D10+Revenue!D15)*Assumptions!D52+(D5/30+D6)*Assumptions!D53 -> 1669.5384 | E8: =(Revenue!E10+Revenue!E15)*Assumptions!E52+(E5/30+E6)*Assumptions!E53 -> 6421.4406 | F8: =(Revenue!F10+Revenue!F15)*Assumptions!F52+(F5/30+F6)*Assumptions!F53 -> 15337.91 | G8: =(Revenue!G10+Revenue!G15)*Assumptions!G52+(G5/30+G6)*Assumptions!G53 -> 29243.243 | H8: =(Revenue!H10+Revenue!H15)*Assumptions!H52+(H5/30+H6)*Assumptions!H53 -> 48146.422 | I8: =(Revenue!I10+Revenue!I15)*Assumptions!I52+(I5/30+I6)*Assumptions!I53 -> 69447.484 | J8: =(Revenue!J10+Revenue!J15)*Assumptions!J52+(J5/30+J6)*Assumptions!J53 -> 89894.348 | ... L8: =(Revenue!L10+Revenue!L15)*Assumptions!L52+(L5/30+L6)*Assumptions!L53 -> 123955.84
A9: Media egress GB | B9: GB/yr | C9: =Drivers!C39*Assumptions!C59*12 -> 0 | D9: =Drivers!D39*Assumptions!D59*12 -> 66848.564 | E9: =Drivers!E39*Assumptions!E59*12 -> 234234.83 | F9: =Drivers!F39*Assumptions!F59*12 -> 497800.51 | G9: =Drivers!G39*Assumptions!G59*12 -> 852426.06 | H9: =Drivers!H39*Assumptions!H59*12 -> 1292374 | I9: =Drivers!I39*Assumptions!I59*12 -> 1790954.4 | J9: =Drivers!J39*Assumptions!J59*12 -> 2250235.1 | ... L9: =Drivers!L39*Assumptions!L59*12 -> 2949990.3
A10: Infrastructure (AWS + CDN) | B10: base + egress | C10: =Assumptions!C58*12+C9*Assumptions!C60 -> 1800 | D10: =Assumptions!D58*12+D9*Assumptions!D60 -> 5574.7885 | E10: =Assumptions!E58*12+E9*Assumptions!E60 -> 13873.879 | F10: =Assumptions!F58*12+F9*Assumptions!F60 -> 27982.404 | G10: =Assumptions!G58*12+G9*Assumptions!G60 -> 45219.408 | H10: =Assumptions!H58*12+H9*Assumptions!H60 -> 61938.992 | I10: =Assumptions!I58*12+I9*Assumptions!I60 -> 77927.635 | J10: =Assumptions!J58*12+J9*Assumptions!J60 -> 92401.881 | ... L10: =Assumptions!L58*12+L9*Assumptions!L60 -> 117199.92
A11: memo: same egress at CloudFront list | B11: the trap | C11: =Assumptions!C58*12+C9*Assumptions!C61 -> 1800 | D11: =Assumptions!D58*12+D9*Assumptions!D61 -> 10053.642 | E11: =Assumptions!E58*12+E9*Assumptions!E61 -> 29567.612 | F11: =Assumptions!F58*12+F9*Assumptions!F61 -> 61335.038 | G11: =Assumptions!G58*12+G9*Assumptions!G61 -> 102331.95 | H11: =Assumptions!H58*12+H9*Assumptions!H61 -> 148528.05 | I11: =Assumptions!I58*12+I9*Assumptions!I61 -> 197921.58 | J11: =Assumptions!J58*12+J9*Assumptions!J61 -> 243167.63 | ... L11: =Assumptions!L58*12+L9*Assumptions!L61 -> 314849.27
A12: Moderation | B12: items x rate | C12: =Drivers!C5*Assumptions!C63*12/1000*Assumptions!C62 -> 792 | D12: =Drivers!D5*Assumptions!D63*12/1000*Assumptions!D62 -> 2376 | E12: =Drivers!E5*Assumptions!E63*12/1000*Assumptions!E62 -> 5385.6 | F12: =Drivers!F5*Assumptions!F63*12/1000*Assumptions!F62 -> 8870.4 | G12: =Drivers!G5*Assumptions!G63*12/1000*Assumptions!G62 -> 12672 | H12: =Drivers!H5*Assumptions!H63*12/1000*Assumptions!H62 -> 16473.6 | I12: =Drivers!I5*Assumptions!I63*12/1000*Assumptions!I62 -> 19958.4 | J12: =Drivers!J5*Assumptions!J63*12/1000*Assumptions!J62 -> 22809.6 | ... L12: =Drivers!L5*Assumptions!L63*12/1000*Assumptions!L62 -> 26928
A13: Athlete verification | B13: reviews x minutes x hourly | C13: =Drivers!C55*Assumptions!C103/60*(Assumptions!C67/Assumptions!C104) -> 465.68627 | D13: =Drivers!D55*Assumptions!D103/60*(Assumptions!D67/Assumptions!D104) -> 1251.2118 | E13: =Drivers!E55*Assumptions!E103/60*(Assumptions!E67/Assumptions!E104) -> 2517.9256 | F13: =Drivers!F55*Assumptions!F103/60*(Assumptions!F67/Assumptions!F104) -> 3193.2737 | G13: =Drivers!G55*Assumptions!G103/60*(Assumptions!G67/Assumptions!G104) -> 3707.495 | H13: =Drivers!H55*Assumptions!H103/60*(Assumptions!H67/Assumptions!H104) -> 4093.7987 | I13: =Drivers!I55*Assumptions!I103/60*(Assumptions!I67/Assumptions!I104) -> 4248.9077 | J13: =Drivers!J55*Assumptions!J103/60*(Assumptions!J67/Assumptions!J104) -> 4211.8344 | ... L13: =Drivers!L55*Assumptions!L103/60*(Assumptions!L67/Assumptions!L104) -> 4172.2157
A14: TOTAL COST OF SALES | C14: =C7+C8+C10+C12+C13 -> 3422.7091 | D14: =D7+D8+D10+D12+D13 -> 31857.287 | E14: =E7+E8+E10+E12+E13 -> 106695.02 | F14: =F7+F8+F10+F12+F13 -> 235197.48 | G14: =G7+G8+G10+G12+G13 -> 421378.21 | H14: =H7+H8+H10+H12+H13 -> 658989.57 | I14: =I7+I8+I10+I12+I13 -> 923988.59 | J14: =J7+J8+J10+J12+J13 -> 1175852.3 | ... L14: =L7+L8+L10+L12+L13 -> 1591699.1
A16: OPERATING COSTS
A17: People | B17: FTE x loaded salary | C17: =Assumptions!C66*Assumptions!C67 -> 38000 | D17: =Assumptions!D66*Assumptions!D67 -> 78000 | E17: =Assumptions!E66*Assumptions!E67 -> 90000 | F17: =Assumptions!F66*Assumptions!F67 -> 128000 | G17: =Assumptions!G66*Assumptions!G67 -> 264000 | H17: =Assumptions!H66*Assumptions!H67 -> 476000 | I17: =Assumptions!I66*Assumptions!I67 -> 700000 | J17: =Assumptions!J66*Assumptions!J67 -> 900000 | ... L17: =Assumptions!L66*Assumptions!L67 -> 1216000
A18: Athlete acquisition: niche | B18: gross adds x CAC | C18: =Drivers!C11*Assumptions!C19 -> 3800 | D18: =Drivers!D11*Assumptions!D19 -> 9299.25 | E18: =Drivers!E11*Assumptions!E19 -> 17547.6 | F18: =Drivers!F11*Assumptions!F19 -> 20236.8 | G18: =Drivers!G11*Assumptions!G19 -> 21513.6 | H18: =Drivers!H11*Assumptions!H19 -> 21624 | I18: =Drivers!I11*Assumptions!I19 -> 22496 | J18: =Drivers!J11*Assumptions!J19 -> 25260.3 | ... L18: =Drivers!L11*Assumptions!L19 -> 25123.68
A19: Athlete acquisition: popular | C19: =Drivers!C25*Assumptions!C31 -> 500 | D19: =Drivers!D25*Assumptions!D31 -> 2369 | E19: =Drivers!E25*Assumptions!E31 -> 15794 | F19: =Drivers!F25*Assumptions!F31 -> 38868 | G19: =Drivers!G25*Assumptions!G31 -> 67536 | H19: =Drivers!H25*Assumptions!H31 -> 95367.2 | I19: =Drivers!I25*Assumptions!I31 -> 112086 | J19: =Drivers!J25*Assumptions!J31 -> 112065.3 | ... L19: =Drivers!L25*Assumptions!L31 -> 118747.2
A20: Sponsor acquisition | C20: =Drivers!C49*Assumptions!C37 -> 16200 | D20: =Drivers!D49*Assumptions!D37 -> 38850 | E20: =Drivers!E49*Assumptions!E37 -> 84000 | F20: =Drivers!F49*Assumptions!F37 -> 161000 | G20: =Drivers!G49*Assumptions!G37 -> 224000 | H20: =Drivers!H49*Assumptions!H37 -> 227500 | I20: =Drivers!I49*Assumptions!I37 -> 209000 | J20: =Drivers!J49*Assumptions!J37 -> 180000 | ... L20: =Drivers!L49*Assumptions!L37 -> 132000
A21: Total marketing / CAC | C21: =SUM(C18:C20) -> 20500 | D21: =SUM(D18:D20) -> 50518.25 | E21: =SUM(E18:E20) -> 117341.6 | F21: =SUM(F18:F20) -> 220104.8 | G21: =SUM(G18:G20) -> 313049.6 | H21: =SUM(H18:H20) -> 344491.2 | I21: =SUM(I18:I20) -> 343582 | J21: =SUM(J18:J20) -> 317325.6 | ... L21: =SUM(L18:L20) -> 275870.88
A22: memo: athlete marketing per application | B22: CAC is per ADMITTED athlete | C22: =(C18+C19)/Drivers!C54 -> 3.44 | D22: =(D18+D19)/Drivers!D54 -> 4.6210891 | E22: =(E18+E19)/Drivers!E54 -> 7.3530346 | F22: =(F18+F19)/Drivers!F54 -> 10.703082 | G22: =(G18+G19)/Drivers!G54 -> 14.062021 | H22: =(H18+H19)/Drivers!H54 -> 17.024667 | I22: =(I18+I19)/Drivers!I54 -> 19.181079 | J22: =(J18+J19)/Drivers!J54 -> 20.179625 | ... L22: =(L18+L19)/Drivers!L54 -> 22.312045
A23: Legal: base | C23: =Assumptions!C69+Assumptions!C70*MAX(0,Assumptions!C66-1) -> 3600 | D23: =Assumptions!D69+Assumptions!D70*MAX(0,Assumptions!D66-1) -> 4050 | E23: =Assumptions!E69+Assumptions!E70*MAX(0,Assumptions!E66-1) -> 4050 | F23: =Assumptions!F69+Assumptions!F70*MAX(0,Assumptions!F66-1) -> 4500 | G23: =Assumptions!G69+Assumptions!G70*MAX(0,Assumptions!G66-1) -> 6300 | H23: =Assumptions!H69+Assumptions!H70*MAX(0,Assumptions!H66-1) -> 9000 | I23: =Assumptions!I69+Assumptions!I70*MAX(0,Assumptions!I66-1) -> 11700 | J23: =Assumptions!J69+Assumptions!J70*MAX(0,Assumptions!J66-1) -> 13950 | ... L23: =Assumptions!L69+Assumptions!L70*MAX(0,Assumptions!L66-1) -> 17100
A24: Legal: incorporation and launch pack | C24: =IF(1=1,Assumptions!C71+Assumptions!C72,0) -> 10500 | D24: =IF(2=1,Assumptions!D71+Assumptions!D72,0) -> 0 | E24: =IF(3=1,Assumptions!E71+Assumptions!E72,0) -> 0 | F24: =IF(4=1,Assumptions!F71+Assumptions!F72,0) -> 0 | G24: =IF(5=1,Assumptions!G71+Assumptions!G72,0) -> 0 | H24: =IF(6=1,Assumptions!H71+Assumptions!H72,0) -> 0 | I24: =IF(7=1,Assumptions!I71+Assumptions!I72,0) -> 0 | J24: =IF(8=1,Assumptions!J71+Assumptions!J72,0) -> 0 | K24: =IF(9=1,Assumptions!K71+Assumptions!K72,0) -> 0 | L24: =IF(10=1,Assumptions!L71+Assumptions!L72,0) -> 0
A25: Legal: DAC7 | C25: =IF(1=1,4000,Assumptions!C73) -> 4000 | D25: =IF(2=1,4000,Assumptions!D73) -> 2500 | E25: =IF(3=1,4000,Assumptions!E73) -> 2500 | F25: =IF(4=1,4000,Assumptions!F73) -> 2500 | G25: =IF(5=1,4000,Assumptions!G73) -> 2500 | H25: =IF(6=1,4000,Assumptions!H73) -> 2500 | I25: =IF(7=1,4000,Assumptions!I73) -> 2500 | J25: =IF(8=1,4000,Assumptions!J73) -> 2500 | K25: =IF(9=1,4000,Assumptions!K73) -> 2500 | L25: =IF(10=1,4000,Assumptions!L73) -> 2500
A26: Legal: content and DSA | C26: =Assumptions!C74 -> 0 | D26: =Assumptions!D74 -> 6000 | E26: =Assumptions!E74 -> 5400 | F26: =Assumptions!F74 -> 5800 | G26: =Assumptions!G74 -> 6200 | H26: =Assumptions!H74 -> 6600 | I26: =Assumptions!I74 -> 7000 | J26: =Assumptions!J74 -> 7400 | ... L26: =Assumptions!L74 -> 8200
A27: Legal: market entry | C27: =Assumptions!C75*MAX(0,IF(1=1,Assumptions!C68,Assumptions!C68-Assumptions!C68)) -> 7000 | D27: =Assumptions!D75*MAX(0,IF(2=1,Assumptions!D68,Assumptions!D68-Assumptions!C68)) -> 7000 | E27: =Assumptions!E75*MAX(0,IF(3=1,Assumptions!E68,Assumptions!E68-Assumptions!D68)) -> 0 | F27: =Assumptions!F75*MAX(0,IF(4=1,Assumptions!F68,Assumptions!F68-Assumptions!E68)) -> 0 | G27: =Assumptions!G75*MAX(0,IF(5=1,Assumptions!G68,Assumptions!G68-Assumptions!F68)) -> 7000 | H27: =Assumptions!H75*MAX(0,IF(6=1,Assumptions!H68,Assumptions!H68-Assumptions!G68)) -> 7000 | I27: =Assumptions!I75*MAX(0,IF(7=1,Assumptions!I68,Assumptions!I68-Assumptions!H68)) -> 7000 | J27: =Assumptions!J75*MAX(0,IF(8=1,Assumptions!J68,Assumptions!J68-Assumptions!I68)) -> 7000 | K27: =Assumptions!K75*MAX(0,IF(9=1,Assumptions!K68,Assumptions!K68-Assumptions!J68)) -> 0 | L27: =Assumptions!L75*MAX(0,IF(10=1,Assumptions!L68,Assumptions!L68-Assumptions!K68)) -> 0
A28: Legal: VAT and tax | C28: =Assumptions!C76*Assumptions!C68 -> 2500 | D28: =Assumptions!D76*Assumptions!D68 -> 5000 | E28: =Assumptions!E76*Assumptions!E68 -> 5000 | F28: =Assumptions!F76*Assumptions!F68 -> 5000 | G28: =Assumptions!G76*Assumptions!G68 -> 7500 | H28: =Assumptions!H76*Assumptions!H68 -> 10000 | I28: =Assumptions!I76*Assumptions!I68 -> 12500 | J28: =Assumptions!J76*Assumptions!J68 -> 15000 | ... L28: =Assumptions!L76*Assumptions!L68 -> 15000
A29: Legal: round documentation | C29: =Assumptions!C77 -> 8000 | D29: =Assumptions!D77 -> 10000 | E29: =Assumptions!E77 -> 0 | F29: =Assumptions!F77 -> 0 | G29: =Assumptions!G77 -> 0 | H29: =Assumptions!H77 -> 25000 | I29: =Assumptions!I77 -> 0 | J29: =Assumptions!J77 -> 0 | ... L29: =Assumptions!L77 -> 0
A30: Legal: IP | C30: =Assumptions!C78+Assumptions!C79*MAX(0,IF(1=1,Assumptions!C68,Assumptions!C68-Assumptions!C68)) -> 8000 | D30: =Assumptions!D78+Assumptions!D79*MAX(0,IF(2=1,Assumptions!D68,Assumptions!D68-Assumptions!C68)) -> 3500 | E30: =Assumptions!E78+Assumptions!E79*MAX(0,IF(3=1,Assumptions!E68,Assumptions!E68-Assumptions!D68)) -> 1500 | F30: =Assumptions!F78+Assumptions!F79*MAX(0,IF(4=1,Assumptions!F68,Assumptions!F68-Assumptions!E68)) -> 1500 | G30: =Assumptions!G78+Assumptions!G79*MAX(0,IF(5=1,Assumptions!G68,Assumptions!G68-Assumptions!F68)) -> 3500 | H30: =Assumptions!H78+Assumptions!H79*MAX(0,IF(6=1,Assumptions!H68,Assumptions!H68-Assumptions!G68)) -> 3500 | I30: =Assumptions!I78+Assumptions!I79*MAX(0,IF(7=1,Assumptions!I68,Assumptions!I68-Assumptions!H68)) -> 3500 | J30: =Assumptions!J78+Assumptions!J79*MAX(0,IF(8=1,Assumptions!J68,Assumptions!J68-Assumptions!I68)) -> 3500 | K30: =Assumptions!K78+Assumptions!K79*MAX(0,IF(9=1,Assumptions!K68,Assumptions!K68-Assumptions!J68)) -> 1500 | L30: =Assumptions!L78+Assumptions!L79*MAX(0,IF(10=1,Assumptions!L68,Assumptions!L68-Assumptions!K68)) -> 1500
A31: Legal: employment | C31: =Assumptions!C80*MAX(0,IF(1=1,Assumptions!C66,Assumptions!C66-Assumptions!C66))+IF(Assumptions!C66>=Assumptions!C82,Assumptions!C81,0) -> 500 | D31: =Assumptions!D80*MAX(0,IF(2=1,Assumptions!D66,Assumptions!D66-Assumptions!C66))+IF(Assumptions!D66>=Assumptions!D82,Assumptions!D81,0) -> 250 | E31: =Assumptions!E80*MAX(0,IF(3=1,Assumptions!E66,Assumptions!E66-Assumptions!D66))+IF(Assumptions!E66>=Assumptions!E82,Assumptions!E81,0) -> 0 | F31: =Assumptions!F80*MAX(0,IF(4=1,Assumptions!F66,Assumptions!F66-Assumptions!E66))+IF(Assumptions!F66>=Assumptions!F82,Assumptions!F81,0) -> 250 | G31: =Assumptions!G80*MAX(0,IF(5=1,Assumptions!G66,Assumptions!G66-Assumptions!F66))+IF(Assumptions!G66>=Assumptions!G82,Assumptions!G81,0) -> 2500 | H31: =Assumptions!H80*MAX(0,IF(6=1,Assumptions!H66,Assumptions!H66-Assumptions!G66))+IF(Assumptions!H66>=Assumptions!H82,Assumptions!H81,0) -> 3000 | I31: =Assumptions!I80*MAX(0,IF(7=1,Assumptions!I66,Assumptions!I66-Assumptions!H66))+IF(Assumptions!I66>=Assumptions!I82,Assumptions!I81,0) -> 3000 | J31: =Assumptions!J80*MAX(0,IF(8=1,Assumptions!J66,Assumptions!J66-Assumptions!I66))+IF(Assumptions!J66>=Assumptions!J82,Assumptions!J81,0) -> 2750 | K31: =Assumptions!K80*MAX(0,IF(9=1,Assumptions!K66,Assumptions!K66-Assumptions!J66))+IF(Assumptions!K66>=Assumptions!K82,Assumptions!K81,0) -> 2500 | L31: =Assumptions!L80*MAX(0,IF(10=1,Assumptions!L66,Assumptions!L66-Assumptions!K66))+IF(Assumptions!L66>=Assumptions!L82,Assumptions!L81,0) -> 2250
A32: Legal: disputes | C32: =Assumptions!C83*Revenue!C20 -> 5.028375 | D32: =Assumptions!D83*Revenue!D20 -> 132.23168 | E32: =Assumptions!E83*Revenue!E20 -> 522.99098 | F32: =Assumptions!F83*Revenue!F20 -> 1298.9817 | G32: =Assumptions!G83*Revenue!G20 -> 2556.3776 | H32: =Assumptions!H83*Revenue!H20 -> 4311.7135 | I32: =Assumptions!I83*Revenue!I20 -> 6282.0788 | J32: =Assumptions!J83*Revenue!J20 -> 8179.6267 | ... L32: =Assumptions!L83*Revenue!L20 -> 11365.296
A33: Legal & compliance | C33: =SUM(C23:C32)*(1+Assumptions!C84) -> 50720.783 | D33: =SUM(D23:D32)*(1+Assumptions!D84) -> 44197.066 | E33: =SUM(E23:E32)*(1+Assumptions!E84) -> 21818.94 | F33: =SUM(F23:F32)*(1+Assumptions!F84) -> 23976.329 | G33: =SUM(G23:G32)*(1+Assumptions!G84) -> 43764.834 | H33: =SUM(H23:H32)*(1+Assumptions!H84) -> 81548.47 | I33: =SUM(I23:I32)*(1+Assumptions!I84) -> 61504.391 | J33: =SUM(J23:J32)*(1+Assumptions!J84) -> 69321.571 | ... L33: =SUM(L23:L32)*(1+Assumptions!L84) -> 66602.591
A34: Other opex | B34: % of revenue | C34: =Revenue!C26*Assumptions!C85 -> 171.7104 | D34: =Revenue!D26*Assumptions!D85 -> 5469.9027 | E34: =Revenue!E26*Assumptions!E85 -> 22945.504 | F34: =Revenue!F26*Assumptions!F85 -> 56293.388 | G34: =Revenue!G26*Assumptions!G85 -> 105708.01 | H34: =Revenue!H26*Assumptions!H85 -> 169923.88 | I34: =Revenue!I26*Assumptions!I85 -> 241053.06 | J34: =Revenue!J26*Assumptions!J85 -> 308275.05 | ... L34: =Revenue!L26*Assumptions!L85 -> 420301.49
A35: TOTAL OPERATING COSTS | C35: =C17+C21+C33+C34 -> 109392.49 | D35: =D17+D21+D33+D34 -> 178185.22 | E35: =E17+E21+E33+E34 -> 252106.04 | F35: =F17+F21+F33+F34 -> 428374.52 | G35: =G17+G21+G33+G34 -> 726522.44 | H35: =H17+H21+H33+H34 -> 1071963.5 | I35: =I17+I21+I33+I34 -> 1346139.4 | J35: =J17+J21+J33+J34 -> 1594922.2 | ... L35: =L17+L21+L33+L34 -> 1978775

Sheet WorkingCap
A1: Working capital, capex and amortisation
A2: Line | B2: Unit | C2: Y1 | D2: Y2 | E2: Y3 | F2: Y4 | G2: Y5 | H2: Y6 | I2: Y7 | J2: Y8 | K2: Y9 | L2: Y10
A4: WORKING CAPITAL
A5: Sponsor receivables | B5: SaaS+take x AR days/365 | C5: =(Revenue!C24+Revenue!C25)*Assumptions!C89/365 -> 264.62219 | D5: =(Revenue!D24+Revenue!D25)*Assumptions!D89/365 -> 2111.1958 | E5: =(Revenue!E24+Revenue!E25)*Assumptions!E89/365 -> 12639.071 | F5: =(Revenue!F24+Revenue!F25)*Assumptions!F89/365 -> 37945.693 | G5: =(Revenue!G24+Revenue!G25)*Assumptions!G89/365 -> 78601.18 | H5: =(Revenue!H24+Revenue!H25)*Assumptions!H89/365 -> 134358.01 | I5: =(Revenue!I24+Revenue!I25)*Assumptions!I89/365 -> 194450.08 | J5: =(Revenue!J24+Revenue!J25)*Assumptions!J89/365 -> 251186.91 | ... L5: =(Revenue!L24+Revenue!L25)*Assumptions!L89/365 -> 348474.05
A6: Athlete payout float | B6: processed GMV owed, not yet paid | C6: =(Revenue!C10+Revenue!C15)*Assumptions!C88/365 -> 688.81849 | D6: =(Revenue!D10+Revenue!D15)*Assumptions!D88/365 -> 21062.538 | E6: =(Revenue!E10+Revenue!E15)*Assumptions!E88/365 -> 82246.27 | F6: =(Revenue!F10+Revenue!F15)*Assumptions!F88/365 -> 200719.68 | G6: =(Revenue!G10+Revenue!G15)*Assumptions!G88/365 -> 389531.04 | H6: =(Revenue!H10+Revenue!H15)*Assumptions!H88/365 -> 650150.8 | I6: =(Revenue!I10+Revenue!I15)*Assumptions!I88/365 -> 943175.45 | J6: =(Revenue!J10+Revenue!J15)*Assumptions!J88/365 -> 1224980.9 | ... L6: =(Revenue!L10+Revenue!L15)*Assumptions!L88/365 -> 1696540.3
A7: Trade payables | B7: opex x AP days/365 | C7: =Costs!C35*Assumptions!C90/365 -> 8991.1638 | D7: =Costs!D35*Assumptions!D90/365 -> 14645.36 | E7: =Costs!E35*Assumptions!E90/365 -> 20721.045 | F7: =Costs!F35*Assumptions!F90/365 -> 35208.864 | G7: =Costs!G35*Assumptions!G90/365 -> 59714.173 | H7: =Costs!H35*Assumptions!H90/365 -> 88106.593 | I7: =Costs!I35*Assumptions!I90/365 -> 110641.6 | J7: =Costs!J35*Assumptions!J90/365 -> 131089.5 | ... L7: =Costs!L35*Assumptions!L90/365 -> 162639.04
A8: Net working capital | B8: AR - float - AP | C8: =C5-C6-C7 -> -9415.3601 | D8: =D5-D6-D7 -> -33596.703 | E8: =E5-E6-E7 -> -90328.243 | F8: =F5-F6-F7 -> -197982.86 | G8: =G5-G6-G7 -> -370644.04 | H8: =H5-H6-H7 -> -603899.39 | I8: =I5-I6-I7 -> -859366.96 | J8: =J5-J6-J7 -> -1104883.5 | ... L8: =L5-L6-L7 -> -1510705.3
A9: Change in NWC | B9: cash impact | C9: =IF(1=1,C8,C8-C8) -> -9415.3601 | D9: =IF(2=1,D8,D8-C8) -> -24181.343 | E9: =IF(3=1,E8,E8-D8) -> -56731.54 | F9: =IF(4=1,F8,F8-E8) -> -107654.61 | G9: =IF(5=1,G8,G8-F8) -> -172661.18 | H9: =IF(6=1,H8,H8-G8) -> -233255.35 | I9: =IF(7=1,I8,I8-H8) -> -255467.58 | J9: =IF(8=1,J8,J8-I8) -> -245516.53 | K9: =IF(9=1,K8,K8-J8) -> -188361.55 | L9: =IF(10=1,L8,L8-K8) -> -217460.22
A11: CAPEX & AMORTISATION
A12: Capitalised development | B12: % of people cost | C12: =Costs!C17*Assumptions!C91 -> 11400 | D12: =Costs!D17*Assumptions!D91 -> 23400 | E12: =Costs!E17*Assumptions!E91 -> 27000 | F12: =Costs!F17*Assumptions!F91 -> 38400 | G12: =Costs!G17*Assumptions!G91 -> 79200 | H12: =Costs!H17*Assumptions!H91 -> 142800 | I12: =Costs!I17*Assumptions!I91 -> 210000 | J12: =Costs!J17*Assumptions!J91 -> 270000 | ... L12: =Costs!L17*Assumptions!L91 -> 364800
A13: Amortisation | B13: 3-yr straight line on trailing capex | C13: =SUM(OFFSET(C12,0,-MIN(Assumptions!C92-1,1-1),1,MIN(Assumptions!C92,1)))/Assumptions!C92 -> 3800 | D13: =SUM(OFFSET(D12,0,-MIN(Assumptions!D92-1,2-1),1,MIN(Assumptions!D92,2)))/Assumptions!D92 -> 11600 | E13: =SUM(OFFSET(E12,0,-MIN(Assumptions!E92-1,3-1),1,MIN(Assumptions!E92,3)))/Assumptions!E92 -> 20600 | F13: =SUM(OFFSET(F12,0,-MIN(Assumptions!F92-1,4-1),1,MIN(Assumptions!F92,4)))/Assumptions!F92 -> 29600 | G13: =SUM(OFFSET(G12,0,-MIN(Assumptions!G92-1,5-1),1,MIN(Assumptions!G92,5)))/Assumptions!G92 -> 48200 | H13: =SUM(OFFSET(H12,0,-MIN(Assumptions!H92-1,6-1),1,MIN(Assumptions!H92,6)))/Assumptions!H92 -> 86800 | I13: =SUM(OFFSET(I12,0,-MIN(Assumptions!I92-1,7-1),1,MIN(Assumptions!I92,7)))/Assumptions!I92 -> 144000 | J13: =SUM(OFFSET(J12,0,-MIN(Assumptions!J92-1,8-1),1,MIN(Assumptions!J92,8)))/Assumptions!J92 -> 207600 | K13: =SUM(OFFSET(K12,0,-MIN(Assumptions!K92-1,9-1),1,MIN(Assumptions!K92,9)))/Assumptions!K92 -> 267300 | L13: =SUM(OFFSET(L12,0,-MIN(Assumptions!L92-1,10-1),1,MIN(Assumptions!L92,10)))/Assumptions!L92 -> 318900
A14: Net intangible assets | B14: closing | C14: =C12-C13 -> 7600 | D14: =C14+D12-D13 -> 19400 | E14: =D14+E12-E13 -> 25800 | F14: =E14+F12-F13 -> 34600 | G14: =F14+G12-G13 -> 65600 | H14: =G14+H12-H13 -> 121600 | I14: =H14+I12-I13 -> 187600 | J14: =I14+J12-J13 -> 250000 | K14: =J14+K12-K13 -> 304600 | L14: =K14+L12-L13 -> 350500

Sheet P&L
A1: Income statement
A2: Line | B2: Unit | C2: Y1 | D2: Y2 | E2: Y3 | F2: Y4 | G2: Y5 | H2: Y6 | I2: Y7 | J2: Y8 | K2: Y9 | L2: Y10
A4: Net revenue | C4: =Revenue!C26 -> 2146.38 | D4: =Revenue!D26 -> 68373.784 | E4: =Revenue!E26 -> 286818.8 | F4: =Revenue!F26 -> 703667.36 | G4: =Revenue!G26 -> 1321350.1 | H4: =Revenue!H26 -> 2124048.5 | I4: =Revenue!I26 -> 3013163.2 | J4: =Revenue!J26 -> 3853438.1 | ... L4: =Revenue!L26 -> 5253768.6
A5: Cost of sales | C5: =-Costs!C14 -> -3422.7091 | D5: =-Costs!D14 -> -31857.287 | E5: =-Costs!E14 -> -106695.02 | F5: =-Costs!F14 -> -235197.48 | G5: =-Costs!G14 -> -421378.21 | H5: =-Costs!H14 -> -658989.57 | I5: =-Costs!I14 -> -923988.59 | J5: =-Costs!J14 -> -1175852.3 | ... L5: =-Costs!L14 -> -1591699.1
A6: GROSS PROFIT | C6: =C4+C5 -> -1276.3291 | D6: =D4+D5 -> 36516.497 | E6: =E4+E5 -> 180123.78 | F6: =F4+F5 -> 468469.87 | G6: =G4+G5 -> 899971.9 | H6: =H4+H5 -> 1465058.9 | I6: =I4+I5 -> 2089174.6 | J6: =J4+J5 -> 2677585.9 | ... L6: =L4+L5 -> 3662069.5
A7: Gross margin | C7: =C6/C4 -> -0.59464263 | D7: =D6/D4 -> 0.53407161 | E7: =E6/E4 -> 0.62800548 | F7: =F6/F4 -> 0.66575473 | G7: =G6/G4 -> 0.68110026 | H7: =H6/H4 -> 0.68974834 | I7: =I6/I4 -> 0.69334931 | J7: =J6/J4 -> 0.69485633 | ... L7: =L6/L4 -> 0.6970367
A9: Operating costs | C9: =-Costs!C35 -> -109392.49 | D9: =-Costs!D35 -> -178185.22 | E9: =-Costs!E35 -> -252106.04 | F9: =-Costs!F35 -> -428374.52 | G9: =-Costs!G35 -> -726522.44 | H9: =-Costs!H35 -> -1071963.5 | I9: =-Costs!I35 -> -1346139.4 | J9: =-Costs!J35 -> -1594922.2 | ... L9: =-Costs!L35 -> -1978775
A10: EBITDA | C10: =C6+C9 -> -110668.82 | D10: =D6+D9 -> -141668.72 | E10: =E6+E9 -> -71982.266 | F10: =F6+F9 -> 40095.355 | G10: =G6+G9 -> 173449.46 | H10: =H6+H9 -> 393095.35 | I10: =I6+I9 -> 743035.18 | J10: =J6+J9 -> 1082663.7 | ... L10: =L6+L9 -> 1683294.6
A11: EBITDA margin | C11: =C10/C4 -> -51.560685 | D11: =D10/D4 -> -2.0719743 | E11: =E10/E4 -> -0.25096774 | F11: =F10/F4 -> 0.056980552 | G11: =G10/G4 -> 0.13126684 | H11: =H10/H4 -> 0.18506892 | I11: =I10/I4 -> 0.24659639 | J11: =J10/J4 -> 0.28096043 | ... L11: =L10/L4 -> 0.32039754
A12: Amortisation | C12: =-WorkingCap!C13 -> -3800 | D12: =-WorkingCap!D13 -> -11600 | E12: =-WorkingCap!E13 -> -20600 | F12: =-WorkingCap!F13 -> -29600 | G12: =-WorkingCap!G13 -> -48200 | H12: =-WorkingCap!H13 -> -86800 | I12: =-WorkingCap!I13 -> -144000 | J12: =-WorkingCap!J13 -> -207600 | ... L12: =-WorkingCap!L13 -> -318900
A13: EBIT | C13: =C10+C12 -> -114468.82 | D13: =D10+D12 -> -153268.72 | E13: =E10+E12 -> -92582.266 | F13: =F10+F12 -> 10495.355 | G13: =G10+G12 -> 125249.46 | H13: =H10+H12 -> 306295.35 | I13: =I10+I12 -> 599035.18 | J13: =J10+J12 -> 875063.65 | ... L13: =L10+L12 -> 1364394.6
A15: TAX: with loss carryforward and the startup-rate step
A16: Losses brought forward | B16: accumulated | C16: =IF(1=1,0,MIN(0,C18)) -> 0 | D16: =IF(2=1,0,MIN(0,C18)) -> -114468.82 | E16: =IF(3=1,0,MIN(0,D18)) -> -267737.54 | F16: =IF(4=1,0,MIN(0,E18)) -> -360319.81 | G16: =IF(5=1,0,MIN(0,F18)) -> -349824.46 | H16: =IF(6=1,0,MIN(0,G18)) -> -224575 | I16: =IF(7=1,0,MIN(0,H18)) -> 0 | J16: =IF(8=1,0,MIN(0,I18)) -> 0 | K16: =IF(9=1,0,MIN(0,J18)) -> 0 | L16: =IF(10=1,0,MIN(0,K18)) -> 0
A17: Taxable profit | B17: after offset | C17: =MAX(0,C13+C16) -> 0 | D17: =MAX(0,D13+D16) -> 0 | E17: =MAX(0,E13+E16) -> 0 | F17: =MAX(0,F13+F16) -> 0 | G17: =MAX(0,G13+G16) -> 0 | H17: =MAX(0,H13+H16) -> 81720.357 | I17: =MAX(0,I13+I16) -> 599035.18 | J17: =MAX(0,J13+J16) -> 875063.65 | ... L17: =MAX(0,L13+L16) -> 1364394.6
A18: Losses carried forward | B18: running | C18: =MIN(0,C13) -> -114468.82 | D18: =MIN(0,D13+C18) -> -267737.54 | E18: =MIN(0,E13+D18) -> -360319.81 | F18: =MIN(0,F13+E18) -> -349824.46 | G18: =MIN(0,G13+F18) -> -224575 | H18: =MIN(0,H13+G18) -> 0 | I18: =MIN(0,I13+H18) -> 0 | J18: =MIN(0,J13+I18) -> 0 | K18: =MIN(0,K13+J18) -> 0 | L18: =MIN(0,L13+K18) -> 0
A19: Applicable tax rate | B19: 15% then 25% | C19: =IF(C17<=0,0,IF(COUNTIF($C17:C17,">0")<=Assumptions!C95,Assumptions!C93,Assumptions!C94)) -> 0 | D19: =IF(D17<=0,0,IF(COUNTIF($C17:D17,">0")<=Assumptions!D95,Assumptions!D93,Assumptions!D94)) -> 0 | E19: =IF(E17<=0,0,IF(COUNTIF($C17:E17,">0")<=Assumptions!E95,Assumptions!E93,Assumptions!E94)) -> 0 | F19: =IF(F17<=0,0,IF(COUNTIF($C17:F17,">0")<=Assumptions!F95,Assumptions!F93,Assumptions!F94)) -> 0 | G19: =IF(G17<=0,0,IF(COUNTIF($C17:G17,">0")<=Assumptions!G95,Assumptions!G93,Assumptions!G94)) -> 0 | H19: =IF(H17<=0,0,IF(COUNTIF($C17:H17,">0")<=Assumptions!H95,Assumptions!H93,Assumptions!H94)) -> 0.15 | I19: =IF(I17<=0,0,IF(COUNTIF($C17:I17,">0")<=Assumptions!I95,Assumptions!I93,Assumptions!I94)) -> 0.15 | J19: =IF(J17<=0,0,IF(COUNTIF($C17:J17,">0")<=Assumptions!J95,Assumptions!J93,Assumptions!J94)) -> 0.15 | ... L19: =IF(L17<=0,0,IF(COUNTIF($C17:L17,">0")<=Assumptions!L95,Assumptions!L93,Assumptions!L94)) -> 0.25
A20: Tax charge | C20: =-C17*C19 -> 0 | D20: =-D17*D19 -> 0 | E20: =-E17*E19 -> 0 | F20: =-F17*F19 -> 0 | G20: =-G17*G19 -> 0 | H20: =-H17*H19 -> -12258.054 | I20: =-I17*I19 -> -89855.277 | J20: =-J17*J19 -> -131259.55 | ... L20: =-L17*L19 -> -341098.64
A21: NET PROFIT | C21: =C13+C20 -> -114468.82 | D21: =D13+D20 -> -153268.72 | E21: =E13+E20 -> -92582.266 | F21: =F13+F20 -> 10495.355 | G21: =G13+G20 -> 125249.46 | H21: =H13+H20 -> 294037.3 | I21: =I13+I20 -> 509179.9 | J21: =J13+J20 -> 743804.1 | ... L21: =L13+L20 -> 1023295.9

Sheet CashFlow
A1: Cash Flow Statement
A2: Line | B2: Unit | C2: Y1 | D2: Y2 | E2: Y3 | F2: Y4 | G2: Y5 | H2: Y6 | I2: Y7 | J2: Y8 | K2: Y9 | L2: Y10
A4: Net profit | C4: ='P&L'!C21 -> -114468.82 | D4: ='P&L'!D21 -> -153268.72 | E4: ='P&L'!E21 -> -92582.266 | F4: ='P&L'!F21 -> 10495.355 | G4: ='P&L'!G21 -> 125249.46 | H4: ='P&L'!H21 -> 294037.3 | I4: ='P&L'!I21 -> 509179.9 | J4: ='P&L'!J21 -> 743804.1 | ... L4: ='P&L'!L21 -> 1023295.9
A5: Add back amortisation | C5: =WorkingCap!C13 -> 3800 | D5: =WorkingCap!D13 -> 11600 | E5: =WorkingCap!E13 -> 20600 | F5: =WorkingCap!F13 -> 29600 | G5: =WorkingCap!G13 -> 48200 | H5: =WorkingCap!H13 -> 86800 | I5: =WorkingCap!I13 -> 144000 | J5: =WorkingCap!J13 -> 207600 | ... L5: =WorkingCap!L13 -> 318900
A6: Change in working capital | C6: =-WorkingCap!C9 -> 9415.3601 | D6: =-WorkingCap!D9 -> 24181.343 | E6: =-WorkingCap!E9 -> 56731.54 | F6: =-WorkingCap!F9 -> 107654.61 | G6: =-WorkingCap!G9 -> 172661.18 | H6: =-WorkingCap!H9 -> 233255.35 | I6: =-WorkingCap!I9 -> 255467.58 | J6: =-WorkingCap!J9 -> 245516.53 | ... L6: =-WorkingCap!L9 -> 217460.22
A7: OPERATING CASH FLOW | C7: =SUM(C4:C6) -> -101253.46 | D7: =SUM(D4:D6) -> -117487.38 | E7: =SUM(E4:E6) -> -15250.726 | F7: =SUM(F4:F6) -> 147749.97 | G7: =SUM(G4:G6) -> 346110.64 | H7: =SUM(H4:H6) -> 614092.65 | I7: =SUM(I4:I6) -> 908647.48 | J7: =SUM(J4:J6) -> 1196920.6 | ... L7: =SUM(L4:L6) -> 1559656.2
A8: Capital expenditure | C8: =-WorkingCap!C12 -> -11400 | D8: =-WorkingCap!D12 -> -23400 | E8: =-WorkingCap!E12 -> -27000 | F8: =-WorkingCap!F12 -> -38400 | G8: =-WorkingCap!G12 -> -79200 | H8: =-WorkingCap!H12 -> -142800 | I8: =-WorkingCap!I12 -> -210000 | J8: =-WorkingCap!J12 -> -270000 | ... L8: =-WorkingCap!L12 -> -364800
A9: FREE CASH FLOW | C9: =C7+C8 -> -112653.46 | D9: =D7+D8 -> -140887.38 | E9: =E7+E8 -> -42250.726 | F9: =F7+F8 -> 109349.97 | G9: =G7+G8 -> 266910.64 | H9: =H7+H8 -> 471292.65 | I9: =I7+I8 -> 698647.48 | J9: =J7+J8 -> 926920.63 | ... L9: =L7+L8 -> 1194856.2
A10: Cumulative free cash flow | C10: =C9 -> -112653.46 | D10: =C10+D9 -> -253540.84 | E10: =D10+E9 -> -295791.57 | F10: =E10+F9 -> -186441.6 | G10: =F10+G9 -> 80469.04 | H10: =G10+H9 -> 551761.69 | I10: =H10+I9 -> 1250409.2 | J10: =I10+J9 -> 2177329.8 | K10: =J10+K9 -> 3225849.7 | L10: =K10+L9 -> 4420705.8
A12: Equity raised | B12: see Funding | C12: =Funding!C4 -> 150000 | D12: =Funding!D4 -> 250000 | E12: =Funding!E4 -> 0 | F12: =Funding!F4 -> 0 | G12: =Funding!G4 -> 0 | H12: =Funding!H4 -> 1500000 | I12: =Funding!I4 -> 0 | J12: =Funding!J4 -> 0 | ... L12: =Funding!L4 -> 0
A13: Opening cash | C13: =0 -> 0 | D13: =C14 -> 37346.538 | E13: =D14 -> 146459.16 | F13: =E14 -> 104208.43 | G13: =F14 -> 213558.4 | H13: =G14 -> 480469.04 | I13: =H14 -> 2451761.7 | J13: =I14 -> 3150409.2 | K13: =J14 -> 4077329.8 | L13: =K14 -> 5125849.7
A14: CLOSING CASH | C14: =C13+C9+C12 -> 37346.538 | D14: =D13+D9+D12 -> 146459.16 | E14: =E13+E9+E12 -> 104208.43 | F14: =F13+F9+F12 -> 213558.4 | G14: =G13+G9+G12 -> 480469.04 | H14: =H13+H9+H12 -> 2451761.7 | I14: =I13+I9+I12 -> 3150409.2 | J14: =J13+J9+J12 -> 4077329.8 | ... L14: =L13+L9+L12 -> 6320705.8

Sheet BalanceSheet
A1: Balance sheet
A2: Line | B2: Unit | C2: Y1 | D2: Y2 | E2: Y3 | F2: Y4 | G2: Y5 | H2: Y6 | I2: Y7 | J2: Y8 | K2: Y9 | L2: Y10
A4: ASSETS
A5: Cash | C5: =CashFlow!C14 -> 37346.538 | D5: =CashFlow!D14 -> 146459.16 | E5: =CashFlow!E14 -> 104208.43 | F5: =CashFlow!F14 -> 213558.4 | G5: =CashFlow!G14 -> 480469.04 | H5: =CashFlow!H14 -> 2451761.7 | I5: =CashFlow!I14 -> 3150409.2 | J5: =CashFlow!J14 -> 4077329.8 | ... L5: =CashFlow!L14 -> 6320705.8
A6: Sponsor receivables | C6: =WorkingCap!C5 -> 264.62219 | D6: =WorkingCap!D5 -> 2111.1958 | E6: =WorkingCap!E5 -> 12639.071 | F6: =WorkingCap!F5 -> 37945.693 | G6: =WorkingCap!G5 -> 78601.18 | H6: =WorkingCap!H5 -> 134358.01 | I6: =WorkingCap!I5 -> 194450.08 | J6: =WorkingCap!J5 -> 251186.91 | ... L6: =WorkingCap!L5 -> 348474.05
A7: Net intangible assets | C7: =WorkingCap!C14 -> 7600 | D7: =WorkingCap!D14 -> 19400 | E7: =WorkingCap!E14 -> 25800 | F7: =WorkingCap!F14 -> 34600 | G7: =WorkingCap!G14 -> 65600 | H7: =WorkingCap!H14 -> 121600 | I7: =WorkingCap!I14 -> 187600 | J7: =WorkingCap!J14 -> 250000 | ... L7: =WorkingCap!L14 -> 350500
A8: TOTAL ASSETS | C8: =SUM(C5:C7) -> 45211.16 | D8: =SUM(D5:D7) -> 167970.35 | E8: =SUM(E5:E7) -> 142647.5 | F8: =SUM(F5:F7) -> 286104.09 | G8: =SUM(G5:G7) -> 624670.22 | H8: =SUM(H5:H7) -> 2707719.7 | I8: =SUM(I5:I7) -> 3532459.3 | J8: =SUM(J5:J7) -> 4578516.7 | ... L8: =SUM(L5:L7) -> 7019679.9
A10: LIABILITIES
A11: Athlete payout float | C11: =WorkingCap!C6 -> 688.81849 | D11: =WorkingCap!D6 -> 21062.538 | E11: =WorkingCap!E6 -> 82246.27 | F11: =WorkingCap!F6 -> 200719.68 | G11: =WorkingCap!G6 -> 389531.04 | H11: =WorkingCap!H6 -> 650150.8 | I11: =WorkingCap!I6 -> 943175.45 | J11: =WorkingCap!J6 -> 1224980.9 | ... L11: =WorkingCap!L6 -> 1696540.3
A12: Trade payables | C12: =WorkingCap!C7 -> 8991.1638 | D12: =WorkingCap!D7 -> 14645.36 | E12: =WorkingCap!E7 -> 20721.045 | F12: =WorkingCap!F7 -> 35208.864 | G12: =WorkingCap!G7 -> 59714.173 | H12: =WorkingCap!H7 -> 88106.593 | I12: =WorkingCap!I7 -> 110641.6 | J12: =WorkingCap!J7 -> 131089.5 | ... L12: =WorkingCap!L7 -> 162639.04
A13: TOTAL LIABILITIES | C13: =C11+C12 -> 9679.9823 | D13: =D11+D12 -> 35707.899 | E13: =E11+E12 -> 102967.31 | F13: =F11+F12 -> 235928.55 | G13: =G11+G12 -> 449245.22 | H13: =H11+H12 -> 738257.4 | I13: =I11+I12 -> 1053817 | J13: =J11+J12 -> 1356070.4 | ... L13: =L11+L12 -> 1859179.3
A15: EQUITY
A16: Paid-in capital | C16: =Funding!C4 -> 150000 | D16: =C16+Funding!D4 -> 400000 | E16: =D16+Funding!E4 -> 400000 | F16: =E16+Funding!F4 -> 400000 | G16: =F16+Funding!G4 -> 400000 | H16: =G16+Funding!H4 -> 1900000 | I16: =H16+Funding!I4 -> 1900000 | J16: =I16+Funding!J4 -> 1900000 | K16: =J16+Funding!K4 -> 1900000 | L16: =K16+Funding!L4 -> 1900000
A17: Retained earnings | C17: ='P&L'!C21 -> -114468.82 | D17: =C17+'P&L'!D21 -> -267737.54 | E17: =D17+'P&L'!E21 -> -360319.81 | F17: =E17+'P&L'!F21 -> -349824.46 | G17: =F17+'P&L'!G21 -> -224575 | H17: =G17+'P&L'!H21 -> 69462.303 | I17: =H17+'P&L'!I21 -> 578642.21 | J17: =I17+'P&L'!J21 -> 1322446.3 | K17: =J17+'P&L'!K21 -> 2237204.6 | L17: =K17+'P&L'!L21 -> 3260500.6
A18: TOTAL EQUITY | C18: =C16+C17 -> 35531.178 | D18: =D16+D17 -> 132262.46 | E18: =E16+E17 -> 39680.19 | F18: =F16+F17 -> 50175.544 | G18: =G16+G17 -> 175425 | H18: =H16+H17 -> 1969462.3 | I18: =I16+I17 -> 2478642.2 | J18: =J16+J17 -> 3222446.3 | ... L18: =L16+L17 -> 5160500.6
A19: Liabilities + equity | C19: =C13+C18 -> 45211.16 | D19: =D13+D18 -> 167970.35 | E19: =E13+E18 -> 142647.5 | F19: =F13+F18 -> 286104.09 | G19: =G13+G18 -> 624670.22 | H19: =H13+H18 -> 2707719.7 | I19: =I13+I18 -> 3532459.3 | J19: =J13+J18 -> 4578516.7 | ... L19: =L13+L18 -> 7019679.9
A20: BALANCE CHECK | B20: must be zero | C20: =ROUND(C8-C19,2) -> 0 | D20: =ROUND(D8-D19,2) -> 0 | E20: =ROUND(E8-E19,2) -> 0 | F20: =ROUND(F8-F19,2) -> 0 | G20: =ROUND(G8-G19,2) -> 0 | H20: =ROUND(H8-H19,2) -> 0 | I20: =ROUND(I8-I19,2) -> 0 | J20: =ROUND(J8-J19,2) -> 0 | ... L20: =ROUND(L8-L19,2) -> 0

Sheet Valuation
A1: Valuation, DCF, NPV, IRR and exit multiples
A2: Line | B2: Unit | C2: Y1 | D2: Y2 | E2: Y3 | F2: Y4 | G2: Y5 | H2: Y6 | I2: Y7 | J2: Y8 | K2: Y9 | L2: Y10
A4: Free cash flow | B4: EUR | C4: =CashFlow!C9 -> -112653.46 | D4: =CashFlow!D9 -> -140887.38 | E4: =CashFlow!E9 -> -42250.726 | F4: =CashFlow!F9 -> 109349.97 | G4: =CashFlow!G9 -> 266910.64 | H4: =CashFlow!H9 -> 471292.65 | I4: =CashFlow!I9 -> 698647.48 | J4: =CashFlow!J9 -> 926920.63 | ... L4: =CashFlow!L9 -> 1194856.2
A5: Discount factor | B5: 1/(1+WACC)^t | C5: =1/(1+Assumptions!$C$110)^1 -> 0.8 | D5: =1/(1+Assumptions!$C$110)^2 -> 0.64 | E5: =1/(1+Assumptions!$C$110)^3 -> 0.512 | F5: =1/(1+Assumptions!$C$110)^4 -> 0.4096 | G5: =1/(1+Assumptions!$C$110)^5 -> 0.32768 | H5: =1/(1+Assumptions!$C$110)^6 -> 0.262144 | I5: =1/(1+Assumptions!$C$110)^7 -> 0.2097152 | J5: =1/(1+Assumptions!$C$110)^8 -> 0.16777216 | K5: =1/(1+Assumptions!$C$110)^9 -> 0.13421773 | L5: =1/(1+Assumptions!$C$110)^10 -> 0.10737418
A6: Discounted FCF | B6: EUR | C6: =C4*C5 -> -90122.77 | D6: =D4*D5 -> -90167.923 | E6: =E4*E5 -> -21632.372 | F6: =F4*F5 -> 44789.746 | G6: =G4*G5 -> 87461.279 | H6: =H4*H5 -> 123546.54 | I6: =I4*I5 -> 146517 | J6: =J4*J5 -> 155511.48 | ... L6: =L4*L5 -> 128296.7
A8: FCF incl. terminal value | B8: for the IRR below | C8: =C4+IF(1=10,$C$11,0) -> -112653.46 | D8: =D4+IF(2=10,$C$11,0) -> -140887.38 | E8: =E4+IF(3=10,$C$11,0) -> -42250.726 | F8: =F4+IF(4=10,$C$11,0) -> 109349.97 | G8: =G4+IF(5=10,$C$11,0) -> 266910.64 | H8: =H4+IF(6=10,$C$11,0) -> 471292.65 | I8: =I4+IF(7=10,$C$11,0) -> 698647.48 | J8: =J4+IF(8=10,$C$11,0) -> 926920.63 | K8: =K4+IF(9=10,$C$11,0) -> 1048519.9 | L8: =L4+IF(10=10,$C$11,0) -> 6788955.4
A9: DCF
A10: PV of explicit forecast | C10: =SUM(C6:L6) -> 624929.63
A11: Terminal value at Y10 | C11: =L4*(1+Assumptions!$C$111)/(Assumptions!$C$110-Assumptions!$C$111) -> 5594099.3
A12: PV of terminal value | C12: =C11*L5 -> 600661.83
A13: ENTERPRISE VALUE (DCF) | C13: =C10+C12 -> 1225591.5
A15: RETURN METRICS
A16: NPV of FCF at WACC | C16: =NPV(Assumptions!$C$110,C4:L4) -> 624929.63
A17: IRR of the plan | C17: =IRR(C4:L4) -> 0.61845154
A18: IRR incl. terminal value | C18: =IRR(C8:L8,0.3) -> 0.70150512
A20: EXIT MULTIPLE
A21: Y10 net revenue | C21: =Revenue!L26 -> 5253768.6
A22: Exit value at Y10 | C22: =C21*Assumptions!$C$112 -> 34149496
A23: Discounted to today | C23: =C22*L5 -> 3666774.2
A25: SENSITIVITY: enterprise value by WACC and terminal growth
A26: Terminal growth \ WACC | C26: 0.18 | D26: 0.2 | E26: 0.22 | F26: 0.25 | G26: 0.28 | H26: 0.3
A27: 0.01 | C27: =CashFlow!C9/(1+C$26)^1+CashFlow!D9/(1+C$26)^2+CashFlow!E9/(1+C$26)^3+CashFlow!F9/(1+C$26)^4+CashFlow!G9/(1+C$26)^5+CashFlow!H9/(1+C$26)^6+CashFlow!I9/(1+C$26)^7+CashFlow!J9/(1+C$26)^8+CashFlow!K9/(1+C$26)^9+CashFlow!L9/(1+C$26)^10+CashFlow!L9*(1+$A27)/(C$26-$A27)/(1+C$26)^10 -> 2412232.2 | D27: =CashFlow!C9/(1+D$26)^1+CashFlow!D9/(1+D$26)^2+CashFlow!E9/(1+D$26)^3+CashFlow!F9/(1+D$26)^4+CashFlow!G9/(1+D$26)^5+CashFlow!H9/(1+D$26)^6+CashFlow!I9/(1+D$26)^7+CashFlow!J9/(1+D$26)^8+CashFlow!K9/(1+D$26)^9+CashFlow!L9/(1+D$26)^10+CashFlow!L9*(1+$A27)/(D$26-$A27)/(1+D$26)^10 -> 1934225.1 | E27: =CashFlow!C9/(1+E$26)^1+CashFlow!D9/(1+E$26)^2+CashFlow!E9/(1+E$26)^3+CashFlow!F9/(1+E$26)^4+CashFlow!G9/(1+E$26)^5+CashFlow!H9/(1+E$26)^6+CashFlow!I9/(1+E$26)^7+CashFlow!J9/(1+E$26)^8+CashFlow!K9/(1+E$26)^9+CashFlow!L9/(1+E$26)^10+CashFlow!L9*(1+$A27)/(E$26-$A27)/(1+E$26)^10 -> 1568747.2 | F27: =CashFlow!C9/(1+F$26)^1+CashFlow!D9/(1+F$26)^2+CashFlow!E9/(1+F$26)^3+CashFlow!F9/(1+F$26)^4+CashFlow!G9/(1+F$26)^5+CashFlow!H9/(1+F$26)^6+CashFlow!I9/(1+F$26)^7+CashFlow!J9/(1+F$26)^8+CashFlow!K9/(1+F$26)^9+CashFlow!L9/(1+F$26)^10+CashFlow!L9*(1+$A27)/(F$26-$A27)/(1+F$26)^10 -> 1164844.9 | G27: =CashFlow!C9/(1+G$26)^1+CashFlow!D9/(1+G$26)^2+CashFlow!E9/(1+G$26)^3+CashFlow!F9/(1+G$26)^4+CashFlow!G9/(1+G$26)^5+CashFlow!H9/(1+G$26)^6+CashFlow!I9/(1+G$26)^7+CashFlow!J9/(1+G$26)^8+CashFlow!K9/(1+G$26)^9+CashFlow!L9/(1+G$26)^10+CashFlow!L9*(1+$A27)/(G$26-$A27)/(1+G$26)^10 -> 877652.38 | H27: =CashFlow!C9/(1+H$26)^1+CashFlow!D9/(1+H$26)^2+CashFlow!E9/(1+H$26)^3+CashFlow!F9/(1+H$26)^4+CashFlow!G9/(1+H$26)^5+CashFlow!H9/(1+H$26)^6+CashFlow!I9/(1+H$26)^7+CashFlow!J9/(1+H$26)^8+CashFlow!K9/(1+H$26)^9+CashFlow!L9/(1+H$26)^10+CashFlow!L9*(1+$A27)/(H$26-$A27)/(1+H$26)^10 -> 730940.14
A28: 0.02 | C28: =CashFlow!C9/(1+C$26)^1+CashFlow!D9/(1+C$26)^2+CashFlow!E9/(1+C$26)^3+CashFlow!F9/(1+C$26)^4+CashFlow!G9/(1+C$26)^5+CashFlow!H9/(1+C$26)^6+CashFlow!I9/(1+C$26)^7+CashFlow!J9/(1+C$26)^8+CashFlow!K9/(1+C$26)^9+CashFlow!L9/(1+C$26)^10+CashFlow!L9*(1+$A28)/(C$26-$A28)/(1+C$26)^10 -> 2511271.7 | D28: =CashFlow!C9/(1+D$26)^1+CashFlow!D9/(1+D$26)^2+CashFlow!E9/(1+D$26)^3+CashFlow!F9/(1+D$26)^4+CashFlow!G9/(1+D$26)^5+CashFlow!H9/(1+D$26)^6+CashFlow!I9/(1+D$26)^7+CashFlow!J9/(1+D$26)^8+CashFlow!K9/(1+D$26)^9+CashFlow!L9/(1+D$26)^10+CashFlow!L9*(1+$A28)/(D$26-$A28)/(1+D$26)^10 -> 2001936 | E28: =CashFlow!C9/(1+E$26)^1+CashFlow!D9/(1+E$26)^2+CashFlow!E9/(1+E$26)^3+CashFlow!F9/(1+E$26)^4+CashFlow!G9/(1+E$26)^5+CashFlow!H9/(1+E$26)^6+CashFlow!I9/(1+E$26)^7+CashFlow!J9/(1+E$26)^8+CashFlow!K9/(1+E$26)^9+CashFlow!L9/(1+E$26)^10+CashFlow!L9*(1+$A28)/(E$26-$A28)/(1+E$26)^10 -> 1616261.9 | F28: =CashFlow!C9/(1+F$26)^1+CashFlow!D9/(1+F$26)^2+CashFlow!E9/(1+F$26)^3+CashFlow!F9/(1+F$26)^4+CashFlow!G9/(1+F$26)^5+CashFlow!H9/(1+F$26)^6+CashFlow!I9/(1+F$26)^7+CashFlow!J9/(1+F$26)^8+CashFlow!K9/(1+F$26)^9+CashFlow!L9/(1+F$26)^10+CashFlow!L9*(1+$A28)/(F$26-$A28)/(1+F$26)^10 -> 1193897.6 | G28: =CashFlow!C9/(1+G$26)^1+CashFlow!D9/(1+G$26)^2+CashFlow!E9/(1+G$26)^3+CashFlow!F9/(1+G$26)^4+CashFlow!G9/(1+G$26)^5+CashFlow!H9/(1+G$26)^6+CashFlow!I9/(1+G$26)^7+CashFlow!J9/(1+G$26)^8+CashFlow!K9/(1+G$26)^9+CashFlow!L9/(1+G$26)^10+CashFlow!L9*(1+$A28)/(G$26-$A28)/(1+G$26)^10 -> 896106.3 | H28: =CashFlow!C9/(1+H$26)^1+CashFlow!D9/(1+H$26)^2+CashFlow!E9/(1+H$26)^3+CashFlow!F9/(1+H$26)^4+CashFlow!G9/(1+H$26)^5+CashFlow!H9/(1+H$26)^6+CashFlow!I9/(1+H$26)^7+CashFlow!J9/(1+H$26)^8+CashFlow!K9/(1+H$26)^9+CashFlow!L9/(1+H$26)^10+CashFlow!L9*(1+$A28)/(H$26-$A28)/(1+H$26)^10 -> 744816.31
A29: 0.03 | C29: =CashFlow!C9/(1+C$26)^1+CashFlow!D9/(1+C$26)^2+CashFlow!E9/(1+C$26)^3+CashFlow!F9/(1+C$26)^4+CashFlow!G9/(1+C$26)^5+CashFlow!H9/(1+C$26)^6+CashFlow!I9/(1+C$26)^7+CashFlow!J9/(1+C$26)^8+CashFlow!K9/(1+C$26)^9+CashFlow!L9/(1+C$26)^10+CashFlow!L9*(1+$A29)/(C$26-$A29)/(1+C$26)^10 -> 2623516.5 | D29: =CashFlow!C9/(1+D$26)^1+CashFlow!D9/(1+D$26)^2+CashFlow!E9/(1+D$26)^3+CashFlow!F9/(1+D$26)^4+CashFlow!G9/(1+D$26)^5+CashFlow!H9/(1+D$26)^6+CashFlow!I9/(1+D$26)^7+CashFlow!J9/(1+D$26)^8+CashFlow!K9/(1+D$26)^9+CashFlow!L9/(1+D$26)^10+CashFlow!L9*(1+$A29)/(D$26-$A29)/(1+D$26)^10 -> 2077612.8 | E29: =CashFlow!C9/(1+E$26)^1+CashFlow!D9/(1+E$26)^2+CashFlow!E9/(1+E$26)^3+CashFlow!F9/(1+E$26)^4+CashFlow!G9/(1+E$26)^5+CashFlow!H9/(1+E$26)^6+CashFlow!I9/(1+E$26)^7+CashFlow!J9/(1+E$26)^8+CashFlow!K9/(1+E$26)^9+CashFlow!L9/(1+E$26)^10+CashFlow!L9*(1+$A29)/(E$26-$A29)/(1+E$26)^10 -> 1668778.1 | F29: =CashFlow!C9/(1+F$26)^1+CashFlow!D9/(1+F$26)^2+CashFlow!E9/(1+F$26)^3+CashFlow!F9/(1+F$26)^4+CashFlow!G9/(1+F$26)^5+CashFlow!H9/(1+F$26)^6+CashFlow!I9/(1+F$26)^7+CashFlow!J9/(1+F$26)^8+CashFlow!K9/(1+F$26)^9+CashFlow!L9/(1+F$26)^10+CashFlow!L9*(1+$A29)/(F$26-$A29)/(1+F$26)^10 -> 1225591.5 | G29: =CashFlow!C9/(1+G$26)^1+CashFlow!D9/(1+G$26)^2+CashFlow!E9/(1+G$26)^3+CashFlow!F9/(1+G$26)^4+CashFlow!G9/(1+G$26)^5+CashFlow!H9/(1+G$26)^6+CashFlow!I9/(1+G$26)^7+CashFlow!J9/(1+G$26)^8+CashFlow!K9/(1+G$26)^9+CashFlow!L9/(1+G$26)^10+CashFlow!L9*(1+$A29)/(G$26-$A29)/(1+G$26)^10 -> 916036.54 | H29: =CashFlow!C9/(1+H$26)^1+CashFlow!D9/(1+H$26)^2+CashFlow!E9/(1+H$26)^3+CashFlow!F9/(1+H$26)^4+CashFlow!G9/(1+H$26)^5+CashFlow!H9/(1+H$26)^6+CashFlow!I9/(1+H$26)^7+CashFlow!J9/(1+H$26)^8+CashFlow!K9/(1+H$26)^9+CashFlow!L9/(1+H$26)^10+CashFlow!L9*(1+$A29)/(H$26-$A29)/(1+H$26)^10 -> 759720.33
A30: 0.04 | C30: =CashFlow!C9/(1+C$26)^1+CashFlow!D9/(1+C$26)^2+CashFlow!E9/(1+C$26)^3+CashFlow!F9/(1+C$26)^4+CashFlow!G9/(1+C$26)^5+CashFlow!H9/(1+C$26)^6+CashFlow!I9/(1+C$26)^7+CashFlow!J9/(1+C$26)^8+CashFlow!K9/(1+C$26)^9+CashFlow!L9/(1+C$26)^10+CashFlow!L9*(1+$A30)/(C$26-$A30)/(1+C$26)^10 -> 2751796.3 | D30: =CashFlow!C9/(1+D$26)^1+CashFlow!D9/(1+D$26)^2+CashFlow!E9/(1+D$26)^3+CashFlow!F9/(1+D$26)^4+CashFlow!G9/(1+D$26)^5+CashFlow!H9/(1+D$26)^6+CashFlow!I9/(1+D$26)^7+CashFlow!J9/(1+D$26)^8+CashFlow!K9/(1+D$26)^9+CashFlow!L9/(1+D$26)^10+CashFlow!L9*(1+$A30)/(D$26-$A30)/(1+D$26)^10 -> 2162749.2 | E30: =CashFlow!C9/(1+E$26)^1+CashFlow!D9/(1+E$26)^2+CashFlow!E9/(1+E$26)^3+CashFlow!F9/(1+E$26)^4+CashFlow!G9/(1+E$26)^5+CashFlow!H9/(1+E$26)^6+CashFlow!I9/(1+E$26)^7+CashFlow!J9/(1+E$26)^8+CashFlow!K9/(1+E$26)^9+CashFlow!L9/(1+E$26)^10+CashFlow!L9*(1+$A30)/(E$26-$A30)/(1+E$26)^10 -> 1727129.5 | F30: =CashFlow!C9/(1+F$26)^1+CashFlow!D9/(1+F$26)^2+CashFlow!E9/(1+F$26)^3+CashFlow!F9/(1+F$26)^4+CashFlow!G9/(1+F$26)^5+CashFlow!H9/(1+F$26)^6+CashFlow!I9/(1+F$26)^7+CashFlow!J9/(1+F$26)^8+CashFlow!K9/(1+F$26)^9+CashFlow!L9/(1+F$26)^10+CashFlow!L9*(1+$A30)/(F$26-$A30)/(1+F$26)^10 -> 1260303.8 | G30: =CashFlow!C9/(1+G$26)^1+CashFlow!D9/(1+G$26)^2+CashFlow!E9/(1+G$26)^3+CashFlow!F9/(1+G$26)^4+CashFlow!G9/(1+G$26)^5+CashFlow!H9/(1+G$26)^6+CashFlow!I9/(1+G$26)^7+CashFlow!J9/(1+G$26)^8+CashFlow!K9/(1+G$26)^9+CashFlow!L9/(1+G$26)^10+CashFlow!L9*(1+$A30)/(G$26-$A30)/(1+G$26)^10 -> 937627.64 | H30: =CashFlow!C9/(1+H$26)^1+CashFlow!D9/(1+H$26)^2+CashFlow!E9/(1+H$26)^3+CashFlow!F9/(1+H$26)^4+CashFlow!G9/(1+H$26)^5+CashFlow!H9/(1+H$26)^6+CashFlow!I9/(1+H$26)^7+CashFlow!J9/(1+H$26)^8+CashFlow!K9/(1+H$26)^9+CashFlow!L9/(1+H$26)^10+CashFlow!L9*(1+$A30)/(H$26-$A30)/(1+H$26)^10 -> 775770.83
A31: 0.05 | C31: =CashFlow!C9/(1+C$26)^1+CashFlow!D9/(1+C$26)^2+CashFlow!E9/(1+C$26)^3+CashFlow!F9/(1+C$26)^4+CashFlow!G9/(1+C$26)^5+CashFlow!H9/(1+C$26)^6+CashFlow!I9/(1+C$26)^7+CashFlow!J9/(1+C$26)^8+CashFlow!K9/(1+C$26)^9+CashFlow!L9/(1+C$26)^10+CashFlow!L9*(1+$A31)/(C$26-$A31)/(1+C$26)^10 -> 2899811.5 | D31: =CashFlow!C9/(1+D$26)^1+CashFlow!D9/(1+D$26)^2+CashFlow!E9/(1+D$26)^3+CashFlow!F9/(1+D$26)^4+CashFlow!G9/(1+D$26)^5+CashFlow!H9/(1+D$26)^6+CashFlow!I9/(1+D$26)^7+CashFlow!J9/(1+D$26)^8+CashFlow!K9/(1+D$26)^9+CashFlow!L9/(1+D$26)^10+CashFlow!L9*(1+$A31)/(D$26-$A31)/(1+D$26)^10 -> 2259237.2 | E31: =CashFlow!C9/(1+E$26)^1+CashFlow!D9/(1+E$26)^2+CashFlow!E9/(1+E$26)^3+CashFlow!F9/(1+E$26)^4+CashFlow!G9/(1+E$26)^5+CashFlow!H9/(1+E$26)^6+CashFlow!I9/(1+E$26)^7+CashFlow!J9/(1+E$26)^8+CashFlow!K9/(1+E$26)^9+CashFlow!L9/(1+E$26)^10+CashFlow!L9*(1+$A31)/(E$26-$A31)/(1+E$26)^10 -> 1792345.7 | F31: =CashFlow!C9/(1+F$26)^1+CashFlow!D9/(1+F$26)^2+CashFlow!E9/(1+F$26)^3+CashFlow!F9/(1+F$26)^4+CashFlow!G9/(1+F$26)^5+CashFlow!H9/(1+F$26)^6+CashFlow!I9/(1+F$26)^7+CashFlow!J9/(1+F$26)^8+CashFlow!K9/(1+F$26)^9+CashFlow!L9/(1+F$26)^10+CashFlow!L9*(1+$A31)/(F$26-$A31)/(1+F$26)^10 -> 1298487.3 | G31: =CashFlow!C9/(1+G$26)^1+CashFlow!D9/(1+G$26)^2+CashFlow!E9/(1+G$26)^3+CashFlow!F9/(1+G$26)^4+CashFlow!G9/(1+G$26)^5+CashFlow!H9/(1+G$26)^6+CashFlow!I9/(1+G$26)^7+CashFlow!J9/(1+G$26)^8+CashFlow!K9/(1+G$26)^9+CashFlow!L9/(1+G$26)^10+CashFlow!L9*(1+$A31)/(G$26-$A31)/(1+G$26)^10 -> 961096.22 | H31: =CashFlow!C9/(1+H$26)^1+CashFlow!D9/(1+H$26)^2+CashFlow!E9/(1+H$26)^3+CashFlow!F9/(1+H$26)^4+CashFlow!G9/(1+H$26)^5+CashFlow!H9/(1+H$26)^6+CashFlow!I9/(1+H$26)^7+CashFlow!J9/(1+H$26)^8+CashFlow!K9/(1+H$26)^9+CashFlow!L9/(1+H$26)^10+CashFlow!L9*(1+$A31)/(H$26-$A31)/(1+H$26)^10 -> 793105.36
A32: Both axes are live inputs: edit a WACC header or a growth label and the grid recomputes.

Sheet Funding
A1: Funding rounds and dilution
A2: Line | B2: Unit | C2: Y1 | D2: Y2 | E2: Y3 | F2: Y4 | G2: Y5 | H2: Y6 | I2: Y7 | J2: Y8 | K2: Y9 | L2: Y10
A4: Equity raised | B4: EUR | C4: 150000 | D4: 250000 | E4: 0 | F4: 0 | G4: 0 | H4: 1500000 | I4: 0 | J4: 0 | K4: 0 | L4: 0
A5: Pre-money valuation | B5: EUR | C5: 1800000 | D5: 3500000 | E5: 0 | F5: 0 | G5: 0 | H5: 12000000 | I5: 0 | J5: 0 | K5: 0 | L5: 0 | M5: Both rounds are priced against Sponsoo, the closest comparable there is: our pre-seed at EUR 1.8M against their EUR 1.55M seed, and the growth round at EUR 12M against their EUR 15.9M Series A.
A6: Post-money valuation | B6: EUR | C6: =IF(C4=0,0,C5+C4) -> 1950000 | D6: =IF(D4=0,0,D5+D4) -> 3750000 | E6: =IF(E4=0,0,E5+E4) -> 0 | F6: =IF(F4=0,0,F5+F4) -> 0 | G6: =IF(G4=0,0,G5+G4) -> 0 | H6: =IF(H4=0,0,H5+H4) -> 13500000 | I6: =IF(I4=0,0,I5+I4) -> 0 | J6: =IF(J4=0,0,J5+J4) -> 0 | ... L6: =IF(L4=0,0,L5+L4) -> 0
A7: New investor stake | B7: % | C7: =IF(C6=0,0,C4/C6) -> 0.076923077 | D7: =IF(D6=0,0,D4/D6) -> 0.066666667 | E7: =IF(E6=0,0,E4/E6) -> 0 | F7: =IF(F6=0,0,F4/F6) -> 0 | G7: =IF(G6=0,0,G4/G6) -> 0 | H7: =IF(H6=0,0,H4/H6) -> 0.11111111 | I7: =IF(I6=0,0,I4/I6) -> 0 | J7: =IF(J6=0,0,J4/J6) -> 0 | ... L7: =IF(L6=0,0,L4/L6) -> 0
A8: Athlete partner equity | B8: % | C8: 0.05 | D8: 0 | E8: 0 | F8: 0 | G8: 0 | H8: 0 | I8: 0 | J8: 0 | K8: 0 | L8: 0 | M8: 5% to an athlete partner at the pre-seed, paid in equity rather than cash. The anchor athlete the pre-seed gate depends on: they put their name and their audience behind a product that does not exist yet. Four-year vesting, one-year cliff.
A9: ESOP pool | B9: % | C9: 0 | D9: 0 | E9: 0 | F9: 0 | G9: 0 | H9: 0.1 | I9: 0 | J9: 0 | K9: 0 | L9: 0 | M9: Employee Stock Option Pool: 10% reserved for employee options at the growth round, which is when there is institutional money and people worth keeping.
A10: Founders + team retained | B10: % | C10: =(1-C7-C8)*(1-C9) -> 0.87307692 | D10: =(C10*(1-D7)-D8)*(1-D9) -> 0.81487179 | E10: =(D10*(1-E7)-E8)*(1-E9) -> 0.81487179 | F10: =(E10*(1-F7)-F8)*(1-F9) -> 0.81487179 | G10: =(F10*(1-G7)-G8)*(1-G9) -> 0.81487179 | H10: =(G10*(1-H7)-H8)*(1-H9) -> 0.65189744 | I10: =(H10*(1-I7)-I8)*(1-I9) -> 0.65189744 | J10: =(I10*(1-J7)-J8)*(1-J9) -> 0.65189744 | K10: =(J10*(1-K7)-K8)*(1-K9) -> 0.65189744 | L10: =(K10*(1-L7)-L8)*(1-L9) -> 0.65189744
A11: Cumulative dilution | B11: % | C11: =1-C10 -> 0.12692308 | D11: =1-D10 -> 0.18512821 | E11: =1-E10 -> 0.18512821 | F11: =1-F10 -> 0.18512821 | G11: =1-G10 -> 0.18512821 | H11: =1-H10 -> 0.34810256 | I11: =1-I10 -> 0.34810256 | J11: =1-J10 -> 0.34810256 | ... L11: =1-L10 -> 0.34810256

Sheet HiringPlan
A1: Hiring plan
A2: Line | B2: Unit | C2: Y1 | D2: Y2 | E2: Y3 | F2: Y4 | G2: Y5 | H2: Y6 | I2: Y7 | J2: Y8 | K2: Y9 | L2: Y10
A4: FTE BY ROLE
A5: Founder / CEO | B5: FTE | C5: 1 | D5: 1 | E5: 1 | F5: 1 | G5: 1 | H5: 1 | I5: 1 | J5: 1 | K5: 1 | L5: 1
A6: Engineering | B6: FTE | C6: 0 | D6: 0.5 | E6: 0.5 | F6: 1 | G6: 1.5 | H6: 2.5 | I6: 3.5 | J6: 4.5 | K6: 5 | L6: 5
A7: BD / partnerships | B7: FTE | C7: 0 | D7: 0 | E7: 0 | F7: 0 | G7: 0.5 | H7: 1 | I7: 2 | J7: 2.5 | K7: 3 | L7: 3.5
A8: Athlete success | B8: FTE | C8: 0 | D8: 0 | E8: 0 | F8: 0 | G8: 0.5 | H8: 1 | I8: 1.5 | J8: 2 | K8: 2.5 | L8: 3
A9: Trust & safety / review | B9: FTE | C9: 0 | D9: 0 | E9: 0 | F9: 0 | G9: 0.5 | H9: 1 | I9: 1 | J9: 1.5 | K9: 1.5 | L9: 2
A10: Finance / operations | B10: FTE | C10: 0 | D10: 0 | E10: 0 | F10: 0 | G10: 0 | H10: 0.5 | I10: 0.5 | J10: 0.5 | K10: 1 | L10: 1
A11: Data protection officer | B11: FTE | C11: 0 | D11: 0 | E11: 0 | F11: 0 | G11: 0 | H11: 0 | I11: 0.5 | J11: 0.5 | K11: 0.5 | L11: 0.5
A12: TOTAL FTE | B12: FTE | C12: =SUM(C5:C11) -> 1 | D12: =SUM(D5:D11) -> 1.5 | E12: =SUM(E5:E11) -> 1.5 | F12: =SUM(F5:F11) -> 2 | G12: =SUM(G5:G11) -> 4 | H12: =SUM(H5:H11) -> 7 | I12: =SUM(I5:I11) -> 10 | J12: =SUM(J5:J11) -> 12.5 | ... L12: =SUM(L5:L11) -> 16
A14: COST: ROLE BUILD-UP AGAINST THE MODEL
A15: Employer social security | B15: on gross | C15: 0.32 | D15: 0.32 | E15: 0.32 | F15: 0.32 | G15: 0.32 | H15: 0.32 | I15: 0.32 | J15: 0.32 | K15: 0.32 | L15: 0.32
A16: GROSS SALARY BY ROLE | B16: EUR, before employer SS
A17: Founder / CEO | B17: EUR | C17: 45000 | D17: =C17 -> 45000 | E17: =C17 -> 45000 | F17: =C17 -> 45000 | G17: =C17 -> 45000 | H17: =C17 -> 45000 | I17: =C17 -> 45000 | J17: =C17 -> 45000 | K17: =C17 -> 45000 | L17: =C17 -> 45000
A18: Engineering | B18: EUR | C18: 55000 | D18: =C18 -> 55000 | E18: =C18 -> 55000 | F18: =C18 -> 55000 | G18: =C18 -> 55000 | H18: =C18 -> 55000 | I18: =C18 -> 55000 | J18: =C18 -> 55000 | K18: =C18 -> 55000 | L18: =C18 -> 55000
A19: BD / partnerships | B19: EUR | C19: 38000 | D19: =C19 -> 38000 | E19: =C19 -> 38000 | F19: =C19 -> 38000 | G19: =C19 -> 38000 | H19: =C19 -> 38000 | I19: =C19 -> 38000 | J19: =C19 -> 38000 | K19: =C19 -> 38000 | L19: =C19 -> 38000
A20: Athlete success | B20: EUR | C20: 30000 | D20: =C20 -> 30000 | E20: =C20 -> 30000 | F20: =C20 -> 30000 | G20: =C20 -> 30000 | H20: =C20 -> 30000 | I20: =C20 -> 30000 | J20: =C20 -> 30000 | K20: =C20 -> 30000 | L20: =C20 -> 30000
A21: Trust & safety / review | B21: EUR | C21: 34000 | D21: =C21 -> 34000 | E21: =C21 -> 34000 | F21: =C21 -> 34000 | G21: =C21 -> 34000 | H21: =C21 -> 34000 | I21: =C21 -> 34000 | J21: =C21 -> 34000 | K21: =C21 -> 34000 | L21: =C21 -> 34000
A22: Finance / operations | B22: EUR | C22: 42000 | D22: =C22 -> 42000 | E22: =C22 -> 42000 | F22: =C22 -> 42000 | G22: =C22 -> 42000 | H22: =C22 -> 42000 | I22: =C22 -> 42000 | J22: =C22 -> 42000 | K22: =C22 -> 42000 | L22: =C22 -> 42000
A23: Data protection officer | B23: EUR | C23: 60000 | D23: =C23 -> 60000 | E23: =C23 -> 60000 | F23: =C23 -> 60000 | G23: =C23 -> 60000 | H23: =C23 -> 60000 | I23: =C23 -> 60000 | J23: =C23 -> 60000 | K23: =C23 -> 60000 | L23: =C23 -> 60000
A25: Founder / CEO: loaded | B25: EUR | C25: =C5*C$17*(1+C15) -> 59400 | D25: =D5*D$17*(1+D15) -> 59400 | E25: =E5*E$17*(1+E15) -> 59400 | F25: =F5*F$17*(1+F15) -> 59400 | G25: =G5*G$17*(1+G15) -> 59400 | H25: =H5*H$17*(1+H15) -> 59400 | I25: =I5*I$17*(1+I15) -> 59400 | J25: =J5*J$17*(1+J15) -> 59400 | ... L25: =L5*L$17*(1+L15) -> 59400
A26: Engineering: loaded | B26: EUR | C26: =C6*C$18*(1+C15) -> 0 | D26: =D6*D$18*(1+D15) -> 36300 | E26: =E6*E$18*(1+E15) -> 36300 | F26: =F6*F$18*(1+F15) -> 72600 | G26: =G6*G$18*(1+G15) -> 108900 | H26: =H6*H$18*(1+H15) -> 181500 | I26: =I6*I$18*(1+I15) -> 254100 | J26: =J6*J$18*(1+J15) -> 326700 | ... L26: =L6*L$18*(1+L15) -> 363000
A27: BD / partnerships: loaded | B27: EUR | C27: =C7*C$19*(1+C15) -> 0 | D27: =D7*D$19*(1+D15) -> 0 | E27: =E7*E$19*(1+E15) -> 0 | F27: =F7*F$19*(1+F15) -> 0 | G27: =G7*G$19*(1+G15) -> 25080 | H27: =H7*H$19*(1+H15) -> 50160 | I27: =I7*I$19*(1+I15) -> 100320 | J27: =J7*J$19*(1+J15) -> 125400 | ... L27: =L7*L$19*(1+L15) -> 175560
A28: Athlete success: loaded | B28: EUR | C28: =C8*C$20*(1+C15) -> 0 | D28: =D8*D$20*(1+D15) -> 0 | E28: =E8*E$20*(1+E15) -> 0 | F28: =F8*F$20*(1+F15) -> 0 | G28: =G8*G$20*(1+G15) -> 19800 | H28: =H8*H$20*(1+H15) -> 39600 | I28: =I8*I$20*(1+I15) -> 59400 | J28: =J8*J$20*(1+J15) -> 79200 | ... L28: =L8*L$20*(1+L15) -> 118800
A29: Trust & safety / review: loaded | B29: EUR | C29: =C9*C$21*(1+C15) -> 0 | D29: =D9*D$21*(1+D15) -> 0 | E29: =E9*E$21*(1+E15) -> 0 | F29: =F9*F$21*(1+F15) -> 0 | G29: =G9*G$21*(1+G15) -> 22440 | H29: =H9*H$21*(1+H15) -> 44880 | I29: =I9*I$21*(1+I15) -> 44880 | J29: =J9*J$21*(1+J15) -> 67320 | ... L29: =L9*L$21*(1+L15) -> 89760
A30: Finance / operations: loaded | B30: EUR | C30: =C10*C$22*(1+C15) -> 0 | D30: =D10*D$22*(1+D15) -> 0 | E30: =E10*E$22*(1+E15) -> 0 | F30: =F10*F$22*(1+F15) -> 0 | G30: =G10*G$22*(1+G15) -> 0 | H30: =H10*H$22*(1+H15) -> 27720 | I30: =I10*I$22*(1+I15) -> 27720 | J30: =J10*J$22*(1+J15) -> 27720 | ... L30: =L10*L$22*(1+L15) -> 55440
A31: Data protection officer: loaded | B31: EUR | C31: =C11*C$23*(1+C15) -> 0 | D31: =D11*D$23*(1+D15) -> 0 | E31: =E11*E$23*(1+E15) -> 0 | F31: =F11*F$23*(1+F15) -> 0 | G31: =G11*G$23*(1+G15) -> 0 | H31: =H11*H$23*(1+H15) -> 0 | I31: =I11*I$23*(1+I15) -> 39600 | J31: =J11*J$23*(1+J15) -> 39600 | ... L31: =L11*L$23*(1+L15) -> 39600
A32: TOTAL, role build-up | B32: EUR | C32: =SUM(C25:C31) -> 59400 | D32: =SUM(D25:D31) -> 95700 | E32: =SUM(E25:E31) -> 95700 | F32: =SUM(F25:F31) -> 132000 | G32: =SUM(G25:G31) -> 235620 | H32: =SUM(H25:H31) -> 403260 | I32: =SUM(I25:I31) -> 585420 | J32: =SUM(J25:J31) -> 725340 | ... L32: =SUM(L25:L31) -> 901560
A33: People cost in the model | B33: Costs | C33: =Costs!C17 -> 38000 | D33: =Costs!D17 -> 78000 | E33: =Costs!E17 -> 90000 | F33: =Costs!F17 -> 128000 | G33: =Costs!G17 -> 264000 | H33: =Costs!H17 -> 476000 | I33: =Costs!I17 -> 700000 | J33: =Costs!J17 -> 900000 | ... L33: =Costs!L17 -> 1216000
A34: Difference: role mix | B34: build-up less model | C34: =C32-C33 -> 21400 | D34: =D32-D33 -> 17700 | E34: =E32-E33 -> 5700 | F34: =F32-F33 -> 4000 | G34: =G32-G33 -> -28380 | H34: =H32-H33 -> -72740 | I34: =I32-I33 -> -114580 | J34: =J32-J33 -> -174660 | ... L34: =L32-L33 -> -314440
A35: memo: build-up per FTE | B35: EUR | C35: =IF(C12=0,0,C32/C12) -> 59400 | D35: =IF(D12=0,0,D32/D12) -> 63800 | E35: =IF(E12=0,0,E32/E12) -> 63800 | F35: =IF(F12=0,0,F32/F12) -> 66000 | G35: =IF(G12=0,0,G32/G12) -> 58905 | H35: =IF(H12=0,0,H32/H12) -> 57608.571 | I35: =IF(I12=0,0,I32/I12) -> 58542 | J35: =IF(J12=0,0,J32/J12) -> 58027.2 | ... L35: =IF(L12=0,0,L32/L12) -> 56347.5
A36: memo: model blended per FTE | B36: EUR | C36: =Assumptions!C67 -> 38000 | D36: =Assumptions!D67 -> 52000 | E36: =Assumptions!E67 -> 60000 | F36: =Assumptions!F67 -> 64000 | G36: =Assumptions!G67 -> 66000 | H36: =Assumptions!H67 -> 68000 | I36: =Assumptions!I67 -> 70000 | J36: =Assumptions!J67 -> 72000 | ... L36: =Assumptions!L67 -> 76000
A38: The FTE block reconciles exactly and is the plan. The cost build-up prices those roles at their own salaries; the model prices the same headcount at a blended loaded average that rises from 38k to 76k over the plan, while the build-up holds today's salaries flat. The two cross over at Y4: the build-up is the higher figure in Y1-Y3, where one founder salary dominates a team of two or three, and the model is higher from Y4 as its blended rate climbs. The model is the one that reaches the P&L either way. The memo rows below make the two rates comparable.

Sheet CAC_CLV
A1: Customer acquisition cost and lifetime value
A2: Line | B2: Unit | C2: Y1 | D2: Y2 | E2: Y3 | F2: Y4 | G2: Y5 | H2: Y6 | I2: Y7 | J2: Y8 | K2: Y9 | L2: Y10
A4: ATHLETE: BLENDED ACROSS SEGMENTS
A5: Niche share of athletes | B5: % | C5: =Assumptions!C6 -> 0.95 | D5: =Assumptions!D6 -> 0.92 | E5: =Assumptions!E6 -> 0.8 | F5: =Assumptions!F6 -> 0.68 | G5: =Assumptions!G6 -> 0.58 | H5: =Assumptions!H6 -> 0.5 | I5: =Assumptions!I6 -> 0.45 | J5: =Assumptions!J6 -> 0.43 | ... L5: =Assumptions!L6 -> 0.41
A6: Blended CAC per athlete acquired | B6: spend / gross adds | C6: =IF(Drivers!C40=0,0,(Costs!C18+Costs!C19)/Drivers!C40) -> 17.2 | D6: =IF(Drivers!D40=0,0,(Costs!D18+Costs!D19)/Drivers!D40) -> 20.538174 | E6: =IF(Drivers!E40=0,0,(Costs!E18+Costs!E19)/Drivers!E40) -> 29.412138 | F6: =IF(Drivers!F40=0,0,(Costs!F18+Costs!F19)/Drivers!F40) -> 39.641046 | G6: =IF(Drivers!G40=0,0,(Costs!G18+Costs!G19)/Drivers!G40) -> 49.340426 | H6: =IF(Drivers!H40=0,0,(Costs!H18+Costs!H19)/Drivers!H40) -> 57.710734 | I6: =IF(Drivers!I40=0,0,(Costs!I18+Costs!I19)/Drivers!I40) -> 62.888785 | J6: =IF(Drivers!J40=0,0,(Costs!J18+Costs!J19)/Drivers!J40) -> 65.095563 | ... L6: =IF(Drivers!L40=0,0,(Costs!L18+Costs!L19)/Drivers!L40) -> 70.274159
A7: Blended athlete churn | B7: gross-add weighted | C7: =IF(Drivers!C40=0,0,(Drivers!C11*Assumptions!C14+Drivers!C25*Assumptions!C26)/Drivers!C40) -> 0.3025 | D7: =IF(Drivers!D40=0,0,(Drivers!D11*Assumptions!D14+Drivers!D25*Assumptions!D26)/Drivers!D40) -> 0.27453245 | E7: =IF(Drivers!E40=0,0,(Drivers!E11*Assumptions!E14+Drivers!E25*Assumptions!E26)/Drivers!E40) -> 0.25577276 | F7: =IF(Drivers!F40=0,0,(Drivers!F11*Assumptions!F14+Drivers!F25*Assumptions!F26)/Drivers!F40) -> 0.24172368 | G7: =IF(Drivers!G40=0,0,(Drivers!G11*Assumptions!G14+Drivers!G25*Assumptions!G26)/Drivers!G40) -> 0.22792553 | H7: =IF(Drivers!H40=0,0,(Drivers!H11*Assumptions!H14+Drivers!H25*Assumptions!H26)/Drivers!H40) -> 0.21577743 | I7: =IF(Drivers!I40=0,0,(Drivers!I11*Assumptions!I14+Drivers!I25*Assumptions!I26)/Drivers!I40) -> 0.20685981 | J7: =IF(Drivers!J40=0,0,(Drivers!J11*Assumptions!J14+Drivers!J25*Assumptions!J26)/Drivers!J40) -> 0.19591297 | ... L7: =IF(Drivers!L40=0,0,(Drivers!L11*Assumptions!L14+Drivers!L25*Assumptions!L26)/Drivers!L40) -> 0.18636474
A8: Expected athlete life | B8: years | C8: =IF(C7=0,0,1/C7) -> 3.3057851 | D8: =IF(D7=0,0,1/D7) -> 3.6425566 | E8: =IF(E7=0,0,1/E7) -> 3.9097205 | F8: =IF(F7=0,0,1/F7) -> 4.1369551 | G8: =IF(G7=0,0,1/G7) -> 4.3873979 | H8: =IF(H7=0,0,1/H7) -> 4.6344051 | I8: =IF(I7=0,0,1/I7) -> 4.8341917 | J8: =IF(J7=0,0,1/J7) -> 5.1043073 | ... L8: =IF(L7=0,0,1/L7) -> 5.365822
A9: Net revenue per athlete | B9: EUR/yr | C9: =IF(Drivers!C5=0,0,Revenue!C26/Drivers!C5) -> 8.58552 | D9: =IF(Drivers!D5=0,0,Revenue!D26/Drivers!D5) -> 91.165045 | E9: =IF(Drivers!E5=0,0,Revenue!E26/Drivers!E5) -> 168.71694 | F9: =IF(Drivers!F5=0,0,Revenue!F26/Drivers!F5) -> 251.30977 | G9: =IF(Drivers!G5=0,0,Revenue!G26/Drivers!G5) -> 330.33753 | H9: =IF(Drivers!H5=0,0,Revenue!H26/Drivers!H5) -> 408.47086 | I9: =IF(Drivers!I5=0,0,Revenue!I26/Drivers!I5) -> 478.27988 | J9: =IF(Drivers!J5=0,0,Revenue!J26/Drivers!J5) -> 535.19974 | ... L9: =IF(Drivers!L5=0,0,Revenue!L26/Drivers!L5) -> 618.09043
A10: Contribution per athlete per year | B10: after COGS | C10: =IF(Revenue!C26=0,0,C9*'P&L'!C6/Revenue!C26) -> -5.1053162 | D10: =IF(Revenue!D26=0,0,D9*'P&L'!D6/Revenue!D26) -> 48.688663 | E10: =IF(Revenue!E26=0,0,E9*'P&L'!E6/Revenue!E26) -> 105.95516 | F10: =IF(Revenue!F26=0,0,F9*'P&L'!F6/Revenue!F26) -> 167.31067 | G10: =IF(Revenue!G26=0,0,G9*'P&L'!G6/Revenue!G26) -> 224.99298 | H10: =IF(Revenue!H26=0,0,H9*'P&L'!H6/Revenue!H26) -> 281.7421 | I10: =IF(Revenue!I26=0,0,I9*'P&L'!I6/Revenue!I26) -> 331.61502 | J10: =IF(Revenue!J26=0,0,J9*'P&L'!J6/Revenue!J26) -> 371.88693 | ... L10: =IF(Revenue!L26=0,0,L9*'P&L'!L6/Revenue!L26) -> 430.83171
A11: ATHLETE LTV | B11: EUR | C11: =C10*C8 -> -16.877078 | D11: =D10*D8 -> 177.35121 | E11: =E10*E8 -> 414.25507 | F11: =F10*F8 -> 692.15673 | G11: =G10*G8 -> 987.13371 | H11: =H10*H8 -> 1305.707 | I11: =I10*I8 -> 1603.0906 | J11: =J10*J8 -> 1898.2252 | ... L11: =L10*L8 -> 2311.7662
A12: LTV / CAC | B12: x | C12: =IF(C6=0,0,C11/C6) -> -0.98122549 | D12: =IF(D6=0,0,D11/D6) -> 8.6351986 | E12: =IF(E6=0,0,E11/E6) -> 14.084494 | F12: =IF(F6=0,0,F11/F6) -> 17.460607 | G12: =IF(G6=0,0,G11/G6) -> 20.006591 | H12: =IF(H6=0,0,H11/H6) -> 22.625028 | I12: =IF(I6=0,0,I11/I6) -> 25.490882 | J12: =IF(J6=0,0,J11/J6) -> 29.160592 | ... L12: =IF(L6=0,0,L11/L6) -> 32.896392
A13: CAC payback | B13: months | C13: =IF(C10<=0,0,12*C6/C10) -> 0 | D13: =IF(D10<=0,0,12*D6/D10) -> 5.0619194 | E13: =IF(E10<=0,0,12*E6/E10) -> 3.331085 | F13: =IF(F10<=0,0,12*F6/F10) -> 2.8431693 | G13: =IF(G10<=0,0,12*G6/G10) -> 2.6315715 | H13: =IF(H10<=0,0,12*H6/H10) -> 2.4580239 | I13: =IF(I10<=0,0,12*I6/I10) -> 2.2757275 | J13: =IF(J10<=0,0,12*J6/J10) -> 2.1004953 | ... L13: =IF(L10<=0,0,12*L6/L10) -> 1.9573534
A15: The athlete LTV/CAC ratio is unusually high, and that is the thesis rather than an error: acquisition is cheap precisely because there is no incumbent agent to outbid in these sports. It should be read alongside the fan LTV below, which is small: the economics work on volume of athletes, not on the value of any one of them.
A18: FAN: NICHE SUBSCRIPTION ONLY | D18: excludes PPV and tips, which the revenue model carries separately
A19: Fan ARPU, VAT inclusive | B19: EUR/mo | C19: =Assumptions!C12 -> 8 | D19: =Assumptions!D12 -> 8.3 | E19: =Assumptions!E12 -> 8.6 | F19: =Assumptions!F12 -> 8.8 | G19: =Assumptions!G12 -> 9 | H19: =Assumptions!H12 -> 9.1 | I19: =Assumptions!I12 -> 9.2 | J19: =Assumptions!J12 -> 9.3 | ... L19: =Assumptions!L12 -> 9.5
A20: Net of VAT | B20: EUR/mo | C20: =C19/(1+Assumptions!C48) -> 6.6115702 | D20: =D19/(1+Assumptions!D48) -> 6.8595041 | E20: =E19/(1+Assumptions!E48) -> 7.107438 | F20: =F19/(1+Assumptions!F48) -> 7.2727273 | G20: =G19/(1+Assumptions!G48) -> 7.4380165 | H20: =H19/(1+Assumptions!H48) -> 7.5206612 | I20: =I19/(1+Assumptions!I48) -> 7.6033058 | J20: =J19/(1+Assumptions!J48) -> 7.6859504 | ... L20: =L19/(1+Assumptions!L48) -> 7.8512397
A21: Our take | B21: EUR/mo | C21: =C20*Assumptions!C40 -> 0.99173554 | D21: =D20*Assumptions!D40 -> 1.0289256 | E21: =E20*Assumptions!E40 -> 1.0661157 | F21: =F20*Assumptions!F40 -> 1.0909091 | G21: =G20*Assumptions!G40 -> 1.1157025 | H21: =H20*Assumptions!H40 -> 1.1280992 | I21: =I20*Assumptions!I40 -> 1.1404959 | J21: =J20*Assumptions!J40 -> 1.1528926 | ... L21: =L20*Assumptions!L40 -> 1.177686
A22: Payment cost on the charge | B22: EUR/mo | C22: =C19*Assumptions!C50+Assumptions!C51 -> 0.402 | D22: =D19*Assumptions!D50+Assumptions!D51 -> 0.4077 | E22: =E19*Assumptions!E50+Assumptions!E51 -> 0.4134 | F22: =F19*Assumptions!F50+Assumptions!F51 -> 0.4172 | G22: =G19*Assumptions!G50+Assumptions!G51 -> 0.421 | H22: =H19*Assumptions!H50+Assumptions!H51 -> 0.4229 | I22: =I19*Assumptions!I50+Assumptions!I51 -> 0.4248 | J22: =J19*Assumptions!J50+Assumptions!J51 -> 0.4267 | ... L22: =L19*Assumptions!L50+Assumptions!L51 -> 0.4305
A23: Payout cost, share per fan month | B23: EUR | C23: =C19*Assumptions!C52+Assumptions!C53/30 -> 0.028333333 | D23: =D19*Assumptions!D52+Assumptions!D53/30 -> 0.029083333 | E23: =E19*Assumptions!E52+Assumptions!E53/30 -> 0.029833333 | F23: =F19*Assumptions!F52+Assumptions!F53/30 -> 0.030333333 | G23: =G19*Assumptions!G52+Assumptions!G53/30 -> 0.030833333 | H23: =H19*Assumptions!H52+Assumptions!H53/30 -> 0.031083333 | I23: =I19*Assumptions!I52+Assumptions!I53/30 -> 0.031333333 | J23: =J19*Assumptions!J52+Assumptions!J53/30 -> 0.031583333 | ... L23: =L19*Assumptions!L52+Assumptions!L53/30 -> 0.032083333
A24: Contribution per fan month | B24: EUR | C24: =C21-C22-C23 -> 0.5614022 | D24: =D21-D22-D23 -> 0.59214229 | E24: =E21-E22-E23 -> 0.62288237 | F24: =F21-F22-F23 -> 0.64337576 | G24: =G21-G22-G23 -> 0.66386915 | H24: =H21-H22-H23 -> 0.67411584 | I24: =I21-I22-I23 -> 0.68436253 | J24: =J21-J22-J23 -> 0.69460923 | ... L24: =L21-L22-L23 -> 0.71510262
A25: Fan churn | B25: per month | C25: =Assumptions!C13 -> 0.09 | D25: =Assumptions!D13 -> 0.085 | E25: =Assumptions!E13 -> 0.08 | F25: =Assumptions!F13 -> 0.075 | G25: =Assumptions!G13 -> 0.07 | H25: =Assumptions!H13 -> 0.065 | I25: =Assumptions!I13 -> 0.06 | J25: =Assumptions!J13 -> 0.058 | ... L25: =Assumptions!L13 -> 0.055
A26: Expected fan life | B26: months | C26: =IF(C25=0,0,1/C25) -> 11.111111 | D26: =IF(D25=0,0,1/D25) -> 11.764706 | E26: =IF(E25=0,0,1/E25) -> 12.5 | F26: =IF(F25=0,0,1/F25) -> 13.333333 | G26: =IF(G25=0,0,1/G25) -> 14.285714 | H26: =IF(H25=0,0,1/H25) -> 15.384615 | I26: =IF(I25=0,0,1/I25) -> 16.666667 | J26: =IF(J25=0,0,1/J25) -> 17.241379 | ... L26: =IF(L25=0,0,1/L25) -> 18.181818
A27: FAN LTV | B27: EUR | C27: =C24*C26 -> 6.2378023 | D27: =D24*D26 -> 6.9663798 | E27: =E24*E26 -> 7.7860296 | F27: =F24*F26 -> 8.5783434 | G27: =G24*G26 -> 9.4838449 | H27: =H24*H26 -> 10.371013 | I27: =I24*I26 -> 11.406042 | J27: =J24*J26 -> 11.976021 | ... L27: =L24*L26 -> 13.001866
A28: Fan CAC | B28: EUR | C28: 0 | D28: 0 | E28: 0 | F28: 0 | G28: 0 | H28: 0 | I28: 0 | J28: 0 | K28: 0 | L28: 0
A30: Fan CAC is zero by construction: athletes bring their own audiences and the model spends nothing acquiring fans. That understates the risk rather than flattering the return, and the plan discloses it as such.
A32: SPONSOR
A33: Sponsor CAC | B33: EUR | C33: =Assumptions!C37 -> 900 | D33: =Assumptions!D37 -> 1050 | E33: =Assumptions!E37 -> 1200 | F33: =Assumptions!F37 -> 1400 | G33: =Assumptions!G37 -> 1600 | H33: =Assumptions!H37 -> 1750 | I33: =Assumptions!I37 -> 1900 | J33: =Assumptions!J37 -> 2000 | ... L33: =Assumptions!L37 -> 2200
A34: SaaS per paying sponsor | B34: EUR/yr | C34: =Assumptions!C36*12 -> 2388 | D34: =Assumptions!D36*12 -> 2748 | E34: =Assumptions!E36*12 -> 3120 | F34: =Assumptions!F36*12 -> 3480 | G34: =Assumptions!G36*12 -> 3840 | H34: =Assumptions!H36*12 -> 4320 | I34: =Assumptions!I36*12 -> 4800 | J34: =Assumptions!J36*12 -> 5160 | ... L34: =Assumptions!L36*12 -> 5700
A35: Sponsorship take per paying sponsor | B35: EUR/yr | C35: =IF(Drivers!C48=0,0,Revenue!C24/Drivers!C48) -> 7151.4667 | D35: =IF(Drivers!D48=0,0,Revenue!D24/Drivers!D48) -> 3182.4394 | E35: =IF(Drivers!E48=0,0,Revenue!E24/Drivers!E48) -> 2555.6767 | F35: =IF(Drivers!F48=0,0,Revenue!F24/Drivers!F48) -> 3269.5994 | G35: =IF(Drivers!G48=0,0,Revenue!G24/Drivers!G48) -> 4548.7224 | H35: =IF(Drivers!H48=0,0,Revenue!H24/Drivers!H48) -> 6364.2426 | I35: =IF(Drivers!I48=0,0,Revenue!I24/Drivers!I48) -> 7919.4049 | J35: =IF(Drivers!J48=0,0,Revenue!J24/Drivers!J48) -> 9187.9222 | ... L35: =IF(Drivers!L48=0,0,Revenue!L24/Drivers!L48) -> 10926.54
A36: Contribution per sponsor per year | B36: EUR | C36: =C34+C35 -> 9539.4667 | D36: =D34+D35 -> 5930.4394 | E36: =E34+E35 -> 5675.6767 | F36: =F34+F35 -> 6749.5994 | G36: =G34+G35 -> 8388.7224 | H36: =H34+H35 -> 10684.243 | I36: =I34+I35 -> 12719.405 | J36: =J34+J35 -> 14347.922 | ... L36: =L34+L35 -> 16626.54
A37: at gross margin | B37: EUR | C37: =C36*'P&L'!C7 -> -5672.5736 | D37: =D36*'P&L'!D7 -> 3167.2793 | E37: =E36*'P&L'!E7 -> 3564.3561 | F37: =F36*'P&L'!F7 -> 4493.5777 | G37: =G36*'P&L'!G7 -> 5713.561 | H37: =H36*'P&L'!H7 -> 7369.4386 | I37: =I36*'P&L'!I7 -> 8818.9906 | J37: =J36*'P&L'!J7 -> 9969.7445 | ... L37: =L36*'P&L'!L7 -> 11589.308
A38: CAC payback | B38: months | C38: =IF(C37<=0,0,12*C33/C37) -> 0 | D38: =IF(D37<=0,0,12*D33/D37) -> 3.9781777 | E38: =IF(E37<=0,0,12*E33/E37) -> 4.0400004 | F38: =IF(F37<=0,0,12*F33/F37) -> 3.7386691 | G38: =IF(G37<=0,0,12*G33/G37) -> 3.3604262 | H38: =IF(H37<=0,0,12*H33/H37) -> 2.8496065 | I38: =IF(I37<=0,0,12*I33/I37) -> 2.5853299 | J38: =IF(J37<=0,0,12*J33/J37) -> 2.4072833 | ... L38: =IF(L37<=0,0,12*L33/L37) -> 2.2779617
A40: No sponsor LTV is shown. It needs a sponsor retention assumption the model does not make, and inventing one here would create a figure nothing else in the plan validates. Payback needs no such assumption, so payback is what is reported.

Sheet KPIs
A1: KPIs
A2: Line | B2: Unit | C2: Y1 | D2: Y2 | E2: Y3 | F2: Y4 | G2: Y5 | H2: Y6 | I2: Y7 | J2: Y8 | K2: Y9 | L2: Y10
A4: SCALE
A5: Active athletes | B5: count | C5: =Drivers!C5 -> 250 | D5: =Drivers!D5 -> 750 | E5: =Drivers!E5 -> 1700 | F5: =Drivers!F5 -> 2800 | G5: =Drivers!G5 -> 4000 | H5: =Drivers!H5 -> 5200 | I5: =Drivers!I5 -> 6300 | J5: =Drivers!J5 -> 7200 | ... L5: =Drivers!L5 -> 8500
A6: Paying fans, year end | B6: count | C6: =Drivers!C38 -> 0 | D6: =Drivers!D38 -> 4911.4298 | E6: =Drivers!E38 -> 14332.926 | F6: =Drivers!F38 -> 28168.914 | G6: =Drivers!G38 -> 46065.966 | H6: =Drivers!H38 -> 67882.18 | I6: =Drivers!I38 -> 92005.2 | J6: =Drivers!J38 -> 111619.44 | ... L6: =Drivers!L38 -> 141502.9
A7: Paying sponsors | B7: count | C7: =Drivers!C48 -> 0.225 | D7: =Drivers!D48 -> 2.8875 | E7: =Drivers!E48 -> 18.0625 | F7: =Drivers!F48 -> 45.6 | G7: =Drivers!G48 -> 76 | H7: =Drivers!H48 -> 102 | I7: =Drivers!I48 -> 124 | J7: =Drivers!J48 -> 142 | ... L7: =Drivers!L48 -> 170
A8: Recurring MRR | B8: subs x take + SaaS / 12 | C8: =(Revenue!C7*Assumptions!C40+Revenue!C25)/12 -> 44.775 | D8: =(Revenue!D7*Assumptions!D40+Revenue!D25)/12 -> 3824.7955 | E8: =(Revenue!E7*Assumptions!E40+Revenue!E25)/12 -> 16072.91 | F8: =(Revenue!F7*Assumptions!F40+Revenue!F25)/12 -> 37661.384 | G8: =(Revenue!G7*Assumptions!G40+Revenue!G25)/12 -> 66530.321 | H8: =(Revenue!H7*Assumptions!H40+Revenue!H25)/12 -> 100562.95 | I8: =(Revenue!I7*Assumptions!I40+Revenue!I25)/12 -> 138239.32 | J8: =(Revenue!J7*Assumptions!J40+Revenue!J25)/12 -> 173160.81 | ... L8: =(Revenue!L7*Assumptions!L40+Revenue!L25)/12 -> 230580.67
A10: QUALITY OF REVENUE
A11: Net revenue | B11: EUR | C11: =Revenue!C26 -> 2146.38 | D11: =Revenue!D26 -> 68373.784 | E11: =Revenue!E26 -> 286818.8 | F11: =Revenue!F26 -> 703667.36 | G11: =Revenue!G26 -> 1321350.1 | H11: =Revenue!H26 -> 2124048.5 | I11: =Revenue!I26 -> 3013163.2 | J11: =Revenue!J26 -> 3853438.1 | ... L11: =Revenue!L26 -> 5253768.6
A12: Gross margin | B12: % | C12: ='P&L'!C7 -> -0.59464263 | D12: ='P&L'!D7 -> 0.53407161 | E12: ='P&L'!E7 -> 0.62800548 | F12: ='P&L'!F7 -> 0.66575473 | G12: ='P&L'!G7 -> 0.68110026 | H12: ='P&L'!H7 -> 0.68974834 | I12: ='P&L'!I7 -> 0.69334931 | J12: ='P&L'!J7 -> 0.69485633 | ... L12: ='P&L'!L7 -> 0.6970367
A13: EBITDA margin | B13: % | C13: ='P&L'!C11 -> -51.560685 | D13: ='P&L'!D11 -> -2.0719743 | E13: ='P&L'!E11 -> -0.25096774 | F13: ='P&L'!F11 -> 0.056980552 | G13: ='P&L'!G11 -> 0.13126684 | H13: ='P&L'!H11 -> 0.18506892 | I13: ='P&L'!I11 -> 0.24659639 | J13: ='P&L'!J11 -> 0.28096043 | ... L13: ='P&L'!L11 -> 0.32039754
A14: Revenue per FTE | B14: EUR | C14: =IF(Assumptions!C66=0,0,Revenue!C26/Assumptions!C66) -> 2146.38 | D14: =IF(Assumptions!D66=0,0,Revenue!D26/Assumptions!D66) -> 45582.523 | E14: =IF(Assumptions!E66=0,0,Revenue!E26/Assumptions!E66) -> 191212.53 | F14: =IF(Assumptions!F66=0,0,Revenue!F26/Assumptions!F66) -> 351833.68 | G14: =IF(Assumptions!G66=0,0,Revenue!G26/Assumptions!G66) -> 330337.53 | H14: =IF(Assumptions!H66=0,0,Revenue!H26/Assumptions!H66) -> 303435.5 | I14: =IF(Assumptions!I66=0,0,Revenue!I26/Assumptions!I66) -> 301316.32 | J14: =IF(Assumptions!J66=0,0,Revenue!J26/Assumptions!J66) -> 308275.05 | ... L14: =IF(Assumptions!L66=0,0,Revenue!L26/Assumptions!L66) -> 328360.54
A16: RETENTION AND EFFICIENCY
A17: Fan churn, niche | B17: per month | C17: =Assumptions!C13 -> 0.09 | D17: =Assumptions!D13 -> 0.085 | E17: =Assumptions!E13 -> 0.08 | F17: =Assumptions!F13 -> 0.075 | G17: =Assumptions!G13 -> 0.07 | H17: =Assumptions!H13 -> 0.065 | I17: =Assumptions!I13 -> 0.06 | J17: =Assumptions!J13 -> 0.058 | ... L17: =Assumptions!L13 -> 0.055
A18: Athlete churn, niche | B18: per year | C18: =Assumptions!C14 -> 0.3 | D18: =Assumptions!D14 -> 0.27 | E18: =Assumptions!E14 -> 0.24 | F18: =Assumptions!F14 -> 0.22 | G18: =Assumptions!G14 -> 0.2 | H18: =Assumptions!H14 -> 0.19 | I18: =Assumptions!I14 -> 0.18 | J18: =Assumptions!J14 -> 0.17 | ... L18: =Assumptions!L14 -> 0.16
A19: Athlete LTV / CAC | B19: x | C19: =CAC_CLV!C12 -> -0.98122549 | D19: =CAC_CLV!D12 -> 8.6351986 | E19: =CAC_CLV!E12 -> 14.084494 | F19: =CAC_CLV!F12 -> 17.460607 | G19: =CAC_CLV!G12 -> 20.006591 | H19: =CAC_CLV!H12 -> 22.625028 | I19: =CAC_CLV!I12 -> 25.490882 | J19: =CAC_CLV!J12 -> 29.160592 | ... L19: =CAC_CLV!L12 -> 32.896392
A20: Take rate on GMV | B20: % | C20: =Revenue!C28 -> 0.12805608 | D20: =Revenue!D28 -> 0.1551227 | E20: =Revenue!E28 -> 0.16452605 | F20: =Revenue!F28 -> 0.16251207 | G20: =Revenue!G28 -> 0.15506513 | H20: =Revenue!H28 -> 0.14778685 | I20: =Revenue!I28 -> 0.14389329 | J20: =Revenue!J28 -> 0.14133059 | ... L20: =Revenue!L28 -> 0.13867924

Sheet Comparables
A1: Comparables - published facts about the platforms we are modelled on
A2: Nothing on this sheet is our estimate. Every figure is published and cited, so it can be refreshed independently of anything we concluded from it. MarketModel derives our assumptions from these numbers; Assumptions then uses what MarketModel produces.
A4: Metric | B4: Value | C4: Unit | D4: Platform | E4: Period | F4: Source
A5: Gross payments (GMV) | B5: 7220000000 | C5: USD | D5: OnlyFans | E5: FY2024 | F5: Fenix International Ltd filed accounts (Companies House 10354575)
A6: Net revenue | B6: 1410000000 | C6: USD | D6: OnlyFans | E6: FY2024 | F6: Fenix International Ltd filed accounts (Companies House 10354575)
A7: Paid to creators | B7: 5800000000 | C7: USD | D7: OnlyFans | E7: FY2024 | F7: Fenix International Ltd filed accounts, 80.3% of gross
A8: Creator accounts | B8: 4634000 | C8: count | D8: OnlyFans | E8: FY2024 | F8: Variety: +13% YoY
A9: Fan accounts | B9: 377500000 | C9: count | D9: OnlyFans | E9: FY2024 | F9: Variety: +24% YoY
A10: Reported average creator earnings | B10: 131 | C10: USD/month | D10: OnlyFans | E10: FY2024 | F10: Sci-Tech Today / ElectroIQ: after platform fees
A11: Revenue concentration | B11: 0.76 | C11: share to top 0.1% | D11: OnlyFans | E11: 2025 | F11: ElectroIQ: power-law distribution
A12: Creators with >=1 paying member | B12: 286287 | C12: count | D12: Patreon | E12: Feb 2026 | F12: Graphtreon
A13: Active creators | B13: 300000 | C13: count | D13: Patreon | E13: 2025 | F13: Jack Conte, Patreon
A14: Active paying members | B14: 10000000 | C14: count | D14: Patreon | E14: 2026 | F14: Patreon / Backlinko
A15: Paid to creators annually | B15: 2000000000 | C15: USD/year | D15: Patreon | E15: 2026 | F15: Patreon / Backlinko
A16: Average monthly support per member | B16: 6.1 | C16: USD/month | D16: Patreon | E16: Aug 2024 | F16: Patreon 2024 Transparency Report; audit of ~1,200 creators
... A25: Claimed speed-to-market gain | B25: 0.6 | C25: share faster | D25: TEKTA | E25: Aug 2026 | F25: Publicis: stated 50-70% vs a traditional agency process
A27: TAKE RATES - what each platform costs a creator
A28: Platform | B28: Headline take | C28: Per txn (USD) | D28: Monthly fee (USD) | F28: Source
A29: OnlyFans | B29: 0.2 | C29: 0 | D29: 0 | F29: Derived: 1.41bn / 7.22bn = 19.5% (filed accounts)
A30: Fansly | B30: 0.2 | C30: 0 | D30: 0 | F30: Not published in terms; widely reported
A31: Fanfix | B31: 0.2 | C31: 0 | D31: 0 | F31: Not published in terms; widely reported
A32: Patreon | B32: 0.1 | C32: 0 | D32: 0 | F32: Published: 10% all-in, processing included
A33: Passes | B33: 0.1 | C33: 0.3 | D33: 29 | F33: Sacra; Passes rebrand release Apr 2026
A34: Stride (proposed) | B34: 0.15 | C34: 0 | D34: 0 | F34: Our decision, see MarketModel
A36: INTERMEDIARIES the athlete already pays
A37: Sports agent: endorsement | B37: 0.1 | C37: 0.2 | F37: Unregulated; widely reported, no primary source
A38: Sports agent: playing contract | B38: 0.02 | C38: 0.05 | F38: NBPA reg. 4.B (Sept 2025); FIFA FFAR art. 15
A39: OnlyFans management agency | B39: 0.2 | C39: 0.5 | F39: Aruna Talent rate guide 2026, on top of the 20%
A41: SPONSORSHIP MARKET - top down, for context not for sizing
A42: European Sponsorship Association, analysis by Nielsen Sports, published 12 Mar 2026. NOTE: none of it breaks below the professional tier, so it is context rather than our addressable market. The athlete funnel on Research is what sizes the business.
A43: Metric | B43: Value | C43: Unit | D43: Scope | E43: Period | F43: Source
A44: Total sponsorship market | B44: 34450000000 | C44: EUR | D44: Europe | E44: 2025 | F44: European Sponsorship Association, analysis by Nielsen Sports, 12 Mar 2026
A45: Sport sponsorship market | B45: 24790000000 | C45: EUR | D45: Europe | E45: 2025 | F45: ESA / Nielsen Sports: 72% of the total, +5.9% YoY
A46: Non-sport sponsorship | B46: 9660000000 | C46: EUR | D46: Europe | E46: 2025 | F46: ESA / Nielsen Sports: +1.8% YoY
A47: Sport sponsorship market | B47: 2180000000 | C47: EUR | D47: Spain | E47: 2025 | F47: ESA / Nielsen Sports: +14%, the fastest growing major European market
A48: Sport sponsorship market | B48: 6260000000 | C48: EUR | D48: Germany | E48: 2025 | F48: ESA / Nielsen Sports: the largest European market
A49: Sport sponsorship market | B49: 6150000000 | C49: EUR | D49: United Kingdom | E49: 2025 | F49: ESA / Nielsen Sports: +10.5%
A50: Sport sponsorship market | B50: 2010000000 | C50: EUR | D50: Italy | E50: 2025 | F50: ESA / Nielsen Sports: +5%
A51: Sport sponsorship market | B51: 1850000000 | C51: EUR | D51: France | E51: 2025 | F51: ESA / Nielsen Sports: +10.3%
A53: European SPORT sponsorship by year, EUR bn
A54: 2019 | B54: 2021 | C54: 2022 | D54: 2023 | E54: 2024 | F54: 2025
A55: 20.26 | B55: 19.8 | C55: 20.69 | D55: 21.98 | E55: 23.41 | F55: 24.79
A56: 2020 is not published in the ESA series. Source: ESA via Statista, retrieved 1 Oct 2026.
A58: FAN DEMAND - published surveys bearing on the fan thesis
A59: Metric | B59: Value | C59: Unit | D59: Scope | E59: Period | F59: Source
A60: Weekly minutes, fan-generated content | B60: 115 | C60: minutes/week | D60: FR DE IT ES UK US | E60: Dec 2025 | F60: Altman Solon / IRIS Sport, 6,000 respondents who watch sports video monthly
A61: Weekly minutes, highlights and clips | B61: 115 | C61: minutes/week | D61: FR DE IT ES UK US | E61: Dec 2025 | F61: Altman Solon / IRIS Sport
A62: Weekly minutes, live games and events | B62: 245 | C62: minutes/week | D62: FR DE IT ES UK US | E62: Dec 2025 | F62: Altman Solon / IRIS Sport
A63: YouTube share of fan-generated viewing | B63: 0.35 | C63: share | D63: FR DE IT ES UK US | E63: Dec 2025 | F63: Altman Solon / IRIS Sport: 40 of 115 minutes, more than linear TV or streaming
A64: Subscribers watching MORE sport after subscribing | B64: 0.7 | C64: share | D64: Worldwide | E64: Nov 2022 | F64: YouGov / Strive, 19,000 respondents: 38% much more + 32% somewhat more
A65: Subscribers watching LESS sport after subscribing | B65: 0.07 | C65: share | D65: Worldwide | E65: Nov 2022 | F65: YouGov / Strive: 3% much less + 4% somewhat less
A67: SPONSORSHIP MARKETPLACES - the direct competitor set
A68: PitchBook company profiles retrieved 1 Oct 2026, reported in EUR. None of the four discloses revenue, so headcount and capital raised are the only scale measures available. Links at the bottom of this sheet.
A69: Company | B69: Founded | C69: Employees (as of) | D69: Total raised | E69: Largest round pre-money | F69: Status
A70: Sponsoo (Germany) | B70: 2014 | C70: 13 | D70: 2170000 | E70: 15900000 | F70: Headcount as of 14 Nov 2025. Privately held, venture backed. Series A 28 Jan 2021; pre-money is a PitchBook ESTIMATE
A71: OpenSponsorship (United States) | B71: 2014 | C71: 23 | D71: 5400000 | F71: Headcount as of 9 Mar 2026. Privately held, venture backed. Last priced round not disclosed
A72: SponsorUnited (United States) | B72: 2016 | C72: 355 | D72: 38760000 | E72: 89380000 | F72: Headcount as of 28 May 2026. Privately held, venture backed. Series A 21 Nov 2022
A73: Hookit (United States) | B73: 2001 | C73: 47 | D73: 21470000 | E73: 38400000 | F73: Headcount as of 8 Feb 2022. Acquired, operating subsidiary. Series C2 24 Feb 2020; pre-money is a PitchBook ESTIMATE
A74: Stride (this plan, at Y10) | B74: 2026 | C74: =Assumptions!L66 -> 16 | D74: =SUM(Funding!C4:L4) -> 1900000 | E74: =Funding!H5 -> 12000000 | F74: Deliberately sized near Sponsoo. Only EUR 400k of the total is capital the plan depends on; the growth round is optional
A76: REVENUE PER EMPLOYEE - what the plan is tested against
A77: Benchmark | B77: EUR per employee | F77: Source
A78: Median private B2B SaaS, all stages | B78: 135000 | F78: SaaS Capital 2025 survey of ~1,000 private B2B SaaS companies
A79: Top quartile private B2B SaaS | B79: 215000 | F79: SaaS Capital 2025 survey, 75th percentile
A80: Efficient public SaaS at scale | B80: 300000 | F80: Public SaaS medians, widely reported range EUR 250-350k
A81: Stride (this plan, Y7) | B81: =KPIs!I14 -> 301316.32 | F81: Above the top quartile. Defended in section 3.2.2: the fan side is self-serve and moderation is a variable cost, not headcount
A82: Multiple of the top quartile | B82: =B81/B79 -> 1.4014713 | F82: The plan's second most aggressive assumption after fan churn
A85: SOURCES
A86: OnlyFans FY2024 filed accounts (Fenix International Ltd) | B86: https://find-and-update.company-information.service.gov.uk/company/10354575/filing-history
A87: OnlyFans FY2024 as reported | B87: https://variety.com/2025/digital/news/onlyfans-fiscal-2024-revenue-earnings-1236495750/
A88: Patreon published take rate | B88: https://www.patreon.com/pricing
A89: Patreon creators | B89: https://backlinko.com/patreon-users
A90: Passes economics | B90: https://sacra.com/c/passes/
A91: Fanfix creator terms (states no take rate) | B91: https://auth.fanfix.io/creator-terms-of-use
A92: Agency commissions | B92: https://arunatalent.com/blog/onlyfans-agency-commission-rates/
A93: NBPA agent fee cap (amended Sept 2025) | B93: https://imgix.cosmicjs.com/cd844850-97c7-11f0-91fa-d9e1671c2776-NBPA-REGULATIONS-GOVERNING-PLAYER-AGENTS-09-2025.pdf
A94: FIFA Football Agent Regulations art. 15 | B94: https://digitalhub.fifa.com/m/1e7b741fa0fae779/original/FIFA-Football-Agent-Regulations.pdf
A95: CJEU upholds the FIFA fee cap (16 Jul 2026) | B95: https://inside.fifa.com/news/welcomes-court-of-justice-european-union-decision-football-agent-regulations
A96: Eurobarometer 525 | B96: https://europa.eu/eurobarometer/surveys/detail/2668
A97: FIP World Padel Report 2025 | B97: https://www.padelfip.com/2025/12/online-the-fip-world-padel-report-2025-a-comprehensive-analysis-of-a-sport-in-constant-growth/
... A110: SaaS Capital revenue per employee benchmarks | B110: https://www.saas-capital.com/blog-posts/revenue-per-employee-benchmarks-for-private-saas-companies/

Sheet MarketModel
A1: Market Model - how the comparables become our assumptions
A2: Each block starts from a published figure on Comparables and ends in a number the Assumptions sheet uses. Adjustment factors are blue because they are our judgement; everything else is a formula you can trace.
C3: Input: change me
A5: 1. PAYING FANS PER MONETISING ATHLETE -> Assumptions
A6: Patreon active paying members | B6: =Comparables!B14 -> 10000000 | D6: Published
A7: Patreon creators with >=1 paying member | B7: =Comparables!B12 -> 286287 | D7: Published
A8: Members per paying creator | B8: =B6/B7 -> 34.929983 | D8: The single most useful benchmark we found: it is measured, not modelled.
A9: OnlyFans fan accounts per creator | B9: =Comparables!B9/Comparables!B8 -> 81.463099 | D9: Fan ACCOUNTS, not paying fans - most follow free. Shown as an upper bound only.
A10: Niche adjustment | B10: 1.06 | D10: OUR JUDGEMENT: +6% on the Patreon benchmark. Sport audiences are smaller but convert better, because the fan usually does the sport themselves.
A11: Popular adjustment | B11: 1.37 | D11: OUR JUDGEMENT: +37%. Much larger followings, much weaker conversion - more paying fans in absolute terms even though a smaller share converts.
A12: → Niche fans per athlete, mature | B12: =B8*B10 -> 37.025782
A13: → Popular fans per athlete, mature | B13: =B8*B11 -> 47.854077
A14: 2. FAN ARPU -> Assumptions
A15: Tier 1 price (Supporter) | B15: 4.99
A16: Tier 2 price (Insider) | B16: 9.99
A17: Tier 3 price (Inner circle) | B17: 24.99
A18: Mix - Tier 1 | B18: 0.4 | D18: Assumed distribution; replace with the real tier mix after P1.
A19: Mix - Tier 2 | B19: 0.5
A20: Mix - Tier 3 | B20: 0.1
A21: Mix check (must be 100%) | B21: =B18+B19+B20 -> 1
A22: → Weighted ARPU per month | B22: =B15*B18+B16*B19+B17*B20 -> 9.49 | D22: Cross-check: Patreon reports $6.10 average support and a $8-12 typical band. Landing inside that band from an independent tier build is a good sign.
A23: Patreon average support (cross-check) | B23: =Comparables!B16 -> 6.1 | D23: Published average - below our figure because Patreon's long tail includes many $1-3 tiers. Our EUR 9.49 sits inside their $8-12 typical band.
A24: Niche ARPU factor | B24: 1 | D24: Niche fans buy knowledge and sit at the tier mix above.
A25: Popular ARPU factor | B25: 0.87 | D25: OUR JUDGEMENT: -13%. Popular-sport fans skew to the cheapest tier.
A26: → Niche ARPU, mature | B26: =B22*B24 -> 9.49
A27: → Popular ARPU, mature | B27: =B22*B25 -> 8.2563
A28: 3. FAN CHURN -> Assumptions
A29: Patreon monthly churn (low) | B29: =Comparables!B19 -> 0.1
A30: Patreon monthly churn (high) | B30: =Comparables!B20 -> 0.15
A31: Benchmark midpoint | B31: =(B29+B30)/2 -> 0.125
A32: Annual-plan churn multiplier | B32: =Comparables!B21 -> 0.333 | D32: Patreon: annual patrons churn at one third the monthly rate.
A33: Share of subscribers on annual plans | B33: 0.3 | D33: Our target for the season pass. This is the one lever that improves churn without changing the product.
A34: Blended benchmark churn | B34: =B31*(1-B33)+B31*B32*B33 -> 0.0999875 | D34: What a Patreon-like platform would see with our annual mix.
A35: Niche engagement factor | B35: 0.55 | D35: OUR CLAIM, UNTESTED, AND THE MOST OPTIMISTIC JUDGEMENT IN THE MODEL: this says niche fans churn 45% SLOWER than the Patreon benchmark, because training content is habitual and competitive seasons create renewal moments. Nothing yet proves it. If it is wrong and we are merely at benchmark, Y10 revenue falls by roughly EUR 7M.
A36: Popular engagement factor | B36: 0.85 | D36: OUR JUDGEMENT: 15% better than benchmark. Impulse follows after a result, with many free substitutes - but still a sport fan rather than a general creator audience.
A37: → Niche churn, mature | B37: =B34*B35 -> 0.054993125
A38: → Popular churn, mature | B38: =B34*B36 -> 0.084989375
A39: 4. WHAT AN ATHLETE ACTUALLY EARNS (sanity check, not an input)
A40: OnlyFans: paid to creators / creator accounts | B40: =Comparables!B7/Comparables!B8/12 -> 104.30154 | D40: Includes dormant accounts, so this is a floor.
A41: Patreon: paid to creators / paying creators | B41: =Comparables!B15/Comparables!B12/12 -> 582.16638 | D41: Denominator is creators WITH members, so this is a ceiling.
A42: Stride: modelled niche athlete, mature | B42: =B12*B22*(1-Assumptions!$C$40) -> 298.66847 | D42: Ours sits between the two, which is where a plausible figure should sit.
A43: Revenue share taken by top 0.1% (OnlyFans) | B43: =Comparables!B11 -> 0.76 | D43: THE CAVEAT ON EVERY AVERAGE ABOVE: earnings follow a power law. Totals are unaffected, but the median athlete earns far less than the mean. Do not pitch the mean to an athlete.
A44: 5. TAKE RATE - what an athlete keeps, by platform
A45: USD to EUR | B45: 0.92 | D45: Comparables are published in USD; this model is in EUR. Applied to the per-transaction and monthly creator fees below.
A46: Athlete monthly fan revenue (test case) | B46: 300 | D46: Change this to see who is cheapest at any revenue level.
A47: OnlyFans - athlete keeps | B47: =B46*(1-Comparables!B29)-B46/Assumptions!$C$54*Comparables!C29*B45-Comparables!D29*B45 -> 240 | D47: Headline take, plus per-transaction and monthly creator fees where they exist.
A48: Patreon - athlete keeps | B48: =B46*(1-Comparables!B32)-B46/Assumptions!$C$54*Comparables!C32*B45-Comparables!D32*B45 -> 270 | D48: Headline take, plus per-transaction and monthly creator fees where they exist.
A49: Passes - athlete keeps | B49: =B46*(1-Comparables!B33)-B46/Assumptions!$C$54*Comparables!C33*B45-Comparables!D33*B45 -> 234.32 | D49: Headline take, plus per-transaction and monthly creator fees where they exist.
A50: Stride (proposed) - athlete keeps | B50: =B46*(1-Comparables!B34)-B46/Assumptions!$C$54*Comparables!C34*B45-Comparables!D34*B45 -> 255 | D50: Headline take, plus per-transaction and monthly creator fees where they exist.
A51: Crossover vs Passes (EUR/month) | B51: =Comparables!D33*B45/((Comparables!B34-Comparables!B33)-Comparables!C33*B45/Assumptions!$C$54) -> 1334 | D51: Below this, our flat 15% pays the athlete more than Passes' 10% plus fees. Our modelled athlete earns far less than this, so the long tail is on our side of the line.
A52: 6. MARKET SIZE -> sanity-checks the athlete trajectory
A53: Population, 34 countries in scope | B53: 2726.2 | D53: Millions. Eurostat / national statistics offices.
A54: Population, Spain | B54: 48.6 | D54: Millions.
A55: Share who do any sport (Spain) | B55: 0.56 | D55: Eurobarometer 525 - Spain sits near the EU average of 55% who exercise at all.
A56: Share with a public athletic identity | B56: 0.02 | D56: OUR ESTIMATE: competes, posts publicly, has a following worth sponsoring.
A57: Share with commercial intent | B57: 0.25 | D57: OUR ESTIMATE: would monetise if the tooling existed.
A58: → Addressable athletes, Spain | B58: =B54*1000000*B55*B56*B57 -> 136080
A59: → Addressable athletes, all 34 countries | B59: =B53*1000000*0.5*B56*B57 -> 6815500 | D59: Using a 50% blended participation rate across the 34 countries.
A60: Y10 athletes in the plan | B60: =Assumptions!$L$5 -> 8500
A61: → Y10 penetration of Spain SAM | B61: =Assumptions!$L$5/B58 -> 0.062463257
A62: → Y10 penetration of full TAM | B62: =Assumptions!$L$5/B59 -> 0.0012471572 | D62: If this reads as implausibly high, the athlete trajectory is too aggressive - that is exactly what this block exists to reveal.

Sheet Research
A1: Research & Benchmarking - where every assumption came from
A2: SOURCED = published figure | BENCHMARKED = set against named comparables | DERIVED = computed from other assumptions | ESTIMATE = judgement, no benchmark yet
A4: Assumption | B4: Model value | C4: Method | D4: Benchmark / comparable | E4: Source | F4: Confidence | G4: What would replace the estimate
A5: PRICING & TAKE RATE
A6: Take rate on fan revenue | B6: =Assumptions!$C$40 -> 0.15 | C6: BENCHMARKED | D6: Passes charges 10% but adds $0.30/txn and a $29/month creator fee; OnlyFans, Fansly and Fanfix are all 20%; Patreon 8-12%. A flat 15% with no monthly fee pays an athlete more than Passes for anyone under EUR 1,380/month of fan revenue. | E6: Sacra company profile (Passes); Passes rebrand release, Apr 2026; MEXC platform comparison 2026 | F6: High | G6: Nothing. This is a pricing decision and the comparables are public.
A7: Sponsorship commission, Scout Pro | B7: =Assumptions!$C$42 -> 0.07 | C7: BENCHMARKED | D7: 7% against a 10% base. A sponsor paying EUR 2,988 a year for the tooling is already paying for the relationship, and charging them the full headline rate on every deal as well is charging twice for it. Below the 10-20% an agent takes, which is the point: the sponsor who commits most pays least on each deal. | E7: Priced against the agent range; the discount itself is a pricing decision | F7: High | G7: Nothing to improve. This is a decision, not a measurement.
A8: Sponsorship commission, Scout Agency | B8: =Assumptions!$C$43 -> 0.05 | C8: BENCHMARKED | D8: 5%, which is half the low end of what an agent charges and a quarter of the high end. The most committed tier pays EUR 11,988 a year, so the deal rate can fall furthest here. | E8: Oreate and Sapling agent-commission surveys, 10-20% | F8: High | G8: Nothing to improve. This is a decision, not a measurement.
A9: Subscriber share of deal volume | B9: =Assumptions!$C$44 -> 2 | C9: ESTIMATE | D9: Subscribers are assumed to run 2.0x the deal volume of the average sponsor, which with a paid rate of 10-20% puts them at 20-40% of GMV. This is the ONLY estimate in the tiering and it is the one that sets the blended rate, which falls from 9.60% in Y1 to 8.56% by Y10. Deliberately conservative: Scout Pro buys five campaigns against the free tier's one, so 2.0x is well below what the campaign allowance alone would imply. Higher multiples lower the blend further. | E9: None. No tier-level deal volume exists yet, because no tier exists yet | F9: Low | G9: The first year of billing settles it exactly.
A10: Take rate on sponsorship | B10: =Assumptions!$C$41 -> 0.1 | C10: BENCHMARKED | D10: Sports agents take 10-20% of an endorsement and 4-10% of a playing contract. On OnlyFans, management agencies take a further 20-50% on top of the platform's 20%. | E10: Oreate and Sapling agent-commission surveys; Aruna Talent agency rate guide 2026 | F10: High | G10: Observed deal data once the marketplace is running.
A11: Suggested tiers 4.99 / 9.99 / 24.99 | B11: see model | C11: BENCHMARKED | D11: Patreon's typical patronage is quoted at $8-12/month, so the EUR 9.99 anchor sits inside the observed band. EUR 4.99 retains only 54% of our take after payment fees, against 71% at EUR 9.99: which is why the floor matters more than the take rate. | E11: Patreon 2024 Transparency Report; independent audits of ~1,200 creators | F11: Medium | G11: Our own tier mix after P1.
A12: Season pass / annual billing | B12: see model | C12: SOURCED | D12: Patreon reports that annual patrons churn at ONE THIRD the rate of monthly patrons. This is the single strongest piece of evidence in the plan for pushing annual billing. | E12: Patreon 2024 Transparency Report | F12: High | G12: Already strong. Confirm on our own cohorts.
A13: FAN ECONOMICS
A14: Fan ARPU per month | B14: =Assumptions!$C$12 -> 8 | C14: BENCHMARKED | D14: Patreon's average monthly support rose from $5.40 to $6.10 during 2024, with typical patronage quoted at $8-12. Our EUR 8.00-9.50 sits in the upper-middle of that range. | E14: Patreon 2024 Transparency Report | F14: Medium | G14: Actual ARPU by tier and sport after P1.
A15: Fan churn per month | B15: =Assumptions!$C$13 -> 0.09 | C15: ESTIMATE | D15: OPTIMISTIC AGAINST BENCHMARK. Patreon runs 10-15% monthly. We assume 6-9% (niche) and 9-13% (popular), arguing that training content is habitual and that competitive seasons create natural renewal moments. That argument is currently untested. | E15: Patreon 2024 Transparency Report (10-15%/month) | F15: Low | G15: THE most important number to measure in P1. Three months of real cohorts settles it. Until then the conservative case should be treated as the plan.
A16: Paying fans per monetising athlete | B16: =Assumptions!$C$11 -> 20 | C16: DERIVED | D16: 20 rising to 48 over ten years. Cross-check: Patreon creators average $350/month and our modelled niche athlete at maturity earns about EUR 313/month, closely aligned, which is reassuring for an assumption built bottom-up rather than from a comparable. | E16: Patreon 2024 Transparency Report (creator average $350/month) | F16: Medium | G16: Observed fans per athlete, banded by follower count.
A17: Share of athletes who monetise | B17: =Assumptions!$C$10 -> 0 | C17: ESTIMATE | D17: 28% rising to 50% for niche sports. No direct comparable exists: neither Patreon nor OnlyFans publishes activation rates for creators who sign up but never charge. | E17: None found | F17: Low | G17: Our own activation funnel, available from P1 onward.
A18: Fan acquisition capacity | B18: see model | C18: ESTIMATE | D18: An athlete can recruit 30-69 new paying fans a year depending on segment. This ceiling is what makes churn bite in the model: without it, higher churn perversely RAISED revenue, because the year-end target was reachable at any churn rate. | E18: None: introduced to fix a modelling flaw found by stress testing | F18: Low | G18: Observed gross adds per athlete per year.
A19: PAYMENT RAILS
A20: PSP percentage fee | B20: =Assumptions!$C$50 -> 0.019 | C20: SOURCED | D20: Stripe for a Spanish entity: 1.5% + EUR 0.25 on EEA domestic cards, 2.5% on UK cards, 3.25% on non-EEA. 1.9% is the blend for a mostly-European fan base. CORRECTION: an earlier version of this model used the US headline of 2.9% and overstated the largest cost line in the business by about a third. | E20: Stripe published EU/EEA pricing, 2026 | F20: High | G20: Interchange-plus terms become negotiable above roughly EUR 5M processed.
A21: PSP fixed fee per transaction | B21: =Assumptions!$C$51 -> 0.25 | C21: SOURCED | D21: EUR 0.25 per transaction. On a EUR 4.99 tier that single fee is a third of our take, which is why the tier floor and annual billing move more margin than the take rate does. | E21: Stripe published pricing, 2026 | F21: High | G21: Volume renegotiation; annual billing turns twelve fees into one.
A22: Payout fees | B22: =Assumptions!$C$52 -> 0.0025 | C22: SOURCED | D22: Stripe Connect Express: roughly 0.25% + EUR 0.25 per payout, plus a monthly active-account fee that is not modelled as a separate line. | E22: Stripe Connect pricing, 2026 | F22: Medium | G22: Actual payout frequency once athletes are onboarded.
A23: MARKET SIZING
A24: Sport participation by country | B24: see model | C24: ESTIMATE | D24: Eurobarometer 525, share who NEVER exercise: Finland 8%, Sweden 12%, Denmark 20%, Poland 65%, Greece 68%, Portugal 73%, EU-27 average 45%. Six of the 34 countries in the index are measured; the other 28 are estimates placed inside that distribution. | E24: Special Eurobarometer 525, Sport and Physical Activity, September 2022 | F24: Medium | G24: Federation licence counts, published annually and free (CSD in Spain).
A25: Padel market size | B25: see model | C25: SOURCED | D25: Spain has ~6.0M active players (12.7% of the population), 109,040 federation licences and 17,300+ courts; globally 35M+ players and 77,000+ courts. This is the clearest case for weighting a sport regionally rather than globally, padel scores 77.7 in Spain and 45.1 worldwide. | E25: FIP World Padel Report 2025 | F25: High | G25: Annual FIP refresh.
A26: Sports fandom by country | B26: see model | C26: ESTIMATE | D26: The weakest layer of the sport index, and it drives both the `demand` and `appetite` signals. Commercial audience panels (Nielsen Sports, YouGov) cost more than the entire Y1-Y2 analytics budget. | E26: None: reasoned estimates only | F26: Low | G26: Our own engagement data per sport per country once connectors are live. This is what makes the index self-improving rather than something anyone could copy.
A27: Athlete count trajectory | B27: =Assumptions!$C$5 -> 250 | C27: ESTIMATE | D27: 250 rising to 8,500 over ten years. This is the PLAN, not a benchmark: marketing spend is derived from it at segment CAC, not the other way round. Everything in the model scales off this line. | E27: None: it is a target | F27: Low | G27: The pre-seed gate tests it directly: 250 athletes and the first paying sponsors.
A28: COSTS
A29: Athlete CAC | B29: =Assumptions!$C$19 -> 16 | C29: ESTIMATE | D29: EUR 16-36 for niche, EUR 40-88 for popular. The gap reflects displacing an existing agent relationship versus reaching someone with no representation at all. No published comparable exists for athlete acquisition in this segment. | E29: None found | F29: Low | G29: Measured CAC by channel from the first federation partnership.
A30: Admission rate, direct applicants | B30: =Assumptions!$C$98 -> 0.2 | C30: DERIVED | D30: 20% of direct applicants are admitted, 25% go to a human, 40% are refused and 15% never finish the form. Not a judgement: it is what the admission policy itself produces when the stress test is run over a modelled applicant mix, so retuning a threshold moves this figure. The sweep holds the model and the policy in step. | E30: Admission stress test, section 7, over a modelled applicant mix | F30: Medium | G30: Real intake data. The mix the sweep assumes is the soft part, not the arithmetic.
A31: Admission rate, club-nominated | B31: =Assumptions!$C$100 -> 0.45 | C31: ESTIMATE | D31: 45% admitted against 20% direct. A verified club's nomination confers a credibility floor of 0.75 x its own legitimacy score, which carries a completed application over the admit line that would otherwise have gone to review. It cannot carry an empty one: no club can supply someone else's date of birth, so the uplift is real but bounded. | E31: None: the mechanism is built and tested, the conversion is not yet measured | F31: Low | G31: The first federation partnership: nominated applicants are tagged, so this is measurable from day one of it.
A32: Athlete verification cost | B32: =Assumptions!$C$103 -> 4 | C32: DERIVED | D32: Four minutes per manual review, priced at the same loaded salary the People line uses, over 1,700 productive hours. Peaks at EUR 47k and 0.64 reviewer-FTE in Y10, which is the finding rather than the cost: verification is not a money problem at this scale. The reason to automate it is latency: an athlete sitting in the queue is not listed, not matchable and not earning. | E32: Derived from the sweep's review volume and the model's own salary line | F32: Medium | G32: Timing real reviews. Four minutes is an estimate of a mechanical task.
A33: Athlete CAC vs the funnel | B33: =Assumptions!$C$19 -> 16 | C33: ESTIMATE | D33: Deliberately NOT multiplied by the admission funnel. Segment CAC is defined as the cost of landing one athlete ON the platform, so scaling it by 1/admission-rate would charge the same money twice. The Costs sheet carries a memo line showing what that CAC works out to per application (EUR 3.40 in Y1 rising to EUR 22), the figure to hold against what a channel actually charges per name reached. | E33: None: this is a definitional choice, made explicit so it is not silently reversed | F33: Low | G33: Channel-level spend against applications, which the funnel now records.
A34: Loaded salary, Spain | B34: =Assumptions!$C$67 -> 38000 | C34: BENCHMARKED | D34: EUR 38k-76k loaded. Spanish employer social security adds roughly 31% on top of gross, so a senior engineer at ~EUR 55k gross costs ~EUR 72k, around half the London equivalent, which is a real argument for being in Spain rather than an accident of geography. | E34: Spanish Seguridad Social employer contribution rates | F34: Medium | G34: Actual offers accepted.
A35: AWS infrastructure | B35: =Assumptions!$C$58 -> 150 | C35: BENCHMARKED | D35: Built up per stage from list prices: Fargate, RDS then Aurora, ElastiCache, S3, MediaConvert, CloudWatch. Reserved capacity and Savings Plans (25-40%) are deliberately excluded and treated as upside. | E35: AWS published list pricing, 2026 | F35: Medium | G35: Actual bills; commit to Savings Plans once usage is stable.
A36: Media egress | B36: =Assumptions!$C$60 -> 0.008 | C36: SOURCED | D36: EUR 0.008/GB behind a zero-egress object store versus EUR 0.075/GB at CloudFront list price. At Y10 volumes that single architectural choice is worth over EUR 1M a year, the largest cost decision in the plan that is settled by engineering rather than negotiation. | E36: Cloudflare R2 and Backblaze B2 pricing; AWS CloudFront list price | F36: High | G36: Nothing. Both are published.
A37: Moderation cost | B37: =Assumptions!$C$62 -> 22 | C37: ESTIMATE | D37: EUR 22 per 1,000 items reviewed, on a hybrid of automated classification and human review. Vendor pricing varies widely with SLA and content type. | E37: None cited | F37: Low | G37: Vendor quotes once P2 scope is fixed.
A38: TAX, CAPITAL & VALUATION
A39: Corporate tax rates | B39: =Assumptions!$C$93 -> 0.15 | C39: SOURCED | D39: 15% for the first four profitable years under the Spanish Startup Law, then the 25% standard rate. Modelled with loss carryforward against the Y1-Y4 losses. | E39: Ley de Startups (Spain); Impuesto sobre Sociedades | F39: High | G39: Confirm eligibility with a Spanish tax adviser before filing.
A40: Risk-free rate | B40: =Assumptions!$C$113 -> 0.032 | C40: SOURCED | D40: Spanish 10-year sovereign yield, ~3.2% in mid-2026. Used as the floor for the founder opportunity-cost calculation rather than as the discount rate. | E40: Spanish 10Y government bond yield | F40: High | G40: Refresh at the date of any raise.
A41: WACC / discount rate | B41: see model | C41: BENCHMARKED | D41: 25%, against a published mature-company anchor of 6.01%. Damodaran's European cost of capital dataset puts Software (Internet) at 6.01% in euros across 23 listed firms, and the European market ex-financials at 6.59%. Those are costs of capital for mature listed companies; this is a pre-revenue venture, and the 19-point gap is the stage premium. It is stated rather than buried because it is the largest single judgement in the valuation. Damodaran publishes no dataset for venture-stage rates, so the premium itself is convention (20-35% is the usual range) and not a sourced figure. The sensitivity grid runs 20-30% because this is arguable rather than knowable. | E41: Aswath Damodaran, NYU Stern, Cost of Capital by Industry (Europe), updated 5 January 2026 | F41: Medium | G41: An actual term sheet prices this for you.
A42: Exit revenue multiple | B42: =Assumptions!$C$112 -> 6.5 | C42: BENCHMARKED | D42: 6.5x blended. Marketplace comparables trade around 4x revenue and high-growth SaaS around 9x; our Y10 mix is roughly 55% marketplace take and 12% SaaS. | E42: Public marketplace and SaaS trading multiples | F42: Medium | G42: Comparable private transactions nearer an exit.
A43: Terminal growth | B43: =Assumptions!$C$111 -> 0.03 | C43: BENCHMARKED | D43: 3%, approximating long-run nominal GDP. Ten explicit forecast years were chosen partly so this assumption carries less of the valuation than it would at Y7. | E43: Standard DCF convention | F43: Medium | G43: Nothing: it is a convention, and the grid shows its effect.
A44: COMPLIANCE
A45: Payout age floor | B45: see model | C45: SOURCED | D45: Stripe Express and Custom Connect require 18. Standard Connect allows 13+, but a legal guardian must own the account and hold the bank account the money lands in. | E45: Stripe Connect documentation | F45: High | G45: Nothing: it is a hard platform rule.
A46: Digital consent age, Spain | B46: see model | C46: SOURCED | D46: 14 today under LOPDGDD Art. 7. A draft Organic Law on the Protection of Minors in Digital Environments would raise it to 16 and make age verification mandatory, which is why 16 is the forward-compatible floor for an account. | E46: LOPDGDD Art. 7; draft Organic Law, Council of Ministers, March 2025 | F46: High | G46: Track the bill through Parliament.
A48: THE THREE ASSUMPTIONS MOST LIKELY TO BE WRONG
A49: 1. Fan churn. We assume 6-13%/month; Patreon reports 10-15%. If Patreon is right, Y10 revenue falls from about EUR 58M to EUR 51M and the capital requirement roughly doubles.
A50: 2. Athlete count. The trajectory is a target, not a forecast, and everything scales off it.
A51: 3. Share of athletes who monetise. No published comparable exists at all.
A53: All three are answered by the same thing: three months of real cohort data from P1.
