Workbook

Sheet README
A1: Stride: Financial Model
A3: 10-year operating model, three statements, and a valuation. EUR. Y1 = 2027.
A5: COLOUR CODE
A6: LIGHT BLUE | B6: Estimated input
A7: LIGHT YELLOW | B7: Sourced input (Stripe pricing, Spanish tax law, AWS list)
A8: WHITE | B8: Computed formula
A9: LIGHT GREEN | B9: Dependent value, pulled from another sheet
A10: LIGHT GREY | B10: Total or subtotal
A11: LIGHT RED | B11: A check that must read zero
A13: SHEETS
A14: INPUTS
A15: Assumptions | B15: Every input and assumption taken into consideration
A17: BUILD-UP
A18: Drivers | B18: Athletes and fans, including monthly cohort churn
A19: Revenue | B19: GMV and net revenue, stream by stream
A20: Costs | B20: COGS and operating costs, line by line
A21: WorkingCap | B21: Receivables, payables, athlete float, capex, D&A
A23: THE THREE FINANCIAL STATEMENTS
A24: P&L | B24: Income statement
A25: CashFlow | B25: Cash flow statement, indirect method, tying to closing cash
A26: BalanceSheet | B26: Balance sheet, with an explicit check row so it must balance
A28: VALUATION AND FUNDING
A29: Valuation | B29: DCF, NPV, IRR, exit multiples, sensitivity
A30: Funding | B30: Funding rounds, dilution, ownership shares
A32: OPERATING PLANS
A33: HiringPlan | B33: Headcount by role, at Spanish loaded salaries
A34: CAC_CLV | B34: Acquisition cost against lifetime value
A35: KPIs | B35: Scale, quality of revenue, efficiency
A37: CONTROL
A38: Check | B38: Internal quality checks. Every variance row must read zero
A40: APPENDIX: RESEARCH AND MODELLING
A41: Comparables | B41: Published facts about Patreon, Passes and agents. The benchmarking source
A42: MarketModel | B42: Modelled assumptions, per market dynamics
A43: Research | B43: Where each baseline assumption came from, and how confident it is

Sheet Assumptions
A1: Assumptions, every input lives here
C2: Input: change me | E2: Sourced fact | G2: Formula (this sheet) | I2: Formula (other sheet) | K2: Total
A3: Line | B3: Unit | C3: Y1 | D3: Y2 | E3: Y3 | F3: Y4 | G3: Y5 | H3: Y6 | I3: Y7 | J3: Y8 | K3: Y9 | L3: Y10
A4: MARKET: the plan's shape
A5: Active athletes (year end) | B5: count | C5: 400 | D5: 1200 | E5: 3000 | F5: 6000 | G5: 10500 | H5: 16000 | I5: 22000 | J5: 28000 | K5: 34000 | L5: 40000
A6: Niche share of athletes | B6: % | C6: 0.95 | D6: 0.92 | E6: 0.8 | F6: 0.68 | G6: 0.58 | H6: 0.5 | I6: 0.45 | J6: 0.43 | K6: 0.42 | L6: 0.41
A7: Athletes needed for full SaaS value | B7: count | C7: 2000 | D7: =C7 | E7: =C7 | F7: =C7 | G7: =C7 | H7: =C7 | I7: =C7 | J7: =C7 | K7: =C7 | L7: =C7 | N7: Below this, sponsor conversion scales with supply, a matching product is worth nothing against an empty directory
A9: SEGMENT: NICHE
A10: Monetising athletes (niche) | B10: % of segment | C10: 0.28 | D10: 0.32 | E10: 0.37 | F10: 0.41 | G10: 0.44 | H10: 0.46 | I10: 0.48 | J10: 0.49 | K10: 0.5 | L10: 0.5
A11: Paying fans per monetising athlete (niche) | B11: count | C11: 20 | D11: 22 | E11: 25 | F11: 28 | G11: 30 | H11: 32 | I11: 34 | J11: 35 | K11: 36 | L11: 37 | N11: derived on MarketModel from Patreon members-per-creator
A12: Fan ARPU per month (niche) | B12: EUR | C12: 8 | D12: 8.3 | E12: 8.6 | F12: 8.8 | G12: 9 | H12: 9.1 | I12: 9.2 | J12: 9.3 | K12: 9.4 | L12: 9.5 | N12: derived on MarketModel from our tier mix, cross-checked against Patreon
A13: Fan churn per month (niche) | B13: % | C13: 0.09 | D13: 0.085 | E13: 0.08 | F13: 0.075 | G13: 0.07 | H13: 0.065 | I13: 0.06 | J13: 0.058 | K13: 0.056 | L13: 0.055 | N13: derived on MarketModel from Patreon churn and our annual-plan mix
A14: Athlete churn per year (niche) | B14: % | C14: 0.3 | D14: 0.27 | E14: 0.24 | F14: 0.22 | G14: 0.2 | H14: 0.19 | I14: 0.18 | J14: 0.17 | K14: 0.16 | L14: 0.16
A15: Max new fans per athlete per year (niche) | B15: capacity ceiling | C15: 30 | D15: 33 | E15: 36 | F15: 40 | G15: 43 | H15: 45 | I15: 47 | J15: 49 | K15: 50 | L15: 52 | N15: An audience is finite; without this ceiling higher churn RAISES revenue
A16: Athletes landing a deal (niche) | B16: % of segment | C16: 0.05 | D16: 0.07 | E16: 0.09 | F16: 0.11 | G16: 0.13 | H16: 0.15 | I16: 0.16 | J16: 0.17 | K16: 0.17 | L16: 0.18
A17: Deals per dealing athlete (niche) | B17: count | C17: 1.1 | D17: 1.2 | E17: 1.3 | F17: 1.5 | G17: 1.6 | H17: 1.7 | I17: 1.8 | J17: 1.9 | K17: 1.9 | L17: 2
A18: Average deal value (niche) | B18: EUR | C18: 900 | D18: 1050 | E18: 1200 | F18: 1350 | G18: 1500 | H18: 1600 | I18: 1700 | J18: 1800 | K18: 1900 | L18: 2000
A19: Athlete CAC (niche) | B19: EUR | C19: 16 | D19: 18 | E19: 21 | F19: 24 | G19: 27 | H19: 30 | I19: 32 | J19: 34 | K19: 35 | L19: 36
A21: SEGMENT: POPULAR
A22: Monetising athletes (popular) | B22: % of segment | C22: 0.14 | D22: 0.17 | E22: 0.2 | F22: 0.23 | G22: 0.26 | H22: 0.28 | I22: 0.3 | J22: 0.31 | K22: 0.32 | L22: 0.32
A23: Paying fans per monetising athlete (popular) | B23: count | C23: 26 | D23: 29 | E23: 32 | F23: 35 | G23: 38 | H23: 41 | I23: 44 | J23: 46 | K23: 47 | L23: 48 | N23: derived on MarketModel from Patreon members-per-creator
A24: Fan ARPU per month (popular) | B24: EUR | C24: 7 | D24: 7.2 | E24: 7.4 | F24: 7.6 | G24: 7.8 | H24: 7.9 | I24: 8 | J24: 8.1 | K24: 8.2 | L24: 8.3 | N24: derived on MarketModel from our tier mix, cross-checked against Patreon
A25: Fan churn per month (popular) | B25: % | C25: 0.13 | D25: 0.125 | E25: 0.12 | F25: 0.11 | G25: 0.105 | H25: 0.1 | I25: 0.09 | J25: 0.088 | K25: 0.086 | L25: 0.085 | N25: derived on MarketModel from Patreon churn and our annual-plan mix
A26: Athlete churn per year (popular) | B26: % | C26: 0.35 | D26: 0.32 | E26: 0.3 | F26: 0.27 | G26: 0.25 | H26: 0.23 | I26: 0.22 | J26: 0.21 | K26: 0.21 | L26: 0.2
A27: Max new fans per athlete per year (popular) | B27: capacity ceiling | C27: 38 | D27: 42 | E27: 46 | F27: 50 | G27: 54 | H27: 58 | I27: 62 | J27: 65 | K27: 67 | L27: 69 | N27: An audience is finite; without this ceiling higher churn RAISES revenue
A28: Athletes landing a deal (popular) | B28: % of segment | C28: 0.14 | D28: 0.17 | E28: 0.2 | F28: 0.24 | G28: 0.27 | H28: 0.29 | I28: 0.3 | J28: 0.31 | K28: 0.31 | L28: 0.32
A29: Deals per dealing athlete (popular) | B29: count | C29: 1.3 | D29: 1.5 | E29: 1.7 | F29: 1.9 | G29: 2.1 | H29: 2.3 | I29: 2.4 | J29: 2.5 | K29: 2.5 | L29: 2.6
A30: Average deal value (popular) | B30: EUR | C30: 2200 | D30: 2500 | E30: 2800 | F30: 3100 | G30: 3400 | H30: 3700 | I30: 4000 | J30: 4200 | K30: 4400 | L30: 4600
A31: Athlete CAC (popular) | B31: EUR | C31: 40 | D31: 46 | E31: 53 | F31: 60 | G31: 67 | H31: 73 | I31: 78 | J31: 82 | K31: 85 | L31: 88
A33: SPONSORS
A34: Registered sponsors | B34: count | C34: 25 | D34: 90 | E34: 230 | F34: 500 | G34: 900 | H34: 1400 | I34: 2000 | J34: 2600 | K34: 3100 | L34: 3600
A35: Share on a paid plan | B35: % | C35: 0.1 | D35: 0.14 | E35: 0.17 | F35: 0.19 | G35: 0.2 | H35: 0.2 | I35: 0.2 | J35: 0.2 | K35: 0.2 | L35: 0.2
A36: Sponsor plan ARPU per month | B36: EUR | C36: 199 | D36: 229 | E36: 260 | F36: 290 | G36: 320 | H36: 360 | I36: 400 | J36: 430 | K36: 455 | L36: 475
A37: Sponsor CAC | B37: EUR | C37: 900 | D37: 1050 | E37: 1200 | F37: 1400 | G37: 1600 | H37: 1750 | I37: 1900 | J37: 2000 | K37: 2100 | L37: 2200
A39: TAKE RATES & PAYMENT RAILS
A40: Take rate: fan revenue | B40: % | C40: 0.15 | D40: =C40 | E40: =C40 | F40: =C40 | G40: =C40 | H40: =C40 | I40: =C40 | J40: =C40 | K40: =C40 | L40: =C40 | N40: Our pricing decision. OnlyFans/Fansly/Fanfix 20%, Passes 10% + $29/mo
A41: Take rate: sponsorship, base | B41: % | C41: 0.1 | D41: =C41 | E41: =C41 | F41: =C41 | G41: =C41 | H41: =C41 | I41: =C41 | J41: =C41 | K41: =C41 | L41: =C41 | N41: Free and Starter plans. Agents take 10-20% of an endorsement
A42: Take rate: sponsorship, Scout Pro | B42: % | C42: 0.07 | D42: =C42 | E42: =C42 | F42: =C42 | G42: =C42 | H42: =C42 | I42: =C42 | J42: =C42 | K42: =C42 | L42: =C42 | N42: A sponsor paying for the tooling pays less on the deal
A43: Take rate: sponsorship, Scout Agency | B43: % | C43: 0.05 | D43: =C43 | E43: =C43 | F43: =C43 | G43: =C43 | H43: =C43 | I43: =C43 | J43: =C43 | K43: =C43 | L43: =C43 | N43: The most committed tier. Half what an agent charges at the low end
A44: Subscriber deal volume, multiple of average | B44: x | C44: 2 | D44: =C44 | E44: =C44 | F44: =C44 | G44: =C44 | H44: =C44 | I44: =C44 | J44: =C44 | K44: =C44 | L44: =C44 | N44: Subscribers buy campaign capacity, so they run more volume than the average sponsor. The only estimate in the tiering
A45: Scout Starter price | B45: EUR/mo | C45: 99 | D45: =C45 | E45: =C45 | F45: =C45 | G45: =C45 | H45: =C45 | I45: =C45 | J45: =C45 | K45: =C45 | L45: =C45
A46: Scout Pro price | B46: EUR/mo | C46: 249 | D46: =C46 | E46: =C46 | F46: =C46 | G46: =C46 | H46: =C46 | I46: =C46 | J46: =C46 | K46: =C46 | L46: =C46
A47: Scout Agency price | B47: EUR/mo | C47: 999 | D47: =C47 | E47: =C47 | F47: =C47 | G47: =C47 | H47: =C47 | I47: =C47 | J47: =C47 | K47: =C47 | L47: =C47
A48: VAT on fan subscriptions | B48: % | C48: 0.21 | D48: =C48 | E48: =C48 | F48: =C48 | G48: =C48 | H48: =C48 | I48: =C48 | J48: =C48 | K48: =C48 | L48: =C48 | N48: Spain's rate. Fan prices are displayed VAT-inclusive, so the take applies to price/(1+VAT) while the processor charges on the price
A49: PPV & tips as multiple of subs | B49: x | C49: 0.35 | D49: =C49 | E49: =C49 | F49: =C49 | G49: =C49 | H49: =C49 | I49: =C49 | J49: =C49 | K49: =C49 | L49: =C49
A50: PSP percentage fee | B50: % | C50: 0.019 | D50: =C50 | E50: =C50 | F50: =C50 | G50: =C50 | H50: =C50 | I50: =C50 | J50: =C50 | K50: =C50 | L50: =C50 | N50: Stripe published pricing
A51: PSP fixed fee per transaction | B51: EUR | C51: 0.25 | D51: =C51 | E51: =C51 | F51: =C51 | G51: =C51 | H51: =C51 | I51: =C51 | J51: =C51 | K51: =C51 | L51: =C51 | N51: Stripe. The single most damaging cost at small ticket sizes
A52: Payout percentage fee | B52: % | C52: 0.0025 | D52: =C52 | E52: =C52 | F52: =C52 | G52: =C52 | H52: =C52 | I52: =C52 | J52: =C52 | K52: =C52 | L52: =C52 | N52: Stripe Connect
A53: Payout fixed fee | B53: EUR | C53: 0.25 | D53: =C53 | E53: =C53 | F53: =C53 | G53: =C53 | H53: =C53 | I53: =C53 | J53: =C53 | K53: =C53 | L53: =C53 | N53: Stripe Connect
A54: Average fan transaction | B54: EUR | C54: 9.2 | D54: =C54 | E54: =C54 | F54: =C54 | G54: =C54 | H54: =C54 | I54: =C54 | J54: =C54 | K54: =C54 | L54: =C54
A55: Average deal transaction | B55: EUR | C55: 1800 | D55: =C55 | E55: =C55 | F55: =C55 | G55: =C55 | H55: =C55 | I55: =C55 | J55: =C55 | K55: =C55 | L55: =C55
A57: INFRASTRUCTURE & CONTENT COSTS
A58: AWS base cost per month | B58: EUR | C58: 180 | D58: 650 | E58: 2100 | F58: 5400 | G58: 11000 | H58: 17000 | I58: 24000 | J58: 30000 | K58: 35000 | L58: 39000
A59: Media GB per paying fan per month | B59: GB | C59: 1.8 | D59: =C59 | E59: =C59 | F59: =C59 | G59: =C59 | H59: =C59 | I59: =C59 | J59: =C59 | K59: =C59 | L59: =C59
A60: Egress cost per GB (zero-egress CDN) | B60: EUR | C60: 0.008 | D60: =C60 | E60: =C60 | F60: =C60 | G60: =C60 | H60: =C60 | I60: =C60 | J60: =C60 | K60: =C60 | L60: =C60 | N60: Cloudflare R2 / Backblaze B2 list
A61: Egress cost per GB (CloudFront list) | B61: EUR | C61: 0.075 | D61: =C61 | E61: =C61 | F61: =C61 | G61: =C61 | H61: =C61 | I61: =C61 | J61: =C61 | K61: =C61 | L61: =C61 | N61: AWS CloudFront list price: the EUR 1.1M/yr trap
A62: Moderation cost per 1,000 items | B62: EUR | C62: 22 | D62: =C62 | E62: =C62 | F62: =C62 | G62: =C62 | H62: =C62 | I62: =C62 | J62: =C62 | K62: =C62 | L62: =C62
A63: Items per athlete per month | B63: count | C63: 12 | D63: =C63 | E63: =C63 | F63: =C63 | G63: =C63 | H63: =C63 | I63: =C63 | J63: =C63 | K63: =C63 | L63: =C63
A65: PEOPLE & OVERHEAD
A66: Headcount | B66: FTE | C66: 1.5 | D66: 2 | E66: 3.5 | F66: 6 | G66: 10 | H66: 15 | I66: 22 | J66: 28 | K66: 33 | L66: 38
A67: Loaded salary (incl. ~31% employer SS) | B67: EUR | C67: 38000 | D67: 52000 | E67: 60000 | F67: 64000 | G67: 66000 | H67: 68000 | I67: 70000 | J67: 72000 | K67: 74000 | L67: 76000
A68: Legal & compliance | B68: EUR | C68: 18000 | D68: 45000 | E68: 90000 | F68: 150000 | G68: 200000 | H68: 235000 | I68: 270000 | J68: 300000 | K68: 325000 | L68: 345000
A69: Other opex as % of revenue | B69: % | C69: 0.08 | D69: =C69 | E69: =C69 | F69: =C69 | G69: =C69 | H69: =C69 | I69: =C69 | J69: =C69 | K69: =C69 | L69: =C69
A71: WORKING CAPITAL, CAPEX & TAX
A72: Athlete payout float | B72: days | C72: 15 | D72: =C72 | E72: =C72 | F72: =C72 | G72: =C72 | H72: =C72 | I72: =C72 | J72: =C72 | K72: =C72 | L72: =C72 | N72: We hold fan money before paying athletes, a cash benefit
A73: Sponsor receivable days | B73: days | C73: 45 | D73: =C73 | E73: =C73 | F73: =C73 | G73: =C73 | H73: =C73 | I73: =C73 | J73: =C73 | K73: =C73 | L73: =C73
A74: Trade payable days | B74: days | C74: 30 | D74: =C74 | E74: =C74 | F74: =C74 | G74: =C74 | H74: =C74 | I74: =C74 | J74: =C74 | K74: =C74 | L74: =C74
A75: Capitalised development | B75: % of people cost | C75: 0.3 | D75: =C75 | E75: =C75 | F75: =C75 | G75: =C75 | H75: =C75 | I75: =C75 | J75: =C75 | K75: =C75 | L75: =C75
A76: Amortisation period | B76: years | C76: 3 | D76: =C76 | E76: =C76 | F76: =C76 | G76: =C76 | H76: =C76 | I76: =C76 | J76: =C76 | K76: =C76 | L76: =C76
A77: Corporate tax: startup rate | B77: % | C77: 0.15 | D77: =C77 | E77: =C77 | F77: =C77 | G77: =C77 | H77: =C77 | I77: =C77 | J77: =C77 | K77: =C77 | L77: =C77 | N77: Spanish Startup Law, first 4 profitable years
A78: Corporate tax: standard rate | B78: % | C78: 0.25 | D78: =C78 | E78: =C78 | F78: =C78 | G78: =C78 | H78: =C78 | I78: =C78 | J78: =C78 | K78: =C78 | L78: =C78 | N78: Spanish corporate income tax
A79: Years at startup rate (from first profit) | B79: years | C79: 4 | D79: =C79 | E79: =C79 | F79: =C79 | G79: =C79 | H79: =C79 | I79: =C79 | J79: =C79 | K79: =C79 | L79: =C79
A81: ADMISSION: the gate between an applicant and an athlete
A82: Admission rate: direct applicants | B82: % admitted | C82: 0.2 | D82: =C82 | E82: =C82 | F82: =C82 | G82: =C82 | H82: =C82 | I82: =C82 | J82: =C82 | K82: =C82 | L82: =C82 | N82: ops-load output of scripts/admission_stress.py
A83: Review rate: direct applicants | B83: % needing a human | C83: 0.25 | D83: =C83 | E83: =C83 | F83: =C83 | G83: =C83 | H83: =C83 | I83: =C83 | J83: =C83 | K83: =C83 | L83: =C83 | N83: ops-load output of scripts/admission_stress.py
A84: Admission rate: club-nominated | B84: % admitted | C84: 0.45 | D84: =C84 | E84: =C84 | F84: =C84 | G84: =C84 | H84: =C84 | I84: =C84 | J84: =C84 | K84: =C84 | L84: =C84 | N84: ESTIMATE: a verified club's floor carries more of them past the bar
A85: Review rate: club-nominated | B85: % needing a human | C85: 0.18 | D85: =C85 | E85: =C85 | F85: =C85 | G85: =C85 | H85: =C85 | I85: =C85 | J85: =C85 | K85: =C85 | L85: =C85 | N85: ESTIMATE
A86: Applicants arriving via a club | B86: % of applicants | C86: 0 | D86: 0.1 | E86: 0.2 | F86: 0.28 | G86: 0.34 | H86: 0.38 | I86: 0.42 | J86: 0.44 | K86: 0.46 | L86: 0.47 | N86: Grows as federation and club partnerships land
A87: Minutes per manual review | B87: min | C87: 4 | D87: =C87 | E87: =C87 | F87: =C87 | G87: =C87 | H87: =C87 | I87: =C87 | J87: =C87 | K87: =C87 | L87: =C87 | N87: Open the link, decide whether it names the applicant
A88: Productive hours per reviewer-year | B88: h | C88: 1700 | D88: =C88 | E88: =C88 | F88: =C88 | G88: =C88 | H88: =C88 | I88: =C88 | J88: =C88 | K88: =C88 | L88: =C88 | N88: Prices review time off the same loaded salary line
A90: VALUATION
A91: WACC / discount rate | B91: % | C91: 0.25 | D91: =C91 | E91: =C91 | F91: =C91 | G91: =C91 | H91: =C91 | I91: =C91 | J91: =C91 | K91: =C91 | L91: =C91 | N91: Early-stage venture hurdle
A92: Terminal growth | B92: % | C92: 0.03 | D92: =C92 | E92: =C92 | F92: =C92 | G92: =C92 | H92: =C92 | I92: =C92 | J92: =C92 | K92: =C92 | L92: =C92
A93: Exit revenue multiple | B93: x | C93: 6.5 | D93: =C93 | E93: =C93 | F93: =C93 | G93: =C93 | H93: =C93 | I93: =C93 | J93: =C93 | K93: =C93 | L93: =C93 | N93: Blended marketplace + SaaS comparables
A94: Risk-free rate (Spanish 10Y) | B94: % | C94: 0.032 | D94: =C94 | E94: =C94 | F94: =C94 | G94: =C94 | H94: =C94 | I94: =C94 | J94: =C94 | K94: =C94 | L94: =C94 | N94: Spanish 10Y government bond, mid-2026
A95: Founder alternative return | B95: % | C95: 0.07 | D95: =C95 | E95: =C95 | F95: =C95 | G95: =C95 | H95: =C95 | I95: =C95 | J95: =C95 | K95: =C95 | L95: =C95

Sheet Drivers
A1: Drivers: athletes and fans, with cohort churn
C2: Input: change me | E2: Sourced fact | G2: Formula (this sheet) | I2: Formula (other sheet) | K2: Total
A3: Line | B3: Unit | C3: Y1 | D3: Y2 | E3: Y3 | F3: Y4 | G3: Y5 | H3: Y6 | I3: Y7 | J3: Y8 | K3: Y9 | L3: Y10
A4: ATHLETES
A5: Total athletes (year end) | C5: =Assumptions!C5 | D5: =Assumptions!D5 | E5: =Assumptions!E5 | F5: =Assumptions!F5 | G5: =Assumptions!G5 | H5: =Assumptions!H5 | I5: =Assumptions!I5 | J5: =Assumptions!J5 | ... L5: =Assumptions!L5
A6: Niche athletes | C6: =Drivers!C5*Assumptions!C6 | D6: =Drivers!D5*Assumptions!D6 | E6: =Drivers!E5*Assumptions!E6 | F6: =Drivers!F5*Assumptions!F6 | G6: =Drivers!G5*Assumptions!G6 | H6: =Drivers!H5*Assumptions!H6 | I6: =Drivers!I5*Assumptions!I6 | J6: =Drivers!J5*Assumptions!J6 | ... L6: =Drivers!L5*Assumptions!L6
A7: Popular athletes | C7: =Drivers!C5-Drivers!C6 | D7: =Drivers!D5-Drivers!D6 | E7: =Drivers!E5-Drivers!E6 | F7: =Drivers!F5-Drivers!F6 | G7: =Drivers!G5-Drivers!G6 | H7: =Drivers!H5-Drivers!H6 | I7: =Drivers!I5-Drivers!I6 | J7: =Drivers!J5-Drivers!J6 | ... L7: =Drivers!L5-Drivers!L6
A9: NICHE: fans and churn
A10: Niche athletes lost to churn | C10: =IF(1=1,0,C6*Assumptions!C14) | D10: =IF(2=1,0,C6*Assumptions!D14) | E10: =IF(3=1,0,D6*Assumptions!E14) | F10: =IF(4=1,0,E6*Assumptions!F14) | G10: =IF(5=1,0,F6*Assumptions!G14) | H10: =IF(6=1,0,G6*Assumptions!H14) | I10: =IF(7=1,0,H6*Assumptions!I14) | J10: =IF(8=1,0,I6*Assumptions!J14) | K10: =IF(9=1,0,J6*Assumptions!K14) | L10: =IF(10=1,0,K6*Assumptions!L14)
A11: Niche athletes acquired (gross) | C11: =MAX(0,C6-IF(1=1,0,C6)+C10) | D11: =MAX(0,D6-IF(2=1,0,C6)+D10) | E11: =MAX(0,E6-IF(3=1,0,D6)+E10) | F11: =MAX(0,F6-IF(4=1,0,E6)+F10) | G11: =MAX(0,G6-IF(5=1,0,F6)+G10) | H11: =MAX(0,H6-IF(6=1,0,G6)+H10) | I11: =MAX(0,I6-IF(7=1,0,H6)+I10) | J11: =MAX(0,J6-IF(8=1,0,I6)+J10) | K11: =MAX(0,K6-IF(9=1,0,J6)+K10) | L11: =MAX(0,L6-IF(10=1,0,K6)+L10)
A12: Niche monetising athletes | C12: =C6*Assumptions!C10 | D12: =D6*Assumptions!D10 | E12: =E6*Assumptions!E10 | F12: =F6*Assumptions!F10 | G12: =G6*Assumptions!G10 | H12: =H6*Assumptions!H10 | I12: =I6*Assumptions!I10 | J12: =J6*Assumptions!J10 | ... L12: =L6*Assumptions!L10
A13: Niche paying fans (target, year end) | C13: =C12*Assumptions!C11 | D13: =D12*Assumptions!D11 | E13: =E12*Assumptions!E11 | F13: =F12*Assumptions!F11 | G13: =G12*Assumptions!G11 | H13: =H12*Assumptions!H11 | I13: =I12*Assumptions!I11 | J13: =J12*Assumptions!J11 | ... L13: =L12*Assumptions!L11
A14: Niche monthly retention r = 1-churn | B14: factor | C14: =1-Assumptions!C13 | D14: =1-Assumptions!D13 | E14: =1-Assumptions!E13 | F14: =1-Assumptions!F13 | G14: =1-Assumptions!G13 | H14: =1-Assumptions!H13 | I14: =1-Assumptions!I13 | J14: =1-Assumptions!J13 | ... L14: =1-Assumptions!L13
A15: Niche opening fans survived 12 months | B15: open x r^12 | C15: =0 | D15: =C17*D14^12 | E15: =D17*E14^12 | F15: =E17*F14^12 | G15: =F17*G14^12 | H15: =G17*H14^12 | I15: =H17*I14^12 | J15: =I17*J14^12 | K15: =J17*K14^12 | L15: =K17*L14^12
A16: Niche monthly gross adds | B16: solved, then capped by capacity | C16: =MIN(MAX(0,(C13-C15)/((1-C14^12)/(1-C14))),C12*Assumptions!C15/12) | D16: =MIN(MAX(0,(D13-D15)/((1-D14^12)/(1-D14))),D12*Assumptions!D15/12) | E16: =MIN(MAX(0,(E13-E15)/((1-E14^12)/(1-E14))),E12*Assumptions!E15/12) | F16: =MIN(MAX(0,(F13-F15)/((1-F14^12)/(1-F14))),F12*Assumptions!F15/12) | G16: =MIN(MAX(0,(G13-G15)/((1-G14^12)/(1-G14))),G12*Assumptions!G15/12) | H16: =MIN(MAX(0,(H13-H15)/((1-H14^12)/(1-H14))),H12*Assumptions!H15/12) | I16: =MIN(MAX(0,(I13-I15)/((1-I14^12)/(1-I14))),I12*Assumptions!I15/12) | J16: =MIN(MAX(0,(J13-J15)/((1-J14^12)/(1-J14))),J12*Assumptions!J15/12) | ... L16: =MIN(MAX(0,(L13-L15)/((1-L14^12)/(1-L14))),L12*Assumptions!L15/12)
A17: Niche paying fans (year end) | B17: survivors + capped adds | C17: =C15+C16*(1-C14^12)/(1-C14) | D17: =D15+D16*(1-D14^12)/(1-D14) | E17: =E15+E16*(1-E14^12)/(1-E14) | F17: =F15+F16*(1-F14^12)/(1-F14) | G17: =G15+G16*(1-G14^12)/(1-G14) | H17: =H15+H16*(1-H14^12)/(1-H14) | I17: =I15+I16*(1-I14^12)/(1-I14) | J17: =J15+J16*(1-J14^12)/(1-J14) | ... L17: =L15+L16*(1-L14^12)/(1-L14)
A18: Niche fans acquired (gross) | B18: x12 months | C18: =C16*12 | D18: =D16*12 | E18: =E16*12 | F18: =F16*12 | G18: =G16*12 | H18: =H16*12 | I18: =I16*12 | J18: =J16*12 | ... L18: =L16*12
A19: Niche S = r(1-r^12)/(1-r) | B19: geometric sum | C19: =C14*(1-C14^12)/(1-C14) | D19: =D14*(1-D14^12)/(1-D14) | E19: =E14*(1-E14^12)/(1-E14) | F19: =F14*(1-F14^12)/(1-F14) | G19: =G14*(1-G14^12)/(1-G14) | H19: =H14*(1-H14^12)/(1-H14) | I19: =I14*(1-I14^12)/(1-I14) | J19: =J14*(1-J14^12)/(1-J14) | ... L19: =L14*(1-L14^12)/(1-L14)
A20: Niche average fans during year | B20: exact mean, revenue basis | C20: =(C16/(1-C14)*(12-C19))/12 | D20: =(C17*D19+D16/(1-D14)*(12-D19))/12 | E20: =(D17*E19+E16/(1-E14)*(12-E19))/12 | F20: =(E17*F19+F16/(1-F14)*(12-F19))/12 | G20: =(F17*G19+G16/(1-G14)*(12-G19))/12 | H20: =(G17*H19+H16/(1-H14)*(12-H19))/12 | I20: =(H17*I19+I16/(1-I14)*(12-I19))/12 | J20: =(I17*J19+J16/(1-J14)*(12-J19))/12 | K20: =(J17*K19+K16/(1-K14)*(12-K19))/12 | L20: =(K17*L19+L16/(1-L14)*(12-L19))/12
A21: Niche fans lost to churn | B21: avg x churn x 12 | C21: =C20*12*Assumptions!C13 | D21: =D20*12*Assumptions!D13 | E21: =E20*12*Assumptions!E13 | F21: =F20*12*Assumptions!F13 | G21: =G20*12*Assumptions!G13 | H21: =H20*12*Assumptions!H13 | I21: =I20*12*Assumptions!I13 | J21: =J20*12*Assumptions!J13 | ... L21: =L20*12*Assumptions!L13
A23: POPULAR: fans and churn
A24: Popular athletes lost to churn | C24: =IF(1=1,0,C7*Assumptions!C26) | D24: =IF(2=1,0,C7*Assumptions!D26) | E24: =IF(3=1,0,D7*Assumptions!E26) | F24: =IF(4=1,0,E7*Assumptions!F26) | G24: =IF(5=1,0,F7*Assumptions!G26) | H24: =IF(6=1,0,G7*Assumptions!H26) | I24: =IF(7=1,0,H7*Assumptions!I26) | J24: =IF(8=1,0,I7*Assumptions!J26) | K24: =IF(9=1,0,J7*Assumptions!K26) | L24: =IF(10=1,0,K7*Assumptions!L26)
A25: Popular athletes acquired (gross) | C25: =MAX(0,C7-IF(1=1,0,C7)+C24) | D25: =MAX(0,D7-IF(2=1,0,C7)+D24) | E25: =MAX(0,E7-IF(3=1,0,D7)+E24) | F25: =MAX(0,F7-IF(4=1,0,E7)+F24) | G25: =MAX(0,G7-IF(5=1,0,F7)+G24) | H25: =MAX(0,H7-IF(6=1,0,G7)+H24) | I25: =MAX(0,I7-IF(7=1,0,H7)+I24) | J25: =MAX(0,J7-IF(8=1,0,I7)+J24) | K25: =MAX(0,K7-IF(9=1,0,J7)+K24) | L25: =MAX(0,L7-IF(10=1,0,K7)+L24)
A26: Popular monetising athletes | C26: =C7*Assumptions!C22 | D26: =D7*Assumptions!D22 | E26: =E7*Assumptions!E22 | F26: =F7*Assumptions!F22 | G26: =G7*Assumptions!G22 | H26: =H7*Assumptions!H22 | I26: =I7*Assumptions!I22 | J26: =J7*Assumptions!J22 | ... L26: =L7*Assumptions!L22
A27: Popular paying fans (target, year end) | C27: =C26*Assumptions!C23 | D27: =D26*Assumptions!D23 | E27: =E26*Assumptions!E23 | F27: =F26*Assumptions!F23 | G27: =G26*Assumptions!G23 | H27: =H26*Assumptions!H23 | I27: =I26*Assumptions!I23 | J27: =J26*Assumptions!J23 | ... L27: =L26*Assumptions!L23
A28: Popular monthly retention r = 1-churn | B28: factor | C28: =1-Assumptions!C25 | D28: =1-Assumptions!D25 | E28: =1-Assumptions!E25 | F28: =1-Assumptions!F25 | G28: =1-Assumptions!G25 | H28: =1-Assumptions!H25 | I28: =1-Assumptions!I25 | J28: =1-Assumptions!J25 | ... L28: =1-Assumptions!L25
A29: Popular opening fans survived 12 months | B29: open x r^12 | C29: =0 | D29: =C31*D28^12 | E29: =D31*E28^12 | F29: =E31*F28^12 | G29: =F31*G28^12 | H29: =G31*H28^12 | I29: =H31*I28^12 | J29: =I31*J28^12 | K29: =J31*K28^12 | L29: =K31*L28^12
A30: Popular monthly gross adds | B30: solved, then capped by capacity | C30: =MIN(MAX(0,(C27-C29)/((1-C28^12)/(1-C28))),C26*Assumptions!C27/12) | D30: =MIN(MAX(0,(D27-D29)/((1-D28^12)/(1-D28))),D26*Assumptions!D27/12) | E30: =MIN(MAX(0,(E27-E29)/((1-E28^12)/(1-E28))),E26*Assumptions!E27/12) | F30: =MIN(MAX(0,(F27-F29)/((1-F28^12)/(1-F28))),F26*Assumptions!F27/12) | G30: =MIN(MAX(0,(G27-G29)/((1-G28^12)/(1-G28))),G26*Assumptions!G27/12) | H30: =MIN(MAX(0,(H27-H29)/((1-H28^12)/(1-H28))),H26*Assumptions!H27/12) | I30: =MIN(MAX(0,(I27-I29)/((1-I28^12)/(1-I28))),I26*Assumptions!I27/12) | J30: =MIN(MAX(0,(J27-J29)/((1-J28^12)/(1-J28))),J26*Assumptions!J27/12) | ... L30: =MIN(MAX(0,(L27-L29)/((1-L28^12)/(1-L28))),L26*Assumptions!L27/12)
A31: Popular paying fans (year end) | B31: survivors + capped adds | C31: =C29+C30*(1-C28^12)/(1-C28) | D31: =D29+D30*(1-D28^12)/(1-D28) | E31: =E29+E30*(1-E28^12)/(1-E28) | F31: =F29+F30*(1-F28^12)/(1-F28) | G31: =G29+G30*(1-G28^12)/(1-G28) | H31: =H29+H30*(1-H28^12)/(1-H28) | I31: =I29+I30*(1-I28^12)/(1-I28) | J31: =J29+J30*(1-J28^12)/(1-J28) | ... L31: =L29+L30*(1-L28^12)/(1-L28)
A32: Popular fans acquired (gross) | B32: x12 months | C32: =C30*12 | D32: =D30*12 | E32: =E30*12 | F32: =F30*12 | G32: =G30*12 | H32: =H30*12 | I32: =I30*12 | J32: =J30*12 | ... L32: =L30*12
A33: Popular S = r(1-r^12)/(1-r) | B33: geometric sum | C33: =C28*(1-C28^12)/(1-C28) | D33: =D28*(1-D28^12)/(1-D28) | E33: =E28*(1-E28^12)/(1-E28) | F33: =F28*(1-F28^12)/(1-F28) | G33: =G28*(1-G28^12)/(1-G28) | H33: =H28*(1-H28^12)/(1-H28) | I33: =I28*(1-I28^12)/(1-I28) | J33: =J28*(1-J28^12)/(1-J28) | ... L33: =L28*(1-L28^12)/(1-L28)
A34: Popular average fans during year | B34: exact mean, revenue basis | C34: =(C30/(1-C28)*(12-C33))/12 | D34: =(C31*D33+D30/(1-D28)*(12-D33))/12 | E34: =(D31*E33+E30/(1-E28)*(12-E33))/12 | F34: =(E31*F33+F30/(1-F28)*(12-F33))/12 | G34: =(F31*G33+G30/(1-G28)*(12-G33))/12 | H34: =(G31*H33+H30/(1-H28)*(12-H33))/12 | I34: =(H31*I33+I30/(1-I28)*(12-I33))/12 | J34: =(I31*J33+J30/(1-J28)*(12-J33))/12 | K34: =(J31*K33+K30/(1-K28)*(12-K33))/12 | L34: =(K31*L33+L30/(1-L28)*(12-L33))/12
A35: Popular fans lost to churn | B35: avg x churn x 12 | C35: =C34*12*Assumptions!C25 | D35: =D34*12*Assumptions!D25 | E35: =E34*12*Assumptions!E25 | F35: =F34*12*Assumptions!F25 | G35: =G34*12*Assumptions!G25 | H35: =H34*12*Assumptions!H25 | I35: =I34*12*Assumptions!I25 | J35: =J34*12*Assumptions!J25 | ... L35: =L34*12*Assumptions!L25
A37: TOTALS
A38: Paying fans (year end) | C38: =C17+C31 | D38: =D17+D31 | E38: =E17+E31 | F38: =F17+F31 | G38: =G17+G31 | H38: =H17+H31 | I38: =I17+I31 | J38: =J17+J31 | ... L38: =L17+L31
A39: Average paying fans | C39: =C20+C34 | D39: =D20+D34 | E39: =E20+E34 | F39: =F20+F34 | G39: =G20+G34 | H39: =H20+H34 | I39: =I20+I34 | J39: =J20+J34 | ... L39: =L20+L34
A40: Athletes acquired (gross) | C40: =C11+C25 | D40: =D11+D25 | E40: =E11+E25 | F40: =F11+F25 | G40: =G11+G25 | H40: =H11+H25 | I40: =I11+I25 | J40: =J11+J25 | ... L40: =L11+L25
A41: Fans lost to churn | C41: =C21+C35 | D41: =D21+D35 | E41: =E21+E35 | F41: =F21+F35 | G41: =G21+G35 | H41: =H21+H35 | I41: =I21+I35 | J41: =J21+J35 | ... L41: =L21+L35
A43: DEALS
A44: Niche deals | C44: =C6*Assumptions!C16*Assumptions!C17 | D44: =D6*Assumptions!D16*Assumptions!D17 | E44: =E6*Assumptions!E16*Assumptions!E17 | F44: =F6*Assumptions!F16*Assumptions!F17 | G44: =G6*Assumptions!G16*Assumptions!G17 | H44: =H6*Assumptions!H16*Assumptions!H17 | I44: =I6*Assumptions!I16*Assumptions!I17 | J44: =J6*Assumptions!J16*Assumptions!J17 | ... L44: =L6*Assumptions!L16*Assumptions!L17
A45: Popular deals | C45: =C7*Assumptions!C28*Assumptions!C29 | D45: =D7*Assumptions!D28*Assumptions!D29 | E45: =E7*Assumptions!E28*Assumptions!E29 | F45: =F7*Assumptions!F28*Assumptions!F29 | G45: =G7*Assumptions!G28*Assumptions!G29 | H45: =H7*Assumptions!H28*Assumptions!H29 | I45: =I7*Assumptions!I28*Assumptions!I29 | J45: =J7*Assumptions!J28*Assumptions!J29 | ... L45: =L7*Assumptions!L28*Assumptions!L29
A46: Total deals | C46: =C44+C45 | D46: =D44+D45 | E46: =E44+E45 | F46: =F44+F45 | G46: =G44+G45 | H46: =H44+H45 | I46: =I44+I45 | J46: =J44+J45 | ... L46: =L44+L45
A47: Supply factor | B47: athletes / floor, capped at 1 | C47: =MIN(1,C5/Assumptions!C7) | D47: =MIN(1,D5/Assumptions!D7) | E47: =MIN(1,E5/Assumptions!E7) | F47: =MIN(1,F5/Assumptions!F7) | G47: =MIN(1,G5/Assumptions!G7) | H47: =MIN(1,H5/Assumptions!H7) | I47: =MIN(1,I5/Assumptions!I7) | J47: =MIN(1,J5/Assumptions!J7) | ... L47: =MIN(1,L5/Assumptions!L7)
A48: Paying sponsors | C48: =Assumptions!C34*Assumptions!C35*C47 | D48: =Assumptions!D34*Assumptions!D35*D47 | E48: =Assumptions!E34*Assumptions!E35*E47 | F48: =Assumptions!F34*Assumptions!F35*F47 | G48: =Assumptions!G34*Assumptions!G35*G47 | H48: =Assumptions!H34*Assumptions!H35*H47 | I48: =Assumptions!I34*Assumptions!I35*I47 | J48: =Assumptions!J34*Assumptions!J35*J47 | ... L48: =Assumptions!L34*Assumptions!L35*L47
A49: Sponsors acquired (gross) | C49: =MAX(0,Assumptions!C34-IF(1=1,0,Assumptions!C34)) | D49: =MAX(0,Assumptions!D34-IF(2=1,0,Assumptions!C34)) | E49: =MAX(0,Assumptions!E34-IF(3=1,0,Assumptions!D34)) | F49: =MAX(0,Assumptions!F34-IF(4=1,0,Assumptions!E34)) | G49: =MAX(0,Assumptions!G34-IF(5=1,0,Assumptions!F34)) | H49: =MAX(0,Assumptions!H34-IF(6=1,0,Assumptions!G34)) | I49: =MAX(0,Assumptions!I34-IF(7=1,0,Assumptions!H34)) | J49: =MAX(0,Assumptions!J34-IF(8=1,0,Assumptions!I34)) | K49: =MAX(0,Assumptions!K34-IF(9=1,0,Assumptions!J34)) | L49: =MAX(0,Assumptions!L34-IF(10=1,0,Assumptions!K34))
A51: ADMISSION FUNNEL
A52: Blended admission rate | B52: weighted by channel | C52: =Assumptions!C86*Assumptions!C84+(1-Assumptions!C86)*Assumptions!C82 | D52: =Assumptions!D86*Assumptions!D84+(1-Assumptions!D86)*Assumptions!D82 | E52: =Assumptions!E86*Assumptions!E84+(1-Assumptions!E86)*Assumptions!E82 | F52: =Assumptions!F86*Assumptions!F84+(1-Assumptions!F86)*Assumptions!F82 | G52: =Assumptions!G86*Assumptions!G84+(1-Assumptions!G86)*Assumptions!G82 | H52: =Assumptions!H86*Assumptions!H84+(1-Assumptions!H86)*Assumptions!H82 | I52: =Assumptions!I86*Assumptions!I84+(1-Assumptions!I86)*Assumptions!I82 | J52: =Assumptions!J86*Assumptions!J84+(1-Assumptions!J86)*Assumptions!J82 | ... L52: =Assumptions!L86*Assumptions!L84+(1-Assumptions!L86)*Assumptions!L82
A53: Blended review rate | B53: weighted by channel | C53: =Assumptions!C86*Assumptions!C85+(1-Assumptions!C86)*Assumptions!C83 | D53: =Assumptions!D86*Assumptions!D85+(1-Assumptions!D86)*Assumptions!D83 | E53: =Assumptions!E86*Assumptions!E85+(1-Assumptions!E86)*Assumptions!E83 | F53: =Assumptions!F86*Assumptions!F85+(1-Assumptions!F86)*Assumptions!F83 | G53: =Assumptions!G86*Assumptions!G85+(1-Assumptions!G86)*Assumptions!G83 | H53: =Assumptions!H86*Assumptions!H85+(1-Assumptions!H86)*Assumptions!H83 | I53: =Assumptions!I86*Assumptions!I85+(1-Assumptions!I86)*Assumptions!I83 | J53: =Assumptions!J86*Assumptions!J85+(1-Assumptions!J86)*Assumptions!J83 | ... L53: =Assumptions!L86*Assumptions!L85+(1-Assumptions!L86)*Assumptions!L83
A54: Applications required | B54: gross adds / admission rate | C54: =C40/C52 | D54: =D40/D52 | E54: =E40/E52 | F54: =F40/F52 | G54: =G40/G52 | H54: =H40/H52 | I54: =I40/I52 | J54: =J40/J52 | ... L54: =L40/L52
A55: Manual reviews | B55: applications x review rate | C55: =C54*C53 | D55: =D54*D53 | E55: =E54*E53 | F55: =F54*F53 | G55: =G54*G53 | H55: =H54*H53 | I55: =I54*I53 | J55: =J54*J53 | ... L55: =L54*L53
A56: Reviewer FTE implied | B56: the real constraint, not the euros | C56: =C55*Assumptions!C87/60/Assumptions!C88 | D56: =D55*Assumptions!D87/60/Assumptions!D88 | E56: =E55*Assumptions!E87/60/Assumptions!E88 | F56: =F55*Assumptions!F87/60/Assumptions!F88 | G56: =G55*Assumptions!G87/60/Assumptions!G88 | H56: =H55*Assumptions!H87/60/Assumptions!H88 | I56: =I55*Assumptions!I87/60/Assumptions!I88 | J56: =J55*Assumptions!J87/60/Assumptions!J88 | ... L56: =L55*Assumptions!L87/60/Assumptions!L88

Sheet Revenue
A1: Revenue: GMV built stream by stream, then our take
C2: Input: change me | E2: Sourced fact | G2: Formula (this sheet) | I2: Formula (other sheet) | K2: Total
A3: Line | B3: Unit | C3: Y1 | D3: Y2 | E3: Y3 | F3: Y4 | G3: Y5 | H3: Y6 | I3: Y7 | J3: Y8 | K3: Y9 | L3: Y10
A4: FAN GMV: what fans pay athletes, net of VAT
A5: Niche subscription GMV | B5: avg fans x ARPU x 12, ex-VAT | C5: =Drivers!C20*Assumptions!C12*12/(1+Assumptions!C48) | D5: =Drivers!D20*Assumptions!D12*12/(1+Assumptions!D48) | E5: =Drivers!E20*Assumptions!E12*12/(1+Assumptions!E48) | F5: =Drivers!F20*Assumptions!F12*12/(1+Assumptions!F48) | G5: =Drivers!G20*Assumptions!G12*12/(1+Assumptions!G48) | H5: =Drivers!H20*Assumptions!H12*12/(1+Assumptions!H48) | I5: =Drivers!I20*Assumptions!I12*12/(1+Assumptions!I48) | J5: =Drivers!J20*Assumptions!J12*12/(1+Assumptions!J48) | ... L5: =Drivers!L20*Assumptions!L12*12/(1+Assumptions!L48)
A6: Popular subscription GMV | B6: ex-VAT | C6: =Drivers!C34*Assumptions!C24*12/(1+Assumptions!C48) | D6: =Drivers!D34*Assumptions!D24*12/(1+Assumptions!D48) | E6: =Drivers!E34*Assumptions!E24*12/(1+Assumptions!E48) | F6: =Drivers!F34*Assumptions!F24*12/(1+Assumptions!F48) | G6: =Drivers!G34*Assumptions!G24*12/(1+Assumptions!G48) | H6: =Drivers!H34*Assumptions!H24*12/(1+Assumptions!H48) | I6: =Drivers!I34*Assumptions!I24*12/(1+Assumptions!I48) | J6: =Drivers!J34*Assumptions!J24*12/(1+Assumptions!J48) | ... L6: =Drivers!L34*Assumptions!L24*12/(1+Assumptions!L48)
A7: Subscription GMV | C7: =C5+C6 | D7: =D5+D6 | E7: =E5+E6 | F7: =F5+F6 | G7: =G5+G6 | H7: =H5+H6 | I7: =I5+I6 | J7: =J5+J6 | ... L7: =L5+L6
A8: PPV and tips GMV | B8: x multiple | C8: =C7*Assumptions!C49 | D8: =D7*Assumptions!D49 | E8: =E7*Assumptions!E49 | F8: =F7*Assumptions!F49 | G8: =G7*Assumptions!G49 | H8: =H7*Assumptions!H49 | I8: =I7*Assumptions!I49 | J8: =J7*Assumptions!J49 | ... L8: =L7*Assumptions!L49
A9: Total fan GMV | B9: ex-VAT, the take base | C9: =C7+C8 | D9: =D7+D8 | E9: =E7+E8 | F9: =F7+F8 | G9: =G7+G8 | H9: =H7+H8 | I9: =I7+I8 | J9: =J7+J8 | ... L9: =L7+L8
A10: Fan GMV including VAT | B10: what cards are charged | C10: =C9*(1+Assumptions!C48) | D10: =D9*(1+Assumptions!D48) | E10: =E9*(1+Assumptions!E48) | F10: =F9*(1+Assumptions!F48) | G10: =G9*(1+Assumptions!G48) | H10: =H9*(1+Assumptions!H48) | I10: =I9*(1+Assumptions!I48) | J10: =J9*(1+Assumptions!J48) | ... L10: =L9*(1+Assumptions!L48)
A12: SPONSORSHIP GMV: what sponsors pay athletes and clubs
A13: Niche sponsorship GMV | C13: =Drivers!C44*Assumptions!C18 | D13: =Drivers!D44*Assumptions!D18 | E13: =Drivers!E44*Assumptions!E18 | F13: =Drivers!F44*Assumptions!F18 | G13: =Drivers!G44*Assumptions!G18 | H13: =Drivers!H44*Assumptions!H18 | I13: =Drivers!I44*Assumptions!I18 | J13: =Drivers!J44*Assumptions!J18 | ... L13: =Drivers!L44*Assumptions!L18
A14: Popular sponsorship GMV | C14: =Drivers!C45*Assumptions!C30 | D14: =Drivers!D45*Assumptions!D30 | E14: =Drivers!E45*Assumptions!E30 | F14: =Drivers!F45*Assumptions!F30 | G14: =Drivers!G45*Assumptions!G30 | H14: =Drivers!H45*Assumptions!H30 | I14: =Drivers!I45*Assumptions!I30 | J14: =Drivers!J45*Assumptions!J30 | ... L14: =Drivers!L45*Assumptions!L30
A15: Total sponsorship GMV | C15: =C13+C14 | D15: =D13+D14 | E15: =E13+E14 | F15: =F13+F14 | G15: =G13+G14 | H15: =H13+H14 | I15: =I13+I14 | J15: =J13+J14 | ... L15: =L13+L14
A16: Agency share of subscribers | C16: =MAX(0,(Assumptions!C36-Assumptions!C46)/(Assumptions!C47-Assumptions!C46)) | D16: =MAX(0,(Assumptions!D36-Assumptions!D46)/(Assumptions!D47-Assumptions!D46)) | E16: =MAX(0,(Assumptions!E36-Assumptions!E46)/(Assumptions!E47-Assumptions!E46)) | F16: =MAX(0,(Assumptions!F36-Assumptions!F46)/(Assumptions!F47-Assumptions!F46)) | G16: =MAX(0,(Assumptions!G36-Assumptions!G46)/(Assumptions!G47-Assumptions!G46)) | H16: =MAX(0,(Assumptions!H36-Assumptions!H46)/(Assumptions!H47-Assumptions!H46)) | I16: =MAX(0,(Assumptions!I36-Assumptions!I46)/(Assumptions!I47-Assumptions!I46)) | J16: =MAX(0,(Assumptions!J36-Assumptions!J46)/(Assumptions!J47-Assumptions!J46)) | ... L16: =MAX(0,(Assumptions!L36-Assumptions!L46)/(Assumptions!L47-Assumptions!L46))
A17: Starter share of subscribers | C17: =MAX(0,(Assumptions!C46-Assumptions!C36)/(Assumptions!C46-Assumptions!C45)) | D17: =MAX(0,(Assumptions!D46-Assumptions!D36)/(Assumptions!D46-Assumptions!D45)) | E17: =MAX(0,(Assumptions!E46-Assumptions!E36)/(Assumptions!E46-Assumptions!E45)) | F17: =MAX(0,(Assumptions!F46-Assumptions!F36)/(Assumptions!F46-Assumptions!F45)) | G17: =MAX(0,(Assumptions!G46-Assumptions!G36)/(Assumptions!G46-Assumptions!G45)) | H17: =MAX(0,(Assumptions!H46-Assumptions!H36)/(Assumptions!H46-Assumptions!H45)) | I17: =MAX(0,(Assumptions!I46-Assumptions!I36)/(Assumptions!I46-Assumptions!I45)) | J17: =MAX(0,(Assumptions!J46-Assumptions!J36)/(Assumptions!J46-Assumptions!J45)) | ... L17: =MAX(0,(Assumptions!L46-Assumptions!L36)/(Assumptions!L46-Assumptions!L45))
A18: Subscriber share of deal volume | C18: =MIN(1,Assumptions!C35*Assumptions!C44) | D18: =MIN(1,Assumptions!D35*Assumptions!D44) | E18: =MIN(1,Assumptions!E35*Assumptions!E44) | F18: =MIN(1,Assumptions!F35*Assumptions!F44) | G18: =MIN(1,Assumptions!G35*Assumptions!G44) | H18: =MIN(1,Assumptions!H35*Assumptions!H44) | I18: =MIN(1,Assumptions!I35*Assumptions!I44) | J18: =MIN(1,Assumptions!J35*Assumptions!J44) | ... L18: =MIN(1,Assumptions!L35*Assumptions!L44)
A19: Effective sponsorship take | C19: =(1-C18)*Assumptions!C41+C18*(C17*Assumptions!C41+(1-C17-C16)*Assumptions!C42+C16*Assumptions!C43) | D19: =(1-D18)*Assumptions!D41+D18*(D17*Assumptions!D41+(1-D17-D16)*Assumptions!D42+D16*Assumptions!D43) | E19: =(1-E18)*Assumptions!E41+E18*(E17*Assumptions!E41+(1-E17-E16)*Assumptions!E42+E16*Assumptions!E43) | F19: =(1-F18)*Assumptions!F41+F18*(F17*Assumptions!F41+(1-F17-F16)*Assumptions!F42+F16*Assumptions!F43) | G19: =(1-G18)*Assumptions!G41+G18*(G17*Assumptions!G41+(1-G17-G16)*Assumptions!G42+G16*Assumptions!G43) | H19: =(1-H18)*Assumptions!H41+H18*(H17*Assumptions!H41+(1-H17-H16)*Assumptions!H42+H16*Assumptions!H43) | I19: =(1-I18)*Assumptions!I41+I18*(I17*Assumptions!I41+(1-I17-I16)*Assumptions!I42+I16*Assumptions!I43) | J19: =(1-J18)*Assumptions!J41+J18*(J17*Assumptions!J41+(1-J17-J16)*Assumptions!J42+J16*Assumptions!J43) | ... L19: =(1-L18)*Assumptions!L41+L18*(L17*Assumptions!L41+(1-L17-L16)*Assumptions!L42+L16*Assumptions!L43)
A20: TOTAL GMV | C20: =C9+C15 | D20: =D9+D15 | E20: =E9+E15 | F20: =F9+F15 | G20: =G9+G15 | H20: =H9+H15 | I20: =I9+I15 | J20: =J9+J15 | ... L20: =L9+L15
A22: NET REVENUE: our share
A23: Fan take | B23: fan GMV x take rate | C23: =C9*Assumptions!C40 | D23: =D9*Assumptions!D40 | E23: =E9*Assumptions!E40 | F23: =F9*Assumptions!F40 | G23: =G9*Assumptions!G40 | H23: =H9*Assumptions!H40 | I23: =I9*Assumptions!I40 | J23: =J9*Assumptions!J40 | ... L23: =L9*Assumptions!L40
A24: Sponsorship take | C24: =C15*C19 | D24: =D15*D19 | E24: =E15*E19 | F24: =F15*F19 | G24: =G15*G19 | H24: =H15*H19 | I24: =I15*I19 | J24: =J15*J19 | ... L24: =L15*L19
A25: Sponsor SaaS | B25: paying sponsors x ARPU x 12 | C25: =Drivers!C48*Assumptions!C36*12 | D25: =Drivers!D48*Assumptions!D36*12 | E25: =Drivers!E48*Assumptions!E36*12 | F25: =Drivers!F48*Assumptions!F36*12 | G25: =Drivers!G48*Assumptions!G36*12 | H25: =Drivers!H48*Assumptions!H36*12 | I25: =Drivers!I48*Assumptions!I36*12 | J25: =Drivers!J48*Assumptions!J36*12 | ... L25: =Drivers!L48*Assumptions!L36*12
A26: NET REVENUE | C26: =SUM(C23:C25) | D26: =SUM(D23:D25) | E26: =SUM(E23:E25) | F26: =SUM(F23:F25) | G26: =SUM(G23:G25) | H26: =SUM(H23:H25) | I26: =SUM(I23:I25) | J26: =SUM(J23:J25) | ... L26: =SUM(L23:L25)
A27: Growth | B27: % YoY | C27: =IF(1=1,"",C26/C26-1) | D27: =IF(2=1,"",D26/C26-1) | E27: =IF(3=1,"",E26/D26-1) | F27: =IF(4=1,"",F26/E26-1) | G27: =IF(5=1,"",G26/F26-1) | H27: =IF(6=1,"",H26/G26-1) | I27: =IF(7=1,"",I26/H26-1) | J27: =IF(8=1,"",J26/I26-1) | K27: =IF(9=1,"",K26/J26-1) | L27: =IF(10=1,"",L26/K26-1)
A28: Take rate on GMV | B28: blended | C28: =C26/C20 | D28: =D26/D20 | E28: =E26/E20 | F28: =F26/F20 | G28: =G26/G20 | H28: =H26/H20 | I28: =I26/I20 | J28: =J26/J20 | ... L28: =L26/L20

Sheet Costs
A1: Costs: every line built from its driver
C2: Input: change me | E2: Sourced fact | G2: Formula (this sheet) | I2: Formula (other sheet) | K2: Total
A3: Line | B3: Unit | C3: Y1 | D3: Y2 | E3: Y3 | F3: Y4 | G3: Y5 | H3: Y6 | I3: Y7 | J3: Y8 | K3: Y9 | L3: Y10
A4: COST OF SALES
A5: Fan transactions | B5: fan GMV incl VAT / avg ticket | C5: =Revenue!C10/Assumptions!C54 | D5: =Revenue!D10/Assumptions!D54 | E5: =Revenue!E10/Assumptions!E54 | F5: =Revenue!F10/Assumptions!F54 | G5: =Revenue!G10/Assumptions!G54 | H5: =Revenue!H10/Assumptions!H54 | I5: =Revenue!I10/Assumptions!I54 | J5: =Revenue!J10/Assumptions!J54 | ... L5: =Revenue!L10/Assumptions!L54
A6: Deal transactions | B6: count | C6: =Revenue!C15/Assumptions!C55 | D6: =Revenue!D15/Assumptions!D55 | E6: =Revenue!E15/Assumptions!E55 | F6: =Revenue!F15/Assumptions!F55 | G6: =Revenue!G15/Assumptions!G55 | H6: =Revenue!H15/Assumptions!H55 | I6: =Revenue!I15/Assumptions!I55 | J6: =Revenue!J15/Assumptions!J55 | ... L6: =Revenue!L15/Assumptions!L55
A7: Payment processing | B7: % of processed + fixed | C7: =(Revenue!C10+Revenue!C15)*Assumptions!C50+(C5+C6)*Assumptions!C51 | D7: =(Revenue!D10+Revenue!D15)*Assumptions!D50+(D5+D6)*Assumptions!D51 | E7: =(Revenue!E10+Revenue!E15)*Assumptions!E50+(E5+E6)*Assumptions!E51 | F7: =(Revenue!F10+Revenue!F15)*Assumptions!F50+(F5+F6)*Assumptions!F51 | G7: =(Revenue!G10+Revenue!G15)*Assumptions!G50+(G5+G6)*Assumptions!G51 | H7: =(Revenue!H10+Revenue!H15)*Assumptions!H50+(H5+H6)*Assumptions!H51 | I7: =(Revenue!I10+Revenue!I15)*Assumptions!I50+(I5+I6)*Assumptions!I51 | J7: =(Revenue!J10+Revenue!J15)*Assumptions!J50+(J5+J6)*Assumptions!J51 | ... L7: =(Revenue!L10+Revenue!L15)*Assumptions!L50+(L5+L6)*Assumptions!L51
A8: Payouts to athletes | B8: % + fixed | C8: =(Revenue!C10+Revenue!C15)*Assumptions!C52+(C5/30+C6)*Assumptions!C53 | D8: =(Revenue!D10+Revenue!D15)*Assumptions!D52+(D5/30+D6)*Assumptions!D53 | E8: =(Revenue!E10+Revenue!E15)*Assumptions!E52+(E5/30+E6)*Assumptions!E53 | F8: =(Revenue!F10+Revenue!F15)*Assumptions!F52+(F5/30+F6)*Assumptions!F53 | G8: =(Revenue!G10+Revenue!G15)*Assumptions!G52+(G5/30+G6)*Assumptions!G53 | H8: =(Revenue!H10+Revenue!H15)*Assumptions!H52+(H5/30+H6)*Assumptions!H53 | I8: =(Revenue!I10+Revenue!I15)*Assumptions!I52+(I5/30+I6)*Assumptions!I53 | J8: =(Revenue!J10+Revenue!J15)*Assumptions!J52+(J5/30+J6)*Assumptions!J53 | ... L8: =(Revenue!L10+Revenue!L15)*Assumptions!L52+(L5/30+L6)*Assumptions!L53
A9: Media egress GB | B9: GB/yr | C9: =Drivers!C39*Assumptions!C59*12 | D9: =Drivers!D39*Assumptions!D59*12 | E9: =Drivers!E39*Assumptions!E59*12 | F9: =Drivers!F39*Assumptions!F59*12 | G9: =Drivers!G39*Assumptions!G59*12 | H9: =Drivers!H39*Assumptions!H59*12 | I9: =Drivers!I39*Assumptions!I59*12 | J9: =Drivers!J39*Assumptions!J59*12 | ... L9: =Drivers!L39*Assumptions!L59*12
A10: Infrastructure (AWS + CDN) | B10: base + egress | C10: =Assumptions!C58*12+C9*Assumptions!C60 | D10: =Assumptions!D58*12+D9*Assumptions!D60 | E10: =Assumptions!E58*12+E9*Assumptions!E60 | F10: =Assumptions!F58*12+F9*Assumptions!F60 | G10: =Assumptions!G58*12+G9*Assumptions!G60 | H10: =Assumptions!H58*12+H9*Assumptions!H60 | I10: =Assumptions!I58*12+I9*Assumptions!I60 | J10: =Assumptions!J58*12+J9*Assumptions!J60 | ... L10: =Assumptions!L58*12+L9*Assumptions!L60
A11: memo: same egress at CloudFront list | B11: the trap | C11: =Assumptions!C58*12+C9*Assumptions!C61 | D11: =Assumptions!D58*12+D9*Assumptions!D61 | E11: =Assumptions!E58*12+E9*Assumptions!E61 | F11: =Assumptions!F58*12+F9*Assumptions!F61 | G11: =Assumptions!G58*12+G9*Assumptions!G61 | H11: =Assumptions!H58*12+H9*Assumptions!H61 | I11: =Assumptions!I58*12+I9*Assumptions!I61 | J11: =Assumptions!J58*12+J9*Assumptions!J61 | ... L11: =Assumptions!L58*12+L9*Assumptions!L61
A12: Moderation | B12: items x rate | C12: =Drivers!C5*Assumptions!C63*12/1000*Assumptions!C62 | D12: =Drivers!D5*Assumptions!D63*12/1000*Assumptions!D62 | E12: =Drivers!E5*Assumptions!E63*12/1000*Assumptions!E62 | F12: =Drivers!F5*Assumptions!F63*12/1000*Assumptions!F62 | G12: =Drivers!G5*Assumptions!G63*12/1000*Assumptions!G62 | H12: =Drivers!H5*Assumptions!H63*12/1000*Assumptions!H62 | I12: =Drivers!I5*Assumptions!I63*12/1000*Assumptions!I62 | J12: =Drivers!J5*Assumptions!J63*12/1000*Assumptions!J62 | ... L12: =Drivers!L5*Assumptions!L63*12/1000*Assumptions!L62
A13: Athlete verification | B13: reviews x minutes x hourly | C13: =Drivers!C55*Assumptions!C87/60*(Assumptions!C67/Assumptions!C88) | D13: =Drivers!D55*Assumptions!D87/60*(Assumptions!D67/Assumptions!D88) | E13: =Drivers!E55*Assumptions!E87/60*(Assumptions!E67/Assumptions!E88) | F13: =Drivers!F55*Assumptions!F87/60*(Assumptions!F67/Assumptions!F88) | G13: =Drivers!G55*Assumptions!G87/60*(Assumptions!G67/Assumptions!G88) | H13: =Drivers!H55*Assumptions!H87/60*(Assumptions!H67/Assumptions!H88) | I13: =Drivers!I55*Assumptions!I87/60*(Assumptions!I67/Assumptions!I88) | J13: =Drivers!J55*Assumptions!J87/60*(Assumptions!J67/Assumptions!J88) | ... L13: =Drivers!L55*Assumptions!L87/60*(Assumptions!L67/Assumptions!L88)
A14: TOTAL COST OF SALES | C14: =C7+C8+C10+C12+C13 | D14: =D7+D8+D10+D12+D13 | E14: =E7+E8+E10+E12+E13 | F14: =F7+F8+F10+F12+F13 | G14: =G7+G8+G10+G12+G13 | H14: =H7+H8+H10+H12+H13 | I14: =I7+I8+I10+I12+I13 | J14: =J7+J8+J10+J12+J13 | ... L14: =L7+L8+L10+L12+L13
A16: OPERATING COSTS
A17: People | B17: FTE x loaded salary | C17: =Assumptions!C66*Assumptions!C67 | D17: =Assumptions!D66*Assumptions!D67 | E17: =Assumptions!E66*Assumptions!E67 | F17: =Assumptions!F66*Assumptions!F67 | G17: =Assumptions!G66*Assumptions!G67 | H17: =Assumptions!H66*Assumptions!H67 | I17: =Assumptions!I66*Assumptions!I67 | J17: =Assumptions!J66*Assumptions!J67 | ... L17: =Assumptions!L66*Assumptions!L67
A18: Athlete acquisition: niche | B18: gross adds x CAC | C18: =Drivers!C11*Assumptions!C19 | D18: =Drivers!D11*Assumptions!D19 | E18: =Drivers!E11*Assumptions!E19 | F18: =Drivers!F11*Assumptions!F19 | G18: =Drivers!G11*Assumptions!G19 | H18: =Drivers!H11*Assumptions!H19 | I18: =Drivers!I11*Assumptions!I19 | J18: =Drivers!J11*Assumptions!J19 | ... L18: =Drivers!L11*Assumptions!L19
A19: Athlete acquisition: popular | C19: =Drivers!C25*Assumptions!C31 | D19: =Drivers!D25*Assumptions!D31 | E19: =Drivers!E25*Assumptions!E31 | F19: =Drivers!F25*Assumptions!F31 | G19: =Drivers!G25*Assumptions!G31 | H19: =Drivers!H25*Assumptions!H31 | I19: =Drivers!I25*Assumptions!I31 | J19: =Drivers!J25*Assumptions!J31 | ... L19: =Drivers!L25*Assumptions!L31
A20: Sponsor acquisition | C20: =Drivers!C49*Assumptions!C37 | D20: =Drivers!D49*Assumptions!D37 | E20: =Drivers!E49*Assumptions!E37 | F20: =Drivers!F49*Assumptions!F37 | G20: =Drivers!G49*Assumptions!G37 | H20: =Drivers!H49*Assumptions!H37 | I20: =Drivers!I49*Assumptions!I37 | J20: =Drivers!J49*Assumptions!J37 | ... L20: =Drivers!L49*Assumptions!L37
A21: Total marketing / CAC | C21: =SUM(C18:C20) | D21: =SUM(D18:D20) | E21: =SUM(E18:E20) | F21: =SUM(F18:F20) | G21: =SUM(G18:G20) | H21: =SUM(H18:H20) | I21: =SUM(I18:I20) | J21: =SUM(J18:J20) | ... L21: =SUM(L18:L20)
A22: memo: athlete marketing per application | B22: CAC is per ADMITTED athlete | C22: =(C18+C19)/Drivers!C54 | D22: =(D18+D19)/Drivers!D54 | E22: =(E18+E19)/Drivers!E54 | F22: =(F18+F19)/Drivers!F54 | G22: =(G18+G19)/Drivers!G54 | H22: =(H18+H19)/Drivers!H54 | I22: =(I18+I19)/Drivers!I54 | J22: =(J18+J19)/Drivers!J54 | ... L22: =(L18+L19)/Drivers!L54
A23: Legal & compliance | C23: =Assumptions!C68 | D23: =Assumptions!D68 | E23: =Assumptions!E68 | F23: =Assumptions!F68 | G23: =Assumptions!G68 | H23: =Assumptions!H68 | I23: =Assumptions!I68 | J23: =Assumptions!J68 | ... L23: =Assumptions!L68
A24: Other opex | B24: % of revenue | C24: =Revenue!C26*Assumptions!C69 | D24: =Revenue!D26*Assumptions!D69 | E24: =Revenue!E26*Assumptions!E69 | F24: =Revenue!F26*Assumptions!F69 | G24: =Revenue!G26*Assumptions!G69 | H24: =Revenue!H26*Assumptions!H69 | I24: =Revenue!I26*Assumptions!I69 | J24: =Revenue!J26*Assumptions!J69 | ... L24: =Revenue!L26*Assumptions!L69
A25: TOTAL OPERATING COSTS | C25: =C17+C21+C23+C24 | D25: =D17+D21+D23+D24 | E25: =E17+E21+E23+E24 | F25: =F17+F21+F23+F24 | G25: =G17+G21+G23+G24 | H25: =H17+H21+H23+H24 | I25: =I17+I21+I23+I24 | J25: =J17+J21+J23+J24 | ... L25: =L17+L21+L23+L24

Sheet WorkingCap
A1: Working capital, capex and amortisation
C2: Input: change me | E2: Sourced fact | G2: Formula (this sheet) | I2: Formula (other sheet) | K2: Total
A3: Line | B3: Unit | C3: Y1 | D3: Y2 | E3: Y3 | F3: Y4 | G3: Y5 | H3: Y6 | I3: Y7 | J3: Y8 | K3: Y9 | L3: Y10
A4: WORKING CAPITAL
A5: Sponsor receivables | B5: SaaS+take x AR days/365 | C5: =(Revenue!C24+Revenue!C25)*Assumptions!C73/365 | D5: =(Revenue!D24+Revenue!D25)*Assumptions!D73/365 | E5: =(Revenue!E24+Revenue!E25)*Assumptions!E73/365 | F5: =(Revenue!F24+Revenue!F25)*Assumptions!F73/365 | G5: =(Revenue!G24+Revenue!G25)*Assumptions!G73/365 | H5: =(Revenue!H24+Revenue!H25)*Assumptions!H73/365 | I5: =(Revenue!I24+Revenue!I25)*Assumptions!I73/365 | J5: =(Revenue!J24+Revenue!J25)*Assumptions!J73/365 | ... L5: =(Revenue!L24+Revenue!L25)*Assumptions!L73/365
A6: Athlete payout float | B6: processed GMV owed, not yet paid | C6: =(Revenue!C10+Revenue!C15)*Assumptions!C72/365 | D6: =(Revenue!D10+Revenue!D15)*Assumptions!D72/365 | E6: =(Revenue!E10+Revenue!E15)*Assumptions!E72/365 | F6: =(Revenue!F10+Revenue!F15)*Assumptions!F72/365 | G6: =(Revenue!G10+Revenue!G15)*Assumptions!G72/365 | H6: =(Revenue!H10+Revenue!H15)*Assumptions!H72/365 | I6: =(Revenue!I10+Revenue!I15)*Assumptions!I72/365 | J6: =(Revenue!J10+Revenue!J15)*Assumptions!J72/365 | ... L6: =(Revenue!L10+Revenue!L15)*Assumptions!L72/365
A7: Trade payables | B7: opex x AP days/365 | C7: =Costs!C25*Assumptions!C74/365 | D7: =Costs!D25*Assumptions!D74/365 | E7: =Costs!E25*Assumptions!E74/365 | F7: =Costs!F25*Assumptions!F74/365 | G7: =Costs!G25*Assumptions!G74/365 | H7: =Costs!H25*Assumptions!H74/365 | I7: =Costs!I25*Assumptions!I74/365 | J7: =Costs!J25*Assumptions!J74/365 | ... L7: =Costs!L25*Assumptions!L74/365
A8: Net working capital | B8: AR - float - AP | C8: =C5-C6-C7 | D8: =D5-D6-D7 | E8: =E5-E6-E7 | F8: =F5-F6-F7 | G8: =G5-G6-G7 | H8: =H5-H6-H7 | I8: =I5-I6-I7 | J8: =J5-J6-J7 | ... L8: =L5-L6-L7
A9: Change in NWC | B9: cash impact | C9: =IF(1=1,C8,C8-C8) | D9: =IF(2=1,D8,D8-C8) | E9: =IF(3=1,E8,E8-D8) | F9: =IF(4=1,F8,F8-E8) | G9: =IF(5=1,G8,G8-F8) | H9: =IF(6=1,H8,H8-G8) | I9: =IF(7=1,I8,I8-H8) | J9: =IF(8=1,J8,J8-I8) | K9: =IF(9=1,K8,K8-J8) | L9: =IF(10=1,L8,L8-K8)
A11: CAPEX & AMORTISATION
A12: Capitalised development | B12: % of people cost | C12: =Costs!C17*Assumptions!C75 | D12: =Costs!D17*Assumptions!D75 | E12: =Costs!E17*Assumptions!E75 | F12: =Costs!F17*Assumptions!F75 | G12: =Costs!G17*Assumptions!G75 | H12: =Costs!H17*Assumptions!H75 | I12: =Costs!I17*Assumptions!I75 | J12: =Costs!J17*Assumptions!J75 | ... L12: =Costs!L17*Assumptions!L75
A13: Amortisation | B13: 3-yr straight line on trailing capex | C13: =SUM(OFFSET(C12,0,-MIN(Assumptions!C76-1,1-1),1,MIN(Assumptions!C76,1)))/Assumptions!C76 | D13: =SUM(OFFSET(D12,0,-MIN(Assumptions!D76-1,2-1),1,MIN(Assumptions!D76,2)))/Assumptions!D76 | E13: =SUM(OFFSET(E12,0,-MIN(Assumptions!E76-1,3-1),1,MIN(Assumptions!E76,3)))/Assumptions!E76 | F13: =SUM(OFFSET(F12,0,-MIN(Assumptions!F76-1,4-1),1,MIN(Assumptions!F76,4)))/Assumptions!F76 | G13: =SUM(OFFSET(G12,0,-MIN(Assumptions!G76-1,5-1),1,MIN(Assumptions!G76,5)))/Assumptions!G76 | H13: =SUM(OFFSET(H12,0,-MIN(Assumptions!H76-1,6-1),1,MIN(Assumptions!H76,6)))/Assumptions!H76 | I13: =SUM(OFFSET(I12,0,-MIN(Assumptions!I76-1,7-1),1,MIN(Assumptions!I76,7)))/Assumptions!I76 | J13: =SUM(OFFSET(J12,0,-MIN(Assumptions!J76-1,8-1),1,MIN(Assumptions!J76,8)))/Assumptions!J76 | K13: =SUM(OFFSET(K12,0,-MIN(Assumptions!K76-1,9-1),1,MIN(Assumptions!K76,9)))/Assumptions!K76 | L13: =SUM(OFFSET(L12,0,-MIN(Assumptions!L76-1,10-1),1,MIN(Assumptions!L76,10)))/Assumptions!L76
A14: Net intangible assets | B14: closing | C14: =C12-C13 | D14: =C14+D12-D13 | E14: =D14+E12-E13 | F14: =E14+F12-F13 | G14: =F14+G12-G13 | H14: =G14+H12-H13 | I14: =H14+I12-I13 | J14: =I14+J12-J13 | K14: =J14+K12-K13 | L14: =K14+L12-L13

Sheet P&L
A1: Income statement
C2: Input: change me | E2: Sourced fact | G2: Formula (this sheet) | I2: Formula (other sheet) | K2: Total
A3: Line | B3: Unit | C3: Y1 | D3: Y2 | E3: Y3 | F3: Y4 | G3: Y5 | H3: Y6 | I3: Y7 | J3: Y8 | K3: Y9 | L3: Y10
A4: Net revenue | C4: =Revenue!C26 | D4: =Revenue!D26 | E4: =Revenue!E26 | F4: =Revenue!F26 | G4: =Revenue!G26 | H4: =Revenue!H26 | I4: =Revenue!I26 | J4: =Revenue!J26 | ... L4: =Revenue!L26
A5: Cost of sales | C5: =-Costs!C14 | D5: =-Costs!D14 | E5: =-Costs!E14 | F5: =-Costs!F14 | G5: =-Costs!G14 | H5: =-Costs!H14 | I5: =-Costs!I14 | J5: =-Costs!J14 | ... L5: =-Costs!L14
A6: GROSS PROFIT | C6: =C4+C5 | D6: =D4+D5 | E6: =E4+E5 | F6: =F4+F5 | G6: =G4+G5 | H6: =H4+H5 | I6: =I4+I5 | J6: =J4+J5 | ... L6: =L4+L5
A7: Gross margin | C7: =C6/C4 | D7: =D6/D4 | E7: =E6/E4 | F7: =F6/F4 | G7: =G6/G4 | H7: =H6/H4 | I7: =I6/I4 | J7: =J6/J4 | ... L7: =L6/L4
A9: Operating costs | C9: =-Costs!C25 | D9: =-Costs!D25 | E9: =-Costs!E25 | F9: =-Costs!F25 | G9: =-Costs!G25 | H9: =-Costs!H25 | I9: =-Costs!I25 | J9: =-Costs!J25 | ... L9: =-Costs!L25
A10: EBITDA | C10: =C6+C9 | D10: =D6+D9 | E10: =E6+E9 | F10: =F6+F9 | G10: =G6+G9 | H10: =H6+H9 | I10: =I6+I9 | J10: =J6+J9 | ... L10: =L6+L9
A11: EBITDA margin | C11: =C10/C4 | D11: =D10/D4 | E11: =E10/E4 | F11: =F10/F4 | G11: =G10/G4 | H11: =H10/H4 | I11: =I10/I4 | J11: =J10/J4 | ... L11: =L10/L4
A12: Amortisation | C12: =-WorkingCap!C13 | D12: =-WorkingCap!D13 | E12: =-WorkingCap!E13 | F12: =-WorkingCap!F13 | G12: =-WorkingCap!G13 | H12: =-WorkingCap!H13 | I12: =-WorkingCap!I13 | J12: =-WorkingCap!J13 | ... L12: =-WorkingCap!L13
A13: EBIT | C13: =C10+C12 | D13: =D10+D12 | E13: =E10+E12 | F13: =F10+F12 | G13: =G10+G12 | H13: =H10+H12 | I13: =I10+I12 | J13: =J10+J12 | ... L13: =L10+L12
A15: TAX: with loss carryforward and the startup-rate step
A16: Losses brought forward | B16: accumulated | C16: =IF(1=1,0,MIN(0,C18)) | D16: =IF(2=1,0,MIN(0,C18)) | E16: =IF(3=1,0,MIN(0,D18)) | F16: =IF(4=1,0,MIN(0,E18)) | G16: =IF(5=1,0,MIN(0,F18)) | H16: =IF(6=1,0,MIN(0,G18)) | I16: =IF(7=1,0,MIN(0,H18)) | J16: =IF(8=1,0,MIN(0,I18)) | K16: =IF(9=1,0,MIN(0,J18)) | L16: =IF(10=1,0,MIN(0,K18))
A17: Taxable profit | B17: after offset | C17: =MAX(0,C13+C16) | D17: =MAX(0,D13+D16) | E17: =MAX(0,E13+E16) | F17: =MAX(0,F13+F16) | G17: =MAX(0,G13+G16) | H17: =MAX(0,H13+H16) | I17: =MAX(0,I13+I16) | J17: =MAX(0,J13+J16) | ... L17: =MAX(0,L13+L16)
A18: Losses carried forward | B18: running | C18: =MIN(0,C13) | D18: =MIN(0,D13+C18) | E18: =MIN(0,E13+D18) | F18: =MIN(0,F13+E18) | G18: =MIN(0,G13+F18) | H18: =MIN(0,H13+G18) | I18: =MIN(0,I13+H18) | J18: =MIN(0,J13+I18) | K18: =MIN(0,K13+J18) | L18: =MIN(0,L13+K18)
A19: Applicable tax rate | B19: 15% then 25% | C19: =IF(C17<=0,0,IF(COUNTIF($C17:C17,">0")<=Assumptions!C79,Assumptions!C77,Assumptions!C78)) | D19: =IF(D17<=0,0,IF(COUNTIF($C17:D17,">0")<=Assumptions!D79,Assumptions!D77,Assumptions!D78)) | E19: =IF(E17<=0,0,IF(COUNTIF($C17:E17,">0")<=Assumptions!E79,Assumptions!E77,Assumptions!E78)) | F19: =IF(F17<=0,0,IF(COUNTIF($C17:F17,">0")<=Assumptions!F79,Assumptions!F77,Assumptions!F78)) | G19: =IF(G17<=0,0,IF(COUNTIF($C17:G17,">0")<=Assumptions!G79,Assumptions!G77,Assumptions!G78)) | H19: =IF(H17<=0,0,IF(COUNTIF($C17:H17,">0")<=Assumptions!H79,Assumptions!H77,Assumptions!H78)) | I19: =IF(I17<=0,0,IF(COUNTIF($C17:I17,">0")<=Assumptions!I79,Assumptions!I77,Assumptions!I78)) | J19: =IF(J17<=0,0,IF(COUNTIF($C17:J17,">0")<=Assumptions!J79,Assumptions!J77,Assumptions!J78)) | ... L19: =IF(L17<=0,0,IF(COUNTIF($C17:L17,">0")<=Assumptions!L79,Assumptions!L77,Assumptions!L78))
A20: Tax charge | C20: =-C17*C19 | D20: =-D17*D19 | E20: =-E17*E19 | F20: =-F17*F19 | G20: =-G17*G19 | H20: =-H17*H19 | I20: =-I17*I19 | J20: =-J17*J19 | ... L20: =-L17*L19
A21: NET PROFIT | C21: =C13+C20 | D21: =D13+D20 | E21: =E13+E20 | F21: =F13+F20 | G21: =G13+G20 | H21: =H13+H20 | I21: =I13+I20 | J21: =J13+J20 | ... L21: =L13+L20

Sheet CashFlow
A1: Cash flow, indirect method
C2: Input: change me | E2: Sourced fact | G2: Formula (this sheet) | I2: Formula (other sheet) | K2: Total
A3: Line | B3: Unit | C3: Y1 | D3: Y2 | E3: Y3 | F3: Y4 | G3: Y5 | H3: Y6 | I3: Y7 | J3: Y8 | K3: Y9 | L3: Y10
A4: Net profit | C4: ='P&L'!C21 | D4: ='P&L'!D21 | E4: ='P&L'!E21 | F4: ='P&L'!F21 | G4: ='P&L'!G21 | H4: ='P&L'!H21 | I4: ='P&L'!I21 | J4: ='P&L'!J21 | ... L4: ='P&L'!L21
A5: Add back amortisation | C5: =WorkingCap!C13 | D5: =WorkingCap!D13 | E5: =WorkingCap!E13 | F5: =WorkingCap!F13 | G5: =WorkingCap!G13 | H5: =WorkingCap!H13 | I5: =WorkingCap!I13 | J5: =WorkingCap!J13 | ... L5: =WorkingCap!L13
A6: Change in working capital | C6: =-WorkingCap!C9 | D6: =-WorkingCap!D9 | E6: =-WorkingCap!E9 | F6: =-WorkingCap!F9 | G6: =-WorkingCap!G9 | H6: =-WorkingCap!H9 | I6: =-WorkingCap!I9 | J6: =-WorkingCap!J9 | ... L6: =-WorkingCap!L9
A7: OPERATING CASH FLOW | C7: =SUM(C4:C6) | D7: =SUM(D4:D6) | E7: =SUM(E4:E6) | F7: =SUM(F4:F6) | G7: =SUM(G4:G6) | H7: =SUM(H4:H6) | I7: =SUM(I4:I6) | J7: =SUM(J4:J6) | ... L7: =SUM(L4:L6)
A8: Capital expenditure | C8: =-WorkingCap!C12 | D8: =-WorkingCap!D12 | E8: =-WorkingCap!E12 | F8: =-WorkingCap!F12 | G8: =-WorkingCap!G12 | H8: =-WorkingCap!H12 | I8: =-WorkingCap!I12 | J8: =-WorkingCap!J12 | ... L8: =-WorkingCap!L12
A9: FREE CASH FLOW | C9: =C7+C8 | D9: =D7+D8 | E9: =E7+E8 | F9: =F7+F8 | G9: =G7+G8 | H9: =H7+H8 | I9: =I7+I8 | J9: =J7+J8 | ... L9: =L7+L8
A10: Cumulative free cash flow | C10: =C9 | D10: =C10+D9 | E10: =D10+E9 | F10: =E10+F9 | G10: =F10+G9 | H10: =G10+H9 | I10: =H10+I9 | J10: =I10+J9 | K10: =J10+K9 | L10: =K10+L9
A12: Equity raised | B12: see Funding | C12: =Funding!C4 | D12: =Funding!D4 | E12: =Funding!E4 | F12: =Funding!F4 | G12: =Funding!G4 | H12: =Funding!H4 | I12: =Funding!I4 | J12: =Funding!J4 | ... L12: =Funding!L4
A13: Opening cash | C13: =0 | D13: =C14 | E13: =D14 | F13: =E14 | G13: =F14 | H13: =G14 | I13: =H14 | J13: =I14 | K13: =J14 | L13: =K14
A14: CLOSING CASH | C14: =C13+C9+C12 | D14: =D13+D9+D12 | E14: =E13+E9+E12 | F14: =F13+F9+F12 | G14: =G13+G9+G12 | H14: =H13+H9+H12 | I14: =I13+I9+I12 | J14: =J13+J9+J12 | ... L14: =L13+L9+L12

Sheet BalanceSheet
A1: Balance sheet
C2: Input: change me | E2: Sourced fact | G2: Formula (this sheet) | I2: Formula (other sheet) | K2: Total
A3: Line | B3: Unit | C3: Y1 | D3: Y2 | E3: Y3 | F3: Y4 | G3: Y5 | H3: Y6 | I3: Y7 | J3: Y8 | K3: Y9 | L3: Y10
A4: ASSETS
A5: Cash | C5: =CashFlow!C14 | D5: =CashFlow!D14 | E5: =CashFlow!E14 | F5: =CashFlow!F14 | G5: =CashFlow!G14 | H5: =CashFlow!H14 | I5: =CashFlow!I14 | J5: =CashFlow!J14 | ... L5: =CashFlow!L14
A6: Sponsor receivables | C6: =WorkingCap!C5 | D6: =WorkingCap!D5 | E6: =WorkingCap!E5 | F6: =WorkingCap!F5 | G6: =WorkingCap!G5 | H6: =WorkingCap!H5 | I6: =WorkingCap!I5 | J6: =WorkingCap!J5 | ... L6: =WorkingCap!L5
A7: Net intangible assets | C7: =WorkingCap!C14 | D7: =WorkingCap!D14 | E7: =WorkingCap!E14 | F7: =WorkingCap!F14 | G7: =WorkingCap!G14 | H7: =WorkingCap!H14 | I7: =WorkingCap!I14 | J7: =WorkingCap!J14 | ... L7: =WorkingCap!L14
A8: TOTAL ASSETS | C8: =SUM(C5:C7) | D8: =SUM(D5:D7) | E8: =SUM(E5:E7) | F8: =SUM(F5:F7) | G8: =SUM(G5:G7) | H8: =SUM(H5:H7) | I8: =SUM(I5:I7) | J8: =SUM(J5:J7) | ... L8: =SUM(L5:L7)
A10: LIABILITIES
A11: Athlete payout float | C11: =WorkingCap!C6 | D11: =WorkingCap!D6 | E11: =WorkingCap!E6 | F11: =WorkingCap!F6 | G11: =WorkingCap!G6 | H11: =WorkingCap!H6 | I11: =WorkingCap!I6 | J11: =WorkingCap!J6 | ... L11: =WorkingCap!L6
A12: Trade payables | C12: =WorkingCap!C7 | D12: =WorkingCap!D7 | E12: =WorkingCap!E7 | F12: =WorkingCap!F7 | G12: =WorkingCap!G7 | H12: =WorkingCap!H7 | I12: =WorkingCap!I7 | J12: =WorkingCap!J7 | ... L12: =WorkingCap!L7
A13: TOTAL LIABILITIES | C13: =C11+C12 | D13: =D11+D12 | E13: =E11+E12 | F13: =F11+F12 | G13: =G11+G12 | H13: =H11+H12 | I13: =I11+I12 | J13: =J11+J12 | ... L13: =L11+L12
A15: EQUITY
A16: Paid-in capital | C16: =Funding!C4 | D16: =C16+Funding!D4 | E16: =D16+Funding!E4 | F16: =E16+Funding!F4 | G16: =F16+Funding!G4 | H16: =G16+Funding!H4 | I16: =H16+Funding!I4 | J16: =I16+Funding!J4 | K16: =J16+Funding!K4 | L16: =K16+Funding!L4
A17: Retained earnings | C17: ='P&L'!C21 | D17: =C17+'P&L'!D21 | E17: =D17+'P&L'!E21 | F17: =E17+'P&L'!F21 | G17: =F17+'P&L'!G21 | H17: =G17+'P&L'!H21 | I17: =H17+'P&L'!I21 | J17: =I17+'P&L'!J21 | K17: =J17+'P&L'!K21 | L17: =K17+'P&L'!L21
A18: TOTAL EQUITY | C18: =C16+C17 | D18: =D16+D17 | E18: =E16+E17 | F18: =F16+F17 | G18: =G16+G17 | H18: =H16+H17 | I18: =I16+I17 | J18: =J16+J17 | ... L18: =L16+L17
A19: Liabilities + equity | C19: =C13+C18 | D19: =D13+D18 | E19: =E13+E18 | F19: =F13+F18 | G19: =G13+G18 | H19: =H13+H18 | I19: =I13+I18 | J19: =J13+J18 | ... L19: =L13+L18
A20: BALANCE CHECK | B20: must be zero | C20: =ROUND(C8-C19,2) | D20: =ROUND(D8-D19,2) | E20: =ROUND(E8-E19,2) | F20: =ROUND(F8-F19,2) | G20: =ROUND(G8-G19,2) | H20: =ROUND(H8-H19,2) | I20: =ROUND(I8-I19,2) | J20: =ROUND(J8-J19,2) | ... L20: =ROUND(L8-L19,2)

Sheet Valuation
A1: Valuation, DCF, NPV, IRR and exit multiples
C2: Input: change me | E2: Sourced fact | G2: Formula (this sheet) | I2: Formula (other sheet) | K2: Total
A3: Line | B3: Unit | C3: Y1 | D3: Y2 | E3: Y3 | F3: Y4 | G3: Y5 | H3: Y6 | I3: Y7 | J3: Y8 | K3: Y9 | L3: Y10
A4: Free cash flow | B4: EUR | C4: =CashFlow!C9 | D4: =CashFlow!D9 | E4: =CashFlow!E9 | F4: =CashFlow!F9 | G4: =CashFlow!G9 | H4: =CashFlow!H9 | I4: =CashFlow!I9 | J4: =CashFlow!J9 | ... L4: =CashFlow!L9
A5: Discount factor | B5: 1/(1+WACC)^t | C5: =1/(1+Assumptions!$C$91)^1 | D5: =1/(1+Assumptions!$C$91)^2 | E5: =1/(1+Assumptions!$C$91)^3 | F5: =1/(1+Assumptions!$C$91)^4 | G5: =1/(1+Assumptions!$C$91)^5 | H5: =1/(1+Assumptions!$C$91)^6 | I5: =1/(1+Assumptions!$C$91)^7 | J5: =1/(1+Assumptions!$C$91)^8 | K5: =1/(1+Assumptions!$C$91)^9 | L5: =1/(1+Assumptions!$C$91)^10
A6: Discounted FCF | B6: EUR | C6: =C4*C5 | D6: =D4*D5 | E6: =E4*E5 | F6: =F4*F5 | G6: =G4*G5 | H6: =H4*H5 | I6: =I4*I5 | J6: =J4*J5 | ... L6: =L4*L5
A8: FCF incl. terminal value | B8: for the IRR below | C8: =C4+IF(1=10,$C$11,0) | D8: =D4+IF(2=10,$C$11,0) | E8: =E4+IF(3=10,$C$11,0) | F8: =F4+IF(4=10,$C$11,0) | G8: =G4+IF(5=10,$C$11,0) | H8: =H4+IF(6=10,$C$11,0) | I8: =I4+IF(7=10,$C$11,0) | J8: =J4+IF(8=10,$C$11,0) | K8: =K4+IF(9=10,$C$11,0) | L8: =L4+IF(10=10,$C$11,0)
A9: DCF
A10: PV of explicit forecast | C10: =SUM(C6:L6)
A11: Terminal value at Y10 | C11: =L4*(1+Assumptions!$C$92)/(Assumptions!$C$91-Assumptions!$C$92)
A12: PV of terminal value | C12: =C11*L5
A13: ENTERPRISE VALUE (DCF) | C13: =C10+C12
A15: RETURN METRICS
A16: NPV of FCF at WACC | C16: =NPV(Assumptions!$C$91,C4:L4)
A17: IRR of the plan | C17: =IRR(C4:L4)
A18: IRR incl. terminal value | C18: =IRR(C8:L8,0.3)
A20: EXIT MULTIPLE
A21: Y10 net revenue | C21: =Revenue!L26
A22: Exit value at Y10 | C22: =C21*Assumptions!$C$93
A23: Discounted to today | C23: =C22*L5
A25: SENSITIVITY: enterprise value by WACC and terminal growth
A26: Terminal growth \ WACC | C26: 0.18 | D26: 0.2 | E26: 0.22 | F26: 0.25 | G26: 0.28 | H26: 0.3
A27: 0.01 | C27: =CashFlow!C9/(1+0.18)^1+CashFlow!D9/(1+0.18)^2+CashFlow!E9/(1+0.18)^3+CashFlow!F9/(1+0.18)^4+CashFlow!G9/(1+0.18)^5+CashFlow!H9/(1+0.18)^6+CashFlow!I9/(1+0.18)^7+CashFlow!J9/(1+0.18)^8+CashFlow!K9/(1+0.18)^9+CashFlow!L9/(1+0.18)^10+CashFlow!L9*(1+0.01)/(0.18-0.01)/(1+0.18)^10 | D27: =CashFlow!C9/(1+0.2)^1+CashFlow!D9/(1+0.2)^2+CashFlow!E9/(1+0.2)^3+CashFlow!F9/(1+0.2)^4+CashFlow!G9/(1+0.2)^5+CashFlow!H9/(1+0.2)^6+CashFlow!I9/(1+0.2)^7+CashFlow!J9/(1+0.2)^8+CashFlow!K9/(1+0.2)^9+CashFlow!L9/(1+0.2)^10+CashFlow!L9*(1+0.01)/(0.2-0.01)/(1+0.2)^10 | E27: =CashFlow!C9/(1+0.22)^1+CashFlow!D9/(1+0.22)^2+CashFlow!E9/(1+0.22)^3+CashFlow!F9/(1+0.22)^4+CashFlow!G9/(1+0.22)^5+CashFlow!H9/(1+0.22)^6+CashFlow!I9/(1+0.22)^7+CashFlow!J9/(1+0.22)^8+CashFlow!K9/(1+0.22)^9+CashFlow!L9/(1+0.22)^10+CashFlow!L9*(1+0.01)/(0.22-0.01)/(1+0.22)^10 | F27: =CashFlow!C9/(1+0.25)^1+CashFlow!D9/(1+0.25)^2+CashFlow!E9/(1+0.25)^3+CashFlow!F9/(1+0.25)^4+CashFlow!G9/(1+0.25)^5+CashFlow!H9/(1+0.25)^6+CashFlow!I9/(1+0.25)^7+CashFlow!J9/(1+0.25)^8+CashFlow!K9/(1+0.25)^9+CashFlow!L9/(1+0.25)^10+CashFlow!L9*(1+0.01)/(0.25-0.01)/(1+0.25)^10 | G27: =CashFlow!C9/(1+0.28)^1+CashFlow!D9/(1+0.28)^2+CashFlow!E9/(1+0.28)^3+CashFlow!F9/(1+0.28)^4+CashFlow!G9/(1+0.28)^5+CashFlow!H9/(1+0.28)^6+CashFlow!I9/(1+0.28)^7+CashFlow!J9/(1+0.28)^8+CashFlow!K9/(1+0.28)^9+CashFlow!L9/(1+0.28)^10+CashFlow!L9*(1+0.01)/(0.28-0.01)/(1+0.28)^10 | H27: =CashFlow!C9/(1+0.3)^1+CashFlow!D9/(1+0.3)^2+CashFlow!E9/(1+0.3)^3+CashFlow!F9/(1+0.3)^4+CashFlow!G9/(1+0.3)^5+CashFlow!H9/(1+0.3)^6+CashFlow!I9/(1+0.3)^7+CashFlow!J9/(1+0.3)^8+CashFlow!K9/(1+0.3)^9+CashFlow!L9/(1+0.3)^10+CashFlow!L9*(1+0.01)/(0.3-0.01)/(1+0.3)^10
A28: 0.02 | C28: =CashFlow!C9/(1+0.18)^1+CashFlow!D9/(1+0.18)^2+CashFlow!E9/(1+0.18)^3+CashFlow!F9/(1+0.18)^4+CashFlow!G9/(1+0.18)^5+CashFlow!H9/(1+0.18)^6+CashFlow!I9/(1+0.18)^7+CashFlow!J9/(1+0.18)^8+CashFlow!K9/(1+0.18)^9+CashFlow!L9/(1+0.18)^10+CashFlow!L9*(1+0.02)/(0.18-0.02)/(1+0.18)^10 | D28: =CashFlow!C9/(1+0.2)^1+CashFlow!D9/(1+0.2)^2+CashFlow!E9/(1+0.2)^3+CashFlow!F9/(1+0.2)^4+CashFlow!G9/(1+0.2)^5+CashFlow!H9/(1+0.2)^6+CashFlow!I9/(1+0.2)^7+CashFlow!J9/(1+0.2)^8+CashFlow!K9/(1+0.2)^9+CashFlow!L9/(1+0.2)^10+CashFlow!L9*(1+0.02)/(0.2-0.02)/(1+0.2)^10 | E28: =CashFlow!C9/(1+0.22)^1+CashFlow!D9/(1+0.22)^2+CashFlow!E9/(1+0.22)^3+CashFlow!F9/(1+0.22)^4+CashFlow!G9/(1+0.22)^5+CashFlow!H9/(1+0.22)^6+CashFlow!I9/(1+0.22)^7+CashFlow!J9/(1+0.22)^8+CashFlow!K9/(1+0.22)^9+CashFlow!L9/(1+0.22)^10+CashFlow!L9*(1+0.02)/(0.22-0.02)/(1+0.22)^10 | F28: =CashFlow!C9/(1+0.25)^1+CashFlow!D9/(1+0.25)^2+CashFlow!E9/(1+0.25)^3+CashFlow!F9/(1+0.25)^4+CashFlow!G9/(1+0.25)^5+CashFlow!H9/(1+0.25)^6+CashFlow!I9/(1+0.25)^7+CashFlow!J9/(1+0.25)^8+CashFlow!K9/(1+0.25)^9+CashFlow!L9/(1+0.25)^10+CashFlow!L9*(1+0.02)/(0.25-0.02)/(1+0.25)^10 | G28: =CashFlow!C9/(1+0.28)^1+CashFlow!D9/(1+0.28)^2+CashFlow!E9/(1+0.28)^3+CashFlow!F9/(1+0.28)^4+CashFlow!G9/(1+0.28)^5+CashFlow!H9/(1+0.28)^6+CashFlow!I9/(1+0.28)^7+CashFlow!J9/(1+0.28)^8+CashFlow!K9/(1+0.28)^9+CashFlow!L9/(1+0.28)^10+CashFlow!L9*(1+0.02)/(0.28-0.02)/(1+0.28)^10 | H28: =CashFlow!C9/(1+0.3)^1+CashFlow!D9/(1+0.3)^2+CashFlow!E9/(1+0.3)^3+CashFlow!F9/(1+0.3)^4+CashFlow!G9/(1+0.3)^5+CashFlow!H9/(1+0.3)^6+CashFlow!I9/(1+0.3)^7+CashFlow!J9/(1+0.3)^8+CashFlow!K9/(1+0.3)^9+CashFlow!L9/(1+0.3)^10+CashFlow!L9*(1+0.02)/(0.3-0.02)/(1+0.3)^10
A29: 0.03 | C29: =CashFlow!C9/(1+0.18)^1+CashFlow!D9/(1+0.18)^2+CashFlow!E9/(1+0.18)^3+CashFlow!F9/(1+0.18)^4+CashFlow!G9/(1+0.18)^5+CashFlow!H9/(1+0.18)^6+CashFlow!I9/(1+0.18)^7+CashFlow!J9/(1+0.18)^8+CashFlow!K9/(1+0.18)^9+CashFlow!L9/(1+0.18)^10+CashFlow!L9*(1+0.03)/(0.18-0.03)/(1+0.18)^10 | D29: =CashFlow!C9/(1+0.2)^1+CashFlow!D9/(1+0.2)^2+CashFlow!E9/(1+0.2)^3+CashFlow!F9/(1+0.2)^4+CashFlow!G9/(1+0.2)^5+CashFlow!H9/(1+0.2)^6+CashFlow!I9/(1+0.2)^7+CashFlow!J9/(1+0.2)^8+CashFlow!K9/(1+0.2)^9+CashFlow!L9/(1+0.2)^10+CashFlow!L9*(1+0.03)/(0.2-0.03)/(1+0.2)^10 | E29: =CashFlow!C9/(1+0.22)^1+CashFlow!D9/(1+0.22)^2+CashFlow!E9/(1+0.22)^3+CashFlow!F9/(1+0.22)^4+CashFlow!G9/(1+0.22)^5+CashFlow!H9/(1+0.22)^6+CashFlow!I9/(1+0.22)^7+CashFlow!J9/(1+0.22)^8+CashFlow!K9/(1+0.22)^9+CashFlow!L9/(1+0.22)^10+CashFlow!L9*(1+0.03)/(0.22-0.03)/(1+0.22)^10 | F29: =CashFlow!C9/(1+0.25)^1+CashFlow!D9/(1+0.25)^2+CashFlow!E9/(1+0.25)^3+CashFlow!F9/(1+0.25)^4+CashFlow!G9/(1+0.25)^5+CashFlow!H9/(1+0.25)^6+CashFlow!I9/(1+0.25)^7+CashFlow!J9/(1+0.25)^8+CashFlow!K9/(1+0.25)^9+CashFlow!L9/(1+0.25)^10+CashFlow!L9*(1+0.03)/(0.25-0.03)/(1+0.25)^10 | G29: =CashFlow!C9/(1+0.28)^1+CashFlow!D9/(1+0.28)^2+CashFlow!E9/(1+0.28)^3+CashFlow!F9/(1+0.28)^4+CashFlow!G9/(1+0.28)^5+CashFlow!H9/(1+0.28)^6+CashFlow!I9/(1+0.28)^7+CashFlow!J9/(1+0.28)^8+CashFlow!K9/(1+0.28)^9+CashFlow!L9/(1+0.28)^10+CashFlow!L9*(1+0.03)/(0.28-0.03)/(1+0.28)^10 | H29: =CashFlow!C9/(1+0.3)^1+CashFlow!D9/(1+0.3)^2+CashFlow!E9/(1+0.3)^3+CashFlow!F9/(1+0.3)^4+CashFlow!G9/(1+0.3)^5+CashFlow!H9/(1+0.3)^6+CashFlow!I9/(1+0.3)^7+CashFlow!J9/(1+0.3)^8+CashFlow!K9/(1+0.3)^9+CashFlow!L9/(1+0.3)^10+CashFlow!L9*(1+0.03)/(0.3-0.03)/(1+0.3)^10
A30: 0.04 | C30: =CashFlow!C9/(1+0.18)^1+CashFlow!D9/(1+0.18)^2+CashFlow!E9/(1+0.18)^3+CashFlow!F9/(1+0.18)^4+CashFlow!G9/(1+0.18)^5+CashFlow!H9/(1+0.18)^6+CashFlow!I9/(1+0.18)^7+CashFlow!J9/(1+0.18)^8+CashFlow!K9/(1+0.18)^9+CashFlow!L9/(1+0.18)^10+CashFlow!L9*(1+0.04)/(0.18-0.04)/(1+0.18)^10 | D30: =CashFlow!C9/(1+0.2)^1+CashFlow!D9/(1+0.2)^2+CashFlow!E9/(1+0.2)^3+CashFlow!F9/(1+0.2)^4+CashFlow!G9/(1+0.2)^5+CashFlow!H9/(1+0.2)^6+CashFlow!I9/(1+0.2)^7+CashFlow!J9/(1+0.2)^8+CashFlow!K9/(1+0.2)^9+CashFlow!L9/(1+0.2)^10+CashFlow!L9*(1+0.04)/(0.2-0.04)/(1+0.2)^10 | E30: =CashFlow!C9/(1+0.22)^1+CashFlow!D9/(1+0.22)^2+CashFlow!E9/(1+0.22)^3+CashFlow!F9/(1+0.22)^4+CashFlow!G9/(1+0.22)^5+CashFlow!H9/(1+0.22)^6+CashFlow!I9/(1+0.22)^7+CashFlow!J9/(1+0.22)^8+CashFlow!K9/(1+0.22)^9+CashFlow!L9/(1+0.22)^10+CashFlow!L9*(1+0.04)/(0.22-0.04)/(1+0.22)^10 | F30: =CashFlow!C9/(1+0.25)^1+CashFlow!D9/(1+0.25)^2+CashFlow!E9/(1+0.25)^3+CashFlow!F9/(1+0.25)^4+CashFlow!G9/(1+0.25)^5+CashFlow!H9/(1+0.25)^6+CashFlow!I9/(1+0.25)^7+CashFlow!J9/(1+0.25)^8+CashFlow!K9/(1+0.25)^9+CashFlow!L9/(1+0.25)^10+CashFlow!L9*(1+0.04)/(0.25-0.04)/(1+0.25)^10 | G30: =CashFlow!C9/(1+0.28)^1+CashFlow!D9/(1+0.28)^2+CashFlow!E9/(1+0.28)^3+CashFlow!F9/(1+0.28)^4+CashFlow!G9/(1+0.28)^5+CashFlow!H9/(1+0.28)^6+CashFlow!I9/(1+0.28)^7+CashFlow!J9/(1+0.28)^8+CashFlow!K9/(1+0.28)^9+CashFlow!L9/(1+0.28)^10+CashFlow!L9*(1+0.04)/(0.28-0.04)/(1+0.28)^10 | H30: =CashFlow!C9/(1+0.3)^1+CashFlow!D9/(1+0.3)^2+CashFlow!E9/(1+0.3)^3+CashFlow!F9/(1+0.3)^4+CashFlow!G9/(1+0.3)^5+CashFlow!H9/(1+0.3)^6+CashFlow!I9/(1+0.3)^7+CashFlow!J9/(1+0.3)^8+CashFlow!K9/(1+0.3)^9+CashFlow!L9/(1+0.3)^10+CashFlow!L9*(1+0.04)/(0.3-0.04)/(1+0.3)^10
A31: 0.05 | C31: =CashFlow!C9/(1+0.18)^1+CashFlow!D9/(1+0.18)^2+CashFlow!E9/(1+0.18)^3+CashFlow!F9/(1+0.18)^4+CashFlow!G9/(1+0.18)^5+CashFlow!H9/(1+0.18)^6+CashFlow!I9/(1+0.18)^7+CashFlow!J9/(1+0.18)^8+CashFlow!K9/(1+0.18)^9+CashFlow!L9/(1+0.18)^10+CashFlow!L9*(1+0.05)/(0.18-0.05)/(1+0.18)^10 | D31: =CashFlow!C9/(1+0.2)^1+CashFlow!D9/(1+0.2)^2+CashFlow!E9/(1+0.2)^3+CashFlow!F9/(1+0.2)^4+CashFlow!G9/(1+0.2)^5+CashFlow!H9/(1+0.2)^6+CashFlow!I9/(1+0.2)^7+CashFlow!J9/(1+0.2)^8+CashFlow!K9/(1+0.2)^9+CashFlow!L9/(1+0.2)^10+CashFlow!L9*(1+0.05)/(0.2-0.05)/(1+0.2)^10 | E31: =CashFlow!C9/(1+0.22)^1+CashFlow!D9/(1+0.22)^2+CashFlow!E9/(1+0.22)^3+CashFlow!F9/(1+0.22)^4+CashFlow!G9/(1+0.22)^5+CashFlow!H9/(1+0.22)^6+CashFlow!I9/(1+0.22)^7+CashFlow!J9/(1+0.22)^8+CashFlow!K9/(1+0.22)^9+CashFlow!L9/(1+0.22)^10+CashFlow!L9*(1+0.05)/(0.22-0.05)/(1+0.22)^10 | F31: =CashFlow!C9/(1+0.25)^1+CashFlow!D9/(1+0.25)^2+CashFlow!E9/(1+0.25)^3+CashFlow!F9/(1+0.25)^4+CashFlow!G9/(1+0.25)^5+CashFlow!H9/(1+0.25)^6+CashFlow!I9/(1+0.25)^7+CashFlow!J9/(1+0.25)^8+CashFlow!K9/(1+0.25)^9+CashFlow!L9/(1+0.25)^10+CashFlow!L9*(1+0.05)/(0.25-0.05)/(1+0.25)^10 | G31: =CashFlow!C9/(1+0.28)^1+CashFlow!D9/(1+0.28)^2+CashFlow!E9/(1+0.28)^3+CashFlow!F9/(1+0.28)^4+CashFlow!G9/(1+0.28)^5+CashFlow!H9/(1+0.28)^6+CashFlow!I9/(1+0.28)^7+CashFlow!J9/(1+0.28)^8+CashFlow!K9/(1+0.28)^9+CashFlow!L9/(1+0.28)^10+CashFlow!L9*(1+0.05)/(0.28-0.05)/(1+0.28)^10 | H31: =CashFlow!C9/(1+0.3)^1+CashFlow!D9/(1+0.3)^2+CashFlow!E9/(1+0.3)^3+CashFlow!F9/(1+0.3)^4+CashFlow!G9/(1+0.3)^5+CashFlow!H9/(1+0.3)^6+CashFlow!I9/(1+0.3)^7+CashFlow!J9/(1+0.3)^8+CashFlow!K9/(1+0.3)^9+CashFlow!L9/(1+0.3)^10+CashFlow!L9*(1+0.05)/(0.3-0.05)/(1+0.3)^10

Sheet Funding
A1: Funding rounds and dilution
C2: Input: change me | E2: Sourced fact | G2: Formula (this sheet) | I2: Formula (other sheet) | K2: Total
A3: Line | B3: Unit | C3: Y1 | D3: Y2 | E3: Y3 | F3: Y4 | G3: Y5 | H3: Y6 | I3: Y7 | J3: Y8 | K3: Y9 | L3: Y10
A4: Equity raised | B4: EUR | C4: 600000 | D4: 0 | E4: 0 | F4: 2000000 | G4: 0 | H4: 8000000 | I4: 0 | J4: 0 | K4: 0 | L4: 0
A5: Pre-money valuation | B5: EUR | C5: 2500000 | D5: 0 | E5: 0 | F5: 10000000 | G5: 0 | H5: 40000000 | I5: 0 | J5: 0 | K5: 0 | L5: 0
A6: Post-money valuation | B6: EUR | C6: =IF(C4=0,0,C5+C4) | D6: =IF(D4=0,0,D5+D4) | E6: =IF(E4=0,0,E5+E4) | F6: =IF(F4=0,0,F5+F4) | G6: =IF(G4=0,0,G5+G4) | H6: =IF(H4=0,0,H5+H4) | I6: =IF(I4=0,0,I5+I4) | J6: =IF(J4=0,0,J5+J4) | ... L6: =IF(L4=0,0,L5+L4)
A7: New investor stake | B7: % | C7: =IF(C6=0,0,C4/C6) | D7: =IF(D6=0,0,D4/D6) | E7: =IF(E6=0,0,E4/E6) | F7: =IF(F6=0,0,F4/F6) | G7: =IF(G6=0,0,G4/G6) | H7: =IF(H6=0,0,H4/H6) | I7: =IF(I6=0,0,I4/I6) | J7: =IF(J6=0,0,J4/J6) | ... L7: =IF(L6=0,0,L4/L6)
A8: Advisory grant | B8: % | C8: 0.02 | D8: 0 | E8: 0 | F8: 0 | G8: 0 | H8: 0 | I8: 0 | J8: 0 | K8: 0 | L8: 0
A9: ESOP pool | B9: % | C9: 0 | D9: 0 | E9: 0 | F9: 0 | G9: 0 | H9: 0.1 | I9: 0 | J9: 0 | K9: 0 | L9: 0
A10: Founders + team retained | B10: % | C10: =(1-C7-C8)*(1-C9) | D10: =(C10*(1-D7)-D8)*(1-D9) | E10: =(D10*(1-E7)-E8)*(1-E9) | F10: =(E10*(1-F7)-F8)*(1-F9) | G10: =(F10*(1-G7)-G8)*(1-G9) | H10: =(G10*(1-H7)-H8)*(1-H9) | I10: =(H10*(1-I7)-I8)*(1-I9) | J10: =(I10*(1-J7)-J8)*(1-J9) | K10: =(J10*(1-K7)-K8)*(1-K9) | L10: =(K10*(1-L7)-L8)*(1-L9)
A11: Cumulative dilution | B11: % | C11: =1-C10 | D11: =1-D10 | E11: =1-E10 | F11: =1-F10 | G11: =1-G10 | H11: =1-H10 | I11: =1-I10 | J11: =1-J10 | ... L11: =1-L10

Sheet HiringPlan
A1: Hiring plan, headcount by role, reconciled to the model
C2: Input: change me | E2: Sourced fact | G2: Formula (this sheet) | I2: Formula (other sheet) | K2: Total
A3: Line | B3: Unit | C3: Y1 | D3: Y2 | E3: Y3 | F3: Y4 | G3: Y5 | H3: Y6 | I3: Y7 | J3: Y8 | K3: Y9 | L3: Y10
A4: FTE BY ROLE
A5: Founder / CEO | B5: FTE | C5: 1 | D5: 1 | E5: 1 | F5: 1 | G5: 1 | H5: 1 | I5: 1 | J5: 1 | K5: 1 | L5: 1
A6: Engineering | B6: FTE | C6: 0.5 | D6: 1 | E6: 1.5 | F6: 2 | G6: 3.5 | H6: 5 | I6: 7 | J6: 9 | K6: 11 | L6: 13
A7: BD / partnerships | B7: FTE | C7: 0 | D7: 0 | E7: 0.5 | F7: 1 | G7: 2 | H7: 3 | I7: 5 | J7: 6 | K7: 7 | L7: 8
A8: Athlete success | B8: FTE | C8: 0 | D8: 0 | E8: 0.5 | F8: 1 | G8: 1.5 | H8: 2.5 | I8: 4 | J8: 5 | K8: 6 | L8: 7
A9: Trust & safety / review | B9: FTE | C9: 0 | D9: 0 | E9: 0 | F9: 0.5 | G9: 1 | H9: 2 | I9: 3 | J9: 4 | K9: 5 | L9: 6
A10: Finance / operations | B10: FTE | C10: 0 | D10: 0 | E10: 0 | F10: 0.5 | G10: 1 | H10: 1 | I10: 1 | J10: 2 | K10: 2 | L10: 2
A11: Data protection officer | B11: FTE | C11: 0 | D11: 0 | E11: 0 | F11: 0 | G11: 0 | H11: 0.5 | I11: 1 | J11: 1 | K11: 1 | L11: 1
A12: TOTAL FTE | B12: FTE | C12: =SUM(C5:C11) | D12: =SUM(D5:D11) | E12: =SUM(E5:E11) | F12: =SUM(F5:F11) | G12: =SUM(G5:G11) | H12: =SUM(H5:H11) | I12: =SUM(I5:I11) | J12: =SUM(J5:J11) | ... L12: =SUM(L5:L11)
A13: Model headcount | B13: Assumptions | C13: =Assumptions!C66 | D13: =Assumptions!D66 | E13: =Assumptions!E66 | F13: =Assumptions!F66 | G13: =Assumptions!G66 | H13: =Assumptions!H66 | I13: =Assumptions!I66 | J13: =Assumptions!J66 | ... L13: =Assumptions!L66
A14: CHECK | B14: must be zero | C14: =ROUND(C12-C13,3) | D14: =ROUND(D12-D13,3) | E14: =ROUND(E12-E13,3) | F14: =ROUND(F12-F13,3) | G14: =ROUND(G12-G13,3) | H14: =ROUND(H12-H13,3) | I14: =ROUND(I12-I13,3) | J14: =ROUND(J12-J13,3) | ... L14: =ROUND(L12-L13,3)
A16: COST: ROLE BUILD-UP AGAINST THE MODEL
A17: Employer social security | B17: on gross | C17: 0.32 | D17: 0.32 | E17: 0.32 | F17: 0.32 | G17: 0.32 | H17: 0.32 | I17: 0.32 | J17: 0.32 | K17: 0.32 | L17: 0.32
A18: Founder / CEO: loaded | B18: EUR | C18: =C5*45000*(1+C17) | D18: =D5*45000*(1+D17) | E18: =E5*45000*(1+E17) | F18: =F5*45000*(1+F17) | G18: =G5*45000*(1+G17) | H18: =H5*45000*(1+H17) | I18: =I5*45000*(1+I17) | J18: =J5*45000*(1+J17) | ... L18: =L5*45000*(1+L17)
A19: Engineering: loaded | B19: EUR | C19: =C6*55000*(1+C17) | D19: =D6*55000*(1+D17) | E19: =E6*55000*(1+E17) | F19: =F6*55000*(1+F17) | G19: =G6*55000*(1+G17) | H19: =H6*55000*(1+H17) | I19: =I6*55000*(1+I17) | J19: =J6*55000*(1+J17) | ... L19: =L6*55000*(1+L17)
A20: BD / partnerships: loaded | B20: EUR | C20: =C7*38000*(1+C17) | D20: =D7*38000*(1+D17) | E20: =E7*38000*(1+E17) | F20: =F7*38000*(1+F17) | G20: =G7*38000*(1+G17) | H20: =H7*38000*(1+H17) | I20: =I7*38000*(1+I17) | J20: =J7*38000*(1+J17) | ... L20: =L7*38000*(1+L17)
A21: Athlete success: loaded | B21: EUR | C21: =C8*30000*(1+C17) | D21: =D8*30000*(1+D17) | E21: =E8*30000*(1+E17) | F21: =F8*30000*(1+F17) | G21: =G8*30000*(1+G17) | H21: =H8*30000*(1+H17) | I21: =I8*30000*(1+I17) | J21: =J8*30000*(1+J17) | ... L21: =L8*30000*(1+L17)
A22: Trust & safety / review: loaded | B22: EUR | C22: =C9*34000*(1+C17) | D22: =D9*34000*(1+D17) | E22: =E9*34000*(1+E17) | F22: =F9*34000*(1+F17) | G22: =G9*34000*(1+G17) | H22: =H9*34000*(1+H17) | I22: =I9*34000*(1+I17) | J22: =J9*34000*(1+J17) | ... L22: =L9*34000*(1+L17)
A23: Finance / operations: loaded | B23: EUR | C23: =C10*42000*(1+C17) | D23: =D10*42000*(1+D17) | E23: =E10*42000*(1+E17) | F23: =F10*42000*(1+F17) | G23: =G10*42000*(1+G17) | H23: =H10*42000*(1+H17) | I23: =I10*42000*(1+I17) | J23: =J10*42000*(1+J17) | ... L23: =L10*42000*(1+L17)
A24: Data protection officer: loaded | B24: EUR | C24: =C11*60000*(1+C17) | D24: =D11*60000*(1+D17) | E24: =E11*60000*(1+E17) | F24: =F11*60000*(1+F17) | G24: =G11*60000*(1+G17) | H24: =H11*60000*(1+H17) | I24: =I11*60000*(1+I17) | J24: =J11*60000*(1+J17) | ... L24: =L11*60000*(1+L17)
A25: TOTAL, role build-up | B25: EUR | C25: =SUM(C18:C24) | D25: =SUM(D18:D24) | E25: =SUM(E18:E24) | F25: =SUM(F18:F24) | G25: =SUM(G18:G24) | H25: =SUM(H18:H24) | I25: =SUM(I18:I24) | J25: =SUM(J18:J24) | ... L25: =SUM(L18:L24)
A26: People cost in the model | B26: Costs | C26: =Costs!C17 | D26: =Costs!D17 | E26: =Costs!E17 | F26: =Costs!F17 | G26: =Costs!G17 | H26: =Costs!H17 | I26: =Costs!I17 | J26: =Costs!J17 | ... L26: =Costs!L17
A27: Difference: role mix | B27: build-up less model | C27: =C25-C26 | D27: =D25-D26 | E27: =E25-E26 | F27: =F25-F26 | G27: =G25-G26 | H27: =H25-H26 | I27: =I25-I26 | J27: =J25-J26 | ... L27: =L25-L26
A28: memo: build-up per FTE | B28: EUR | C28: =IF(C12=0,0,C25/C12) | D28: =IF(D12=0,0,D25/D12) | E28: =IF(E12=0,0,E25/E12) | F28: =IF(F12=0,0,F25/F12) | G28: =IF(G12=0,0,G25/G12) | H28: =IF(H12=0,0,H25/H12) | I28: =IF(I12=0,0,I25/I12) | J28: =IF(J12=0,0,J25/J12) | ... L28: =IF(L12=0,0,L25/L12)
A29: memo: model blended per FTE | B29: EUR | C29: =Assumptions!C67 | D29: =Assumptions!D67 | E29: =Assumptions!E67 | F29: =Assumptions!F67 | G29: =Assumptions!G67 | H29: =Assumptions!H67 | I29: =Assumptions!I67 | J29: =Assumptions!J67 | ... L29: =Assumptions!L67
A31: The FTE block reconciles exactly and is the plan. The cost build-up prices those roles at their own salaries; the model prices the same headcount at a blended loaded average that rises from 38k to 76k over the plan, while the build-up holds today's salaries flat. The two cross over at Y4: the build-up is the higher figure in Y1-Y3, where one founder salary dominates a team of two or three, and the model is higher from Y4 as its blended rate climbs. The model is the one that reaches the P&L either way. The memo rows below make the two rates comparable.

Sheet CAC_CLV
A1: Customer acquisition cost and lifetime value
C2: Input: change me | E2: Sourced fact | G2: Formula (this sheet) | I2: Formula (other sheet) | K2: Total
A3: Line | B3: Unit | C3: Y1 | D3: Y2 | E3: Y3 | F3: Y4 | G3: Y5 | H3: Y6 | I3: Y7 | J3: Y8 | K3: Y9 | L3: Y10
A4: ATHLETE: BLENDED ACROSS SEGMENTS
A5: Niche share of athletes | B5: % | C5: =Assumptions!C6 | D5: =Assumptions!D6 | E5: =Assumptions!E6 | F5: =Assumptions!F6 | G5: =Assumptions!G6 | H5: =Assumptions!H6 | I5: =Assumptions!I6 | J5: =Assumptions!J6 | ... L5: =Assumptions!L6
A6: Blended CAC per athlete acquired | B6: spend / gross adds | C6: =IF(Drivers!C40=0,0,(Costs!C18+Costs!C19)/Drivers!C40) | D6: =IF(Drivers!D40=0,0,(Costs!D18+Costs!D19)/Drivers!D40) | E6: =IF(Drivers!E40=0,0,(Costs!E18+Costs!E19)/Drivers!E40) | F6: =IF(Drivers!F40=0,0,(Costs!F18+Costs!F19)/Drivers!F40) | G6: =IF(Drivers!G40=0,0,(Costs!G18+Costs!G19)/Drivers!G40) | H6: =IF(Drivers!H40=0,0,(Costs!H18+Costs!H19)/Drivers!H40) | I6: =IF(Drivers!I40=0,0,(Costs!I18+Costs!I19)/Drivers!I40) | J6: =IF(Drivers!J40=0,0,(Costs!J18+Costs!J19)/Drivers!J40) | ... L6: =IF(Drivers!L40=0,0,(Costs!L18+Costs!L19)/Drivers!L40)
A7: Blended athlete churn | B7: gross-add weighted | C7: =IF(Drivers!C40=0,0,(Drivers!C11*Assumptions!C14+Drivers!C25*Assumptions!C26)/Drivers!C40) | D7: =IF(Drivers!D40=0,0,(Drivers!D11*Assumptions!D14+Drivers!D25*Assumptions!D26)/Drivers!D40) | E7: =IF(Drivers!E40=0,0,(Drivers!E11*Assumptions!E14+Drivers!E25*Assumptions!E26)/Drivers!E40) | F7: =IF(Drivers!F40=0,0,(Drivers!F11*Assumptions!F14+Drivers!F25*Assumptions!F26)/Drivers!F40) | G7: =IF(Drivers!G40=0,0,(Drivers!G11*Assumptions!G14+Drivers!G25*Assumptions!G26)/Drivers!G40) | H7: =IF(Drivers!H40=0,0,(Drivers!H11*Assumptions!H14+Drivers!H25*Assumptions!H26)/Drivers!H40) | I7: =IF(Drivers!I40=0,0,(Drivers!I11*Assumptions!I14+Drivers!I25*Assumptions!I26)/Drivers!I40) | J7: =IF(Drivers!J40=0,0,(Drivers!J11*Assumptions!J14+Drivers!J25*Assumptions!J26)/Drivers!J40) | ... L7: =IF(Drivers!L40=0,0,(Drivers!L11*Assumptions!L14+Drivers!L25*Assumptions!L26)/Drivers!L40)
A8: Expected athlete life | B8: years | C8: =IF(C7=0,0,1/C7) | D8: =IF(D7=0,0,1/D7) | E8: =IF(E7=0,0,1/E7) | F8: =IF(F7=0,0,1/F7) | G8: =IF(G7=0,0,1/G7) | H8: =IF(H7=0,0,1/H7) | I8: =IF(I7=0,0,1/I7) | J8: =IF(J7=0,0,1/J7) | ... L8: =IF(L7=0,0,1/L7)
A9: Net revenue per athlete | B9: EUR/yr | C9: =IF(Drivers!C5=0,0,Revenue!C26/Drivers!C5) | D9: =IF(Drivers!D5=0,0,Revenue!D26/Drivers!D5) | E9: =IF(Drivers!E5=0,0,Revenue!E26/Drivers!E5) | F9: =IF(Drivers!F5=0,0,Revenue!F26/Drivers!F5) | G9: =IF(Drivers!G5=0,0,Revenue!G26/Drivers!G5) | H9: =IF(Drivers!H5=0,0,Revenue!H26/Drivers!H5) | I9: =IF(Drivers!I5=0,0,Revenue!I26/Drivers!I5) | J9: =IF(Drivers!J5=0,0,Revenue!J26/Drivers!J5) | ... L9: =IF(Drivers!L5=0,0,Revenue!L26/Drivers!L5)
A10: Contribution per athlete per year | B10: after COGS | C10: =IF(Revenue!C26=0,0,C9*'P&L'!C6/Revenue!C26) | D10: =IF(Revenue!D26=0,0,D9*'P&L'!D6/Revenue!D26) | E10: =IF(Revenue!E26=0,0,E9*'P&L'!E6/Revenue!E26) | F10: =IF(Revenue!F26=0,0,F9*'P&L'!F6/Revenue!F26) | G10: =IF(Revenue!G26=0,0,G9*'P&L'!G6/Revenue!G26) | H10: =IF(Revenue!H26=0,0,H9*'P&L'!H6/Revenue!H26) | I10: =IF(Revenue!I26=0,0,I9*'P&L'!I6/Revenue!I26) | J10: =IF(Revenue!J26=0,0,J9*'P&L'!J6/Revenue!J26) | ... L10: =IF(Revenue!L26=0,0,L9*'P&L'!L6/Revenue!L26)
A11: ATHLETE LTV | B11: EUR | C11: =C10*C8 | D11: =D10*D8 | E11: =E10*E8 | F11: =F10*F8 | G11: =G10*G8 | H11: =H10*H8 | I11: =I10*I8 | J11: =J10*J8 | ... L11: =L10*L8
A12: LTV / CAC | B12: x | C12: =IF(C6=0,0,C11/C6) | D12: =IF(D6=0,0,D11/D6) | E12: =IF(E6=0,0,E11/E6) | F12: =IF(F6=0,0,F11/F6) | G12: =IF(G6=0,0,G11/G6) | H12: =IF(H6=0,0,H11/H6) | I12: =IF(I6=0,0,I11/I6) | J12: =IF(J6=0,0,J11/J6) | ... L12: =IF(L6=0,0,L11/L6)
A13: CAC payback | B13: months | C13: =IF(C10<=0,0,12*C6/C10) | D13: =IF(D10<=0,0,12*D6/D10) | E13: =IF(E10<=0,0,12*E6/E10) | F13: =IF(F10<=0,0,12*F6/F10) | G13: =IF(G10<=0,0,12*G6/G10) | H13: =IF(H10<=0,0,12*H6/H10) | I13: =IF(I10<=0,0,12*I6/I10) | J13: =IF(J10<=0,0,12*J6/J10) | ... L13: =IF(L10<=0,0,12*L6/L10)
A15: The athlete LTV/CAC ratio is unusually high, and that is the thesis rather than an error: acquisition is cheap precisely because there is no incumbent agent to outbid in these sports. It should be read alongside the fan LTV below, which is small: the economics work on volume of athletes, not on the value of any one of them.
A18: FAN: NICHE SUBSCRIPTION ONLY | D18: excludes PPV and tips, which the revenue model carries separately
A19: Fan ARPU, VAT inclusive | B19: EUR/mo | C19: =Assumptions!C12 | D19: =Assumptions!D12 | E19: =Assumptions!E12 | F19: =Assumptions!F12 | G19: =Assumptions!G12 | H19: =Assumptions!H12 | I19: =Assumptions!I12 | J19: =Assumptions!J12 | ... L19: =Assumptions!L12
A20: Net of VAT | B20: EUR/mo | C20: =C19/(1+Assumptions!C48) | D20: =D19/(1+Assumptions!D48) | E20: =E19/(1+Assumptions!E48) | F20: =F19/(1+Assumptions!F48) | G20: =G19/(1+Assumptions!G48) | H20: =H19/(1+Assumptions!H48) | I20: =I19/(1+Assumptions!I48) | J20: =J19/(1+Assumptions!J48) | ... L20: =L19/(1+Assumptions!L48)
A21: Our take | B21: EUR/mo | C21: =C20*Assumptions!C40 | D21: =D20*Assumptions!D40 | E21: =E20*Assumptions!E40 | F21: =F20*Assumptions!F40 | G21: =G20*Assumptions!G40 | H21: =H20*Assumptions!H40 | I21: =I20*Assumptions!I40 | J21: =J20*Assumptions!J40 | ... L21: =L20*Assumptions!L40
A22: Payment cost on the charge | B22: EUR/mo | C22: =C19*Assumptions!C50+Assumptions!C51 | D22: =D19*Assumptions!D50+Assumptions!D51 | E22: =E19*Assumptions!E50+Assumptions!E51 | F22: =F19*Assumptions!F50+Assumptions!F51 | G22: =G19*Assumptions!G50+Assumptions!G51 | H22: =H19*Assumptions!H50+Assumptions!H51 | I22: =I19*Assumptions!I50+Assumptions!I51 | J22: =J19*Assumptions!J50+Assumptions!J51 | ... L22: =L19*Assumptions!L50+Assumptions!L51
A23: Payout cost, share per fan month | B23: EUR | C23: =C19*Assumptions!C52+Assumptions!C53/30 | D23: =D19*Assumptions!D52+Assumptions!D53/30 | E23: =E19*Assumptions!E52+Assumptions!E53/30 | F23: =F19*Assumptions!F52+Assumptions!F53/30 | G23: =G19*Assumptions!G52+Assumptions!G53/30 | H23: =H19*Assumptions!H52+Assumptions!H53/30 | I23: =I19*Assumptions!I52+Assumptions!I53/30 | J23: =J19*Assumptions!J52+Assumptions!J53/30 | ... L23: =L19*Assumptions!L52+Assumptions!L53/30
A24: Contribution per fan month | B24: EUR | C24: =C21-C22-C23 | D24: =D21-D22-D23 | E24: =E21-E22-E23 | F24: =F21-F22-F23 | G24: =G21-G22-G23 | H24: =H21-H22-H23 | I24: =I21-I22-I23 | J24: =J21-J22-J23 | ... L24: =L21-L22-L23
A25: Fan churn | B25: per month | C25: =Assumptions!C13 | D25: =Assumptions!D13 | E25: =Assumptions!E13 | F25: =Assumptions!F13 | G25: =Assumptions!G13 | H25: =Assumptions!H13 | I25: =Assumptions!I13 | J25: =Assumptions!J13 | ... L25: =Assumptions!L13
A26: Expected fan life | B26: months | C26: =IF(C25=0,0,1/C25) | D26: =IF(D25=0,0,1/D25) | E26: =IF(E25=0,0,1/E25) | F26: =IF(F25=0,0,1/F25) | G26: =IF(G25=0,0,1/G25) | H26: =IF(H25=0,0,1/H25) | I26: =IF(I25=0,0,1/I25) | J26: =IF(J25=0,0,1/J25) | ... L26: =IF(L25=0,0,1/L25)
A27: FAN LTV | B27: EUR | C27: =C24*C26 | D27: =D24*D26 | E27: =E24*E26 | F27: =F24*F26 | G27: =G24*G26 | H27: =H24*H26 | I27: =I24*I26 | J27: =J24*J26 | ... L27: =L24*L26
A28: Fan CAC | B28: EUR | C28: 0 | D28: 0 | E28: 0 | F28: 0 | G28: 0 | H28: 0 | I28: 0 | J28: 0 | K28: 0 | L28: 0
A30: Fan CAC is zero by construction: athletes bring their own audiences and the model spends nothing acquiring fans. That understates the risk rather than flattering the return, and the plan discloses it as such.
A32: SPONSOR
A33: Sponsor CAC | B33: EUR | C33: =Assumptions!C37 | D33: =Assumptions!D37 | E33: =Assumptions!E37 | F33: =Assumptions!F37 | G33: =Assumptions!G37 | H33: =Assumptions!H37 | I33: =Assumptions!I37 | J33: =Assumptions!J37 | ... L33: =Assumptions!L37
A34: SaaS per paying sponsor | B34: EUR/yr | C34: =Assumptions!C36*12 | D34: =Assumptions!D36*12 | E34: =Assumptions!E36*12 | F34: =Assumptions!F36*12 | G34: =Assumptions!G36*12 | H34: =Assumptions!H36*12 | I34: =Assumptions!I36*12 | J34: =Assumptions!J36*12 | ... L34: =Assumptions!L36*12
A35: Sponsorship take per paying sponsor | B35: EUR/yr | C35: =IF(Drivers!C48=0,0,Revenue!C24/Drivers!C48) | D35: =IF(Drivers!D48=0,0,Revenue!D24/Drivers!D48) | E35: =IF(Drivers!E48=0,0,Revenue!E24/Drivers!E48) | F35: =IF(Drivers!F48=0,0,Revenue!F24/Drivers!F48) | G35: =IF(Drivers!G48=0,0,Revenue!G24/Drivers!G48) | H35: =IF(Drivers!H48=0,0,Revenue!H24/Drivers!H48) | I35: =IF(Drivers!I48=0,0,Revenue!I24/Drivers!I48) | J35: =IF(Drivers!J48=0,0,Revenue!J24/Drivers!J48) | ... L35: =IF(Drivers!L48=0,0,Revenue!L24/Drivers!L48)
A36: Contribution per sponsor per year | B36: EUR | C36: =C34+C35 | D36: =D34+D35 | E36: =E34+E35 | F36: =F34+F35 | G36: =G34+G35 | H36: =H34+H35 | I36: =I34+I35 | J36: =J34+J35 | ... L36: =L34+L35
A37: at gross margin | B37: EUR | C37: =C36*'P&L'!C7 | D37: =D36*'P&L'!D7 | E37: =E36*'P&L'!E7 | F37: =F36*'P&L'!F7 | G37: =G36*'P&L'!G7 | H37: =H36*'P&L'!H7 | I37: =I36*'P&L'!I7 | J37: =J36*'P&L'!J7 | ... L37: =L36*'P&L'!L7
A38: CAC payback | B38: months | C38: =IF(C37<=0,0,12*C33/C37) | D38: =IF(D37<=0,0,12*D33/D37) | E38: =IF(E37<=0,0,12*E33/E37) | F38: =IF(F37<=0,0,12*F33/F37) | G38: =IF(G37<=0,0,12*G33/G37) | H38: =IF(H37<=0,0,12*H33/H37) | I38: =IF(I37<=0,0,12*I33/I37) | J38: =IF(J37<=0,0,12*J33/J37) | ... L38: =IF(L37<=0,0,12*L33/L37)
A40: No sponsor LTV is shown. It needs a sponsor retention assumption the model does not make, and inventing one here would create a figure nothing else in the plan validates. Payback needs no such assumption, so payback is what is reported.

Sheet KPIs
A1: KPIs: the dozen numbers that describe the business
C2: Input: change me | E2: Sourced fact | G2: Formula (this sheet) | I2: Formula (other sheet) | K2: Total
A3: Line | B3: Unit | C3: Y1 | D3: Y2 | E3: Y3 | F3: Y4 | G3: Y5 | H3: Y6 | I3: Y7 | J3: Y8 | K3: Y9 | L3: Y10
A4: SCALE
A5: Active athletes | B5: count | C5: =Drivers!C5 | D5: =Drivers!D5 | E5: =Drivers!E5 | F5: =Drivers!F5 | G5: =Drivers!G5 | H5: =Drivers!H5 | I5: =Drivers!I5 | J5: =Drivers!J5 | ... L5: =Drivers!L5
A6: Paying fans, year end | B6: count | C6: =Drivers!C38 | D6: =Drivers!D38 | E6: =Drivers!E38 | F6: =Drivers!F38 | G6: =Drivers!G38 | H6: =Drivers!H38 | I6: =Drivers!I38 | J6: =Drivers!J38 | ... L6: =Drivers!L38
A7: Paying sponsors | B7: count | C7: =Drivers!C48 | D7: =Drivers!D48 | E7: =Drivers!E48 | F7: =Drivers!F48 | G7: =Drivers!G48 | H7: =Drivers!H48 | I7: =Drivers!I48 | J7: =Drivers!J48 | ... L7: =Drivers!L48
A8: Recurring MRR | B8: subs x take + SaaS / 12 | C8: =(Revenue!C7*Assumptions!C40+Revenue!C25)/12 | D8: =(Revenue!D7*Assumptions!D40+Revenue!D25)/12 | E8: =(Revenue!E7*Assumptions!E40+Revenue!E25)/12 | F8: =(Revenue!F7*Assumptions!F40+Revenue!F25)/12 | G8: =(Revenue!G7*Assumptions!G40+Revenue!G25)/12 | H8: =(Revenue!H7*Assumptions!H40+Revenue!H25)/12 | I8: =(Revenue!I7*Assumptions!I40+Revenue!I25)/12 | J8: =(Revenue!J7*Assumptions!J40+Revenue!J25)/12 | ... L8: =(Revenue!L7*Assumptions!L40+Revenue!L25)/12
A10: QUALITY OF REVENUE
A11: Net revenue | B11: EUR | C11: =Revenue!C26 | D11: =Revenue!D26 | E11: =Revenue!E26 | F11: =Revenue!F26 | G11: =Revenue!G26 | H11: =Revenue!H26 | I11: =Revenue!I26 | J11: =Revenue!J26 | ... L11: =Revenue!L26
A12: Gross margin | B12: % | C12: ='P&L'!C7 | D12: ='P&L'!D7 | E12: ='P&L'!E7 | F12: ='P&L'!F7 | G12: ='P&L'!G7 | H12: ='P&L'!H7 | I12: ='P&L'!I7 | J12: ='P&L'!J7 | ... L12: ='P&L'!L7
A13: EBITDA margin | B13: % | C13: ='P&L'!C11 | D13: ='P&L'!D11 | E13: ='P&L'!E11 | F13: ='P&L'!F11 | G13: ='P&L'!G11 | H13: ='P&L'!H11 | I13: ='P&L'!I11 | J13: ='P&L'!J11 | ... L13: ='P&L'!L11
A14: Revenue per FTE | B14: EUR | C14: =IF(Assumptions!C66=0,0,Revenue!C26/Assumptions!C66) | D14: =IF(Assumptions!D66=0,0,Revenue!D26/Assumptions!D66) | E14: =IF(Assumptions!E66=0,0,Revenue!E26/Assumptions!E66) | F14: =IF(Assumptions!F66=0,0,Revenue!F26/Assumptions!F66) | G14: =IF(Assumptions!G66=0,0,Revenue!G26/Assumptions!G66) | H14: =IF(Assumptions!H66=0,0,Revenue!H26/Assumptions!H66) | I14: =IF(Assumptions!I66=0,0,Revenue!I26/Assumptions!I66) | J14: =IF(Assumptions!J66=0,0,Revenue!J26/Assumptions!J66) | ... L14: =IF(Assumptions!L66=0,0,Revenue!L26/Assumptions!L66)
A16: RETENTION AND EFFICIENCY
A17: Fan churn, niche | B17: per month | C17: =Assumptions!C13 | D17: =Assumptions!D13 | E17: =Assumptions!E13 | F17: =Assumptions!F13 | G17: =Assumptions!G13 | H17: =Assumptions!H13 | I17: =Assumptions!I13 | J17: =Assumptions!J13 | ... L17: =Assumptions!L13
A18: Athlete churn, niche | B18: per year | C18: =Assumptions!C14 | D18: =Assumptions!D14 | E18: =Assumptions!E14 | F18: =Assumptions!F14 | G18: =Assumptions!G14 | H18: =Assumptions!H14 | I18: =Assumptions!I14 | J18: =Assumptions!J14 | ... L18: =Assumptions!L14
A19: Athlete LTV / CAC | B19: x | C19: =CAC_CLV!C12 | D19: =CAC_CLV!D12 | E19: =CAC_CLV!E12 | F19: =CAC_CLV!F12 | G19: =CAC_CLV!G12 | H19: =CAC_CLV!H12 | I19: =CAC_CLV!I12 | J19: =CAC_CLV!J12 | ... L19: =CAC_CLV!L12
A20: Take rate on GMV | B20: % | C20: =Revenue!C28 | D20: =Revenue!D28 | E20: =Revenue!E28 | F20: =Revenue!F28 | G20: =Revenue!G28 | H20: =Revenue!H28 | I20: =Revenue!I28 | J20: =Revenue!J28 | ... L20: =Revenue!L28

Sheet Check
A1: Check: Excel's own answers against the Python model
A2: Each pair is the Python model's figure and the workbook's own calculation. VARIANCE must be zero: if a formula is wrong, it shows up here on open. | C2: Input: change me | E2: Sourced fact | G2: Formula (this sheet) | I2: Formula (other sheet) | K2: Total
A3: Line | B3: Unit | C3: Y1 | D3: Y2 | E3: Y3 | F3: Y4 | G3: Y5 | H3: Y6 | I3: Y7 | J3: Y8 | K3: Y9 | L3: Y10
A4: NET REVENUE
A5: Python model | B5: model.py | C5: 24669.763 | D5: 133178.29 | E5: 525298.32 | F5: 1461114.4 | G5: 3293651.9 | H5: 6223273.2 | I5: 10161584 | J5: 14573482 | K5: 18838964 | L5: 23911468
A6: This workbook | B6: recalculated | C6: =Revenue!C26 | D6: =Revenue!D26 | E6: =Revenue!E26 | F6: =Revenue!F26 | G6: =Revenue!G26 | H6: =Revenue!H26 | I6: =Revenue!I26 | J6: =Revenue!J26 | ... L6: =Revenue!L26
A7: VARIANCE | B7: must be 0 | C7: =ROUND(C6-C5,0) | D7: =ROUND(D6-D5,0) | E7: =ROUND(E6-E5,0) | F7: =ROUND(F6-F5,0) | G7: =ROUND(G6-G5,0) | H7: =ROUND(H6-H5,0) | I7: =ROUND(I6-I5,0) | J7: =ROUND(J6-J5,0) | ... L7: =ROUND(L6-L5,0)
A9: COST OF SALES
A10: Python model | B10: model.py | C10: 13341.248 | D10: 57150.571 | E10: 191124.2 | F10: 503136.22 | G10: 1098498 | H10: 2007712 | I10: 3213123 | J10: 4546711.1 | K10: 5865676 | L10: 7377275.6
A11: This workbook | B11: recalculated | C11: =Costs!C14 | D11: =Costs!D14 | E11: =Costs!E14 | F11: =Costs!F14 | G11: =Costs!G14 | H11: =Costs!H14 | I11: =Costs!I14 | J11: =Costs!J14 | ... L11: =Costs!L14
A12: VARIANCE | B12: must be 0 | C12: =ROUND(C11-C10,0) | D12: =ROUND(D11-D10,0) | E12: =ROUND(E11-E10,0) | F12: =ROUND(F11-F10,0) | G12: =ROUND(G11-G10,0) | H12: =ROUND(H11-H10,0) | I12: =ROUND(I11-I10,0) | J12: =ROUND(J11-J10,0) | ... L12: =ROUND(L11-L10,0)
A14: GROSS PROFIT
A15: Python model | B15: model.py | C15: 11328.516 | D15: 76027.717 | E15: 334174.13 | F15: 957978.22 | G15: 2195153.8 | H15: 4215561.2 | I15: 6948460.6 | J15: 10026771 | K15: 12973288 | L15: 16534192
A16: This workbook | B16: recalculated | C16: ='P&L'!C6 | D16: ='P&L'!D6 | E16: ='P&L'!E6 | F16: ='P&L'!F6 | G16: ='P&L'!G6 | H16: ='P&L'!H6 | I16: ='P&L'!I6 | J16: ='P&L'!J6 | ... L16: ='P&L'!L6
A17: VARIANCE | B17: must be 0 | C17: =ROUND(C16-C15,0) | D17: =ROUND(D16-D15,0) | E17: =ROUND(E16-E15,0) | F17: =ROUND(F16-F15,0) | G17: =ROUND(G16-G15,0) | H17: =ROUND(H16-H15,0) | I17: =ROUND(I16-I15,0) | J17: =ROUND(J16-J15,0) | ... L17: =ROUND(L16-L15,0)
A19: OPERATING COSTS
A20: Python model | B20: model.py | C20: 106353.58 | D20: 246573.46 | E20: 571042.43 | F20: 1170801.2 | G20: 2038784.1 | H20: 3055988.8 | I20: 4326886.7 | J20: 5336742.6 | K20: 6074427.2 | L20: 7093002.2
A21: This workbook | B21: recalculated | C21: =Costs!C25 | D21: =Costs!D25 | E21: =Costs!E25 | F21: =Costs!F25 | G21: =Costs!G25 | H21: =Costs!H25 | I21: =Costs!I25 | J21: =Costs!J25 | ... L21: =Costs!L25
A22: VARIANCE | B22: must be 0 | C22: =ROUND(C21-C20,0) | D22: =ROUND(D21-D20,0) | E22: =ROUND(E21-E20,0) | F22: =ROUND(F21-F20,0) | G22: =ROUND(G21-G20,0) | H22: =ROUND(H21-H20,0) | I22: =ROUND(I21-I20,0) | J22: =ROUND(J21-J20,0) | ... L22: =ROUND(L21-L20,0)
A24: EBITDA
A25: Python model | B25: model.py | C25: -95025.065 | D25: -170545.75 | E25: -236868.3 | F25: -212822.94 | G25: 156369.67 | H25: 1159572.5 | I25: 2621573.9 | J25: 4690028.5 | K25: 6898861.3 | L25: 9441189.9
A26: This workbook | B26: recalculated | C26: ='P&L'!C10 | D26: ='P&L'!D10 | E26: ='P&L'!E10 | F26: ='P&L'!F10 | G26: ='P&L'!G10 | H26: ='P&L'!H10 | I26: ='P&L'!I10 | J26: ='P&L'!J10 | ... L26: ='P&L'!L10
A27: VARIANCE | B27: must be 0 | C27: =ROUND(C26-C25,0) | D27: =ROUND(D26-D25,0) | E27: =ROUND(E26-E25,0) | F27: =ROUND(F26-F25,0) | G27: =ROUND(G26-G25,0) | H27: =ROUND(H26-H25,0) | I27: =ROUND(I26-I25,0) | J27: =ROUND(J26-J25,0) | ... L27: =ROUND(L26-L25,0)
A29: PAYING FANS (YEAR END)
A30: Python model | B30: model.py | C30: 2057.8417 | D30: 8148.2349 | E30: 25287.702 | F30: 60196.83 | G30: 120075.74 | H30: 206657.95 | I30: 321288 | J30: 434075.6 | K30: 553628.8 | L30: 665896
A31: This workbook | B31: recalculated | C31: =Drivers!C38 | D31: =Drivers!D38 | E31: =Drivers!E38 | F31: =Drivers!F38 | G31: =Drivers!G38 | H31: =Drivers!H38 | I31: =Drivers!I38 | J31: =Drivers!J38 | ... L31: =Drivers!L38
A32: VARIANCE | B32: must be 0 | C32: =ROUND(C31-C30,0) | D32: =ROUND(D31-D30,0) | E32: =ROUND(E31-E30,0) | F32: =ROUND(F31-F30,0) | G32: =ROUND(G31-G30,0) | H32: =ROUND(H31-H30,0) | I32: =ROUND(I31-I30,0) | J32: =ROUND(J31-J30,0) | ... L32: =ROUND(L31-L30,0)
A34: AVERAGE PAYING FANS
A35: Python model | B35: model.py | C35: 1305.6164 | D35: 5897.1224 | E35: 18938.524 | F35: 47228.174 | G35: 97836.517 | H35: 174457.64 | I35: 277910.99 | J35: 391108.48 | K35: 507748.25 | L35: 622730.67
A36: This workbook | B36: recalculated | C36: =Drivers!C39 | D36: =Drivers!D39 | E36: =Drivers!E39 | F36: =Drivers!F39 | G36: =Drivers!G39 | H36: =Drivers!H39 | I36: =Drivers!I39 | J36: =Drivers!J39 | ... L36: =Drivers!L39
A37: VARIANCE | B37: must be 0 | C37: =ROUND(C36-C35,0) | D37: =ROUND(D36-D35,0) | E37: =ROUND(E36-E35,0) | F37: =ROUND(F36-F35,0) | G37: =ROUND(G36-G35,0) | H37: =ROUND(H36-H35,0) | I37: =ROUND(I36-I35,0) | J37: =ROUND(J36-J35,0) | ... L37: =ROUND(L36-L35,0)
A39: TOTAL GMV
A40: Python model | B40: model.py | C40: 166159.57 | D40: 809909.72 | E40: 3053787.5 | F40: 9029784.5 | G40: 21701556 | H40: 43115734 | I40: 71777410 | J40: 1.0439324e+08 | K40: 1.3555553e+08 | L40: 1.7590483e+08
A41: This workbook | B41: recalculated | C41: =Revenue!C20 | D41: =Revenue!D20 | E41: =Revenue!E20 | F41: =Revenue!F20 | G41: =Revenue!G20 | H41: =Revenue!H20 | I41: =Revenue!I20 | J41: =Revenue!J20 | ... L41: =Revenue!L20
A42: VARIANCE | B42: must be 0 | C42: =ROUND(C41-C40,0) | D42: =ROUND(D41-D40,0) | E42: =ROUND(E41-E40,0) | F42: =ROUND(F41-F40,0) | G42: =ROUND(G41-G40,0) | H42: =ROUND(H41-H40,0) | I42: =ROUND(I41-I40,0) | J42: =ROUND(J41-J40,0) | ... L42: =ROUND(L41-L40,0)
A44: DEALS
A45: Python model | B45: model.py | C45: 24.54 | D45: 117.216 | E45: 484.8 | F45: 1548.72 | G45: 3767.19 | H45: 7376 | I45: 11563.2 | J45: 16257.92 | K45: 19895.44 | L45: 25539.2
A46: This workbook | B46: recalculated | C46: =Drivers!C46 | D46: =Drivers!D46 | E46: =Drivers!E46 | F46: =Drivers!F46 | G46: =Drivers!G46 | H46: =Drivers!H46 | I46: =Drivers!I46 | J46: =Drivers!J46 | ... L46: =Drivers!L46
A47: VARIANCE | B47: must be 0 | C47: =ROUND(C46-C45,0) | D47: =ROUND(D46-D45,0) | E47: =ROUND(E46-E45,0) | F47: =ROUND(F46-F45,0) | G47: =ROUND(G46-G45,0) | H47: =ROUND(H46-H45,0) | I47: =ROUND(I46-I45,0) | J47: =ROUND(J46-J45,0) | ... L47: =ROUND(L46-L45,0)
A49: APPLICATIONS REQUIRED
A50: Python model | B50: model.py | C50: 2000 | D50: 4040 | E50: 8375.04 | F50: 13666.667 | G50: 20336.842 | H50: 26004.746 | I50: 30163.934 | J50: 32980.645 | K50: 35803.175 | L50: 38515.906
A51: This workbook | B51: recalculated | C51: =Drivers!C54 | D51: =Drivers!D54 | E51: =Drivers!E54 | F51: =Drivers!F54 | G51: =Drivers!G54 | H51: =Drivers!H54 | I51: =Drivers!I54 | J51: =Drivers!J54 | ... L51: =Drivers!L54
A52: VARIANCE | B52: must be 0 | C52: =ROUND(C51-C50,0) | D52: =ROUND(D51-D50,0) | E52: =ROUND(E51-E50,0) | F52: =ROUND(F51-F50,0) | G52: =ROUND(G51-G50,0) | H52: =ROUND(H51-H50,0) | I52: =ROUND(I51-I50,0) | J52: =ROUND(J51-J50,0) | ... L52: =ROUND(L51-L50,0)
A54: ATHLETE VERIFICATION
A55: Python model | B55: model.py | C55: 745.09804 | D55: 2001.9388 | E55: 4650.6104 | F55: 7902.8706 | G55: 11906.384 | H55: 15491.894 | I55: 18266.332 | J55: 20412.303 | K55: 22629.291 | L55: 24921.452
A56: This workbook | B56: recalculated | C56: =Costs!C13 | D56: =Costs!D13 | E56: =Costs!E13 | F56: =Costs!F13 | G56: =Costs!G13 | H56: =Costs!H13 | I56: =Costs!I13 | J56: =Costs!J13 | ... L56: =Costs!L13
A57: VARIANCE | B57: must be 0 | C57: =ROUND(C56-C55,0) | D57: =ROUND(D56-D55,0) | E57: =ROUND(E56-E55,0) | F57: =ROUND(F56-F55,0) | G57: =ROUND(G56-G55,0) | H57: =ROUND(H56-H55,0) | I57: =ROUND(I56-I55,0) | J57: =ROUND(J56-J55,0) | ... L57: =ROUND(L56-L55,0)
A59: TAX CHARGE
A60: Python model | B60: model.py | C60: 0 | D60: 0 | E60: 0 | F60: 0 | G60: 0 | H60: 21027.017 | I60: 344936.08 | J60: 634864.28 | K60: 944859.19 | L60: 2176647.5
A61: This workbook | B61: recalculated | C61: =-'P&L'!C20 | D61: =-'P&L'!D20 | E61: =-'P&L'!E20 | F61: =-'P&L'!F20 | G61: =-'P&L'!G20 | H61: =-'P&L'!H20 | I61: =-'P&L'!I20 | J61: =-'P&L'!J20 | ... L61: =-'P&L'!L20
A62: VARIANCE | B62: must be 0 | C62: =ROUND(C61-C60,0) | D62: =ROUND(D61-D60,0) | E62: =ROUND(E61-E60,0) | F62: =ROUND(F61-F60,0) | G62: =ROUND(G61-G60,0) | H62: =ROUND(H61-H60,0) | I62: =ROUND(I61-I60,0) | J62: =ROUND(J61-J60,0) | ... L62: =ROUND(L61-L60,0)
A64: NET PROFIT
A65: Python model | B65: model.py | C65: -100725.07 | D65: -186645.75 | E65: -273968.3 | F65: -282622.94 | G65: 30969.673 | H65: 932145.47 | I65: 1954637.8 | J65: 3597564.2 | K65: 5354202.1 | L65: 6529942.4
A66: This workbook | B66: recalculated | C66: ='P&L'!C21 | D66: ='P&L'!D21 | E66: ='P&L'!E21 | F66: ='P&L'!F21 | G66: ='P&L'!G21 | H66: ='P&L'!H21 | I66: ='P&L'!I21 | J66: ='P&L'!J21 | ... L66: ='P&L'!L21
A67: VARIANCE | B67: must be 0 | C67: =ROUND(C66-C65,0) | D67: =ROUND(D66-D65,0) | E67: =ROUND(E66-E65,0) | F67: =ROUND(F66-F65,0) | G67: =ROUND(G66-G65,0) | H67: =ROUND(H66-H65,0) | I67: =ROUND(I66-I65,0) | J67: =ROUND(J66-J65,0) | ... L67: =ROUND(L66-L65,0)
A69: FREE CASH FLOW
A70: Python model | B70: model.py | C70: -95817.276 | D70: -163256.1 | E70: -188798.95 | F70: -60058.23 | G70: 484377.44 | H70: 1673919.6 | I70: 2936196.9 | J70: 4692204.5 | K70: 6419322.4 | L70: 7900590.2
A71: This workbook | B71: recalculated | C71: =CashFlow!C9 | D71: =CashFlow!D9 | E71: =CashFlow!E9 | F71: =CashFlow!F9 | G71: =CashFlow!G9 | H71: =CashFlow!H9 | I71: =CashFlow!I9 | J71: =CashFlow!J9 | ... L71: =CashFlow!L9
A72: VARIANCE | B72: must be 0 | C72: =ROUND(C71-C70,0) | D72: =ROUND(D71-D70,0) | E72: =ROUND(E71-E70,0) | F72: =ROUND(F71-F70,0) | G72: =ROUND(G71-G70,0) | H72: =ROUND(H71-H70,0) | I72: =ROUND(I71-I70,0) | J72: =ROUND(J71-J70,0) | ... L72: =ROUND(L71-L70,0)
A74: Balance sheet check (from BalanceSheet, must be zero):
A75: Assets less liabilities and equity | B75: must be 0 | C75: =BalanceSheet!C20 | D75: =BalanceSheet!D20 | E75: =BalanceSheet!E20 | F75: =BalanceSheet!F20 | G75: =BalanceSheet!G20 | H75: =BalanceSheet!H20 | I75: =BalanceSheet!I20 | J75: =BalanceSheet!J20 | ... L75: =BalanceSheet!L20

Sheet Comparables
A1: Comparables - published facts about the platforms we are modelled on
A2: Nothing on this sheet is our estimate. Every figure is published and cited, so it can be refreshed independently of anything we concluded from it. MarketModel derives our assumptions from these numbers; Assumptions then uses what MarketModel produces.
A4: Metric | B4: Value | C4: Unit | D4: Platform | E4: Period | F4: Source
A5: Gross payments (GMV) | B5: 7220000000 | C5: USD | D5: OnlyFans | E5: FY2024 | F5: Fenix International Ltd filed accounts (Companies House 10354575)
A6: Net revenue | B6: 1410000000 | C6: USD | D6: OnlyFans | E6: FY2024 | F6: Fenix International Ltd filed accounts (Companies House 10354575)
A7: Paid to creators | B7: 5800000000 | C7: USD | D7: OnlyFans | E7: FY2024 | F7: Fenix International Ltd filed accounts, 80.3% of gross
A8: Creator accounts | B8: 4634000 | C8: count | D8: OnlyFans | E8: FY2024 | F8: Variety: +13% YoY
A9: Fan accounts | B9: 377500000 | C9: count | D9: OnlyFans | E9: FY2024 | F9: Variety: +24% YoY
A10: Reported average creator earnings | B10: 131 | C10: USD/month | D10: OnlyFans | E10: FY2024 | F10: Sci-Tech Today / ElectroIQ: after platform fees
A11: Revenue concentration | B11: 0.76 | C11: share to top 0.1% | D11: OnlyFans | E11: 2025 | F11: ElectroIQ: power-law distribution
A12: Creators with >=1 paying member | B12: 286287 | C12: count | D12: Patreon | E12: Feb 2026 | F12: Graphtreon
A13: Active creators | B13: 300000 | C13: count | D13: Patreon | E13: 2025 | F13: Jack Conte, Patreon
A14: Active paying members | B14: 10000000 | C14: count | D14: Patreon | E14: 2026 | F14: Patreon / Backlinko
A15: Paid to creators annually | B15: 2000000000 | C15: USD/year | D15: Patreon | E15: 2026 | F15: Patreon / Backlinko
A16: Average monthly support per member | B16: 6.1 | C16: USD/month | D16: Patreon | E16: Aug 2024 | F16: Patreon 2024 Transparency Report; audit of ~1,200 creators
... A25: Claimed speed-to-market gain | B25: 0.6 | C25: share faster | D25: TEKTA | E25: Aug 2026 | F25: Publicis: stated 50-70% vs a traditional agency process
A27: TAKE RATES - what each platform costs a creator
A28: Platform | B28: Headline take | C28: Per txn (USD) | D28: Monthly fee (USD) | F28: Source
A29: OnlyFans | B29: 0.2 | C29: 0 | D29: 0 | F29: Derived: 1.41bn / 7.22bn = 19.5% (filed accounts)
A30: Fansly | B30: 0.2 | C30: 0 | D30: 0 | F30: Not published in terms; widely reported
A31: Fanfix | B31: 0.2 | C31: 0 | D31: 0 | F31: Not published in terms; widely reported
A32: Patreon | B32: 0.1 | C32: 0 | D32: 0 | F32: Published: 10% all-in, processing included
A33: Passes | B33: 0.1 | C33: 0.3 | D33: 29 | F33: Sacra; Passes rebrand release Apr 2026
A34: Stride (proposed) | B34: 0.15 | C34: 0 | D34: 0 | F34: Our decision, see MarketModel
A36: INTERMEDIARIES the athlete already pays
A37: Sports agent: endorsement | B37: 0.1 | C37: 0.2 | F37: Unregulated; widely reported, no primary source
A38: Sports agent: playing contract | B38: 0.02 | C38: 0.05 | F38: NBPA reg. 4.B (Sept 2025); FIFA FFAR art. 15
A39: OnlyFans management agency | B39: 0.2 | C39: 0.5 | F39: Aruna Talent rate guide 2026, on top of the 20%
A42: SOURCES
A43: OnlyFans FY2024 filed accounts (Fenix International Ltd) | B43: https://find-and-update.company-information.service.gov.uk/company/10354575/filing-history
A44: OnlyFans FY2024 as reported | B44: https://variety.com/2025/digital/news/onlyfans-fiscal-2024-revenue-earnings-1236495750/
A45: Patreon published take rate | B45: https://www.patreon.com/pricing
A46: Patreon creators | B46: https://backlinko.com/patreon-users
A47: Passes economics | B47: https://sacra.com/c/passes/
A48: Fanfix creator terms (states no take rate) | B48: https://auth.fanfix.io/creator-terms-of-use
A49: Agency commissions | B49: https://arunatalent.com/blog/onlyfans-agency-commission-rates/
A50: NBPA agent fee cap (amended Sept 2025) | B50: https://imgix.cosmicjs.com/cd844850-97c7-11f0-91fa-d9e1671c2776-NBPA-REGULATIONS-GOVERNING-PLAYER-AGENTS-09-2025.pdf
A51: FIFA Football Agent Regulations art. 15 | B51: https://digitalhub.fifa.com/m/1e7b741fa0fae779/original/FIFA-Football-Agent-Regulations.pdf
A52: CJEU upholds the FIFA fee cap (16 Jul 2026) | B52: https://inside.fifa.com/news/welcomes-court-of-justice-european-union-decision-football-agent-regulations
A53: Eurobarometer 525 | B53: https://europa.eu/eurobarometer/surveys/detail/2668
A54: FIP World Padel Report 2025 | B54: https://www.padelfip.com/2025/12/online-the-fip-world-padel-report-2025-a-comprehensive-analysis-of-a-sport-in-constant-growth/
... A57: Stripe Connect age | B57: https://support.stripe.com/questions/age-requirement-to-create-a-stripe-account

Sheet MarketModel
A1: Market Model - how the comparables become our assumptions
A2: Each block starts from a published figure on Comparables and ends in a number the Assumptions sheet uses. Adjustment factors are blue because they are our judgement; everything else is a formula you can trace.
C3: Input: change me | E3: Sourced fact | G3: Formula (this sheet) | I3: Formula (other sheet) | K3: Total
A5: 1. PAYING FANS PER MONETISING ATHLETE -> Assumptions
A6: Patreon active paying members | B6: =Comparables!B14 | D6: Published
A7: Patreon creators with >=1 paying member | B7: =Comparables!B12 | D7: Published
A8: Members per paying creator | B8: =B6/B7 | D8: The single most useful benchmark we found: it is measured, not modelled.
A9: OnlyFans fan accounts per creator | B9: =Comparables!B9/Comparables!B8 | D9: Fan ACCOUNTS, not paying fans - most follow free. Shown as an upper bound only.
A10: Niche adjustment | B10: 1.06 | D10: OUR JUDGEMENT: +6% on the Patreon benchmark. Sport audiences are smaller but convert better, because the fan usually does the sport themselves.
A11: Popular adjustment | B11: 1.37 | D11: OUR JUDGEMENT: +37%. Much larger followings, much weaker conversion - more paying fans in absolute terms even though a smaller share converts.
A12: → Niche fans per athlete, mature | B12: =B8*B10
A13: → Popular fans per athlete, mature | B13: =B8*B11
A14: 2. FAN ARPU -> Assumptions
A15: Tier 1 price (Supporter) | B15: 4.99
A16: Tier 2 price (Insider) | B16: 9.99
A17: Tier 3 price (Inner circle) | B17: 24.99
A18: Mix - Tier 1 | B18: 0.4 | D18: Assumed distribution; replace with the real tier mix after P1.
A19: Mix - Tier 2 | B19: 0.5
A20: Mix - Tier 3 | B20: 0.1
A21: Mix check (must be 100%) | B21: =B18+B19+B20
A22: → Weighted ARPU per month | B22: =B15*B18+B16*B19+B17*B20 | D22: Cross-check: Patreon reports $6.10 average support and a $8-12 typical band. Landing inside that band from an independent tier build is a good sign.
A23: Patreon average support (cross-check) | B23: =Comparables!B16 | D23: Published average - below our figure because Patreon's long tail includes many $1-3 tiers. Our EUR 9.49 sits inside their $8-12 typical band.
A24: Niche ARPU factor | B24: 1 | D24: Niche fans buy knowledge and sit at the tier mix above.
A25: Popular ARPU factor | B25: 0.87 | D25: OUR JUDGEMENT: -13%. Popular-sport fans skew to the cheapest tier.
A26: → Niche ARPU, mature | B26: =B22*B24
A27: → Popular ARPU, mature | B27: =B22*B25
A28: 3. FAN CHURN -> Assumptions
A29: Patreon monthly churn (low) | B29: =Comparables!B19
A30: Patreon monthly churn (high) | B30: =Comparables!B20
A31: Benchmark midpoint | B31: =(B29+B30)/2
A32: Annual-plan churn multiplier | B32: =Comparables!B21 | D32: Patreon: annual patrons churn at one third the monthly rate.
A33: Share of subscribers on annual plans | B33: 0.3 | D33: Our target for the season pass. This is the one lever that improves churn without changing the product.
A34: Blended benchmark churn | B34: =B31*(1-B33)+B31*B32*B33 | D34: What a Patreon-like platform would see with our annual mix.
A35: Niche engagement factor | B35: 0.55 | D35: OUR CLAIM, UNTESTED, AND THE MOST OPTIMISTIC JUDGEMENT IN THE MODEL: this says niche fans churn 45% SLOWER than the Patreon benchmark, because training content is habitual and competitive seasons create renewal moments. Nothing yet proves it. If it is wrong and we are merely at benchmark, Y10 revenue falls by roughly EUR 7M.
A36: Popular engagement factor | B36: 0.85 | D36: OUR JUDGEMENT: 15% better than benchmark. Impulse follows after a result, with many free substitutes - but still a sport fan rather than a general creator audience.
A37: → Niche churn, mature | B37: =B34*B35
A38: → Popular churn, mature | B38: =B34*B36
A39: 4. WHAT AN ATHLETE ACTUALLY EARNS (sanity check, not an input)
A40: OnlyFans: paid to creators / creator accounts | B40: =Comparables!B7/Comparables!B8/12 | D40: Includes dormant accounts, so this is a floor.
A41: Patreon: paid to creators / paying creators | B41: =Comparables!B15/Comparables!B12/12 | D41: Denominator is creators WITH members, so this is a ceiling.
A42: Stride: modelled niche athlete, mature | B42: =B12*B22*(1-Assumptions!$C$40) | D42: Ours sits between the two, which is where a plausible figure should sit.
A43: Revenue share taken by top 0.1% (OnlyFans) | B43: =Comparables!B11 | D43: THE CAVEAT ON EVERY AVERAGE ABOVE: earnings follow a power law. Totals are unaffected, but the median athlete earns far less than the mean. Do not pitch the mean to an athlete.
A44: 5. TAKE RATE - what an athlete keeps, by platform
A45: USD to EUR | B45: 0.92 | D45: Comparables are published in USD; this model is in EUR. Applied to the per-transaction and monthly creator fees below.
A46: Athlete monthly fan revenue (test case) | B46: 300 | D46: Change this to see who is cheapest at any revenue level.
A47: OnlyFans - athlete keeps | B47: =B46*(1-Comparables!B29)-B46/Assumptions!$C$54*Comparables!C29*B45-Comparables!D29*B45 | D47: Headline take, plus per-transaction and monthly creator fees where they exist.
A48: Patreon - athlete keeps | B48: =B46*(1-Comparables!B32)-B46/Assumptions!$C$54*Comparables!C32*B45-Comparables!D32*B45 | D48: Headline take, plus per-transaction and monthly creator fees where they exist.
A49: Passes - athlete keeps | B49: =B46*(1-Comparables!B33)-B46/Assumptions!$C$54*Comparables!C33*B45-Comparables!D33*B45 | D49: Headline take, plus per-transaction and monthly creator fees where they exist.
A50: Stride (proposed) - athlete keeps | B50: =B46*(1-Comparables!B34)-B46/Assumptions!$C$54*Comparables!C34*B45-Comparables!D34*B45 | D50: Headline take, plus per-transaction and monthly creator fees where they exist.
A51: Crossover vs Passes (EUR/month) | B51: =Comparables!D33*B45/((Comparables!B34-Comparables!B33)-Comparables!C33*B45/Assumptions!$C$54) | D51: Below this, our flat 15% pays the athlete more than Passes' 10% plus fees. Our modelled athlete earns far less than this, so the long tail is on our side of the line.
A52: 6. MARKET SIZE -> sanity-checks the athlete trajectory
A53: Population, 34 countries in scope | B53: 2726.2 | D53: Millions. Eurostat / national statistics offices.
A54: Population, Spain | B54: 48.6 | D54: Millions.
A55: Share who do any sport (Spain) | B55: 0.56 | D55: Eurobarometer 525 - Spain sits near the EU average of 55% who exercise at all.
A56: Share with a public athletic identity | B56: 0.02 | D56: OUR ESTIMATE: competes, posts publicly, has a following worth sponsoring.
A57: Share with commercial intent | B57: 0.25 | D57: OUR ESTIMATE: would monetise if the tooling existed.
A58: → Addressable athletes, Spain | B58: =B54*1000000*B55*B56*B57
A59: → Addressable athletes, all 34 countries | B59: =B53*1000000*0.5*B56*B57 | D59: Using a 50% blended participation rate across the 34 countries.
A60: Y10 athletes in the plan | B60: =Assumptions!$L$5
A61: → Y10 penetration of Spain SAM | B61: =Assumptions!$L$5/B58
A62: → Y10 penetration of full TAM | B62: =Assumptions!$L$5/B59 | D62: If this reads as implausibly high, the athlete trajectory is too aggressive - that is exactly what this block exists to reveal.

Sheet Research
A1: Research & Benchmarking - where every assumption came from
A2: SOURCED = published figure | BENCHMARKED = set against named comparables | DERIVED = computed from other assumptions | ESTIMATE = judgement, no benchmark yet
A4: Assumption | B4: Model value | C4: Method | D4: Benchmark / comparable | E4: Source | F4: Confidence | G4: What would replace the estimate
A5: : PRICING & TAKE RATE:
A6: Take rate on fan revenue | B6: =Assumptions!$C$40 | C6: BENCHMARKED | D6: Passes charges 10% but adds $0.30/txn and a $29/month creator fee; OnlyFans, Fansly and Fanfix are all 20%; Patreon 8-12%. A flat 15% with no monthly fee pays an athlete more than Passes for anyone under EUR 1,380/month of fan revenue. | E6: Sacra company profile (Passes); Passes rebrand release, Apr 2026; MEXC platform comparison 2026 | F6: High | G6: Nothing. This is a pricing decision and the comparables are public.
A7: Take rate on sponsorship | B7: =Assumptions!$C$41 | C7: BENCHMARKED | D7: Sports agents take 10-20% of an endorsement and 4-10% of a playing contract. On OnlyFans, management agencies take a further 20-50% on top of the platform's 20%. | E7: Oreate and Sapling agent-commission surveys; Aruna Talent agency rate guide 2026 | F7: High | G7: Observed deal data once the marketplace is running.
A8: Suggested tiers 4.99 / 9.99 / 24.99 | B8: see model | C8: BENCHMARKED | D8: Patreon's typical patronage is quoted at $8-12/month, so the EUR 9.99 anchor sits inside the observed band. EUR 4.99 retains only 54% of our take after payment fees, against 71% at EUR 9.99: which is why the floor matters more than the take rate. | E8: Patreon 2024 Transparency Report; independent audits of ~1,200 creators | F8: Medium | G8: Our own tier mix after P1.
A9: Season pass / annual billing | B9: see model | C9: SOURCED | D9: Patreon reports that annual patrons churn at ONE THIRD the rate of monthly patrons. This is the single strongest piece of evidence in the plan for pushing annual billing. | E9: Patreon 2024 Transparency Report | F9: High | G9: Already strong. Confirm on our own cohorts.
A10: : FAN ECONOMICS:
A11: Fan ARPU per month | B11: =Assumptions!$C$12 | C11: BENCHMARKED | D11: Patreon's average monthly support rose from $5.40 to $6.10 during 2024, with typical patronage quoted at $8-12. Our EUR 8.00-9.50 sits in the upper-middle of that range. | E11: Patreon 2024 Transparency Report | F11: Medium | G11: Actual ARPU by tier and sport after P1.
A12: Fan churn per month | B12: =Assumptions!$C$13 | C12: ESTIMATE | D12: OPTIMISTIC AGAINST BENCHMARK. Patreon runs 10-15% monthly. We assume 6-9% (niche) and 9-13% (popular), arguing that training content is habitual and that competitive seasons create natural renewal moments. That argument is currently untested. | E12: Patreon 2024 Transparency Report (10-15%/month) | F12: Low | G12: THE most important number to measure in P1. Three months of real cohorts settles it. Until then the conservative case should be treated as the plan.
A13: Paying fans per monetising athlete | B13: =Assumptions!$C$11 | C13: DERIVED | D13: 20 rising to 48 over ten years. Cross-check: Patreon creators average $350/month and our modelled niche athlete at maturity earns about EUR 313/month, closely aligned, which is reassuring for an assumption built bottom-up rather than from a comparable. | E13: Patreon 2024 Transparency Report (creator average $350/month) | F13: Medium | G13: Observed fans per athlete, banded by follower count.
A14: Share of athletes who monetise | B14: =Assumptions!$C$10 | C14: ESTIMATE | D14: 28% rising to 50% for niche sports. No direct comparable exists: neither Patreon nor OnlyFans publishes activation rates for creators who sign up but never charge. | E14: None found | F14: Low | G14: Our own activation funnel, available from P1 onward.
A15: Fan acquisition capacity | B15: see model | C15: ESTIMATE | D15: An athlete can recruit 30-69 new paying fans a year depending on segment. This ceiling is what makes churn bite in the model: without it, higher churn perversely RAISED revenue, because the year-end target was reachable at any churn rate. | E15: None: introduced to fix a modelling flaw found by stress testing | F15: Low | G15: Observed gross adds per athlete per year.
A16: : PAYMENT RAILS:
A17: PSP percentage fee | B17: =Assumptions!$C$50 | C17: SOURCED | D17: Stripe for a Spanish entity: 1.5% + EUR 0.25 on EEA domestic cards, 2.5% on UK cards, 3.25% on non-EEA. 1.9% is the blend for a mostly-European fan base. CORRECTION: an earlier version of this model used the US headline of 2.9% and overstated the largest cost line in the business by about a third. | E17: Stripe published EU/EEA pricing, 2026 | F17: High | G17: Interchange-plus terms become negotiable above roughly EUR 5M processed.
A18: PSP fixed fee per transaction | B18: =Assumptions!$C$51 | C18: SOURCED | D18: EUR 0.25 per transaction. On a EUR 4.99 tier that single fee is a third of our take, which is why the tier floor and annual billing move more margin than the take rate does. | E18: Stripe published pricing, 2026 | F18: High | G18: Volume renegotiation; annual billing turns twelve fees into one.
A19: Payout fees | B19: =Assumptions!$C$52 | C19: SOURCED | D19: Stripe Connect Express: roughly 0.25% + EUR 0.25 per payout, plus a monthly active-account fee that is not modelled as a separate line. | E19: Stripe Connect pricing, 2026 | F19: Medium | G19: Actual payout frequency once athletes are onboarded.
A20: : MARKET SIZING:
A21: Sport participation by country | B21: see model | C21: ESTIMATE | D21: Eurobarometer 525, share who NEVER exercise: Finland 8%, Sweden 12%, Denmark 20%, Poland 65%, Greece 68%, Portugal 73%, EU-27 average 45%. Six of the 34 countries in the index are measured; the other 28 are estimates placed inside that distribution. | E21: Special Eurobarometer 525, Sport and Physical Activity, September 2022 | F21: Medium | G21: Federation licence counts, published annually and free (CSD in Spain).
A22: Padel market size | B22: see model | C22: SOURCED | D22: Spain has ~6.0M active players (12.7% of the population), 109,040 federation licences and 17,300+ courts; globally 35M+ players and 77,000+ courts. This is the clearest case for weighting a sport regionally rather than globally, padel scores 77.7 in Spain and 45.1 worldwide. | E22: FIP World Padel Report 2025 | F22: High | G22: Annual FIP refresh.
A23: Sports fandom by country | B23: see model | C23: ESTIMATE | D23: The weakest layer of the sport index, and it drives both the `demand` and `appetite` signals. Commercial audience panels (Nielsen Sports, YouGov) cost more than the entire Y1-Y2 analytics budget. | E23: None: reasoned estimates only | F23: Low | G23: Our own engagement data per sport per country once connectors are live. This is what makes the index self-improving rather than something anyone could copy.
A24: Athlete count trajectory | B24: =Assumptions!$C$5 | C24: ESTIMATE | D24: 400 rising to 40,000 over ten years. This is the PLAN, not a benchmark: marketing spend is derived from it at segment CAC, not the other way round. Everything in the model scales off this line. | E24: None: it is a target | F24: Low | G24: The pre-seed gate tests it directly: 400 athletes and EUR 10k MRR.
A25: : COSTS:
A26: Athlete CAC | B26: =Assumptions!$C$19 | C26: ESTIMATE | D26: EUR 16-36 for niche, EUR 40-88 for popular. The gap reflects displacing an existing agent relationship versus reaching someone with no representation at all. No published comparable exists for athlete acquisition in this segment. | E26: None found | F26: Low | G26: Measured CAC by channel from the first federation partnership.
A27: Admission rate, direct applicants | B27: =Assumptions!$C$82 | C27: DERIVED | D27: 20% of direct applicants are admitted, 25% go to a human, 40% are refused and 15% never finish the form. Not a judgement: it is the ops-load output of scripts/admission_stress.py run over the admission policy itself, so retuning a threshold moves this figure. The sweep asserts the model and the policy stay in step and fails if they drift. | E27: scripts/admission_stress.py, section 7, over a modelled applicant mix | F27: Medium | G27: Real intake data. The mix the sweep assumes is the soft part, not the arithmetic.
A28: Admission rate, club-nominated | B28: =Assumptions!$C$84 | C28: ESTIMATE | D28: 45% admitted against 20% direct. A verified club's nomination confers a credibility floor of 0.75 x its own legitimacy score, which carries a completed application over the admit line that would otherwise have gone to review. It cannot carry an empty one: no club can supply someone else's date of birth, so the uplift is real but bounded. | E28: None: the mechanism is built and tested, the conversion is not yet measured | F28: Low | G28: The first federation partnership: nominated applicants are tagged, so this is measurable from day one of it.
A29: Athlete verification cost | B29: =Assumptions!$C$87 | C29: DERIVED | D29: Four minutes per manual review, priced at the same loaded salary the People line uses, over 1,700 productive hours. Peaks at EUR 47k and 0.64 reviewer-FTE in Y10, which is the finding rather than the cost: verification is not a money problem at this scale. The reason to automate it is latency: an athlete sitting in the queue is not listed, not matchable and not earning. | E29: Derived from the sweep's review volume and the model's own salary line | F29: Medium | G29: Timing real reviews. Four minutes is an estimate of a mechanical task.
A30: Athlete CAC vs the funnel | B30: =Assumptions!$C$19 | C30: ESTIMATE | D30: Deliberately NOT multiplied by the admission funnel. Segment CAC is defined as the cost of landing one athlete ON the platform, so scaling it by 1/admission-rate would charge the same money twice. The Costs sheet carries a memo line showing what that CAC works out to per application (EUR 3.40 in Y1 rising to EUR 22), the figure to hold against what a channel actually charges per name reached. | E30: None: this is a definitional choice, made explicit so it is not silently reversed | F30: Low | G30: Channel-level spend against applications, which the funnel now records.
A31: Loaded salary, Spain | B31: =Assumptions!$C$67 | C31: BENCHMARKED | D31: EUR 38k-76k loaded. Spanish employer social security adds roughly 31% on top of gross, so a senior engineer at ~EUR 55k gross costs ~EUR 72k, around half the London equivalent, which is a real argument for being in Spain rather than an accident of geography. | E31: Spanish Seguridad Social employer contribution rates | F31: Medium | G31: Actual offers accepted.
A32: AWS infrastructure | B32: =Assumptions!$C$58 | C32: BENCHMARKED | D32: Built up per stage from list prices: Fargate, RDS then Aurora, ElastiCache, S3, MediaConvert, CloudWatch. Reserved capacity and Savings Plans (25-40%) are deliberately excluded and treated as upside. | E32: AWS published list pricing, 2026 | F32: Medium | G32: Actual bills; commit to Savings Plans once usage is stable.
A33: Media egress | B33: =Assumptions!$C$60 | C33: SOURCED | D33: EUR 0.008/GB behind a zero-egress object store versus EUR 0.075/GB at CloudFront list price. At Y10 volumes that single architectural choice is worth over EUR 1M a year, the largest cost decision in the plan that is settled by engineering rather than negotiation. | E33: Cloudflare R2 and Backblaze B2 pricing; AWS CloudFront list price | F33: High | G33: Nothing. Both are published.
A34: Moderation cost | B34: =Assumptions!$C$62 | C34: ESTIMATE | D34: EUR 22 per 1,000 items reviewed, on a hybrid of automated classification and human review. Vendor pricing varies widely with SLA and content type. | E34: None cited | F34: Low | G34: Vendor quotes once P2 scope is fixed.
A35: : TAX, CAPITAL & VALUATION:
A36: Corporate tax rates | B36: =Assumptions!$C$77 | C36: SOURCED | D36: 15% for the first four profitable years under the Spanish Startup Law, then the 25% standard rate. Modelled with loss carryforward against the Y1-Y4 losses. | E36: Ley de Startups (Spain); Impuesto sobre Sociedades | F36: High | G36: Confirm eligibility with a Spanish tax adviser before filing.
A37: Risk-free rate | B37: =Assumptions!$C$94 | C37: SOURCED | D37: Spanish 10-year sovereign yield, ~3.2% in mid-2026. Used as the floor for the founder opportunity-cost calculation rather than as the discount rate. | E37: Spanish 10Y government bond yield | F37: High | G37: Refresh at the date of any raise.
A38: WACC / discount rate | B38: =Assumptions!$C$91 | C38: BENCHMARKED | D38: 25%, against a published mature-company anchor of 6.01%. Damodaran's European cost of capital dataset puts Software (Internet) at 6.01% in euros across 23 listed firms, and the European market ex-financials at 6.59%. Those are costs of capital for mature listed companies; this is a pre-revenue venture, and the 19-point gap is the stage premium. It is stated rather than buried because it is the largest single judgement in the valuation. Damodaran publishes no dataset for venture-stage rates, so the premium itself is convention (20-35% is the usual range) and not a sourced figure. The sensitivity grid runs 18-30% because this is arguable rather than knowable. | E38: Aswath Damodaran, NYU Stern, Cost of Capital by Industry (Europe), updated 5 January 2026 | F38: Medium | G38: An actual term sheet prices this for you.
A39: Exit revenue multiple | B39: =Assumptions!$C$93 | C39: BENCHMARKED | D39: 6.5x blended. Marketplace comparables trade around 4x revenue and high-growth SaaS around 9x; our Y10 mix is roughly 55% marketplace take and 12% SaaS. | E39: Public marketplace and SaaS trading multiples | F39: Medium | G39: Comparable private transactions nearer an exit.
A40: Terminal growth | B40: =Assumptions!$C$92 | C40: BENCHMARKED | D40: 3%, approximating long-run nominal GDP. Ten explicit forecast years were chosen partly so this assumption carries less of the valuation than it would at Y7. | E40: Standard DCF convention | F40: Medium | G40: Nothing: it is a convention, and the grid shows its effect.
A41: : COMPLIANCE:
A42: Payout age floor | B42: see model | C42: SOURCED | D42: Stripe Express and Custom Connect require 18. Standard Connect allows 13+, but a legal guardian must own the account and hold the bank account the money lands in. | E42: Stripe Connect documentation | F42: High | G42: Nothing: it is a hard platform rule.
A43: Digital consent age, Spain | B43: see model | C43: SOURCED | D43: 14 today under LOPDGDD Art. 7. A draft Organic Law on the Protection of Minors in Digital Environments would raise it to 16 and make age verification mandatory, which is why 16 is the forward-compatible floor for an account. | E43: LOPDGDD Art. 7; draft Organic Law, Council of Ministers, March 2025 | F43: High | G43: Track the bill through Parliament.
A45: THE THREE ASSUMPTIONS MOST LIKELY TO BE WRONG
A46: 1. Fan churn. We assume 6-13%/month; Patreon reports 10-15%. If Patreon is right, Y10 revenue falls from about EUR 58M to EUR 51M and the capital requirement roughly doubles.
A47: 2. Athlete count. The trajectory is a target, not a forecast, and everything scales off it.
A48: 3. Share of athletes who monetise. No published comparable exists at all.
A50: All three are answered by the same thing: three months of real cohort data from P1.
